Workbook
Name \0: #N/A
Name \a: #REF!
Name \c: #REF!
Name \p: #REF!
Name \q: [1]FRYPROD!#REF!
Name ___RSE2: '[2]CMA Calculations'!$H$1066
Name __DAT1: "$#REF!.$A$1:$A$394"
Name __DAT10: #REF!
Name __DAT11: #REF!
Name __DAT12: #REF!
Name __DAT13: #REF!
Name __DAT14: #REF!
Name __DAT15: #REF!
Name __DAT16: #REF!
Name __DAT2: "$#REF!.$B$1:$B$394"
Name __DAT3: "$#REF!.$#REF!$#REF!:$#REF!$#REF!"
Name __DAT6: #REF!
Name __DAT7: #REF!
Name __DAT8: #REF!
Name __DAT9: #REF!
Name __NPW1: '[3]Permanent info'!$E$5
Name __NPW10: '[3]Permanent info'!$R$5
Name __NPW11: '[3]Permanent info'!$S$5
Name __NPW2: '[3]Permanent info'!$G$5
Name __NPW3: '[3]Permanent info'!$H$5
Name __NPW4: '[3]Permanent info'!$I$5
Name __NPW5: '[3]Permanent info'!$K$5
Name __NPW6: '[3]Permanent info'!$L$5
Name __NPW7: '[3]Permanent info'!$M$5
Name __NPW8: '[3]Permanent info'!$O$5
Name __NPW9: '[3]Permanent info'!$Q$5
Name __poc01: #REF!
Name __poc02: #REF!
Name __poc03: #REF!
Name __poc04: #REF!
Name __poc05: #REF!
Name __PPH25: #REF!
Name __RSE2: '[2]CMA Calculations'!$H$1066
Name __vib01: #REF!
Name __vib02: #REF!
Name __vib03: #REF!
Name __vib04: #REF!
Name __vib05: #REF!
Name __vib06: #REF!
Name __vib07: #REF!
Name __WS1: #REF!
Name __WS2: #REF!
Name _1: #REF!
Name _15: #REF!
Name _15_2: #REF!
Name _3: #REF!
Name _CDD763: #REF!
Name _DAT1: "$#REF!.$A$1:$A$394"
Name _DAT10: #REF!
Name _DAT11: #REF!
Name _DAT12: #REF!
Name _DAT13: #REF!
Name _DAT14: #REF!
Name _DAT15: #REF!
Name _DAT16: #REF!

Sheet TB
B1: TB July 2020
B3: Ledger account | C3: Name | D3: Opening balance | E3: Debit | F3: Credit | G3: Closing balance | I3: MainAccount | J3: Name | K3: Opening balance | L3: Debit | M3: Credit | N3: Closing balance
B4: 1510000 | C4: Land | G4: =IFERROR(VLOOKUP(B4,$I$4:$N$27,6,FALSE),0) -> 102037368651 | H4: =LEFT(I4,3) -> 421 | I4: 4215400 | J4: Gain from Sold FA Machinary & Equipment- | K4: -12006757 | L4: 0 | M4: 0 | N4: -12006757 | P4: 102037368651 | Q4: =P4-N4 -> 102049375408
B5: 1520000 | C5: Buildings | G5: =IFERROR(VLOOKUP(B5,$I$4:$N$27,6,FALSE),0) -> 2.8312631e+11 | H5: =LEFT(I5,3) -> 421 | I5: 4215500 | J5: Gain from Sold FA Vehicles- | K5: -1.4130901e+09 | L5: 0 | M5: 0 | N5: -1.4130901e+09 | P5: 2.8331437e+11 | Q5: =P5-N5 -> 2.8472746e+11
B6: 1530000 | C6: Structures | G6: =IFERROR(VLOOKUP(B6,$I$4:$N$27,6,FALSE),0) -> 9.6658306e+09 | H6: =LEFT(I6,3) -> 421 | I6: 4215600 | J6: Gain from Sold FA Tools, Furniture & Fixtures- | K6: -30900901 | L6: 0 | M6: 0 | N6: -30900901 | P6: 9.4307277e+09 | Q6: =P6-N6 -> 9.4616286e+09
B7: 1540000 | C7: Machinery & Equipment | G7: =IFERROR(VLOOKUP(B7,$I$4:$N$27,6,FALSE),0) -> 7.7229168e+10 | H7: =LEFT(I7,3) -> 152 | I7: 1520000 | J7: Buildings- | K7: 2.8312631e+11 | L7: 0 | M7: 0 | N7: 2.8312631e+11 | P7: 7.8722001e+10 | Q7: =P7-N7 -> -2.0440431e+11
B8: 1550000 | C8: Vehicles | G8: =IFERROR(VLOOKUP(B8,$I$4:$N$27,6,FALSE),0) -> 4.3952486e+11 | H8: =LEFT(I8,3) -> 161 | I8: 1615500 | J8: Down Payment: Vehicles- | K8: 3335691892 | L8: 0 | M8: 471891891 | N8: 2863800001 | P8: 4.4178311e+11 | Q8: =P8-N8 -> 4.3891931e+11
B9: 1560000 | C9: Tools, Furniture & Fixtures | G9: =IFERROR(VLOOKUP(B9,$I$4:$N$27,6,FALSE),0) -> 1.4168663e+10 | H9: =LEFT(I9,3) -> 251 | I9: 2515200 | J9: Accumulated Depreciation: Building- | K9: -1.5718812e+11 | L9: 0 | M9: 1.1383784e+09 | N9: -1.583265e+11 | P9: 1.3614925e+10 | Q9: =P9-N9 -> 1.7194143e+11
B10: 1585400 | C10: Lease Hold Improvement Machine& Equipment | G10: =IFERROR(VLOOKUP(B10,$I$4:$N$27,6,FALSE),0) -> 0 | H10: =LEFT(I10,3) -> 161 | I10: 1615400 | J10: Down Payment: Machinary & Equipment- | K10: 0 | L10: 0 | M10: 0 | N10: 0 | P10: 620000000 | Q10: =P10-N10 -> 620000000
B11: 1585500 | C11: Lease Hold Improvement Vehicle | G11: =IFERROR(VLOOKUP(B11,$I$4:$N$27,6,FALSE),0) -> 0 | H11: =LEFT(I11,3) -> 156 | I11: 1560000 | J11: Tools, Furniture & Fixtures- | K11: 1.4168663e+10 | L11: 0 | M11: 0 | N11: 1.4168663e+10 | P11: 1434345000 | Q11: =P11-N11 -> -1.2734318e+10
B12: 1615200 | C12: Down Payment: Building | G12: =IFERROR(VLOOKUP(B12,$I$4:$N$27,6,FALSE),0) -> 0 | H12: =LEFT(I12,3) -> 151 | I12: 1510000 | J12: Land- | K12: 102037368651 | L12: 0 | M12: 0 | N12: 102037368651 | P12: 0 | Q12: =P12-N12 -> -102037368651
B13: 1615300 | C13: Down Payment: Structures | G13: =IFERROR(VLOOKUP(B13,$I$4:$N$27,6,FALSE),0) -> 0 | H13: =LEFT(I13,3) -> 154 | I13: 1540000 | J13: Machinery & Equipment- | K13: 7.7109498e+10 | L13: 119669272 | M13: 0 | N13: 7.7229168e+10 | P13: -1.1295559e+11 | Q13: =P13-N13 -> -1.9018475e+11
B14: 1615400 | C14: Down Payment: Machinary & Equipment | G14: =IFERROR(VLOOKUP(B14,$I$4:$N$27,6,FALSE),0) -> 0 | H14: =LEFT(I14,3) -> 153 | I14: 1530000 | J14: Structures- | K14: 9.6658306e+09 | L14: 0 | M14: 0 | N14: 9.6658306e+09 | P14: -7.9542433e+09 | Q14: =P14-N14 -> -1.7620074e+10
B15: 1615500 | C15: Down Payment: Vehicles | G15: =IFERROR(VLOOKUP(B15,$I$4:$N$27,6,FALSE),0) -> 2863800001 | H15: =LEFT(I15,3) -> 172 | I15: 1720000 | J15: System & Software- | K15: 156000000 | L15: 56670000 | M15: 0 | N15: 212670000 | P15: -6.5588325e+10 | Q15: =P15-N15 -> -6.5800995e+10
... B18: 2515400 | C18: Accumulated Depreciation: Machine | G18: =IFERROR(VLOOKUP(B18,$I$4:$N$27,6,FALSE),0) -> -6.8709828e+10 | H18: =LEFT(I18,3) -> 251 | I18: 2515400 | J18: Accumulated Depreciation: Machine- | K18: -6.8540838e+10 | L18: 0 | M18: 1.6899033e+08 | N18: -6.8709828e+10 | P18: -1.1221614e+09 | Q18: =P18-N18 -> 6.7587666e+10
B19: 2515500 | C19: Accumulated Depreciation: Vehicles | G19: =IFERROR(VLOOKUP(B19,$I$4:$N$27,6,FALSE),0) -> -3.3108136e+11 | H19: =LEFT(I19,3) -> 251 | I19: 2515300 | J19: Accumulated Depreciation: Structures- | K19: -9.0126204e+09 | L19: 0 | M19: 20322217 | N19: -9.0329426e+09
B20: 2515600 | C20: Accumulated Depreciation: Tools, Furniture & Fixtures | G20: =IFERROR(VLOOKUP(B20,$I$4:$N$27,6,FALSE),0) -> -1.1129343e+10 | H20: =LEFT(I20,3) -> 254 | I20: 2540000 | J20: Accumulated Depreciation: System & Software- | K20: -26260000 | L20: 0 | M20: 3669500 | N20: -29929500
B21: 1615600 | C21: Down Payment: Tools, Furniture & Fixtures | G21: =IFERROR(VLOOKUP(B21,$I$4:$N$27,6,FALSE),0) -> 0 | H21: =LEFT(I21,3) -> 251 | I21: 2515500 | J21: Accumulated Depreciation: Vehicles- | K21: -3.2873047e+11 | L21: 5.67e+08 | M21: 2.9178912e+09 | N21: -3.3108136e+11
B22: 4215500 | C22: Gain from Sold FA Vehicles | G22: =IFERROR(VLOOKUP(B22,$I$4:$N$27,6,FALSE),0) -> -1.4130901e+09 | I22: 1615600 | J22: Down Payment: Tools, Furniture & Fixtures- | K22: 0 | L22: 0 | M22: 0 | N22: 0
B23: 4215600 | C23: Gain from Sold FA Tools, Furniture & Fixtures | G23: =IFERROR(VLOOKUP(B23,$I$4:$N$27,6,FALSE),0) -> -30900901
B24: 4215400 | C24: Gain from Sold FA Machinary & Equipment | G24: =IFERROR(VLOOKUP(B24,$I$4:$N$27,6,FALSE),0) -> -12006757
B25: 4215200 | C25: Gain from Sold FA Building | G25: =IFERROR(VLOOKUP(B25,$I$4:$N$27,6,FALSE),0) -> 0
B26: 1720000 | C26: System & Software | G26: =IFERROR(VLOOKUP(B26,$I$4:$N$27,6,FALSE),0) -> 212670000
B27: 2540000 | C27: Accumulated Depreciation: System & Software | G27: =IFERROR(VLOOKUP(B27,$I$4:$N$27,6,FALSE),0) -> -29929500
D30: =H4&"*,"&H5&"*,"&H6&"*,"&H7&"*,"&H8&"*,"&H9&"*,"&H10&"*,"&H11&"*,"&H13&"*,"&H14&"*,"&H15&"*,"&H16&"*,"&H17&"*,"&H18&"*,"&H19&"*,"&H20&"*,"&H12 -> 421*,421*,421*,152*,161*,251*,161*,156*,154*,153*,172*,155*,251*,251*,251*,254*,151
D31: 151*,152*,153*,154*,155*,156*,161*,251*,161*158*,42*,17*,254*
J35: MNE000001
J36: MNE000002
J37: MNE000003
J38: MNE000004
J39: MNE000005
J40: MNE000006
J41: MNE000007
J42: MNE000008
J43: FNF000002
J44: FNF000003
J45: FNF000004
J46: FNF000005
... J53: FNF000047

Sheet TOTAL
A1: PT. Sankyu Indonesia International
A2: Total of Fixed Asset
A3: 30 September 2025
A5: No. | B5: Name of Fixed Assets | C5: Fixed Asset (List) | I5: D365
C6: Beginning Balance | D6: Additional | E6: Disposals | F6: Adjustment | G6: Ending Balace | I6: Total | J6: Different
G7: a | I7: b | J7: c = a - b
A8: Purchase Price
A9: 152 | B9: Buildings | C9: 2.8312631e+11 | D9: =SUMIFS(FA_2025!$T$26:$T$38,FA_2025!$D$26:$D$38,TOTAL!$A$9,FA_2025!$AR$26:$AR$38,TOTAL!$D$6) -> 0 | E9: =-SUMIFS(FA_2025!$T$26:$T$38,FA_2025!$D$26:$D$38,TOTAL!$A$9,FA_2025!$AS$26:$AS$38,TOTAL!$E$6) -> 0 | G9: =+C9+D9+E9+F9 -> 2.8312631e+11 | I9: =TB!G5 -> 2.8312631e+11 | J9: =+G9-I9 -> 0
A10: 153 | B10: Structures | C10: 9.6658306e+09 | D10: =SUMIFS(FA_2025!$T$39:$T$63,FA_2025!$D$39:$D$63,TOTAL!$A$10,FA_2025!$AR$39:$AR$63,TOTAL!$D$6) -> 0 | E10: =-SUMIFS(FA_2025!$T$39:$T$63,FA_2025!$D$39:$D$63,TOTAL!$A$10,FA_2025!$AS$39:$AS$63,TOTAL!$E$6) -> 0 | G10: =+C10+D10+E10+F10 -> 9.6658306e+09 | I10: =TB!G6 -> 9.6658306e+09 | J10: =+G10-I10 -> 0
A11: 154 | B11: Machinery & Equipments | C11: 7.9065598e+10 | D11: =SUMIFS(FA_2025!$T$64:$T$101,FA_2025!$D$64:$D$101,TOTAL!$A$11,FA_2025!$AR$64:$AR$101,TOTAL!$D$6) -> 145223481 | E11: =-SUMIFS(FA_2025!$T$64:$T$101,FA_2025!$D$64:$D$101,TOTAL!$A$11,FA_2025!$AS$64:$AS$101,TOTAL!$E$6) -> 0 | G11: =+C11+D11+E11+F11 -> 7.9210821e+10 | I11: =TB!G7 -> 7.7229168e+10 | J11: =+G11-I11 -> 1981653528
A12: 159 | B12: Vessels | C12: 0 | D12: 0 | E12: 0 | G12: =+C12+D12+E12+F12 -> 0 | I12: 0 | J12: =+G12-I12 -> 0
A13: 155 | B13: Vehicles | C13: 4.2545379e+11 | D13: =SUMIFS(FA_2025!$T$102:$T$219,FA_2025!$D$102:$D$219,TOTAL!$A$13,FA_2025!$AR$102:$AR$219,TOTAL!$D$6) -> 4433108108 | E13: =-SUMIFS(FA_2025!$T$102:$T$219,FA_2025!$D$102:$D$219,TOTAL!$A$13,FA_2025!$AS$102:$AS$219,TOTAL!$E$6) -> -4.5663943e+09 | G13: =C13+D13+E13+F13 -> 4.253205e+11 | I13: =TB!G8 -> 4.3952486e+11 | J13: =+G13-I13 -> -1.4204357e+10
A14: 156 | B14: Tools, Furnitures & Fixtures | C14: 1.4017656e+10 | D14: =SUMIFS(FA_2025!$T$220:$T$250,FA_2025!$D$220:$D$250,TOTAL!$A$14,FA_2025!$AR$220:$AR$250,TOTAL!$D$6) -> 122000000 | E14: =-SUMIFS(FA_2025!$T$220:$T$250,FA_2025!$D$220:$D$250,TOTAL!$A$14,FA_2025!$AS$220:$AS$250,TOTAL!$E$6) -> 0 | G14: =+C14+D14+E14+F14 -> 1.4139656e+10 | I14: =TB!G9 -> 1.4168663e+10 | J14: =+G14-I14 -> -29007666
A15: 172 | B15: System | C15: 109050000 | D15: =SUMIFS(FA_2025!$T$220:$T$250,FA_2025!$D$220:$D$250,TOTAL!$A$15,FA_2025!$AR$220:$AR$250,TOTAL!$D$6) -> 0 | E15: =-SUMIFS(FA_2025!$T$220:$T$250,FA_2025!$D$220:$D$250,TOTAL!$A$15,FA_2025!$AS$220:$AS$250,TOTAL!$E$6) -> 0 | G15: =+C15+D15+E15+F15 -> 109050000 | I15: =TB!G26 -> 212670000 | J15: =+G15-I15 -> -103620000
A16: 151 | B16: Land | C16: 102037368651 | D16: =-SUMIFS(FA_2025!$T$256:$T$330,FA_2025!$D$256:$D$330,TOTAL!$A$16,FA_2025!$AR$256:$AR$330,TOTAL!$D$6) -> 0 | E16: =-SUMIFS(FA_2025!#REF!,FA_2025!#REF!,TOTAL!$A$16,FA_2025!#REF!,TOTAL!$E$6) -> #REF! | G16: =+C16+D16+E16+F16 -> #REF! | I16: 102037368651 | J16: =+G16-I16 -> #REF!
A17: 161 | B17: Construction In Process | C17: 4108230270 | D17: =SUMIFS(FA_2025!$T$256:$T$256,FA_2025!$D$256:$D$256,TOTAL!$A$17,FA_2025!$AR$256:$AR$256,TOTAL!$D$6) -> 0 | E17: =-SUMIFS(FA_2025!$AQ$256:$AQ$256,FA_2025!$D$256:$D$256,TOTAL!$A$17,FA_2025!$AS$256:$AS$256,TOTAL!$E$6) -> 0 | G17: =+C17+D17+E17+F17 -> 4108230270 | I17: =SUM(TB!G12:G15,TB!G21) -> 2863800001 | J17: =+G17-I17 -> 1244430269
B18: Grand Total | C18: 9.1758383e+11 | D18: =SUM(D9:D17) -> 4700331589 | E18: =SUM(E9:E17) -> #REF! | F18: =SUM(F9:F17) -> 0 | G18: =SUM(G9:G17) -> #REF! | I18: =SUM(I9:I17) -> 9.2882867e+11 | J18: =SUM(J9:J17) -> #REF!
C19: 9.134756e+11 | G19: =G18-G17 -> #REF!
A20: Accumulated Depreciation (251)
A21: 152 | B21: Buildings | C21: 1.480811e+11 | D21: =SUM(FA_2025!#REF!) -> #REF! | E21: =-SUMIFS(FA_2025!$AP$26:$AP$1036,FA_2025!$D$26:$D$1036,TOTAL!$A21,FA_2025!$AS$26:$AS$1036,TOTAL!$E$6) -> 0 | G21: =+C21+D21+E21+F21 -> #REF! | I21: =TB!G16 -> -1.583265e+11 | J21: =+G21+I21 -> #REF!
A22: 153 | B22: Structures | C22: 8.8439239e+09 | D22: =SUM(FA_2025!#REF!) -> #REF! | E22: =-SUMIFS(FA_2025!$AP$26:$AP$1036,FA_2025!$D$26:$D$1036,TOTAL!$A22,FA_2025!$AS$26:$AS$1036,TOTAL!$E$6) -> 0 | G22: =+C22+D22+E22+F22 -> #REF! | I22: =TB!G17 -> -9.0329426e+09 | J22: =+G22+I22 -> #REF!
A23: 154 | B23: Machinery & Equipments | C23: 6.9407991e+10 | D23: =SUM(FA_2025!#REF!) -> #REF! | E23: =-SUMIFS(FA_2025!$AP$26:$AP$1036,FA_2025!$D$26:$D$1036,TOTAL!$A23,FA_2025!$AS$26:$AS$1036,TOTAL!$E$6) -> 0 | G23: =+C23+D23+E23+F23 -> #REF! | I23: =TB!G18 -> -6.8709828e+10 | J23: =+G23+I23 -> #REF!
A24: 159 | B24: Vessels | C24: 0 | D24: 0 | E24: =-SUMIFS(FA_2025!$AP$26:$AP$1036,FA_2025!$D$26:$D$1036,TOTAL!$A24,FA_2025!$AS$26:$AS$1036,TOTAL!$E$6) -> 0 | G24: =+C24+D24+E24+F24 -> 0 | J24: =+G24+I24 -> 0
A25: 155 | B25: Vehicles | C25: 3.3226321e+11 | D25: =SUM(FA_2025!#REF!) -> #REF! | E25: =-SUMIFS(FA_2025!$AP$26:$AP$1036,FA_2025!$D$26:$D$1036,TOTAL!$A25,FA_2025!$AS$26:$AS$1036,TOTAL!$E$6) -> -4.5663943e+09 | G25: =+C25+D25+E25+F25 -> #REF! | I25: =TB!G19 -> -3.3108136e+11 | J25: =+G25+I25 -> #REF!
A26: 156 | B26: Tools, Furnitures & Fixtures | C26: 1.0974552e+10 | D26: =SUM(FA_2025!#REF!) -> #REF! | E26: =-SUMIFS(FA_2025!$AP$26:$AP$1036,FA_2025!$D$26:$D$1036,TOTAL!$A26,FA_2025!$AS$26:$AS$1036,TOTAL!$E$6) -> 0 | G26: =+C26+D26+E26+F26 -> #REF! | I26: =TB!G20 -> -1.1129343e+10 | J26: =+G26+I26 -> #REF!
A27: 172 | B27: System | C27: 9155000 | D27: =SUM(FA_2025!#REF!) -> #REF! | E27: =-SUMIFS(FA_2025!$AP$26:$AP$1036,FA_2025!$D$26:$D$1036,TOTAL!$A27,FA_2025!$AS$26:$AS$1036,TOTAL!$E$6) -> 0 | G27: =+C27+D27+E27+F27 -> #REF! | I27: =TB!G27 -> -29929500 | J27: =+G27+I27 -> #REF!
B28: Grand Total | C28: 5.6957993e+11 | D28: =SUM(D21:D27) -> #REF! | E28: =SUM(E21:E27) -> -4.5663943e+09 | F28: =SUM(F21:F27) -> 0 | G28: =SUM(G21:G27) -> #REF! | I28: =SUM(I21:I27) -> -5.783099e+11 | J28: =SUM(J21:J26) -> #REF!
C30: =C18-C28 -> 3.480039e+11 | E30: Fixed Asset (Net) | G30: =+G18-G28 -> #REF!
A31: Net Book Value (251) | C31: =C30+C40 -> #REF!
A32: 151 | B32: Land | C32: =G16 -> #REF!
A33: 152 | B33: Buildings | C33: =G9-G21 -> #REF!
A34: 153 | B34: Structures | C34: =G10-G22 -> #REF!
A35: 154 | B35: Machinery & Equipments | C35: =G11-G23 -> #REF!
A36: 159 | B36: Vessels | C36: =G12-G24 -> 0
A37: 155 | B37: Vehicles | C37: =G13-G25 -> #REF!
A38: 156 | B38: Tools, Furnitures & Fixtures | C38: =G14-G26 -> #REF!
A39: 172 | B39: System | C39: =G15-G27 -> #REF!
C40: =SUM(C32:C38) -> #REF!

Sheet FA_2025
A1: PT. SANKYU INDONESIA INTERNATIONAL
A2: LIST OF FIXED ASSETS AND DEPRECIATION SCHEDULE
A3: 46022
F5: CATEGORY | G5: JANUARY | H5: FEBRUARY | I5: MARCH | J5: APRIL | K5: MAY | L5: JUNE | M5: JULY | N5: AUGUST | O5: SEPTEMBER | P5: OCTOBER | Q5: NOVEMBER | R5: DECEMBER | S5: TOTAL/YEAR
E6: Warehouse 1 | F6: WH1 | G6: =SUMIF($E$25:$E$280,F6,$AD$25:$AD$280) -> 3.034665e+08 | H6: =SUMIF($E$25:$E$281,F6,$AE$25:$AE$281) -> 3.034665e+08 | I6: =SUMIF($E$25:$E$281,F6,$AF$25:$AF$281) -> 3.034665e+08 | J6: =SUMIF($E$25:$E$281,F6,$AG$25:$AG$281) -> 3.034665e+08 | K6: =SUMIF($E$25:$E$281,F6,$AH$25:$AH$281) -> 3.034665e+08 | L6: =SUMIF($E$25:$E$281,F6,$AI$25:$AI$280) -> 3.034665e+08 | M6: =SUMIF($E$25:$E$281,F6,$AJ$25:$AJ$281) -> 3.034665e+08 | N6: =SUMIF($E$25:$E$280,F6,$AK$25:$AK$280) -> 3.034665e+08 | O6: =SUMIF($E$25:$E$280,F6,$AL$25:$AL$280) -> 3.034665e+08 | P6: =SUMIF($E$25:$E$280,F6,$AM$25:$AM$280) -> 3.034665e+08 | Q6: =SUMIF($E$25:$E$280,F6,$AN$25:$AN$280) -> 3.034665e+08 | R6: =SUMIF($E$25:$E$280,F6,$AO$25:$AO$280) -> 3.034665e+08 | S6: =SUM(G6:R6) -> 3.641598e+09
E7: Warehouse 2 | F7: WH2 | G7: =SUMIF($E$25:$E$280,F7,$AD$25:$AD$280) -> 6.5201362e+08 | H7: =SUMIF($E$25:$E$280,F7,$AE$25:$AE$280) -> 6.5201362e+08 | I7: =SUMIF($E$25:$E$280,F7,$AF$25:$AF$280) -> 6.5201362e+08 | J7: =SUMIF($E$25:$E$280,F7,$AG$25:$AG$280) -> 6.5201362e+08 | K7: =SUMIF($E$25:$E$280,F7,$AH$25:$AH$280) -> 6.5201362e+08 | L7: =SUMIF($E$25:$E$280,F7,$AI$25:$AI$280) -> 6.5201362e+08 | M7: =SUMIF($E$25:$E$280,F7,$AJ$25:$AJ$280) -> 6.5201362e+08 | N7: =SUMIF($E$25:$E$280,F7,$AK$25:$AK$280) -> 6.5201362e+08 | O7: =SUMIF($E$25:$E$280,F7,$AL$25:$AL$280) -> 6.5201362e+08 | P7: =SUMIF($E$25:$E$280,F7,$AM$25:$AM$280) -> 6.5201362e+08 | Q7: =SUMIF($E$25:$E$280,F7,$AN$25:$AN$280) -> 6.5201362e+08 | R7: =SUMIF($E$25:$E$280,F7,$AO$25:$AO$280) -> 6.5201362e+08 | S7: =SUM(G7:R7) -> 7.8241634e+09
E8: Transport | F8: TRP | G8: =SUMIF($E$25:$E$281,F8,$AD$25:$AD$280) -> 12888438 | H8: =SUMIF($E$25:$E$281,F8,$AE$25:$AE$280) -> 12888438 | I8: =SUMIF($E$25:$E$280,F8,$AF$25:$AF$281) -> 12888438 | J8: =SUMIF($E$25:$E$280,F8,$AG$25:$AG$280) -> 31452402 | K8: =SUMIF($E$25:$E$280,F8,$AH$25:$AH$280) -> 31452402 | L8: =SUMIF($E$25:$E$280,F8,$AI$25:$AI$280) -> 31452402 | M8: =SUMIF($E$25:$E$280,F8,$AJ$25:$AJ$280) -> 31452402 | N8: =SUMIF($E$25:$E$280,F8,$AK$25:$AK$280) -> 31452402 | O8: =SUMIF($E$25:$E$280,F8,$AL$25:$AL$280) -> 64723574 | P8: =SUMIF($E$25:$E$280,F8,$AM$25:$AM$280) -> 67290240 | Q8: =SUMIF($E$25:$E$280,F8,$AN$25:$AN$280) -> 67290240 | R8: =SUMIF($E$25:$E$280,F8,$AO$25:$AO$280) -> 67290240 | S8: =SUM(G8:R8) -> 4.6252162e+08
E9: Bali | F9: BALI | G9: =SUMIF($E$25:$E$281,F9,$AD$25:$AD$280) -> 14100000 | H9: =SUMIF($E$25:$E$281,F9,$AE$25:$AE$280) -> 14100000 | I9: =SUMIF($E$25:$E$280,F9,$AF$25:$AF$281) -> 14100000 | J9: =SUMIF($E$25:$E$280,F9,$AG$25:$AG$280) -> 14100000 | K9: =SUMIF($E$25:$E$280,F9,$AH$25:$AH$280) -> 14100000 | L9: =SUMIF($E$25:$E$280,F9,$AI$25:$AI$280) -> 1.1998584e+08 | M9: =SUMIF($E$25:$E$280,F9,$AJ$25:$AJ$280) -> 1.1998584e+08 | N9: =SUMIF($E$25:$E$280,F9,$AK$25:$AK$280) -> 1.1998584e+08 | O9: =SUMIF($E$25:$E$280,F9,$AL$25:$AL$280) -> 1.1998584e+08 | P9: =SUMIF($E$25:$E$280,F9,$AM$25:$AM$280) -> 1.1998584e+08 | Q9: =SUMIF($E$25:$E$280,F9,$AN$25:$AN$280) -> 1.1998584e+08 | R9: =SUMIF($E$25:$E$280,F9,$AO$25:$AO$280) -> 1.1998584e+08 | S9: =SUM(G9:R9) -> 9.1040086e+08
E10: Medan | F10: MDN | G10: =SUMIF($E$25:$E$281,F10,$AD$25:$AD$280) -> 0 | H10: =SUMIF($E$25:$E$281,F10,$AE$25:$AE$280) -> 0 | I10: =SUMIF($E$25:$E$280,F10,$AF$25:$AF$281) -> 0 | J10: =SUMIF($E$25:$E$280,F10,$AG$25:$AG$280) -> 0 | K10: =SUMIF($E$25:$E$280,F10,$AH$25:$AH$280) -> 0 | L10: =SUMIF($E$25:$E$280,F10,$AI$25:$AI$280) -> 0 | M10: =SUMIF($E$25:$E$280,F10,$AJ$25:$AJ$280) -> 0 | N10: =SUMIF($E$25:$E$280,F10,$AK$25:$AK$280) -> 0 | O10: =SUMIF($E$25:$E$280,F10,$AL$25:$AL$280) -> 0 | P10: =SUMIF($E$25:$E$280,F10,$AM$25:$AM$280) -> 0 | Q10: =SUMIF($E$25:$E$280,F10,$AN$25:$AN$280) -> 0 | R10: =SUMIF($E$25:$E$280,F10,$AO$25:$AO$280) -> 0 | S10: =SUM(G10:R10) -> 0
E11: Palembang | F11: PBG | G11: =SUMIF($E$25:$E$281,F11,$AD$25:$AD$280) -> 13333333 | H11: =SUMIF($E$25:$E$281,F11,$AE$25:$AE$280) -> 13333333 | I11: =SUMIF($E$25:$E$280,F11,$AF$25:$AF$281) -> 13333333 | J11: =SUMIF($E$25:$E$280,F11,$AG$25:$AG$280) -> 13333333 | K11: =SUMIF($E$25:$E$280,F11,$AH$25:$AH$280) -> 13333333 | L11: =SUMIF($E$25:$E$280,F11,$AI$25:$AI$280) -> 13333333 | M11: =SUMIF($E$25:$E$280,F11,$AJ$25:$AJ$280) -> 13333333 | N11: =SUMIF($E$25:$E$280,F11,$AK$25:$AK$280) -> 13333333 | O11: =SUMIF($E$25:$E$280,F11,$AL$25:$AL$280) -> 13333333 | P11: =SUMIF($E$25:$E$280,F11,$AM$25:$AM$280) -> 13333333 | Q11: =SUMIF($E$25:$E$280,F11,$AN$25:$AN$280) -> 13333333 | R11: =SUMIF($E$25:$E$280,F11,$AO$25:$AO$280) -> 13333333 | S11: =SUM(G11:R11) -> 159999996
E12: Makassar | F12: MKS | G12: =SUMIF($E$25:$E$281,F12,$AD$25:$AD$280) -> 0 | H12: =SUMIF($E$25:$E$281,F12,$AE$25:$AE$280) -> 0 | I12: =SUMIF($E$25:$E$280,F12,$AF$25:$AF$281) -> 0 | J12: =SUMIF($E$25:$E$280,F12,$AG$25:$AG$280) -> 0 | K12: =SUMIF($E$25:$E$280,F12,$AH$25:$AH$280) -> 0 | L12: =SUMIF($E$25:$E$280,F12,$AI$25:$AI$280) -> 0 | M12: =SUMIF($E$25:$E$280,F12,$AJ$25:$AJ$280) -> 0 | N12: =SUMIF($E$25:$E$280,F12,$AK$25:$AK$280) -> 0 | O12: =SUMIF($E$25:$E$280,F12,$AL$25:$AL$280) -> 0 | P12: =SUMIF($E$25:$E$280,F12,$AM$25:$AM$280) -> 0 | Q12: =SUMIF($E$25:$E$280,F12,$AN$25:$AN$280) -> 0 | R12: =SUMIF($E$25:$E$280,F12,$AO$25:$AO$280) -> 0 | S12: =SUM(G12:R12) -> 0
E13: Surabaya | F13: SBY | G13: =SUMIF($E$25:$E$281,F13,$AD$25:$AD$280) -> 74120370 | H13: =SUMIF($E$25:$E$281,F13,$AE$25:$AE$280) -> 74120370 | I13: =SUMIF($E$25:$E$280,F13,$AF$25:$AF$281) -> 74120370 | J13: =SUMIF($E$25:$E$280,F13,$AG$25:$AG$280) -> 74120370 | K13: =SUMIF($E$25:$E$280,F13,$AH$25:$AH$280) -> 74120370 | L13: =SUMIF($E$25:$E$280,F13,$AI$25:$AI$280) -> 74120370 | M13: =SUMIF($E$25:$E$280,F13,$AJ$25:$AJ$280) -> 74120370 | N13: =SUMIF($E$25:$E$280,F13,$AK$25:$AK$280) -> 0 | O13: =SUMIF($E$25:$E$280,F13,$AL$25:$AL$280) -> 0 | P13: =SUMIF($E$25:$E$280,F13,$AM$25:$AM$280) -> 0 | Q13: =SUMIF($E$25:$E$280,F13,$AN$25:$AN$280) -> 0 | R13: =SUMIF($E$25:$E$280,F13,$AO$25:$AO$280) -> 0 | S13: =SUM(G13:R13) -> 518842590
E14: Forklift, Shuttle Car, Equipment, Nestainer Rack | F14: OTHERS | G14: =SUMIF($E$25:$E$281,F14,$AD$25:$AD$280) -> 98631187 | H14: =SUMIF($E$25:$E$281,F14,$AE$25:$AE$280) -> 1.2068119e+08 | I14: =SUMIF($E$25:$E$280,F14,$AF$25:$AF$281) -> 1.2068119e+08 | J14: =SUMIF($E$25:$E$280,F14,$AG$25:$AG$280) -> 1.2068119e+08 | K14: =SUMIF($E$25:$E$280,F14,$AH$25:$AH$280) -> 1.2068119e+08 | L14: =SUMIF($E$25:$E$280,F14,$AI$25:$AI$280) -> 1.2068119e+08 | M14: =SUMIF($E$25:$E$280,F14,$AJ$25:$AJ$280) -> 1.1380285e+08 | N14: =SUMIF($E$25:$E$280,F14,$AK$25:$AK$280) -> 1.1380285e+08 | O14: =SUMIF($E$25:$E$280,F14,$AL$25:$AL$280) -> 1.1380285e+08 | P14: =SUMIF($E$25:$E$280,F14,$AM$25:$AM$280) -> 1.1746952e+08 | Q14: =SUMIF($E$25:$E$280,F14,$AN$25:$AN$280) -> 1.1746952e+08 | R14: =SUMIF($E$25:$E$280,F14,$AO$25:$AO$280) -> 1.1746952e+08 | S14: =SUM(G14:R14) -> 1.3958542e+09
G15: =SUBTOTAL(9,G6:G14) -> 1.1685534e+09 | H15: =SUBTOTAL(9,H6:H14) -> 1.1906034e+09 | I15: =SUBTOTAL(9,I6:I14) -> 1.1906034e+09 | J15: =SUBTOTAL(9,J6:J14) -> 1.2091674e+09 | K15: =SUBTOTAL(9,K6:K14) -> 1.2091674e+09 | L15: =SUBTOTAL(9,L6:L14) -> 1.3150532e+09 | M15: =SUBTOTAL(9,M6:M14) -> 1.3081749e+09 | N15: =SUBTOTAL(9,N6:N14) -> 1.2340545e+09 | ... S15: =SUBTOTAL(9,S6:S14) -> 1.4913381e+10
F17: SITE | G17: JANUARY | H17: FEBRUARY | I17: MARCH | J17: APRIL | K17: MAY | L17: JUNE | M17: JULY | N17: AUGUST | O17: SEPTEMBER | P17: OCTOBER | Q17: NOVEMBER | R17: DECEMBER | S17: TOTAL/YEAR
F18: CLCWH | G18: =SUMIF($C$25:$C$280,F18,$AD$25:$AD$280) -> 1.0682113e+09 | H18: =SUMIF($C$25:$C$280,F18,$AE$25:$AE$280) -> 1.0902613e+09 | I18: =SUMIF($C$25:$C$280,F18,$AF$25:$AF$280) -> 1.0902613e+09 | J18: =SUMIF($C$25:$C$280,F18,$AG$25:$AG$280) -> 1.0902613e+09 | K18: =SUMIF($C$25:$C$280,F18,$AH$25:$AH$280) -> 1.0902613e+09 | L18: =SUMIF($C$25:$C$280,F18,$AI$25:$AI$280) -> 1.0902613e+09 | M18: =SUMIF($C$25:$C$280,F18,$AJ$25:$AJ$280) -> 1.083383e+09 | N18: =SUMIF($C$25:$C$280,F18,$AK$25:$AK$280) -> 1.083383e+09 | O18: =SUMIF($C$25:$C$280,F18,$AL$25:$AL$280) -> 1.083383e+09 | P18: =SUMIF($C$25:$C$280,F18,$AM$25:$AM$280) -> 1.0870496e+09 | Q18: =SUMIF($C$25:$C$280,F18,$AN$25:$AN$280) -> 1.0870496e+09 | R18: =SUMIF($C$25:$C$280,F18,$AO$25:$AO$280) -> 1.0870496e+09 | S18: =SUM(G18:R18) -> 1.3030816e+10
F19: CLCOWH | G19: =SUMIF($C$25:$C$280,F19,$AD$25:$AD$280) -> 87453703 | H19: =SUMIF($C$25:$C$280,F19,$AE$25:$AE$280) -> 87453703 | I19: =SUMIF($C$25:$C$280,F19,$AF$25:$AF$280) -> 87453703 | J19: =SUMIF($C$25:$C$280,F19,$AG$25:$AG$280) -> 87453703 | K19: =SUMIF($C$25:$C$280,F19,$AH$25:$AH$280) -> 87453703 | L19: =SUMIF($C$25:$C$280,F19,$AI$25:$AI$280) -> 1.9333954e+08 | M19: =SUMIF($C$25:$C$280,F19,$AJ$25:$AJ$280) -> 1.9333954e+08 | N19: =SUMIF($C$25:$C$280,F19,$AK$25:$AK$280) -> 1.1921917e+08 | O19: =SUMIF($C$25:$C$280,F19,$AL$25:$AL$280) -> 1.1921917e+08 | P19: =SUMIF($C$25:$C$280,F19,$AM$25:$AM$280) -> 1.1921917e+08 | Q19: =SUMIF($C$25:$C$280,F19,$AN$25:$AN$280) -> 1.1921917e+08 | R19: =SUMIF($C$25:$C$280,F19,$AO$25:$AO$280) -> 1.1921917e+08 | S19: =SUM(G19:R19) -> 1.4200434e+09
F20: CLCTRP | G20: =SUMIF($C$25:$C$280,F20,$AD$25:$AD$280) -> 12888438 | H20: =SUMIF($C$25:$C$280,F20,$AE$25:$AE$280) -> 12888438 | I20: =SUMIF($C$25:$C$280,F20,$AF$25:$AF$280) -> 12888438 | J20: =SUMIF($C$25:$C$280,F20,$AG$25:$AG$280) -> 31452402 | K20: =SUMIF($C$25:$C$280,F20,$AH$25:$AH$280) -> 31452402 | L20: =SUMIF($C$25:$C$280,F20,$AI$25:$AI$280) -> 31452402 | M20: =SUMIF($C$25:$C$280,F20,$AJ$25:$AJ$280) -> 31452402 | N20: =SUMIF($C$25:$C$280,F20,$AK$25:$AK$280) -> 31452402 | O20: =SUMIF($C$25:$C$280,F20,$AL$25:$AL$280) -> 64723574 | P20: =SUMIF($C$25:$C$280,F20,$AM$25:$AM$280) -> 67290240 | Q20: =SUMIF($C$25:$C$280,F20,$AN$25:$AN$280) -> 67290240 | R20: =SUMIF($C$25:$C$280,F20,$AO$25:$AO$280) -> 67290240 | S20: =SUM(G20:R20) -> 4.6252162e+08
G21: =SUM(G18:G20) -> 1.1685534e+09 | H21: =SUM(H18:H20) -> 1.1906034e+09 | I21: =SUM(I18:I20) -> 1.1906034e+09 | J21: =SUM(J18:J20) -> 1.2091674e+09 | K21: =SUM(K18:K20) -> 1.2091674e+09 | L21: =SUM(L18:L20) -> 1.3150532e+09 | M21: =SUM(M18:M20) -> 1.3081749e+09 | N21: =SUM(N18:N20) -> 1.2340545e+09 | ... S21: =SUM(S18:S20) -> 1.4913381e+10
A23: No. | B23: Site/ Location | C23: Job | D23: Account | E23: Category | F23: Asset | G23: Fixed asset number | H23: Purchase Date | I23: Group | J23: Voucher | K23: Name of Fixed Asset | L23: Maker/Type/Location | M23: Capacity/Size/User | N23: Year | O23: Police | P23: Machine | Q23: Chasis | R23: Quantity | S23: Valas | T23: Purchase Price | U23: Monthly Depreciation | V23: Depreciation Period | AA23: Accumulated Depreciation | AB23: Net Book Value | AC23: Depreciation Expense Current | AD23: DEPRECIATION 2025 ( MONTHLY ) | AP23: Accumulated Depreciation | AQ23: Net Book Value | AR23: Status | AT23: Acquisition | AU23: Remark | AV23: Photo Status | AX23: Checker Name ( A ) | AZ23: Existing ( B ) | BB23: If Yes (Existing) ( C ) | BD23: If Not Used ( D ) | BF23: Sticker ( E )
D24: No. | F24: No. | G24: AX | J24: No. | O24: No. | P24: No. | Q24: No. | V24: Total | W24: Acc. 2024 | X24: Yearly 2025 | Y24: Until 2025 | Z24: Remain > 2026 | AA24: 45657 | AB24: 45657 | AC24: =+A3 -> 46022 | AD24: Jan | AE24: Feb | AF24: Mar | AG24: Apr | AH24: May | AI24: Jun | AJ24: Jul | AK24: Aug | AL24: Sep | AM24: Oct | AN24: Nov | AO24: Dec | AP24: =A3 -> 46022 | AQ24: =+AP24 -> 46022 | AR24: Additional | AS24: Disposals | AT24: Condition | AX24: Site | AY24: HO | AZ24: Yes | BA24: No | BB24: Still Used | BC24: Not Used | BD24: Repair | BE24: Disposals | BF24: Good | BG24: Bad
T25: a | U25: b=a:c | V25: c | W25: d=h:b | X25: e=j:b | Y25: f=d+e | Z25: g=c-f | AA25: l=h+j | AB25: m=a-l | AC25: j=total k (jAC-des) | AD25: k | AE25: k | AF25: k | AG25: k | AH25: k | AI25: k | AJ25: k | AK25: k | AL25: k | AM25: k | AN25: k | AO25: k | AP25: l=h+j | AQ25: m=a-l | AW25: Check
A26: 1 | B26: CLC | C26: CLCWH | D26: 152 | E26: WH1 | F26: CLC131-001 | G26: BLD000048 | H26: 41639 | I26: Building | J26: 111 | K26: Cikarang Warehouse and Office | L26: Kawasan Industri Terpadu Indonesia China (KITIC) Kav. 20, Cikarang, West Java | M26: Head Ofice & Cikarang Logistic | N26: 2013 | R26: 1 | T26: 7.1701319e+10 | U26: =+T26/V26 -> 2.987555e+08 | V26: 240 | W26: 133 | X26: =+AC26/U26 -> 12 | Y26: =+W26+X26 -> 145 | Z26: =+V26-Y26 -> 95 | AA26: 3.9734481e+10 | AB26: 3.1966838e+10 | AC26: =SUM(AD26:AO26) -> 3.585066e+09 | AD26: 2.987555e+08 | AE26: 2.987555e+08 | AF26: 2.987555e+08 | AG26: 2.987555e+08 | AH26: 2.987555e+08 | AI26: 2.987555e+08 | AJ26: 2.987555e+08 | AK26: 2.987555e+08 | AL26: 2.987555e+08 | AM26: 2.987555e+08 | AN26: 2.987555e+08 | AO26: 2.987555e+08 | AP26: =+AA26+AC26 -> 4.3319547e+10 | AQ26: =IF(AS26=$AS$24,((T26-AP26)*0),T26-AP26) -> 2.8381772e+10 | AV26: Ok | AW26: =IFERROR(VLOOKUP(G26,'[70]Detail Deprec_202508'!$D$33:$I$357,6,FALSE),0) -> 2.987555e+08 | AX26: =AW26-AK26 -> 0.00058341026
A27: 2 | B27: CLC | C27: CLCWH | D27: 152 | E27: WH2 | F27: CLC131-004 | G27: BLD000063 | H27: 42398 | I27: Building | J27: 84 | K27: IMB Tax Warehouse Phase II | L27: Kawasan Industri Terpadu Indonesia China (KITIC) Kav. 20, Cikarang, West Java | M27: Cikarang Logistic Center | N27: 2016 | R27: 1 | T27: 2061766435 | U27: =+T27/V27 -> 8590693.5 | V27: 240 | W27: 108 | X27: =+AC27/U27 -> 12 | Y27: =+W27+X27 -> 120 | Z27: =+V27-Y27 -> 120 | AA27: 9.277949e+08 | AB27: 1.1339715e+09 | AC27: =SUM(AD27:AO27) -> 1.0308832e+08 | AD27: 8590693.5 | AE27: 8590693.5 | AF27: 8590693.5 | AG27: 8590693.5 | AH27: 8590693.5 | AI27: 8590693.5 | AJ27: 8590693.5 | AK27: 8590693.5 | AL27: 8590693.5 | AM27: 8590693.5 | AN27: 8590693.5 | AO27: 8590693.5 | AP27: =+AA27+AC27 -> 1.0308832e+09 | AQ27: =IF(AS27=$AS$24,((T27-AP27)*0),T27-AP27) -> 1.0308832e+09 | AV27: Ok | AW27: =IFERROR(VLOOKUP(G27,'[70]Detail Deprec_202508'!$D$33:$I$357,6,FALSE),0) -> 8590693.5 | AX27: =AW27-AK27 -> 0.0008333344
A28: 3 | B28: CLC | C28: CLCWH | D28: 152 | E28: WH2 | F28: CLC131-002 | G28: BLD000064 | H28: 42387 | I28: Building | J28: 05 | K28: Lobby & Office Phase 2 | L28: Kawasan Industri Terpadu Indonesia China (KITIC) Kav. 20, Cikarang, West Java | M28: Cikarang Logistic Center | N28: 2016 | R28: 1 | T28: 5000000000 | U28: =+T28/V28 -> 20833333 | V28: 240 | W28: 108 | X28: =+AC28/U28 -> 12 | Y28: =+W28+X28 -> 120 | Z28: =+V28-Y28 -> 120 | AA28: 2.25e+09 | AB28: 2.75e+09 | AC28: =SUM(AD28:AO28) -> 2.5e+08 | AD28: 20833333 | AE28: 20833333 | AF28: 20833333 | AG28: 20833333 | AH28: 20833333 | AI28: 20833333 | AJ28: 20833333 | AK28: 20833333 | AL28: 20833333 | AM28: 20833333 | AN28: 20833333 | AO28: 20833333 | AP28: =+AA28+AC28 -> 2.5e+09 | AQ28: =IF(AS28=$AS$24,((T28-AP28)*0),T28-AP28) -> 2.5e+09 | AV28: Ok | AW28: =IFERROR(VLOOKUP(G28,'[70]Detail Deprec_202508'!$D$33:$I$357,6,FALSE),0) -> 20833333 | AX28: =AW28-AK28 -> -0.0033333339
A29: 4 | B29: CLC | C29: CLCWH | D29: 152 | E29: WH2 | F29: CLC131-002 | G29: BLD000065 | H29: 42387 | I29: Building | J29: 05 | K29: Warehouse Phase 2 Floor 2 | L29: Kawasan Industri Terpadu Indonesia China (KITIC) Kav. 20, Cikarang, West Java | M29: Cikarang Logistic Center | N29: 2016 | R29: 1 | T29: 44455000000 | U29: =+T29/V29 -> 1.8522917e+08 | V29: 240 | W29: 108 | X29: =+AC29/U29 -> 12 | Y29: =+W29+X29 -> 120 | Z29: =+V29-Y29 -> 120 | AA29: 2.000475e+10 | AB29: 2.445025e+10 | AC29: =SUM(AD29:AO29) -> 2.22275e+09 | AD29: 1.8522917e+08 | AE29: 1.8522917e+08 | AF29: 1.8522917e+08 | AG29: 1.8522917e+08 | AH29: 1.8522917e+08 | AI29: 1.8522917e+08 | AJ29: 1.8522917e+08 | AK29: 1.8522917e+08 | AL29: 1.8522917e+08 | AM29: 1.8522917e+08 | AN29: 1.8522917e+08 | AO29: 1.8522917e+08 | AP29: =+AA29+AC29 -> 2.22275e+10 | AQ29: =IF(AS29=$AS$24,((T29-AP29)*0),T29-AP29) -> 2.22275e+10 | AV29: Ok | AW29: =IFERROR(VLOOKUP(G29,'[70]Detail Deprec_202508'!$D$33:$I$357,6,FALSE),0) -> 1.8522917e+08 | AX29: =AW29-AK29 -> 0.0033333302
A30: 5 | B30: CLC | C30: CLCWH | D30: 152 | E30: WH2 | F30: CLC131-002 | G30: BLD000066 | H30: 42387 | I30: Building | J30: 05 | K30: Warehouse Phase 2 Floor 1 | L30: Kawasan Industri Terpadu Indonesia China (KITIC) Kav. 20, Cikarang, West Java | M30: Cikarang Logistic Center | N30: 2016 | R30: 1 | T30: 49455000000 | U30: =+T30/V30 -> 206062500 | V30: 240 | W30: 108 | X30: =+AC30/U30 -> 12 | Y30: =+W30+X30 -> 120 | Z30: =+V30-Y30 -> 120 | AA30: 22254750000 | AB30: 27200250000 | AC30: =SUM(AD30:AO30) -> 2472750000 | AD30: 206062500 | AE30: 206062500 | AF30: 206062500 | AG30: 206062500 | AH30: 206062500 | AI30: 206062500 | AJ30: 206062500 | AK30: 206062500 | AL30: 206062500 | AM30: 206062500 | AN30: 206062500 | AO30: 206062500 | AP30: =+AA30+AC30 -> 24727500000 | AQ30: =IF(AS30=$AS$24,((T30-AP30)*0),T30-AP30) -> 24727500000 | AV30: Ok | AW30: =IFERROR(VLOOKUP(G30,'[70]Detail Deprec_202508'!$D$33:$I$357,6,FALSE),0) -> 206062500 | AX30: =AW30-AK30 -> 0
A31: 6 | B31: CLC | C31: CLCWH | D31: 152 | E31: WH2 | F31: CLC131-002 | G31: BLD000067 | H31: 42387 | I31: Building | J31: 05 | K31: Cold Room Area Phase 2 | L31: Kawasan Industri Terpadu Indonesia China (KITIC) Kav. 20, Cikarang, West Java | M31: Cikarang Logistic Center | N31: 2016 | R31: 1 | T31: 35325000000 | U31: =+T31/V31 -> 147187500 | V31: 240 | W31: 108 | X31: =+AC31/U31 -> 12 | Y31: =+W31+X31 -> 120 | Z31: =+V31-Y31 -> 120 | AA31: 15896250000 | AB31: 19428750000 | AC31: =SUM(AD31:AO31) -> 1766250000 | AD31: 147187500 | AE31: 147187500 | AF31: 147187500 | AG31: 147187500 | AH31: 147187500 | AI31: 147187500 | AJ31: 147187500 | AK31: 147187500 | AL31: 147187500 | AM31: 147187500 | AN31: 147187500 | AO31: 147187500 | AP31: =+AA31+AC31 -> 17662500000 | AQ31: =IF(AS31=$AS$24,((T31-AP31)*0),T31-AP31) -> 17662500000 | AV31: Ok | AW31: =IFERROR(VLOOKUP(G31,'[70]Detail Deprec_202508'!$D$33:$I$357,6,FALSE),0) -> 147187500 | AX31: =AW31-AK31 -> 0
A32: 7 | B32: CLC | C32: CLCWH | D32: 152 | E32: WH2 | F32: CLC131-002 | G32: BLD000068 | H32: 42387 | I32: Building | J32: 05 | K32: Cargo Lifter Phase 2 | L32: Kawasan Industri Terpadu Indonesia China (KITIC) Kav. 20, Cikarang, West Java | M32: Cikarang Logistic Center | N32: 2016 | R32: 1 | S32: 271320 | T32: 3375220800 | U32: =+T32/V32 -> 14063420 | V32: 240 | W32: 108 | X32: =+AC32/U32 -> 12 | Y32: =+W32+X32 -> 120 | Z32: =+V32-Y32 -> 120 | AA32: 1518849360 | AB32: 1856371440 | AC32: =SUM(AD32:AO32) -> 168761040 | AD32: 14063420 | AE32: 14063420 | AF32: 14063420 | AG32: 14063420 | AH32: 14063420 | AI32: 14063420 | AJ32: 14063420 | AK32: 14063420 | AL32: 14063420 | AM32: 14063420 | AN32: 14063420 | AO32: 14063420 | AP32: =+AA32+AC32 -> 1687610400 | AQ32: =IF(AS32=$AS$24,((T32-AP32)*0),T32-AP32) -> 1687610400 | AV32: Ok | AW32: =IFERROR(VLOOKUP(G32,'[70]Detail Deprec_202508'!$D$33:$I$357,6,FALSE),0) -> 14063420 | AX32: =AW32-AK32 -> 0
A33: 8 | B33: CLC | C33: CLCWH | D33: 152 | E33: WH2 | F33: CLC131-003 | G33: BLD000069 | H33: 42387 | I33: Building | J33: 05 | K33: Cargo Lifter Phase 2 | L33: Kawasan Industri Terpadu Indonesia China (KITIC) Kav. 20, Cikarang, West Java | M33: Cikarang Logistic Center | N33: 2016 | R33: 1 | S33: 271320 | T33: 3549950880 | U33: =+T33/V33 -> 14791462 | V33: 240 | W33: 108 | X33: =+AC33/U33 -> 12 | Y33: =+W33+X33 -> 120 | Z33: =+V33-Y33 -> 120 | AA33: 1597477896 | AB33: 1952472984 | AC33: =SUM(AD33:AO33) -> 177497544 | AD33: 14791462 | AE33: 14791462 | AF33: 14791462 | AG33: 14791462 | AH33: 14791462 | AI33: 14791462 | AJ33: 14791462 | AK33: 14791462 | AL33: 14791462 | AM33: 14791462 | AN33: 14791462 | AO33: 14791462 | AP33: =+AA33+AC33 -> 1774975440 | AQ33: =IF(AS33=$AS$24,((T33-AP33)*0),T33-AP33) -> 1774975440 | AV33: Ok | AW33: =IFERROR(VLOOKUP(G33,'[70]Detail Deprec_202508'!$D$33:$I$357,6,FALSE),0) -> 14791462 | AX33: =AW33-AK33 -> 0
A34: 9 | B34: CLC | C34: CLCWH | D34: 152 | E34: WH2 | F34: CLC131-003 | G34: BLD000070 | H34: 42387 | I34: Building | J34: 05 | K34: Canopy Area Phase 2 | L34: Kawasan Industri Terpadu Indonesia China (KITIC) Kav. 20, Cikarang, West Java | M34: Cikarang Logistic Center | N34: 2016 | R34: 1 | S34: 193800 | T34: 2612617800 | U34: =+T34/V34 -> 10885908 | V34: 240 | W34: 108 | X34: =+AC34/U34 -> 12 | Y34: =+W34+X34 -> 120 | Z34: =+V34-Y34 -> 120 | AA34: 1175678010 | AB34: 1436939790 | AC34: =SUM(AD34:AO34) -> 130630890 | AD34: 10885908 | AE34: 10885908 | AF34: 10885908 | AG34: 10885908 | AH34: 10885908 | AI34: 10885908 | AJ34: 10885908 | AK34: 10885908 | AL34: 10885908 | AM34: 10885908 | AN34: 10885908 | AO34: 10885908 | AP34: =+AA34+AC34 -> 1306308900 | AQ34: =IF(AS34=$AS$24,((T34-AP34)*0),T34-AP34) -> 1306308900 | AV34: Ok | AW34: =IFERROR(VLOOKUP(G34,'[70]Detail Deprec_202508'!$D$33:$I$357,6,FALSE),0) -> 10885908 | AX34: =AW34-AK34 -> 0
A35: 10 | B35: CLC | C35: CLCWH | D35: 152 | E35: WH2 | F35: CLC131-003 | G35: BLD000071 | H35: 42387 | I35: Building | J35: 05 | K35: Omni Lifter Phase 2 | L35: Kawasan Industri Terpadu Indonesia China (KITIC) Kav. 20, Cikarang, West Java | M35: Cikarang Logistic Center | N35: 2016 | R35: 1 | T35: 7065000000 | U35: =+T35/V35 -> 29437500 | V35: 240 | W35: 108 | X35: =+AC35/U35 -> 12 | Y35: =+W35+X35 -> 120 | Z35: =+V35-Y35 -> 120 | AA35: 3179250000 | AB35: 3885750000 | AC35: =SUM(AD35:AO35) -> 353250000 | AD35: 29437500 | AE35: 29437500 | AF35: 29437500 | AG35: 29437500 | AH35: 29437500 | AI35: 29437500 | AJ35: 29437500 | AK35: 29437500 | AL35: 29437500 | AM35: 29437500 | AN35: 29437500 | AO35: 29437500 | AP35: =+AA35+AC35 -> 3532500000 | AQ35: =IF(AS35=$AS$24,((T35-AP35)*0),T35-AP35) -> 3532500000 | AV35: Ok | AW35: =IFERROR(VLOOKUP(G35,'[70]Detail Deprec_202508'!$D$33:$I$357,6,FALSE),0) -> 29437500 | AX35: =AW35-AK35 -> 0
A36: 11 | B36: CLC | C36: CLCWH | D36: 152 | E36: WH2 | F36: CLC131-003 | G36: BLD000072 | H36: 42387 | I36: Building | J36: 05 | K36: Omni Lifter Phase 2 | L36: Kawasan Industri Terpadu Indonesia China (KITIC) Kav. 20, Cikarang, West Java | M36: Cikarang Logistic Center | N36: 2016 | R36: 1 | S36: 38760 | T36: 534694200 | U36: =+T36/V36 -> 2227892.5 | V36: 240 | W36: 108 | X36: =+AC36/U36 -> 12 | Y36: =+W36+X36 -> 120 | Z36: =+V36-Y36 -> 120 | AA36: 240612390 | AB36: 294081810 | AC36: =SUM(AD36:AO36) -> 26734710 | AD36: 2227892.5 | AE36: 2227892.5 | AF36: 2227892.5 | AG36: 2227892.5 | AH36: 2227892.5 | AI36: 2227892.5 | AJ36: 2227892.5 | AK36: 2227892.5 | AL36: 2227892.5 | AM36: 2227892.5 | AN36: 2227892.5 | AO36: 2227892.5 | AP36: =+AA36+AC36 -> 267347100 | AQ36: =IF(AS36=$AS$24,((T36-AP36)*0),T36-AP36) -> 267347100 | AV36: Ok | AW36: =IFERROR(VLOOKUP(G36,'[70]Detail Deprec_202508'!$D$33:$I$357,6,FALSE),0) -> 2227892.5 | AX36: =AW36-AK36 -> 0
A37: 12 | B37: CLC | C37: CLCWH | D37: 152 | E37: WH2 | F37: CLC131-003 | G37: BLD000073 | H37: 42387 | I37: Building | J37: 05 | K37: Mezzanine Area Phase 2 | L37: Kawasan Industri Terpadu Indonesia China (KITIC) Kav. 20, Cikarang, West Java | M37: Cikarang Logistic Center | N37: 2016 | R37: 1 | T37: 1338483845 | U37: =+T37/V37 -> 5577016 | V37: 240 | W37: 108 | X37: =+AC37/U37 -> 12 | Y37: =+W37+X37 -> 120 | Z37: =+V37-Y37 -> 120 | AA37: 6.0231773e+08 | AB37: 7.3616611e+08 | AC37: =SUM(AD37:AO37) -> 66924192 | AD37: 5577016 | AE37: 5577016 | AF37: 5577016 | AG37: 5577016 | AH37: 5577016 | AI37: 5577016 | AJ37: 5577016 | AK37: 5577016 | AL37: 5577016 | AM37: 5577016 | AN37: 5577016 | AO37: 5577016 | AP37: =+AA37+AC37 -> 6.6924192e+08 | AQ37: =IF(AS37=$AS$24,((T37-AP37)*0),T37-AP37) -> 6.6924192e+08 | AV37: Ok | AW37: =IFERROR(VLOOKUP(G37,'[70]Detail Deprec_202508'!$D$33:$I$357,6,FALSE),0) -> 5577016 | AX37: =AW37-AK37 -> -0.00083333347
A38: 13 | B38: CLC | C38: CLCWH | D38: 152 | E38: WH2 | F38: CLC131-005 | G38: BLD000076 | H38: 43830 | I38: Building | J38: 007-12 | K38: Roof for Motorcycle Parking Area (80%) | L38: SII JKC | M38: KITIC Office | N38: 2019 | R38: 1 | T38: 177294305 | U38: =+T38/V38 -> 738726.27 | V38: 240 | W38: 61 | X38: =+AC38/U38 -> 12 | Y38: =+W38+X38 -> 73 | Z38: =+V38-Y38 -> 167 | AA38: 45062303 | AB38: 1.32232e+08 | AC38: =SUM(AD38:AO38) -> 8864715.2 | AD38: 738726.27 | AE38: 738726.27 | AF38: 738726.27 | AG38: 738726.27 | AH38: 738726.27 | AI38: 738726.27 | AJ38: 738726.27 | AK38: 738726.27 | AL38: 738726.27 | AM38: 738726.27 | AN38: 738726.27 | AO38: 738726.27 | AP38: =+AA38+AC38 -> 53927018 | AQ38: =IF(AS38=$AS$24,((T38-AP38)*0),T38-AP38) -> 1.2336729e+08 | AV38: Ok | AW38: =IFERROR(VLOOKUP(G38,'[70]Detail Deprec_202508'!$D$33:$I$357,6,FALSE),0) -> 738726.27 | AX38: =AW38-AK38 -> -0.00083333335
A39: 14 | B39: CLC | C39: CLCWH | D39: 153 | E39: WH1 | F39: CLC133-001 | G39: STR000005 | H39: 41639 | I39: Structures | J39: 2005 | K39: Security system & installation | L39: SECOM Indonesia | M39: Cikarang Warehouse & Office | N39: 2013 | R39: 1 | S39: 4082 | T39: 48890114 | U39: =+T39/V39 -> 814835.23 | V39: 60 | W39: 60 | X39: =+AC39/U39 -> 0 | Y39: =+W39+X39 -> 60 | Z39: =+V39-Y39 -> 0 | AA39: 48890114 | AB39: 1.4901161e-08 | AC39: =SUM(AD39:AL39) -> 0 | AP39: =+AA39+AC39 -> 48890114 | AQ39: =IF(AS39=$AS$24,((T39-AP39)*0),T39-AP39) -> 1.4901161e-08 | AV39: Ok | AW39: =IFERROR(VLOOKUP(G39,'[70]Detail Deprec_202508'!$D$33:$I$357,6,FALSE),0) -> 0 | AX39: =AW39-AK39 -> 0
A40: =+A39+1 -> 15 | B40: CLC | C40: CLCWH | D40: 153 | E40: WH1 | F40: CLC133-002 | G40: STR000006 | H40: 41639 | I40: Structures | J40: 2007 | K40: CCTV system WH 1 | L40: SECOM Indonesia | M40: Cikarang Warehouse & Office | N40: 2013 | R40: 1 | S40: 40583.96 | T40: 4.8607409e+08 | U40: =+T40/V40 -> 8101234.8 | V40: 60 | W40: 60 | X40: =+AC40/U40 -> 0 | Y40: =+W40+X40 -> 60 | Z40: =+V40-Y40 -> 0 | AA40: 4.8607409e+08 | AB40: -1.1920929e-07 | AC40: =SUM(AD40:AL40) -> 0 | AP40: =+AA40+AC40 -> 4.8607409e+08 | AQ40: =IF(AS40=$AS$24,((T40-AP40)*0),T40-AP40) -> -1.1920929e-07 | AV40: Ok | AW40: =IFERROR(VLOOKUP(G40,'[70]Detail Deprec_202508'!$D$33:$I$357,6,FALSE),0) -> 0 | AX40: =AW40-AK40 -> 0
A41: =+A40+1 -> 16 | B41: CLC | C41: CLCWH | D41: 153 | E41: WH1 | F41: CLC133-003 | G41: STR000007 | H41: 41639 | I41: Structures | J41: 2008 | K41: Access control | L41: SECOM Indonesia | M41: Cikarang Warehouse & Office | N41: 2013 | R41: 1 | S41: 4246 | T41: 50854342 | U41: =+T41/V41 -> 847572.37 | V41: 60 | W41: 60 | X41: =+AC41/U41 -> 0 | Y41: =+W41+X41 -> 60 | Z41: =+V41-Y41 -> 0 | AA41: 50854342 | AB41: -2.2351742e-08 | AC41: =SUM(AD41:AL41) -> 0 | AP41: =+AA41+AC41 -> 50854342 | AQ41: =IF(AS41=$AS$24,((T41-AP41)*0),T41-AP41) -> -2.2351742e-08 | AV41: Ok | AW41: =IFERROR(VLOOKUP(G41,'[70]Detail Deprec_202508'!$D$33:$I$357,6,FALSE),0) -> 0 | AX41: =AW41-AK41 -> 0
A42: =+A41+1 -> 17 | B42: CLC | C42: CLCWH | D42: 153 | E42: WH1 | F42: CLC133-004 | G42: STR000008 | H42: 41639 | I42: Structures | J42: 2011 | K42: Security system & installation | L42: SECOM Indonesia | M42: Cikarang Warehouse & Office | N42: 2013 | R42: 1 | S42: 519 | T42: 6216063 | U42: =+T42/V42 -> 103601.05 | V42: 60 | W42: 60 | X42: =+AC42/U42 -> 0 | Y42: =+W42+X42 -> 60 | Z42: =+V42-Y42 -> 0 | AA42: 6216063 | AB42: -1.8626451e-09 | AC42: =SUM(AD42:AL42) -> 0 | AP42: =+AA42+AC42 -> 6216063 | AQ42: =IF(AS42=$AS$24,((T42-AP42)*0),T42-AP42) -> -1.8626451e-09 | AV42: Ok | AW42: =IFERROR(VLOOKUP(G42,'[70]Detail Deprec_202508'!$D$33:$I$357,6,FALSE),0) -> 0 | AX42: =AW42-AK42 -> 0
A43: =+A42+1 -> 18 | B43: CLC | C43: CLCWH | D43: 153 | E43: WH1 | F43: CLC133-026 | G43: STR000013 | H43: 41759 | I43: Structures | J43: 64 | K43: Wifi Terminal DG | L43: Dangerous Room (KDDI Indonesia) | N43: 2014 | R43: 1 | T43: 156382893 | U43: =+T43/V43 -> 2606381.5 | V43: 60 | W43: 60 | X43: =+AC43/U43 -> 0 | Y43: =+W43+X43 -> 60 | Z43: =+V43-Y43 -> 0 | AA43: 156382893 | AB43: 0 | AC43: =SUM(AD43:AL43) -> 0 | AP43: =+AA43+AC43 -> 156382893 | AQ43: =IF(AS43=$AS$24,((T43-AP43)*0),T43-AP43) -> 0 | AV43: Ok | AW43: =IFERROR(VLOOKUP(G43,'[70]Detail Deprec_202508'!$D$33:$I$357,6,FALSE),0) -> 0 | AX43: =AW43-AK43 -> 0
A44: =+A43+1 -> 19 | B44: CLC_SBY | C44: CLCWH | D44: 153 | E44: SBY | F44: CLC133-007 | G44: STR000023 | H44: 42366 | I44: Structures | J44: 20 | K44: Wifi Instalation Warehouse Surabaya | L44: KDDI Indonesia | N44: 2015 | R44: 1 | S44: 26310 | T44: 364130400 | U44: =+T44/V44 -> 6068840 | V44: 60 | W44: 60 | X44: =+AC44/U44 -> 0 | Y44: =+W44+X44 -> 60 | Z44: =+V44-Y44 -> 0 | AA44: 364130400 | AB44: 0 | AC44: =SUM(AD44:AL44) -> 0 | AP44: =+AA44+AC44 -> 364130400 | AQ44: =IF(AS44=$AS$24,((T44-AP44)*0),T44-AP44) -> 0 | AV44: Ok | AW44: =IFERROR(VLOOKUP(G44,'[70]Detail Deprec_202508'!$D$33:$I$357,6,FALSE),0) -> 0 | AX44: =AW44-AK44 -> 0
A45: =+A44+1 -> 20 | B45: CLC | C45: CLCWH | D45: 153 | E45: WH1 | F45: CLC133-008 | G45: STR000024 | H45: 42366 | I45: Structures | J45: 22 | K45: Installation High Bay Lighting Warehouse | L45: Seamec Asia | M45: WH 1 | N45: 2015 | R45: 1 | T45: 227000000 | U45: =+T45/V45 -> 3783333.3 | V45: 60 | W45: 60 | X45: =+AC45/U45 -> 0 | Y45: =+W45+X45 -> 60 | Z45: =+V45-Y45 -> 0 | AA45: 2.27e+08 | AB45: -2.9802322e-08 | AC45: =SUM(AD45:AL45) -> 0 | AP45: =+AA45+AC45 -> 2.27e+08 | AQ45: =IF(AS45=$AS$24,((T45-AP45)*0),T45-AP45) -> -2.9802322e-08 | AV45: Ok | AW45: =IFERROR(VLOOKUP(G45,'[70]Detail Deprec_202508'!$D$33:$I$357,6,FALSE),0) -> 0 | AX45: =AW45-AK45 -> 0
A46: =+A45+1 -> 21 | B46: CLC | C46: CLCWH | D46: 153 | E46: WH2 | F46: CLC133-009 | G46: STR000025 | H46: 42397 | I46: Structures | J46: 16 | K46: Internet System | L46: KDDI Indonesia | M46: WH & Office Phase 2 | N46: 2016 | R46: 1 | T46: 745885600 | U46: =+T46/V46 -> 12431427 | V46: 60 | W46: 60 | X46: =+AC46/U46 -> 0 | Y46: =+W46+X46 -> 60 | Z46: =+V46-Y46 -> 0 | AA46: 745885600 | AB46: 0 | AC46: =SUM(AD46:AL46) -> 0 | AP46: =+AA46+AC46 -> 745885600 | AQ46: =IF(AS46=$AS$24,((T46-AP46)*0),T46-AP46) -> 0 | AV46: Ok | AW46: =IFERROR(VLOOKUP(G46,'[70]Detail Deprec_202508'!$D$33:$I$357,6,FALSE),0) -> 0 | AX46: =AW46-AK46 -> 0
A47: =+A46+1 -> 22 | B47: CLC | C47: CLCWH | D47: 153 | E47: OTHERS | F47: CLC133-010 | G47: STR000026 | H47: 42429 | I47: Structures | J47: 27 | K47: Install PABX | L47: KDDI Indonesia | M47: Install New PABX at server room | N47: 2016 | R47: 1 | T47: 45560000 | U47: =+T47/V47 -> 759333.33 | V47: 60 | W47: 60 | X47: =+AC47/U47 -> 0 | Y47: =+W47+X47 -> 60 | Z47: =+V47-Y47 -> 0 | AA47: 45560000 | AB47: 7.4505806e-09 | AC47: =SUM(AD47:AL47) -> 0 | AP47: =+AA47+AC47 -> 45560000 | AQ47: =IF(AS47=$AS$24,((T47-AP47)*0),T47-AP47) -> 7.4505806e-09 | AV47: Ok | AW47: =IFERROR(VLOOKUP(G47,'[70]Detail Deprec_202508'!$D$33:$I$357,6,FALSE),0) -> 0 | AX47: =AW47-AK47 -> 0
A48: =+A47+1 -> 23 | B48: CLC | C48: CLCWH | D48: 153 | E48: WH2 | F48: CLC133-011 | G48: STR000027 | H48: 42489 | I48: Structures | J48: 35 | K48: CCTV system | L48: SECOM Indonesia | M48: WH 2 | N48: 2016 | R48: 1 | S48: 66652.35 | T48: 8.848766e+08 | U48: =+T48/V48 -> 14747943 | V48: 60 | W48: 60 | X48: =+AC48/U48 -> 0 | Y48: =+W48+X48 -> 60 | Z48: =+V48-Y48 -> 0 | AA48: 8.848766e+08 | AB48: 0 | AC48: =SUM(AD48:AL48) -> 0 | AP48: =+AA48+AC48 -> 8.848766e+08 | AQ48: =IF(AS48=$AS$24,((T48-AP48)*0),T48-AP48) -> 0 | AV48: Ok | AW48: =IFERROR(VLOOKUP(G48,'[70]Detail Deprec_202508'!$D$33:$I$357,6,FALSE),0) -> 0 | AX48: =AW48-AK48 -> 0
A49: =+A48+1 -> 24 | B49: CLC | C49: CLCWH | D49: 153 | E49: OTHERS | F49: CLC133-012 | G49: STR000028 | H49: 42489 | I49: Structures | J49: 35 | K49: Pariometer Border System | L49: SECOM Indonesia | N49: 2016 | R49: 1 | T49: 303068283 | U49: =+T49/V49 -> 5051138 | V49: 60 | W49: 60 | X49: =+AC49/U49 -> 0 | Y49: =+W49+X49 -> 60 | Z49: =+V49-Y49 -> 0 | AA49: 3.0306828e+08 | AB49: 5.9604645e-08 | AC49: =SUM(AD49:AL49) -> 0 | AP49: =+AA49+AC49 -> 3.0306828e+08 | AQ49: =IF(AS49=$AS$24,((T49-AP49)*0),T49-AP49) -> 5.9604645e-08 | AV49: Ok | AW49: =IFERROR(VLOOKUP(G49,'[70]Detail Deprec_202508'!$D$33:$I$357,6,FALSE),0) -> 0 | AX49: =AW49-AK49 -> 0
A50: =+A49+1 -> 25 | B50: CLC | C50: CLCWH | D50: 153 | E50: WH2 | F50: CLC133-013 | G50: STR000029 | H50: 42719 | I50: Structures | J50: 08 | K50: CCTV system fr Security Guard House | L50: SECOM Indonesia | N50: 2016 | R50: 1 | S50: 4947.09 | T50: 67097382 | U50: =+T50/V50 -> 1118289.7 | V50: 60 | W50: 60 | X50: =+AC50/U50 -> 0 | Y50: =+W50+X50 -> 60 | Z50: =+V50-Y50 -> 0 | AA50: 67097382 | AB50: 1.4901161e-08 | AC50: =SUM(AD50:AL50) -> 0 | AP50: =+AA50+AC50 -> 67097382 | AQ50: =IF(AS50=$AS$24,((T50-AP50)*0),T50-AP50) -> 1.4901161e-08 | AV50: Ok | AW50: =IFERROR(VLOOKUP(G50,'[70]Detail Deprec_202508'!$D$33:$I$357,6,FALSE),0) -> 0 | AX50: =AW50-AK50 -> 0
A51: =+A50+1 -> 26 | B51: CLC | C51: CLCWH | D51: 153 | E51: WH2 | F51: CLC133-014 | G51: STR000030 | H51: 42719 | I51: Structures | J51: 08 | K51: Finger Scan Acces for W/H Phase 2 | L51: SECOM Indonesia | N51: 2016 | R51: 1 | T51: 36326195 | U51: =+T51/V51 -> 605436.58 | V51: 60 | W51: 60 | X51: =+AC51/U51 -> 0 | Y51: =+W51+X51 -> 60 | Z51: =+V51-Y51 -> 0 | AA51: 36326195 | AB51: 0 | AC51: =SUM(AD51:AL51) -> 0 | AP51: =+AA51+AC51 -> 36326195 | AQ51: =IF(AS51=$AS$24,((T51-AP51)*0),T51-AP51) -> 0 | AV51: Ok | AW51: =IFERROR(VLOOKUP(G51,'[70]Detail Deprec_202508'!$D$33:$I$357,6,FALSE),0) -> 0 | AX51: =AW51-AK51 -> 0
A52: =+A51+1 -> 27 | B52: CLC | C52: CLCWH | D52: 153 | E52: OTHERS | F52: CLC133-015 | G52: STR000031 | H52: 42733 | I52: Structures | J52: 18 | K52: Pariometer Border System in Central Area W/H CLC | L52: SECOM Indonesia | N52: 2016 | R52: 1 | T52: 92140414 | U52: =+T52/V52 -> 1535673.6 | V52: 60 | W52: 60 | X52: =+AC52/U52 -> 0 | Y52: =+W52+X52 -> 60 | Z52: =+V52-Y52 -> 0 | AA52: 92140414 | AB52: 0 | AC52: =SUM(AD52:AL52) -> 0 | AP52: =+AA52+AC52 -> 92140414 | AQ52: =IF(AS52=$AS$24,((T52-AP52)*0),T52-AP52) -> 0 | AV52: Ok | AW52: =IFERROR(VLOOKUP(G52,'[70]Detail Deprec_202508'!$D$33:$I$357,6,FALSE),0) -> 0 | AX52: =AW52-AK52 -> 0
A53: =+A52+1 -> 28 | B53: CLC | C53: CLCWH | D53: 153 | E53: WH1 | F53: CLC133-016 | G53: STR000035 | H53: 42885 | I53: Structures | J53: 15 | K53: New Panic Bar | L53: SMCC Utama | N53: 2017 | R53: 1 | T53: 80000000 | U53: =+T53/V53 -> 1333333.3 | V53: 60 | W53: 60 | X53: =+AC53/U53 -> 0 | Y53: =+W53+X53 -> 60 | Z53: =+V53-Y53 -> 0 | AA53: 80000000 | AB53: 0 | AC53: =SUM(AD53:AL53) -> 0 | AP53: =+AA53+AC53 -> 80000000 | AQ53: =IF(AS53=$AS$24,((T53-AP53)*0),T53-AP53) -> 0 | AV53: Ok | AW53: =IFERROR(VLOOKUP(G53,'[70]Detail Deprec_202508'!$D$33:$I$357,6,FALSE),0) -> 0 | AX53: =AW53-AK53 -> 0
A54: =+A53+1 -> 29 | B54: CLC | C54: CLCWH | D54: 153 | E54: MDN | F54: CLC133-017 | G54: STR000045 | H54: 43006 | I54: Structures | J54: 05 | K54: WIFI Installation Warehouse Medan | L54: KDDI Indonesia | N54: 2017 | R54: 1 | T54: 94507530 | U54: =+T54/V54 -> 1575125.5 | V54: 60 | W54: 60 | X54: =+AC54/U54 -> 0 | Y54: =+W54+X54 -> 60 | Z54: =+V54-Y54 -> 0 | AA54: 94507530 | AB54: 0 | AC54: =SUM(AD54:AL54) -> 0 | AP54: =+AA54+AC54 -> 94507530 | AQ54: =IF(AS54=$AS$24,((T54-AP54)*0),T54-AP54) -> 0 | AV54: Ok | AW54: =IFERROR(VLOOKUP(G54,'[70]Detail Deprec_202508'!$D$33:$I$357,6,FALSE),0) -> 0 | AX54: =AW54-AK54 -> 0
A55: =+A54+1 -> 30 | B55: CLC | C55: CLCWH | D55: 153 | E55: WH1 | F55: CLC133-018 | G55: STR000048 | H55: 43097 | I55: Structures | J55: 25 | K55: Wifi Installation WH 1 | L55: KDDI Indonesia | N55: 2017 | R55: 1 | T55: 76595000 | U55: =+T55/V55 -> 1276583.3 | V55: 60 | W55: 60 | X55: =+AC55/U55 -> 0 | Y55: =+W55+X55 -> 60 | Z55: =+V55-Y55 -> 0 | AA55: 76595000 | AB55: 0 | AC55: =SUM(AD55:AL55) -> 0 | AP55: =+AA55+AC55 -> 76595000 | AQ55: =IF(AS55=$AS$24,((T55-AP55)*0),T55-AP55) -> 0 | AV55: Ok | AW55: =IFERROR(VLOOKUP(G55,'[70]Detail Deprec_202508'!$D$33:$I$357,6,FALSE),0) -> 0 | AX55: =AW55-AK55 -> 0
A56: =+A55+1 -> 31 | B56: CLC | C56: CLCWH | D56: 153 | E56: WH2 | F56: CLC133-019 | G56: STR000050 | H56: 43220 | I56: Structures | K56: CCTV System fr PLB Area WH II | L56: SECOM Indonesia | N56: 2018 | R56: 1 | T56: 214296550 | U56: =+T56/V56 -> 3571609.2 | V56: 60 | W56: 60 | X56: =+AC56/U56 -> 0 | Y56: =+W56+X56 -> 60 | Z56: =+V56-Y56 -> 0 | AA56: 214296550 | AB56: 0 | AC56: =SUM(AD56:AL56) -> 0 | AP56: =+AA56+AC56 -> 214296550 | AQ56: =IF(AS56=$AS$24,((T56-AP56)*0),T56-AP56) -> 0 | AV56: Ok | AX56: =AW56-AK56 -> 0
A57: =+A56+1 -> 32 | B57: CLC | C57: CLCWH | D57: 153 | E57: OTHERS | F57: CLC133-020 | G57: STR000051 | H57: 43403 | I57: Structures | J57: JKT_GL004975 | K57: Wifi Installation at Pekan Baru | L57: KDDI Indonesia | N57: 2018 | R57: 1 | T57: 195741000 | U57: =+T57/V57 -> 3262350 | V57: 60 | W57: 60 | X57: =+AC57/U57 -> 0 | Y57: =+W57+X57 -> 60 | Z57: =+V57-Y57 -> 0 | AA57: 195741000 | AB57: 0 | AC57: =SUM(AD57:AL57) -> 0 | AP57: =+AA57+AC57 -> 195741000 | AQ57: =IF(AS57=$AS$24,((T57-AP57)*0),T57-AP57) -> 0 | AV57: Ok | AW57: =IFERROR(VLOOKUP(G57,'[70]Detail Deprec_202508'!$D$33:$I$357,6,FALSE),0) -> 0 | AX57: =AW57-AK57 -> 0
A58: =+A57+1 -> 33 | B58: CLC | C58: CLCWH | D58: 153 | E58: MDN | F58: CLC133-021 | G58: STR000053 | H58: 43570 | I58: Structures | J58: JKT_GL007420 | K58: Wifi Installation at Medan B7 | L58: KDDI Indonesia | N58: 2019 | R58: 1 | T58: 109550000 | U58: =+T58/V58 -> 1825833.3 | V58: 60 | W58: 60 | X58: =+AC58/U58 -> 0 | Y58: =+W58+X58 -> 60 | Z58: =+V58-Y58 -> 0 | AA58: 109550000 | AB58: 0 | AC58: =SUM(AD58:AL58) -> 0 | AP58: =+AA58+AC58 -> 109550000 | AQ58: =IF(AS58=$AS$24,((T58-AP58)*0),T58-AP58) -> 0 | AV58: Ok | AW58: =IFERROR(VLOOKUP(G58,'[70]Detail Deprec_202508'!$D$33:$I$357,6,FALSE),0) -> 0 | AX58: =AW58-AK58 -> 0
A59: =+A58+1 -> 34 | B59: CLC | C59: CLCWH | D59: 153 | E59: PBG | F59: CLC133-022 | G59: STR000055 | H59: 43827 | I59: Structures | J59: JKT_GL010375 | K59: Wifi Installation at W/H Palembang | L59: KDDI Indonesia | N59: 2019 | R59: 1 | T59: 103960000 | U59: =+T59/V59 -> 1732666.7 | V59: 60 | W59: 60 | X59: =+AC59/U59 -> 0 | Y59: =+W59+X59 -> 60 | Z59: =+V59-Y59 -> 0 | AA59: 103960000 | AB59: 0 | AC59: =SUM(AD59:AL59) -> 0 | AP59: =+AA59+AC59 -> 103960000 | AQ59: =IF(AS59=$AS$24,((T59-AP59)*0),T59-AP59) -> 0 | AV59: Ok | AW59: =IFERROR(VLOOKUP(G59,'[70]Detail Deprec_202508'!$D$33:$I$357,6,FALSE),0) -> 0 | AX59: =AW59-AK59 -> 0
A60: =+A59+1 -> 35 | B60: CLC | C60: CLCWH | D60: 153 | E60: WH1 | F60: CLC134-021 | G60: STR000062 | H60: 44560 | I60: Structures | J60: JKT_GL016704 | K60: Handrail at Loading Dock WH 1 | L60: SMCC Utama | N60: 2021 | R60: 1 | T60: 120000000 | U60: =+T60/V60 -> 3333333.3 | V60: 36 | W60: 36 | X60: =+AC60/U60 -> 0 | Y60: =+W60+X60 -> 36 | Z60: =+V60-Y60 -> 0 | AA60: 120000000 | AB60: 0 | AC60: =SUM(AD60:AL60) -> 0 | AP60: =+AA60+AC60 -> 120000000 | AQ60: =IF(AS60=$AS$24,((T60-AP60)*0),T60-AP60) -> 0 | AV60: Ok | AW60: =IFERROR(VLOOKUP(G60,'[70]Detail Deprec_202508'!$D$33:$I$357,6,FALSE),0) -> 0 | AX60: =AW60-AK60 -> 0
A61: =+A60+1 -> 36 | B61: CLC | C61: CLCWH | D61: 153 | E61: WH2 | F61: CLC134-022 | G61: STR000063 | H61: 44560 | I61: Structures | J61: JKT_GL016759 | K61: Handrail at Loading Dock WH 2 | L61: SMCC Utama | N61: 2021 | R61: 1 | T61: 122900000 | U61: =+T61/V61 -> 3413888.9 | V61: 36 | W61: 36 | X61: =+AC61/U61 -> 0 | Y61: =+W61+X61 -> 36 | Z61: =+V61-Y61 -> 0 | AA61: 1.229e+08 | AB61: 1.4901161e-08 | AC61: =SUM(AD61:AL61) -> 0 | AP61: =+AA61+AC61 -> 1.229e+08 | AQ61: =IF(AS61=$AS$24,((T61-AP61)*0),T61-AP61) -> 1.4901161e-08 | AV61: Ok | AW61: =IFERROR(VLOOKUP(G61,'[70]Detail Deprec_202508'!$D$33:$I$357,6,FALSE),0) -> 0 | AX61: =AW61-AK61 -> 0
A62: =+A61+1 -> 37 | B62: CLC | C62: CLCWH | D62: 153 | E62: OTHERS | F62: CLC134-023 | G62: STR000068 | H62: 44865 | I62: Structures | J62: JKT_GL019011 | K62: Body Harness Hangers | L62: JKTC | N62: 2022 | R62: 1 | T62: 62500000 | U62: =+T62/V62 -> 1041666.7 | V62: 60 | W62: 27 | X62: =+AC62/U62 -> 12 | Y62: =+W62+X62 -> 39 | Z62: =+V62-Y62 -> 21 | AA62: 28125000 | AB62: 34375000 | AC62: =SUM(AD62:AO62) -> 12500000 | AD62: 1041666.7 | AE62: 1041666.7 | AF62: 1041666.7 | AG62: 1041666.7 | AH62: 1041666.7 | AI62: 1041666.7 | AJ62: 1041666.7 | AK62: 1041666.7 | AL62: 1041666.7 | AM62: 1041666.7 | AN62: 1041666.7 | AO62: 1041666.7 | AP62: =+AA62+AC62 -> 40625000 | AQ62: =IF(AS62=$AS$24,((T62-AP62)*0),T62-AP62) -> 21875000 | AV62: Ok | AW62: =IFERROR(VLOOKUP(G62,'[70]Detail Deprec_202508'!$D$33:$I$357,6,FALSE),0) -> 1041666.7 | AX62: =AW62-AK62 -> 0.0033333334
A63: =+A62+1 -> 38 | B63: CLC | C63: CLCWH | D63: 153 | E63: OTHERS | F63: CLC134-023 | G63: STR000069 | H63: 44865 | I63: Structures | J63: JKT_GL019011 | K63: Body Harness Hangers | L63: JKTC | N63: 2022 | R63: 1 | T63: 62500000 | U63: =+T63/V63 -> 1041666.7 | V63: 60 | W63: 27 | X63: =+AC63/U63 -> 12 | Y63: =+W63+X63 -> 39 | Z63: =+V63-Y63 -> 21 | AA63: 28125000 | AB63: 34375000 | AC63: =SUM(AD63:AO63) -> 12500000 | AD63: 1041666.7 | AE63: 1041666.7 | AF63: 1041666.7 | AG63: 1041666.7 | AH63: 1041666.7 | AI63: 1041666.7 | AJ63: 1041666.7 | AK63: 1041666.7 | AL63: 1041666.7 | AM63: 1041666.7 | AN63: 1041666.7 | AO63: 1041666.7 | AP63: =+AA63+AC63 -> 40625000 | AQ63: =IF(AS63=$AS$24,((T63-AP63)*0),T63-AP63) -> 21875000 | AV63: Ok | AW63: =IFERROR(VLOOKUP(G63,'[70]Detail Deprec_202508'!$D$33:$I$357,6,FALSE),0) -> 1041666.7 | AX63: =AW63-AK63 -> 0.0033333334
A64: =+A63+1 -> 39 | B64: CLC | C64: CLCWH | D64: 154 | E64: OTHERS | F64: CLC134-016 | G64: MNE000029 | H64: 36980 | I64: Machinary and Equipment | K64: Container | M64: 20 Feet | N64: 2001 | R64: 1 | T64: 10000000 | U64: =+T64/V64 -> 166666.67 | V64: 60 | W64: 60 | X64: =+AC64/U64 -> 0 | Y64: =+W64+X64 -> 60 | Z64: =+V64-Y64 -> 0 | AA64: 10000000 | AB64: 0 | AC64: =SUM(AD64:AL64) -> 0 | AP64: =+AA64+AC64 -> 10000000 | AQ64: =IF(AS64=$AS$24,((T64-AP64)*0),T64-AP64) -> 0 | AV64: Ok | AW64: =IFERROR(VLOOKUP(G64,'[70]Detail Deprec_202508'!$D$33:$I$357,6,FALSE),0) -> 0 | AX64: =AW64-AK64 -> 0
A65: =+A64+1 -> 40 | B65: CLC | C65: CLCWH | D65: 154 | E65: WH1 | F65: CLC134-001 | G65: MNE000131 | H65: 41726 | I65: Machinary and Equipment | J65: 25 | K65: VNA Racking System | L65: VNA | N65: 2014 | R65: 1 | S65: 61170 | T65: 711651780 | U65: =+T65/V65 -> 11860863 | V65: 60 | W65: 60 | X65: =+AC65/U65 -> 0 | Y65: =+W65+X65 -> 60 | Z65: =+V65-Y65 -> 0 | AA65: 711651780 | AB65: 0 | AC65: =SUM(AD65:AL65) -> 0 | AP65: =+AA65+AC65 -> 711651780 | AQ65: =IF(AS65=$AS$24,((T65-AP65)*0),T65-AP65) -> 0 | AV65: Ok | AW65: =IFERROR(VLOOKUP(G65,'[70]Detail Deprec_202508'!$D$33:$I$357,6,FALSE),0) -> 0 | AX65: =AW65-AK65 -> 0
A66: =+A65+1 -> 41 | B66: CLC | C66: CLCWH | D66: 154 | E66: OTHERS | F66: CLC134-003 | G66: MNE000132 | H66: 41759 | I66: Machinary and Equipment | J66: 115 | K66: Racking System | L66: JSR Trading | N66: 2014 | R66: 1 | S66: 21840 | T66: 249063360 | U66: =+T66/V66 -> 4151056 | V66: 60 | W66: 60 | X66: =+AC66/U66 -> 0 | Y66: =+W66+X66 -> 60 | Z66: =+V66-Y66 -> 0 | AA66: 249063360 | AB66: 0 | AC66: =SUM(AD66:AL66) -> 0 | AP66: =+AA66+AC66 -> 249063360 | AQ66: =IF(AS66=$AS$24,((T66-AP66)*0),T66-AP66) -> 0 | AV66: Ok | AW66: =IFERROR(VLOOKUP(G66,'[70]Detail Deprec_202508'!$D$33:$I$357,6,FALSE),0) -> 0 | AX66: =AW66-AK66 -> 0
A67: =+A66+1 -> 42 | B67: CLC | C67: CLCWH | D67: 154 | E67: OTHERS | F67: CLC134-006 | G67: MNE000135 | H67: 41764 | I67: Machinary and Equipment | J67: 7 | K67: Fire Extinguisher & Alarm System | L67: Citra Teknik Safetindo | N67: 2014 | R67: 1 | T67: 66224000 | U67: =+T67/V67 -> 1103733.3 | V67: 60 | W67: 60 | X67: =+AC67/U67 -> 0 | Y67: =+W67+X67 -> 60 | Z67: =+V67-Y67 -> 0 | AA67: 66224000 | AB67: 0 | AC67: =SUM(AD67:AL67) -> 0 | AP67: =+AA67+AC67 -> 66224000 | AQ67: =IF(AS67=$AS$24,((T67-AP67)*0),T67-AP67) -> 0 | AV67: Ok | AW67: =IFERROR(VLOOKUP(G67,'[70]Detail Deprec_202508'!$D$33:$I$357,6,FALSE),0) -> 0 | AX67: =AW67-AK67 -> 0
A68: =+A67+1 -> 43 | B68: CLC | C68: CLCWH | D68: 154 | E68: OTHERS | F68: CLC134-002 | G68: MNE000136 | H68: 41789 | I68: Machinary and Equipment | J68: 112 | K68: Racking System | L68: VNA | N68: 2014 | R68: 1 | S68: 99500 | T68: 1117783000 | U68: =+T68/V68 -> 18629717 | V68: 60 | W68: 60 | X68: =+AC68/U68 -> 0 | Y68: =+W68+X68 -> 60 | Z68: =+V68-Y68 -> 0 | AA68: 1117783000 | AB68: 0 | AC68: =SUM(AD68:AL68) -> 0 | AP68: =+AA68+AC68 -> 1117783000 | AQ68: =IF(AS68=$AS$24,((T68-AP68)*0),T68-AP68) -> 0 | AV68: Ok | AW68: =IFERROR(VLOOKUP(G68,'[70]Detail Deprec_202508'!$D$33:$I$357,6,FALSE),0) -> 0 | AX68: =AW68-AK68 -> 0
A69: =+A68+1 -> 44 | B69: CLC | C69: CLCWH | D69: 154 | E69: OTHERS | F69: CLC134-007 | G69: MNE000137 | H69: 41820 | I69: Machinary and Equipment | J69: 2008 | K69: Racking System | M69: JSR Trading | N69: 2014 | R69: 1 | S69: 31716 | T69: 368254476 | U69: =+T69/V69 -> 6137574.6 | V69: 60 | W69: 60 | X69: =+AC69/U69 -> 0 | Y69: =+W69+X69 -> 60 | Z69: =+V69-Y69 -> 0 | AA69: 368254476 | AB69: 0 | AC69: =SUM(AD69:AL69) -> 0 | AP69: =+AA69+AC69 -> 368254476 | AQ69: =IF(AS69=$AS$24,((T69-AP69)*0),T69-AP69) -> 0 | AV69: Ok | AW69: =IFERROR(VLOOKUP(G69,'[70]Detail Deprec_202508'!$D$33:$I$357,6,FALSE),0) -> 0 | AX69: =AW69-AK69 -> 0
A70: =+A69+1 -> 45 | B70: CLC | C70: CLCWH | D70: 154 | E70: OTHERS | F70: CLC134-008 | G70: MNE000138 | H70: 41828 | I70: Machinary and Equipment | J70: 8 | K70: Racking System | L70: Nutech Industries | N70: 2014 | R70: 1 | S70: 209350 | T70: 2505710150 | U70: =+T70/V70 -> 41761836 | V70: 60 | W70: 60 | X70: =+AC70/U70 -> 0 | Y70: =+W70+X70 -> 60 | Z70: =+V70-Y70 -> 0 | AA70: 2505710150 | AB70: 0 | AC70: =SUM(AD70:AL70) -> 0 | AP70: =+AA70+AC70 -> 2505710150 | AQ70: =IF(AS70=$AS$24,((T70-AP70)*0),T70-AP70) -> 0 | AV70: Ok | AW70: =IFERROR(VLOOKUP(G70,'[70]Detail Deprec_202508'!$D$33:$I$357,6,FALSE),0) -> 0 | AX70: =AW70-AK70 -> 0
A71: =+A70+1 -> 46 | B71: CLC | C71: CLCWH | D71: 154 | E71: OTHERS | F71: CLC-A-001 | G71: MNE000141 | H71: 41866 | I71: Machinary and Equipment | K71: Scruber Dryer | L71: Gaddle GT50 | N71: 2014 | R71: 1 | T71: 41472000 | U71: =+T71/V71 -> 691200 | V71: 60 | W71: 60 | X71: =+AC71/U71 -> 0 | Y71: =+W71+X71 -> 60 | Z71: =+V71-Y71 -> 0 | AA71: 41472000 | AB71: 0 | AC71: =SUM(AD71:AL71) -> 0 | AP71: =+AA71+AC71 -> 41472000 | AQ71: =IF(AS71=$AS$24,((T71-AP71)*0),T71-AP71) -> 0 | AV71: Ok | AW71: =IFERROR(VLOOKUP(G71,'[70]Detail Deprec_202508'!$D$33:$I$357,6,FALSE),0) -> 0 | AX71: =AW71-AK71 -> 0
A72: =+A71+1 -> 47 | B72: CLC | C72: CLCWH | D72: 154 | E72: OTHERS | F72: CLC134-009 | G72: MNE000142 | H72: 41879 | I72: Machinary and Equipment | K72: Racking System | L72: Seamec Asia | N72: 2014 | R72: 1 | S72: 20895 | T72: 242193945 | U72: =+T72/V72 -> 4036565.8 | V72: 60 | W72: 60 | X72: =+AC72/U72 -> 0 | Y72: =+W72+X72 -> 60 | Z72: =+V72-Y72 -> 0 | AA72: 242193945 | AB72: 0 | AC72: =SUM(AD72:AL72) -> 0 | AP72: =+AA72+AC72 -> 242193945 | AQ72: =IF(AS72=$AS$24,((T72-AP72)*0),T72-AP72) -> 0 | AV72: Ok | AW72: =IFERROR(VLOOKUP(G72,'[70]Detail Deprec_202508'!$D$33:$I$357,6,FALSE),0) -> 0 | AX72: =AW72-AK72 -> 0
A73: =+A72+1 -> 48 | B73: CLC | C73: CLCWH | D73: 154 | E73: OTHERS | F73: CLC134-010 | G73: MNE000159 | H73: 41911 | I73: Machinary and Equipment | J73: 17 | K73: Racking System | L73: JSR Trading | N73: 2014 | R73: 1 | T73: 259871343 | U73: =+T73/V73 -> 4331189 | V73: 60 | W73: 60 | X73: =+AC73/U73 -> 0 | Y73: =+W73+X73 -> 60 | Z73: =+V73-Y73 -> 0 | AA73: 2.5987134e+08 | AB73: 5.9604645e-08 | AC73: =SUM(AD73:AL73) -> 0 | AP73: =+AA73+AC73 -> 2.5987134e+08 | AQ73: =IF(AS73=$AS$24,((T73-AP73)*0),T73-AP73) -> 5.9604645e-08 | AV73: Ok | AW73: =IFERROR(VLOOKUP(G73,'[70]Detail Deprec_202508'!$D$33:$I$357,6,FALSE),0) -> 0 | AX73: =AW73-AK73 -> 0
A74: =+A73+1 -> 49 | B74: CLC | C74: CLCWH | D74: 154 | E74: OTHERS | F74: CLC134-011 | G74: MNE000186 | H74: 42143 | I74: Machinary and Equipment | J74: 5 | K74: Nestainer & Joint Pallet | L74: Hanwa Indonesia | N74: 2015 | R74: 381 | T74: 344590000 | U74: =+T74/V74 -> 5743166.7 | V74: 60 | W74: 60 | X74: =+AC74/U74 -> 0 | Y74: =+W74+X74 -> 60 | Z74: =+V74-Y74 -> 0 | AA74: 344590000 | AB74: 0 | AC74: =SUM(AD74:AL74) -> 0 | AP74: =+AA74+AC74 -> 344590000 | AQ74: =IF(AS74=$AS$24,((T74-AP74)*0),T74-AP74) -> 0 | AV74: Ok | AW74: =IFERROR(VLOOKUP(G74,'[70]Detail Deprec_202508'!$D$33:$I$357,6,FALSE),0) -> 0 | AX74: =AW74-AK74 -> 0
A75: =+A74+1 -> 50 | B75: CLC | C75: CLCWH | D75: 154 | E75: SBY | F75: CLC134-013 | G75: MNE000202 | H75: 42338 | I75: Machinary and Equipment | J75: 102 | K75: Lightening Rod | L75: Joko | M75: WH Surabaya | N75: 2015 | R75: 1 | T75: 17300000 | U75: =+T75/V75 -> 288333.33 | V75: 60 | W75: 60 | X75: =+AC75/U75 -> 0 | Y75: =+W75+X75 -> 60 | Z75: =+V75-Y75 -> 0 | AA75: 17300000 | AB75: 0 | AC75: =SUM(AD75:AL75) -> 0 | AP75: =+AA75+AC75 -> 17300000 | AQ75: =IF(AS75=$AS$24,((T75-AP75)*0),T75-AP75) -> 0 | AV75: Ok | AW75: =IFERROR(VLOOKUP(G75,'[70]Detail Deprec_202508'!$D$33:$I$357,6,FALSE),0) -> 0 | AX75: =AW75-AK75 -> 0
A76: =+A75+1 -> 51 | B76: CLC | C76: CLCWH | D76: 154 | E76: SBY | F76: CLC134-014 | G76: MNE000203 | H76: 42338 | I76: Machinary and Equipment | J76: 102 | K76: Fire Alarm | L76: Gagas Mandiri | M76: WH Surabaya | N76: 2015 | R76: 1 | T76: 41500000 | U76: =+T76/V76 -> 691666.67 | V76: 60 | W76: 60 | X76: =+AC76/U76 -> 0 | Y76: =+W76+X76 -> 60 | Z76: =+V76-Y76 -> 0 | AA76: 41500000 | AB76: 0 | AC76: =SUM(AD76:AL76) -> 0 | AP76: =+AA76+AC76 -> 41500000 | AQ76: =IF(AS76=$AS$24,((T76-AP76)*0),T76-AP76) -> 0 | AV76: Ok | AW76: =IFERROR(VLOOKUP(G76,'[70]Detail Deprec_202508'!$D$33:$I$357,6,FALSE),0) -> 0 | AX76: =AW76-AK76 -> 0
A77: =+A76+1 -> 52 | B77: CLC | C77: CLCWH | D77: 154 | E77: WH1 | F77: CLC134-015 | G77: MNE000204 | H77: 42338 | I77: Machinary and Equipment | J77: 102 | K77: Exsposion proof lamp | N77: 2015 | R77: 1 | T77: 23100000 | U77: =+T77/V77 -> 385000 | V77: 60 | W77: 60 | X77: =+AC77/U77 -> 0 | Y77: =+W77+X77 -> 60 | Z77: =+V77-Y77 -> 0 | AA77: 23100000 | AB77: 0 | AC77: =SUM(AD77:AL77) -> 0 | AP77: =+AA77+AC77 -> 23100000 | AQ77: =IF(AS77=$AS$24,((T77-AP77)*0),T77-AP77) -> 0 | AV77: Ok | AW77: =IFERROR(VLOOKUP(G77,'[70]Detail Deprec_202508'!$D$33:$I$357,6,FALSE),0) -> 0 | AX77: =AW77-AK77 -> 0
A78: =+A77+1 -> 53 | B78: CLC | C78: CLCWH | D78: 154 | E78: OTHERS | F78: CLC-R-01 | G78: MNE000208 | H78: 42398 | I78: Machinary and Equipment | J78: 09 | K78: Nestainer & Joint Pallet | L78: Sankyu Construction Jakarta | N78: 2016 | R78: 1 | T78: 202500000 | U78: =+T78/V78 -> 3375000 | V78: 60 | W78: 60 | X78: =+AC78/U78 -> 0 | Y78: =+W78+X78 -> 60 | Z78: =+V78-Y78 -> 0 | AA78: 202500000 | AB78: 0 | AC78: =SUM(AD78:AL78) -> 0 | AP78: =+AA78+AC78 -> 202500000 | AQ78: =IF(AS78=$AS$24,((T78-AP78)*0),T78-AP78) -> 0 | AV78: Ok | AW78: =IFERROR(VLOOKUP(G78,'[70]Detail Deprec_202508'!$D$33:$I$357,6,FALSE),0) -> 0 | AX78: =AW78-AK78 -> 0
A79: =+A78+1 -> 54 | B79: CLC | C79: CLCWH | D79: 154 | E79: OTHERS | F79: CLC-R-02 | G79: MNE000209 | H79: 42398 | I79: Machinary and Equipment | J79: 09 | K79: Nestainer & Joint Pallet | L79: Sankyu Construction Jakarta | N79: 2016 | R79: 1 | T79: 179250000 | U79: =+T79/V79 -> 2987500 | V79: 60 | W79: 60 | X79: =+AC79/U79 -> 0 | Y79: =+W79+X79 -> 60 | Z79: =+V79-Y79 -> 0 | AA79: 179250000 | AB79: 0 | AC79: =SUM(AD79:AL79) -> 0 | AP79: =+AA79+AC79 -> 179250000 | AQ79: =IF(AS79=$AS$24,((T79-AP79)*0),T79-AP79) -> 0 | AV79: Ok | AW79: =IFERROR(VLOOKUP(G79,'[70]Detail Deprec_202508'!$D$33:$I$357,6,FALSE),0) -> 0 | AX79: =AW79-AK79 -> 0
A80: =+A79+1 -> 55 | B80: CLC | C80: CLCWH | D80: 154 | E80: OTHERS | F80: CLC-R-03 | G80: MNE000211 | H80: 42612 | I80: Machinary and Equipment | J80: 22 | K80: Nestainer | L80: Hanwa Indonesia | N80: 2016 | R80: 50 | T80: 82500000 | U80: =+T80/V80 -> 1375000 | V80: 60 | W80: 60 | X80: =+AC80/U80 -> 0 | Y80: =+W80+X80 -> 60 | Z80: =+V80-Y80 -> 0 | AA80: 82500000 | AB80: 0 | AC80: =SUM(AD80:AL80) -> 0 | AP80: =+AA80+AC80 -> 82500000 | AQ80: =IF(AS80=$AS$24,((T80-AP80)*0),T80-AP80) -> 0 | AV80: Ok | AW80: =IFERROR(VLOOKUP(G80,'[70]Detail Deprec_202508'!$D$33:$I$357,6,FALSE),0) -> 0 | AX80: =AW80-AK80 -> 0
A81: =+A80+1 -> 56 | B81: CLC | C81: CLCWH | D81: 154 | E81: OTHERS | F81: CLC-R-04 | G81: MNE000212 | H81: 42613 | I81: Machinary and Equipment | J81: 2025 | K81: Nestainer & Joint Pallet | L81: Hanwa Indonesia | N81: 2016 | R81: 230 | T81: 173355000 | U81: =+T81/V81 -> 2889250 | V81: 60 | W81: 60 | X81: =+AC81/U81 -> 0 | Y81: =+W81+X81 -> 60 | Z81: =+V81-Y81 -> 0 | AA81: 173355000 | AB81: 0 | AC81: =SUM(AD81:AL81) -> 0 | AP81: =+AA81+AC81 -> 173355000 | AQ81: =IF(AS81=$AS$24,((T81-AP81)*0),T81-AP81) -> 0 | AV81: Ok | AW81: =IFERROR(VLOOKUP(G81,'[70]Detail Deprec_202508'!$D$33:$I$357,6,FALSE),0) -> 0 | AX81: =AW81-AK81 -> 0
A82: =+A81+1 -> 57 | B82: CLC | C82: CLCWH | D82: 154 | E82: OTHERS | F82: CLC-R-05 | G82: MNE000215 | H82: 42733 | I82: Machinary and Equipment | J82: 18 | K82: Nestainer Rack | L82: Hanwa Indonesia | N82: 2016 | R82: 1 | T82: 29600000 | U82: =+T82/V82 -> 493333.33 | V82: 60 | W82: 60 | X82: =+AC82/U82 -> 0 | Y82: =+W82+X82 -> 60 | Z82: =+V82-Y82 -> 0 | AA82: 29600000 | AB82: 3.7252903e-09 | AC82: =SUM(AD82:AL82) -> 0 | AP82: =+AA82+AC82 -> 29600000 | AQ82: =IF(AS82=$AS$24,((T82-AP82)*0),T82-AP82) -> 3.7252903e-09 | AV82: Ok | AW82: =IFERROR(VLOOKUP(G82,'[70]Detail Deprec_202508'!$D$33:$I$357,6,FALSE),0) -> 0 | AX82: =AW82-AK82 -> 0
A83: =+A82+1 -> 58 | B83: CLC | C83: CLCWH | D83: 154 | E83: OTHERS | F83: CLC-R-06 | G83: MNE000218 | H83: 42860 | I83: Machinary and Equipment | J83: 03 | K83: Nestainer and Joint Pallet | L83: Hanwa Indonesia | N83: 2017 | R83: 1 | T83: 72000000 | U83: =+T83/V83 -> 1200000 | V83: 60 | W83: 60 | X83: =+AC83/U83 -> 0 | Y83: =+W83+X83 -> 60 | Z83: =+V83-Y83 -> 0 | AA83: 72000000 | AB83: 0 | AC83: =SUM(AD83:AL83) -> 0 | AP83: =+AA83+AC83 -> 72000000 | AQ83: =IF(AS83=$AS$24,((T83-AP83)*0),T83-AP83) -> 0 | AV83: Ok | AW83: =IFERROR(VLOOKUP(G83,'[70]Detail Deprec_202508'!$D$33:$I$357,6,FALSE),0) -> 0 | AX83: =AW83-AK83 -> 0
A84: =+A83+1 -> 59 | B84: CLC | C84: CLCWH | D84: 154 | E84: WH1 | F84: CLC134-017 | G84: MNE000219 | H84: 42885 | I84: Machinary and Equipment | J84: 15 | K84: Modification Eye Washer | L84: SMCC Utama | N84: 2017 | R84: 1 | T84: 180000000 | U84: =+T84/V84 -> 3000000 | V84: 60 | W84: 60 | X84: =+AC84/U84 -> 0 | Y84: =+W84+X84 -> 60 | Z84: =+V84-Y84 -> 0 | AA84: 180000000 | AB84: 0 | AC84: =SUM(AD84:AL84) -> 0 | AP84: =+AA84+AC84 -> 180000000 | AQ84: =IF(AS84=$AS$24,((T84-AP84)*0),T84-AP84) -> 0 | AV84: Ok | AW84: =IFERROR(VLOOKUP(G84,'[70]Detail Deprec_202508'!$D$33:$I$357,6,FALSE),0) -> 0 | AX84: =AW84-AK84 -> 0
A85: =+A84+1 -> 60 | B85: CLC | C85: CLCWH | D85: 154 | E85: OTHERS | F85: CLC-R-07 | G85: MNE000220 | H85: 42908 | I85: Machinary and Equipment | J85: 19 | K85: Nestainer and Joint Pallet | L85: Hanwa Indonesia | N85: 2017 | R85: 393 | T85: 417780000 | U85: =+T85/V85 -> 6963000 | V85: 60 | W85: 60 | X85: =+AC85/U85 -> 0 | Y85: =+W85+X85 -> 60 | Z85: =+V85-Y85 -> 0 | AA85: 417780000 | AB85: 0 | AC85: =SUM(AD85:AL85) -> 0 | AP85: =+AA85+AC85 -> 417780000 | AQ85: =IF(AS85=$AS$24,((T85-AP85)*0),T85-AP85) -> 0 | AV85: Ok | AW85: =IFERROR(VLOOKUP(G85,'[70]Detail Deprec_202508'!$D$33:$I$357,6,FALSE),0) -> 0 | AX85: =AW85-AK85 -> 0
A86: =+A85+1 -> 61 | B86: CLC | C86: CLCWH | D86: 154 | E86: OTHERS | F86: CLC-R-08 | G86: MNE000230 | H86: 43097 | I86: Machinary and Equipment | J86: 23 | K86: Nestainer Rack | L86: Hanwa Indonesia | N86: 2017 | R86: 454 | T86: 588744000 | U86: =+T86/V86 -> 9812400 | V86: 60 | W86: 60 | X86: =+AC86/U86 -> 0 | Y86: =+W86+X86 -> 60 | Z86: =+V86-Y86 -> 0 | AA86: 588744000 | AB86: 0 | AC86: =SUM(AD86:AL86) -> 0 | AP86: =+AA86+AC86 -> 588744000 | AQ86: =IF(AS86=$AS$24,((T86-AP86)*0),T86-AP86) -> 0 | AV86: Ok | AW86: =IFERROR(VLOOKUP(G86,'[70]Detail Deprec_202508'!$D$33:$I$357,6,FALSE),0) -> 0 | AX86: =AW86-AK86 -> 0
A87: =+A86+1 -> 62 | B87: CLC | C87: CLCWH | D87: 154 | E87: OTHERS | F87: CLC-R-09 | G87: MNE000233 | H87: 43158 | I87: Machinary and Equipment | J87: JKT_GL000856 | K87: Nestainer and Joint Pallet | L87: Hanwa Indonesia | N87: 2018 | R87: 848 | T87: 865600000 | U87: =+T87/V87 -> 14426667 | V87: 60 | W87: 60 | X87: =+AC87/U87 -> 0 | Y87: =+W87+X87 -> 60 | Z87: =+V87-Y87 -> 0 | AA87: 865600000 | AB87: 0 | AC87: =SUM(AD87:AL87) -> 0 | AP87: =+AA87+AC87 -> 865600000 | AQ87: =IF(AS87=$AS$24,((T87-AP87)*0),T87-AP87) -> 0 | AU87: Finish 28 Feb 23 | AV87: Ok | AW87: =IFERROR(VLOOKUP(G87,'[70]Detail Deprec_202508'!$D$33:$I$357,6,FALSE),0) -> 0 | AX87: =AW87-AK87 -> 0
A88: =+A87+1 -> 63 | B88: CLC | C88: CLCWH | D88: 154 | E88: OTHERS | F88: CLC134-066 | G88: MNE000236 | H88: 43220 | I88: Machinary and Equipment | K88: Container 40 Ft (Second) | L88: Wahana Bintang Transindo | N88: 2018 | R88: 1 | T88: 29500000 | U88: =+T88/V88 -> 819444.44 | V88: 36 | W88: 36 | X88: =+AC88/U88 -> 0 | Y88: =+W88+X88 -> 36 | Z88: =+V88-Y88 -> 0 | AA88: 29500000 | AB88: 3.7252903e-09 | AC88: =SUM(AD88:AL88) -> 0 | AP88: =+AA88+AC88 -> 29500000 | AQ88: =IF(AS88=$AS$24,((T88-AP88)*0),T88-AP88) -> 3.7252903e-09 | AV88: Ok | AW88: =IFERROR(VLOOKUP(G88,'[70]Detail Deprec_202508'!$D$33:$I$357,6,FALSE),0) -> 0 | AX88: =AW88-AK88 -> 0
A89: =+A88+1 -> 64 | B89: CLC | C89: CLCWH | D89: 154 | E89: OTHERS | F89: CLC134-067 | G89: MNE000237 | H89: 43220 | I89: Machinary and Equipment | K89: Container 40 Ft (Second) | L89: Wahana Bintang Transindo | N89: 2018 | R89: 1 | T89: 29500000 | U89: =+T89/V89 -> 819444.44 | V89: 36 | W89: 36 | X89: =+AC89/U89 -> 0 | Y89: =+W89+X89 -> 36 | Z89: =+V89-Y89 -> 0 | AA89: 29500000 | AB89: 3.7252903e-09 | AC89: =SUM(AD89:AL89) -> 0 | AP89: =+AA89+AC89 -> 29500000 | AQ89: =IF(AS89=$AS$24,((T89-AP89)*0),T89-AP89) -> 3.7252903e-09 | AV89: Ok | AW89: =IFERROR(VLOOKUP(G89,'[70]Detail Deprec_202508'!$D$33:$I$357,6,FALSE),0) -> 0 | AX89: =AW89-AK89 -> 0
A90: =+A89+1 -> 65 | B90: CLC | C90: CLCWH | D90: 154 | E90: OTHERS | F90: CLC134-068 | G90: MNE000238 | H90: 43220 | I90: Machinary and Equipment | K90: Container 40 Ft (Second) | L90: Wahana Bintang Transindo | N90: 2018 | R90: 1 | T90: 29500000 | U90: =+T90/V90 -> 819444.44 | V90: 36 | W90: 36 | X90: =+AC90/U90 -> 0 | Y90: =+W90+X90 -> 36 | Z90: =+V90-Y90 -> 0 | AA90: 29500000 | AB90: 3.7252903e-09 | AC90: =SUM(AD90:AL90) -> 0 | AP90: =+AA90+AC90 -> 29500000 | AQ90: =IF(AS90=$AS$24,((T90-AP90)*0),T90-AP90) -> 3.7252903e-09 | AV90: Ok | AW90: =IFERROR(VLOOKUP(G90,'[70]Detail Deprec_202508'!$D$33:$I$357,6,FALSE),0) -> 0 | AX90: =AW90-AK90 -> 0
A91: =+A90+1 -> 66 | B91: CLC | C91: CLCWH | D91: 154 | E91: OTHERS | F91: CLC134-069 | G91: MNE000239 | H91: 43220 | I91: Machinary and Equipment | K91: Container 40 Ft (Second) | L91: Wahana Bintang Transindo | N91: 2018 | R91: 1 | T91: 29500000 | U91: =+T91/V91 -> 819444.44 | V91: 36 | W91: 36 | X91: =+AC91/U91 -> 0 | Y91: =+W91+X91 -> 36 | Z91: =+V91-Y91 -> 0 | AA91: 29500000 | AB91: 3.7252903e-09 | AC91: =SUM(AD91:AL91) -> 0 | AP91: =+AA91+AC91 -> 29500000 | AQ91: =IF(AS91=$AS$24,((T91-AP91)*0),T91-AP91) -> 3.7252903e-09 | AV91: Ok | AW91: =IFERROR(VLOOKUP(G91,'[70]Detail Deprec_202508'!$D$33:$I$357,6,FALSE),0) -> 0 | AX91: =AW91-AK91 -> 0
A92: =+A91+1 -> 67 | B92: CLC | C92: CLCWH | D92: 154 | E92: OTHERS | F92: CLC-R-10 | G92: MNE000243 | H92: 43343 | I92: Machinary and Equipment | J92: JKT_GL003844 | K92: Nestainer and Joint Pallet | L92: Hanwa Indonesia | N92: 2018 | R92: 701 | T92: 847200000 | U92: =+T92/V92 -> 14120000 | V92: 60 | W92: 60 | X92: =+AC92/U92 -> 0 | Y92: =+W92+X92 -> 60 | Z92: =+V92-Y92 -> 0 | AA92: 847200000 | AB92: 0 | AC92: =SUM(AD92:AL92) -> 0 | AP92: =+AA92+AC92 -> 847200000 | AQ92: =IF(AS92=$AS$24,((T92-AP92)*0),T92-AP92) -> 0 | AV92: Ok | AW92: =IFERROR(VLOOKUP(G92,'[70]Detail Deprec_202508'!$D$33:$I$357,6,FALSE),0) -> 0 | AX92: =AW92-AK92 -> 0
A93: =+A92+1 -> 68 | B93: CLC | C93: CLCWH | D93: 154 | E93: OTHERS | F93: CLC-R-11 | G93: MNE000244 | H93: 43343 | I93: Machinary and Equipment | J93: JKT_GL003850 | K93: Nestainer and Joint Pallet | L93: Hanwa Indonesia | N93: 2018 | R93: 255 | T93: 636750000 | U93: =+T93/V93 -> 10612500 | V93: 60 | W93: 60 | X93: =+AC93/U93 -> 0 | Y93: =+W93+X93 -> 60 | Z93: =+V93-Y93 -> 0 | AA93: 636750000 | AB93: 0 | AC93: =SUM(AD93:AL93) -> 0 | AP93: =+AA93+AC93 -> 636750000 | AQ93: =IF(AS93=$AS$24,((T93-AP93)*0),T93-AP93) -> 0 | AV93: Ok | AW93: =IFERROR(VLOOKUP(G93,'[70]Detail Deprec_202508'!$D$33:$I$357,6,FALSE),0) -> 0 | AX93: =AW93-AK93 -> 0
A94: =+A93+1 -> 69 | B94: CLC_SBY | C94: CLCWH | D94: 154 | E94: SBY | F94: CLC134-018 | G94: MNE000251 | H94: 43370 | I94: Machinary and Equipment | J94: JKT_GL004318 | K94: Fire Alarm System at Surabaya | L94: Panca Jaya Kencana | M94: Surabaya | N94: 2018 | R94: 1 | T94: 70726150 | U94: =+T94/V94 -> 1178769.2 | V94: 60 | W94: 60 | X94: =+AC94/U94 -> 0 | Y94: =+W94+X94 -> 60 | Z94: =+V94-Y94 -> 0 | AA94: 70726150 | AB94: 0 | AC94: =SUM(AD94:AL94) -> 0 | AP94: =+AA94+AC94 -> 70726150 | AQ94: =IF(AS94=$AS$24,((T94-AP94)*0),T94-AP94) -> 0 | AV94: Ok | AW94: =IFERROR(VLOOKUP(G94,'[70]Detail Deprec_202508'!$D$33:$I$357,6,FALSE),0) -> 0 | AX94: =AW94-AK94 -> 0
A95: =+A94+1 -> 70 | B95: CLC_SBY | C95: CLCWH | D95: 154 | E95: SBY | F95: CLC134-019 | G95: MNE000250 | H95: 43370 | I95: Machinary and Equipment | J95: JKT_GL004318 | K95: CCTV Warehouse at Surabaya | L95: Panca Jaya Kencana | M95: Surabaya | N95: 2018 | R95: 1 | T95: 32227800 | U95: =+T95/V95 -> 537130 | V95: 60 | W95: 60 | X95: =+AC95/U95 -> 0 | Y95: =+W95+X95 -> 60 | Z95: =+V95-Y95 -> 0 | AA95: 32227800 | AB95: 0 | AC95: =SUM(AD95:AL95) -> 0 | AP95: =+AA95+AC95 -> 32227800 | AQ95: =IF(AS95=$AS$24,((T95-AP95)*0),T95-AP95) -> 0 | AV95: Ok | AW95: =IFERROR(VLOOKUP(G95,'[70]Detail Deprec_202508'!$D$33:$I$357,6,FALSE),0) -> 0 | AX95: =AW95-AK95 -> 0
A96: =+A95+1 -> 71 | B96: CLC_SBY | C96: CLCWH | D96: 154 | E96: SBY | F96: CLC134-020 | G96: MNE000249 | H96: 43370 | I96: Machinary and Equipment | J96: JKT_GL004318 | K96: Fire Alarm (Smoke Detector) at Surabaya | L96: Panca Jaya Kencana | M96: Surabaya | N96: 2018 | R96: 1 | T96: 228315940 | U96: =+T96/V96 -> 3805265.7 | V96: 60 | W96: 60 | X96: =+AC96/U96 -> 0 | Y96: =+W96+X96 -> 60 | Z96: =+V96-Y96 -> 0 | AA96: 228315940 | AB96: 0 | AC96: =SUM(AD96:AL96) -> 0 | AP96: =+AA96+AC96 -> 228315940 | AQ96: =IF(AS96=$AS$24,((T96-AP96)*0),T96-AP96) -> 0 | AV96: Ok | AW96: =IFERROR(VLOOKUP(G96,'[70]Detail Deprec_202508'!$D$33:$I$357,6,FALSE),0) -> 0 | AX96: =AW96-AK96 -> 0
A97: =+A96+1 -> 72 | B97: CLC | C97: CLCWH | D97: 154 | E97: OTHERS | F97: CLC-R-13 | G97: MNE000290 | H97: 44027 | I97: Machinary and Equipment | J97: JKT_GL012307 | K97: Nestainer | L97: Hanwa Indonesia | N97: 2020 | O97: 344 Unit | P97: 182 Rack Nestainer | Q97: 162 Joint Pallet | R97: 344 | T97: 412700000 | U97: =+T97/V97 -> 6878333.3 | V97: 60 | W97: 54 | X97: =+AC97/U97 -> 6 | Y97: =+W97+X97 -> 60 | Z97: =+V97-Y97 -> 0 | AA97: 371430000 | AB97: 41270000 | AC97: =SUM(AD97:AO97) -> 41270000 | AD97: 6878333.3 | AE97: 6878333.3 | AF97: 6878333.3 | AG97: 6878333.3 | AH97: 6878333.3 | AI97: 6878333.3 | AP97: =+AA97+AC97 -> 412700000 | AQ97: =IF(AS97=$AS$24,((T97-AP97)*0),T97-AP97) -> 0 | AV97: Ok | AW97: =IFERROR(VLOOKUP(G97,'[70]Detail Deprec_202508'!$D$33:$I$357,6,FALSE),0) -> 0 | AX97: =AW97-AK97 -> 0
A98: =+A97+1 -> 73 | B98: CLC | C98: CLCWH | D98: 154 | E98: OTHERS | F98: CLC133-025 | G98: MNE000292 | H98: 44042 | I98: Machinary and Equipment | J98: JKT_GL012424 | K98: Stand Baterry | L98: Jakarta Construction | N98: 2020 | O98: 1 Unit | R98: 1 | T98: 35180636 | U98: =+T98/V98 -> 586343.93 | V98: 60 | W98: 60 | X98: =+AC98/U98 -> 0 | Y98: =+W98+X98 -> 60 | Z98: =+V98-Y98 -> 0 | AA98: 35180636 | AB98: -7.4505806e-09 | AC98: =SUM(AD98:AL98) -> 0 | AP98: =+AA98+AC98 -> 35180636 | AQ98: =IF(AS98=$AS$24,((T98-AP98)*0),T98-AP98) -> -7.4505806e-09 | AV98: Ok | AW98: =IFERROR(VLOOKUP(G98,'[70]Detail Deprec_202508'!$D$33:$I$357,6,FALSE),0) -> 0 | AX98: =AW98-AK98 -> 0
A99: =+A98+1 -> 74 | B99: CLC | C99: CLCWH | D99: 154 | E99: OTHERS | F99: CLC-R-12 | G99: MNE000298 | H99: 44286 | I99: Machinary and Equipment | J99: JKT_GL014337 | K99: Nistainer | L99: JKTC | N99: 2021 | O99: 905 Unit | P99: L1190xW1250xH1250 | Q99: W 1250 (L1250) | R99: 905 | T99: 1487754320 | U99: =+T99/V99 -> 24795905 | V99: 60 | W99: 46 | X99: =+AC99/U99 -> 12 | Y99: =+W99+X99 -> 58 | Z99: =+V99-Y99 -> 2 | AA99: 1.1406116e+09 | AB99: 3.4714267e+08 | AC99: =SUM(AD99:AO99) -> 297550864 | AD99: 24795905 | AE99: 24795905 | AF99: 24795905 | AG99: 24795905 | AH99: 24795905 | AI99: 24795905 | AJ99: 24795905 | AK99: 24795905 | AL99: 24795905 | AM99: 24795905 | AN99: 24795905 | AO99: 24795905 | AP99: =+AA99+AC99 -> 1.4381625e+09 | AQ99: =IF(AS99=$AS$24,((T99-AP99)*0),T99-AP99) -> 49591811 | AU99: 44286 | AV99: Ok | AW99: =IFERROR(VLOOKUP(G99,'[70]Detail Deprec_202508'!$D$33:$I$357,6,FALSE),0) -> 24795905 | AX99: =AW99-AK99 -> -0.0033333339
A100: =+A99+1 -> 75 | B100: CLC | C100: CLCWH | D100: 154 | E100: OTHERS | F100: CLC-R-14 | G100: MNE000315 | H100: 44957 | I100: Machinary and Equipment | J100: JKTGL_019643 | K100: Racking System | L100: Jakarta Construction | M100: 445 Set | N100: 2023 | O100: Nestainer 227 Set | P100: Join 218 Set | R100: 445 | T100: 929200000 | U100: =+T100/V100 -> 15486667 | V100: 60 | W100: 24 | X100: =+AC100/U100 -> 12 | Y100: =+W100+X100 -> 36 | Z100: =+V100-Y100 -> 24 | AA100: 3.7168e+08 | AB100: 557520000 | AC100: =SUM(AD100:AO100) -> 1.8584e+08 | AD100: 15486667 | AE100: 15486667 | AF100: 15486667 | AG100: 15486667 | AH100: 15486667 | AI100: 15486667 | AJ100: 15486667 | AK100: 15486667 | AL100: 15486667 | AM100: 15486667 | AN100: 15486667 | AO100: 15486667 | AP100: =+AA100+AC100 -> 5.5752e+08 | AQ100: =IF(AS100=$AS$24,((T100-AP100)*0),T100-AP100) -> 3.7168e+08 | AU100: 44925 | AV100: Ok | AW100: =IFERROR(VLOOKUP(G100,'[70]Detail Deprec_202508'!$D$33:$I$357,6,FALSE),0) -> 15486667 | AX100: =AW100-AK100 -> 0.0033333339
A101: =+A100+1 -> 76 | B101: CLC | C101: CLCOWH | D101: 154 | E101: BALI | F101: CLC134-071 | G101: MNE000332 | H101: 45838 | I101: Machinary and Equipment | K101: Loading/Unloading Ramping System | L101: Indotara | M101: 10 T | N101: 2025 | O101: PTR10WM/10T | P101: A825-138 | Q101: DHE-809-80 | R101: 1 | T101: 145223481 | U101: =+T101/V101 -> 4033985.6 | V101: 36 | W101: 0 | X101: =+AC101/U101 -> 7 | Y101: =+W101+X101 -> 7 | Z101: =+V101-Y101 -> 29 | AC101: =SUM(AD101:AO101) -> 28237899 | AI101: 4033985.6 | AJ101: 4033985.6 | AK101: 4033985.6 | AL101: 4033985.6 | AM101: 4033985.6 | AN101: 4033985.6 | AO101: 4033985.6 | AP101: =+AA101+AC101 -> 28237899 | AQ101: =IF(AS101=$AS$24,((T101-AP101)*0),T101-AP101) -> 1.1698558e+08 | AR101: Additional | AV101: OK | AW101: =IFERROR(VLOOKUP(G101,'[70]Detail Deprec_202508'!$D$33:$I$357,6,FALSE),0) -> 4033985.6 | AX101: =AW101-AK101 -> -0.023333333
A102: =+A101+1 -> 77 | B102: CLC | C102: CLCTRP | D102: 155 | E102: TRP | F102: TG-C-015 | G102: VEH000067 | H102: 38541 | I102: Vehicles | J102: 8006 | K102: Head Trucktor | L102: Nissan Diesel | M102: 26T | N102: 2005 | O102: A 9174 RM | P102: PE6195714T | Q102: MHPWM432H5K000005 | R102: 1 | T102: 505454546 | U102: =+T102/V102 -> 8424242.4 | V102: 60 | W102: 60 | X102: =+AC102/U102 -> 0 | Y102: =+W102+X102 -> 60 | Z102: =+V102-Y102 -> 0 | AA102: 505454546 | AB102: 0 | AC102: =SUM(AD102:AL102) -> 0 | AP102: =+AA102+AC102 -> 505454546 | AQ102: =IF(AS102=$AS$24,((T102-AP102)*0),T102-AP102) -> 0 | AS102: Disposals | AU102: 45838 | AV102: Ok | AW102: =IFERROR(VLOOKUP(G102,'[71]Detail Deprec_202501'!$D$246:$I$393,6,FALSE),0) -> 0 | AX102: =AW102-AK102 -> 0
A103: =+A102+1 -> 78 | B103: CLC | C103: CLCTRP | D103: 155 | E103: TRP | F103: TG-C-014 | G103: VEH000068 | H103: 38541 | I103: Vehicles | J103: 8006 | K103: Head Trucktor | L103: Nissan Diesel | M103: 25T | N103: 2005 | O103: A 9173 RM | P103: PE6195713T | Q103: MHPWM432H5K000004 | R103: 1 | T103: 505454546 | U103: =+T103/V103 -> 8424242.4 | V103: 60 | W103: 60 | X103: =+AC103/U103 -> 0 | Y103: =+W103+X103 -> 60 | Z103: =+V103-Y103 -> 0 | AA103: 505454546 | AB103: 0 | AC103: =SUM(AD103:AL103) -> 0 | AP103: =+AA103+AC103 -> 505454546 | AQ103: =IF(AS103=$AS$24,((T103-AP103)*0),T103-AP103) -> 0 | AS103: Disposals | AU103: 45838 | AV103: Ok | AW103: =IFERROR(VLOOKUP(G103,'[71]Detail Deprec_202501'!$D$246:$I$393,6,FALSE),0) -> 0 | AX103: =AW103-AK103 -> 0
...

Sheet FA_2026
A1: PT. SANKYU INDONESIA INTERNATIONAL
A2: LIST OF FIXED ASSETS AND DEPRECIATION SCHEDULE
A3: 46387
F5: CATEGORY | G5: JANUARY | H5: FEBRUARY | I5: MARCH | J5: APRIL | K5: MAY | L5: JUNE | M5: JULY | N5: AUGUST | O5: SEPTEMBER | P5: OCTOBER | Q5: NOVEMBER | R5: DECEMBER | S5: TOTAL/YEAR
E6: Warehouse 1 | F6: WH1 | G6: =SUMIF($E$25:$E$281,F6,$AD$25:$AD$281) -> 3.034665e+08 | H6: =SUMIF($E$25:$E$282,F6,$AE$25:$AE$282) -> 3.034665e+08 | I6: =SUMIF($E$25:$E$282,F6,$AF$25:$AF$282) -> 3.034665e+08 | J6: =SUMIF($E$25:$E$282,F6,$AG$25:$AG$282) -> 3.034665e+08 | K6: =SUMIF($E$25:$E$282,F6,$AH$25:$AH$282) -> 3.034665e+08 | L6: =SUMIF($E$25:$E$282,F6,$AI$25:$AI$281) -> 3.034665e+08 | M6: =SUMIF($E$25:$E$282,F6,$AJ$25:$AJ$282) -> 3.034665e+08 | N6: =SUMIF($E$25:$E$281,F6,$AK$25:$AK$281) -> 3.034665e+08 | O6: =SUMIF($E$25:$E$281,F6,$AL$25:$AL$281) -> 3.034665e+08 | P6: =SUMIF($E$25:$E$281,F6,$AM$25:$AM$281) -> 3.034665e+08 | Q6: =SUMIF($E$25:$E$281,F6,$AN$25:$AN$281) -> 3.034665e+08 | R6: =SUMIF($E$25:$E$281,F6,$AO$25:$AO$281) -> 3.034665e+08 | S6: =SUM(G6:R6) -> 3.641598e+09
E7: Warehouse 2 | F7: WH2 | G7: =SUMIF($E$25:$E$281,F7,$AD$25:$AD$281) -> 6.5201362e+08 | H7: =SUMIF($E$25:$E$281,F7,$AE$25:$AE$281) -> 6.5201362e+08 | I7: =SUMIF($E$25:$E$281,F7,$AF$25:$AF$281) -> 6.5201362e+08 | J7: =SUMIF($E$25:$E$281,F7,$AG$25:$AG$281) -> 6.5201362e+08 | K7: =SUMIF($E$25:$E$281,F7,$AH$25:$AH$281) -> 6.5201362e+08 | L7: =SUMIF($E$25:$E$281,F7,$AI$25:$AI$281) -> 6.5201362e+08 | M7: =SUMIF($E$25:$E$281,F7,$AJ$25:$AJ$281) -> 6.5201362e+08 | N7: =SUMIF($E$25:$E$281,F7,$AK$25:$AK$281) -> 6.5201362e+08 | O7: =SUMIF($E$25:$E$281,F7,$AL$25:$AL$281) -> 6.5201362e+08 | P7: =SUMIF($E$25:$E$281,F7,$AM$25:$AM$281) -> 6.5201362e+08 | Q7: =SUMIF($E$25:$E$281,F7,$AN$25:$AN$281) -> 6.5201362e+08 | R7: =SUMIF($E$25:$E$281,F7,$AO$25:$AO$281) -> 6.5201362e+08 | S7: =SUM(G7:R7) -> 7.8241634e+09
E8: Transport | F8: TRP | G8: =SUMIF($E$25:$E$282,F8,$AD$25:$AD$281) -> 67290240 | H8: =SUMIF($E$25:$E$282,F8,$AE$25:$AE$281) -> 67290240 | I8: =SUMIF($E$25:$E$281,F8,$AF$25:$AF$282) -> 67290240 | J8: =SUMIF($E$25:$E$281,F8,$AG$25:$AG$281) -> 67290240 | K8: =SUMIF($E$25:$E$281,F8,$AH$25:$AH$281) -> 67290240 | L8: =SUMIF($E$25:$E$281,F8,$AI$25:$AI$281) -> 67290240 | M8: =SUMIF($E$25:$E$281,F8,$AJ$25:$AJ$281) -> 67290240 | N8: =SUMIF($E$25:$E$281,F8,$AK$25:$AK$281) -> 67290240 | O8: =SUMIF($E$25:$E$281,F8,$AL$25:$AL$281) -> 67290240 | P8: =SUMIF($E$25:$E$281,F8,$AM$25:$AM$281) -> 67290240 | Q8: =SUMIF($E$25:$E$281,F8,$AN$25:$AN$281) -> 67290240 | R8: =SUMIF($E$25:$E$281,F8,$AO$25:$AO$281) -> 67290240 | S8: =SUM(G8:R8) -> 8.0748288e+08
E9: Bali | F9: BALI | G9: =SUMIF($E$25:$E$282,F9,$AD$25:$AD$281) -> 1.1998584e+08 | H9: =SUMIF($E$25:$E$282,F9,$AE$25:$AE$281) -> 1.1998584e+08 | I9: =SUMIF($E$25:$E$281,F9,$AF$25:$AF$282) -> 1.1998584e+08 | J9: =SUMIF($E$25:$E$281,F9,$AG$25:$AG$281) -> 1.1998584e+08 | K9: =SUMIF($E$25:$E$281,F9,$AH$25:$AH$281) -> 1.1998584e+08 | L9: =SUMIF($E$25:$E$281,F9,$AI$25:$AI$281) -> 1.1998584e+08 | M9: =SUMIF($E$25:$E$281,F9,$AJ$25:$AJ$281) -> 1.1998584e+08 | N9: =SUMIF($E$25:$E$281,F9,$AK$25:$AK$281) -> 1.1998584e+08 | O9: =SUMIF($E$25:$E$281,F9,$AL$25:$AL$281) -> 1.1998584e+08 | P9: =SUMIF($E$25:$E$281,F9,$AM$25:$AM$281) -> 1.1998584e+08 | Q9: =SUMIF($E$25:$E$281,F9,$AN$25:$AN$281) -> 1.1998584e+08 | R9: =SUMIF($E$25:$E$281,F9,$AO$25:$AO$281) -> 1.1998584e+08 | S9: =SUM(G9:R9) -> 1439830051
E10: Medan | F10: MDN | G10: =SUMIF($E$25:$E$282,F10,$AD$25:$AD$281) -> 0 | H10: =SUMIF($E$25:$E$282,F10,$AE$25:$AE$281) -> 0 | I10: =SUMIF($E$25:$E$281,F10,$AF$25:$AF$282) -> 0 | J10: =SUMIF($E$25:$E$281,F10,$AG$25:$AG$281) -> 0 | K10: =SUMIF($E$25:$E$281,F10,$AH$25:$AH$281) -> 0 | L10: =SUMIF($E$25:$E$281,F10,$AI$25:$AI$281) -> 0 | M10: =SUMIF($E$25:$E$281,F10,$AJ$25:$AJ$281) -> 0 | N10: =SUMIF($E$25:$E$281,F10,$AK$25:$AK$281) -> 0 | O10: =SUMIF($E$25:$E$281,F10,$AL$25:$AL$281) -> 0 | P10: =SUMIF($E$25:$E$281,F10,$AM$25:$AM$281) -> 0 | Q10: =SUMIF($E$25:$E$281,F10,$AN$25:$AN$281) -> 0 | R10: =SUMIF($E$25:$E$281,F10,$AO$25:$AO$281) -> 0 | S10: =SUM(G10:R10) -> 0
E11: Palembang | F11: PBG | G11: =SUMIF($E$25:$E$282,F11,$AD$25:$AD$281) -> 13333333 | H11: =SUMIF($E$25:$E$282,F11,$AE$25:$AE$281) -> 13333333 | I11: =SUMIF($E$25:$E$281,F11,$AF$25:$AF$282) -> 13333333 | J11: =SUMIF($E$25:$E$281,F11,$AG$25:$AG$281) -> 13333333 | K11: =SUMIF($E$25:$E$281,F11,$AH$25:$AH$281) -> 0 | L11: =SUMIF($E$25:$E$281,F11,$AI$25:$AI$281) -> 0 | M11: =SUMIF($E$25:$E$281,F11,$AJ$25:$AJ$281) -> 0 | N11: =SUMIF($E$25:$E$281,F11,$AK$25:$AK$281) -> 0 | O11: =SUMIF($E$25:$E$281,F11,$AL$25:$AL$281) -> 0 | P11: =SUMIF($E$25:$E$281,F11,$AM$25:$AM$281) -> 0 | Q11: =SUMIF($E$25:$E$281,F11,$AN$25:$AN$281) -> 0 | R11: =SUMIF($E$25:$E$281,F11,$AO$25:$AO$281) -> 0 | S11: =SUM(G11:R11) -> 53333332
E12: Makassar | F12: MKS | G12: =SUMIF($E$25:$E$282,F12,$AD$25:$AD$281) -> 0 | H12: =SUMIF($E$25:$E$282,F12,$AE$25:$AE$281) -> 0 | I12: =SUMIF($E$25:$E$281,F12,$AF$25:$AF$282) -> 0 | J12: =SUMIF($E$25:$E$281,F12,$AG$25:$AG$281) -> 0 | K12: =SUMIF($E$25:$E$281,F12,$AH$25:$AH$281) -> 0 | L12: =SUMIF($E$25:$E$281,F12,$AI$25:$AI$281) -> 0 | M12: =SUMIF($E$25:$E$281,F12,$AJ$25:$AJ$281) -> 0 | N12: =SUMIF($E$25:$E$281,F12,$AK$25:$AK$281) -> 0 | O12: =SUMIF($E$25:$E$281,F12,$AL$25:$AL$281) -> 0 | P12: =SUMIF($E$25:$E$281,F12,$AM$25:$AM$281) -> 0 | Q12: =SUMIF($E$25:$E$281,F12,$AN$25:$AN$281) -> 0 | R12: =SUMIF($E$25:$E$281,F12,$AO$25:$AO$281) -> 0 | S12: =SUM(G12:R12) -> 0
E13: Surabaya | F13: SBY | G13: =SUMIF($E$25:$E$282,F13,$AD$25:$AD$281) -> 0 | H13: =SUMIF($E$25:$E$282,F13,$AE$25:$AE$281) -> 0 | I13: =SUMIF($E$25:$E$281,F13,$AF$25:$AF$282) -> 0 | J13: =SUMIF($E$25:$E$281,F13,$AG$25:$AG$281) -> 0 | K13: =SUMIF($E$25:$E$281,F13,$AH$25:$AH$281) -> 0 | L13: =SUMIF($E$25:$E$281,F13,$AI$25:$AI$281) -> 0 | M13: =SUMIF($E$25:$E$281,F13,$AJ$25:$AJ$281) -> 0 | N13: =SUMIF($E$25:$E$281,F13,$AK$25:$AK$281) -> 0 | O13: =SUMIF($E$25:$E$281,F13,$AL$25:$AL$281) -> 0 | P13: =SUMIF($E$25:$E$281,F13,$AM$25:$AM$281) -> 0 | Q13: =SUMIF($E$25:$E$281,F13,$AN$25:$AN$281) -> 0 | R13: =SUMIF($E$25:$E$281,F13,$AO$25:$AO$281) -> 0 | S13: =SUM(G13:R13) -> 0
E14: Forklift, Shuttle Car, Equipment, Nestainer Rack | F14: OTHERS | G14: =SUMIF($E$25:$E$282,F14,$AD$25:$AD$281) -> 1.1746952e+08 | H14: =SUMIF($E$25:$E$282,F14,$AE$25:$AE$281) -> 1.1746952e+08 | I14: =SUMIF($E$25:$E$281,F14,$AF$25:$AF$282) -> 1.1650695e+08 | J14: =SUMIF($E$25:$E$281,F14,$AG$25:$AG$281) -> 1.1650695e+08 | K14: =SUMIF($E$25:$E$281,F14,$AH$25:$AH$281) -> 1.1617695e+08 | L14: =SUMIF($E$25:$E$281,F14,$AI$25:$AI$281) -> 1.1056028e+08 | M14: =SUMIF($E$25:$E$281,F14,$AJ$25:$AJ$281) -> 1.1056028e+08 | N14: =SUMIF($E$25:$E$281,F14,$AK$25:$AK$281) -> 1.1056028e+08 | O14: =SUMIF($E$25:$E$281,F14,$AL$25:$AL$281) -> 1.1056028e+08 | P14: =SUMIF($E$25:$E$281,F14,$AM$25:$AM$281) -> 1.1056028e+08 | Q14: =SUMIF($E$25:$E$281,F14,$AN$25:$AN$281) -> 1.1056028e+08 | R14: =SUMIF($E$25:$E$281,F14,$AO$25:$AO$281) -> 1.1056028e+08 | S14: =SUM(G14:R14) -> 1.3580519e+09
G15: =SUBTOTAL(9,G6:G14) -> 1.273559e+09 | H15: =SUBTOTAL(9,H6:H14) -> 1.273559e+09 | I15: =SUBTOTAL(9,I6:I14) -> 1.2725965e+09 | J15: =SUBTOTAL(9,J6:J14) -> 1.2725965e+09 | K15: =SUBTOTAL(9,K6:K14) -> 1.2589331e+09 | L15: =SUBTOTAL(9,L6:L14) -> 1.2533165e+09 | M15: =SUBTOTAL(9,M6:M14) -> 1.2533165e+09 | N15: =SUBTOTAL(9,N6:N14) -> 1.2533165e+09 | ... S15: =SUBTOTAL(9,S6:S14) -> 1.512446e+10
F17: SITE | G17: JANUARY | H17: FEBRUARY | I17: MARCH | J17: APRIL | K17: MAY | L17: JUNE | M17: JULY | N17: AUGUST | O17: SEPTEMBER | P17: OCTOBER | Q17: NOVEMBER | R17: DECEMBER | S17: TOTAL/YEAR
F18: CLCWH | G18: =SUMIF($C$25:$C$281,F18,$AD$25:$AD$281) -> 1.0870496e+09 | H18: =SUMIF($C$25:$C$281,F18,$AE$25:$AE$281) -> 1.0870496e+09 | I18: =SUMIF($C$25:$C$281,F18,$AF$25:$AF$281) -> 1.0860871e+09 | J18: =SUMIF($C$25:$C$281,F18,$AG$25:$AG$281) -> 1.0860871e+09 | K18: =SUMIF($C$25:$C$281,F18,$AH$25:$AH$281) -> 1.0857571e+09 | L18: =SUMIF($C$25:$C$281,F18,$AI$25:$AI$281) -> 1.0801404e+09 | M18: =SUMIF($C$25:$C$281,F18,$AJ$25:$AJ$281) -> 1.0801404e+09 | N18: =SUMIF($C$25:$C$281,F18,$AK$25:$AK$281) -> 1.0801404e+09 | O18: =SUMIF($C$25:$C$281,F18,$AL$25:$AL$281) -> 1.0801404e+09 | P18: =SUMIF($C$25:$C$281,F18,$AM$25:$AM$281) -> 1.0801404e+09 | Q18: =SUMIF($C$25:$C$281,F18,$AN$25:$AN$281) -> 1.0801404e+09 | R18: =SUMIF($C$25:$C$281,F18,$AO$25:$AO$281) -> 1.0801404e+09 | S18: =SUM(G18:R18) -> 1.2993013e+10
F19: CLCOWH | G19: =SUMIF($C$25:$C$281,F19,$AD$25:$AD$281) -> 1.1921917e+08 | H19: =SUMIF($C$25:$C$281,F19,$AE$25:$AE$281) -> 1.1921917e+08 | I19: =SUMIF($C$25:$C$281,F19,$AF$25:$AF$281) -> 1.1921917e+08 | J19: =SUMIF($C$25:$C$281,F19,$AG$25:$AG$281) -> 1.1921917e+08 | K19: =SUMIF($C$25:$C$281,F19,$AH$25:$AH$281) -> 1.0588584e+08 | L19: =SUMIF($C$25:$C$281,F19,$AI$25:$AI$281) -> 1.0588584e+08 | M19: =SUMIF($C$25:$C$281,F19,$AJ$25:$AJ$281) -> 1.0588584e+08 | N19: =SUMIF($C$25:$C$281,F19,$AK$25:$AK$281) -> 1.0588584e+08 | O19: =SUMIF($C$25:$C$281,F19,$AL$25:$AL$281) -> 1.0588584e+08 | P19: =SUMIF($C$25:$C$281,F19,$AM$25:$AM$281) -> 1.0588584e+08 | Q19: =SUMIF($C$25:$C$281,F19,$AN$25:$AN$281) -> 1.0588584e+08 | R19: =SUMIF($C$25:$C$281,F19,$AO$25:$AO$281) -> 1.0588584e+08 | S19: =SUM(G19:R19) -> 1323963383
F20: CLCTRP | G20: =SUMIF($C$25:$C$281,F20,$AD$25:$AD$281) -> 67290240 | H20: =SUMIF($C$25:$C$281,F20,$AE$25:$AE$281) -> 67290240 | I20: =SUMIF($C$25:$C$281,F20,$AF$25:$AF$281) -> 67290240 | J20: =SUMIF($C$25:$C$281,F20,$AG$25:$AG$281) -> 67290240 | K20: =SUMIF($C$25:$C$281,F20,$AH$25:$AH$281) -> 67290240 | L20: =SUMIF($C$25:$C$281,F20,$AI$25:$AI$281) -> 67290240 | M20: =SUMIF($C$25:$C$281,F20,$AJ$25:$AJ$281) -> 67290240 | N20: =SUMIF($C$25:$C$281,F20,$AK$25:$AK$281) -> 67290240 | O20: =SUMIF($C$25:$C$281,F20,$AL$25:$AL$281) -> 67290240 | P20: =SUMIF($C$25:$C$281,F20,$AM$25:$AM$281) -> 67290240 | Q20: =SUMIF($C$25:$C$281,F20,$AN$25:$AN$281) -> 67290240 | R20: =SUMIF($C$25:$C$281,F20,$AO$25:$AO$281) -> 67290240 | S20: =SUM(G20:R20) -> 8.0748288e+08
G21: =SUM(G18:G20) -> 1.273559e+09 | H21: =SUM(H18:H20) -> 1.273559e+09 | I21: =SUM(I18:I20) -> 1.2725965e+09 | J21: =SUM(J18:J20) -> 1.2725965e+09 | K21: =SUM(K18:K20) -> 1.2589331e+09 | L21: =SUM(L18:L20) -> 1.2533165e+09 | M21: =SUM(M18:M20) -> 1.2533165e+09 | N21: =SUM(N18:N20) -> 1.2533165e+09 | ... S21: =SUM(S18:S20) -> 1.512446e+10
A23: No. | B23: Site/ Location | C23: Job | D23: Account | E23: Category | F23: Asset | G23: Fixed asset number | H23: Purchase Date | I23: Group | J23: Voucher | K23: Name of Fixed Asset | L23: Maker/Type/Location | M23: Capacity/Size/User | N23: Year | O23: Police | P23: Machine | Q23: Chasis | R23: Quantity | S23: Valas | T23: Purchase Price | U23: Monthly Depreciation | V23: Depreciation Period | AA23: Accumulated Depreciation | AB23: Net Book Value | AC23: Depreciation Expense Current | AD23: DEPRECIATION 2026 ( MONTHLY ) | AP23: Accumulated Depreciation | AQ23: Net Book Value | AR23: Status | AT23: Acquisition | AU23: Remark | AV23: Photo Status | AX23: Checker Name ( A ) | AZ23: Existing ( B ) | BB23: If Yes (Existing) ( C ) | BD23: If Not Used ( D ) | BF23: Sticker ( E )
D24: No. | F24: No. | G24: AX | J24: No. | O24: No. | P24: No. | Q24: No. | V24: Total | W24: Acc. 2025 | X24: Yearly 2026 | Y24: Until 2026 | Z24: Remain > 2027 | AA24: 46022 | AB24: 46022 | AC24: =+A3 -> 46387 | AD24: Jan | AE24: Feb | AF24: Mar | AG24: Apr | AH24: May | AI24: Jun | AJ24: Jul | AK24: Aug | AL24: Sep | AM24: Oct | AN24: Nov | AO24: Dec | AP24: =A3 -> 46387 | AQ24: =+AP24 -> 46387 | AR24: Additional | AS24: Disposals | AT24: Condition | AX24: Site | AY24: HO | AZ24: Yes | BA24: No | BB24: Still Used | BC24: Not Used | BD24: Repair | BE24: Disposals | BF24: Good | BG24: Bad
T25: a | U25: b=a:c | V25: c | W25: d=h:b | X25: e=j:b | Y25: f=d+e | Z25: g=c-f | AA25: l=h+j | AB25: m=a-l | AC25: j=total k (jAC-des) | AD25: k | AE25: k | AF25: k | AG25: k | AH25: k | AI25: k | AJ25: k | AK25: k | AL25: k | AM25: k | AN25: k | AO25: k | AP25: l=h+j | AQ25: m=a-l | AW25: Check
A26: 1 | B26: CLC | C26: CLCWH | D26: 152 | E26: WH1 | F26: CLC131-001 | G26: BLD000048 | H26: 41639 | I26: Building | J26: 111 | K26: Cikarang Warehouse and Office | L26: Kawasan Industri Terpadu Indonesia China (KITIC) Kav. 20, Cikarang, West Java | M26: Head Ofice & Cikarang Logistic | N26: 2013 | R26: 1 | T26: 7.1701319e+10 | U26: =+T26/V26 -> 2.987555e+08 | V26: 240 | W26: =133+12 -> 145 | X26: =+AC26/U26 -> 12 | Y26: =+W26+X26 -> 157 | Z26: =+V26-Y26 -> 83 | AA26: 4.3319547e+10 | AB26: 2.8381772e+10 | AC26: =SUM(AD26:AO26) -> 3.585066e+09 | AD26: 2.987555e+08 | AE26: 2.987555e+08 | AF26: 2.987555e+08 | AG26: 2.987555e+08 | AH26: 2.987555e+08 | AI26: 2.987555e+08 | AJ26: 2.987555e+08 | AK26: 2.987555e+08 | AL26: 2.987555e+08 | AM26: 2.987555e+08 | AN26: 2.987555e+08 | AO26: 2.987555e+08 | AP26: =+AA26+AC26 -> 4.6904613e+10 | AQ26: =IF(AS26=$AS$24,((T26-AP26)*0),T26-AP26) -> 2.4796706e+10 | AV26: Ok | AW26: =IFERROR(VLOOKUP(G26,'[70]Detail Deprec_202508'!$D$33:$I$357,6,FALSE),0) -> 2.987555e+08 | AX26: =AW26-AK26 -> 0.00058341026
A27: 2 | B27: CLC | C27: CLCWH | D27: 152 | E27: WH2 | F27: CLC131-004 | G27: BLD000063 | H27: 42398 | I27: Building | J27: 84 | K27: IMB Tax Warehouse Phase II | L27: Kawasan Industri Terpadu Indonesia China (KITIC) Kav. 20, Cikarang, West Java | M27: Cikarang Logistic Center | N27: 2016 | R27: 1 | T27: 2061766435 | U27: =+T27/V27 -> 8590693.5 | V27: 240 | W27: =108+12 -> 120 | X27: =+AC27/U27 -> 12 | Y27: =+W27+X27 -> 132 | Z27: =+V27-Y27 -> 108 | AA27: 1.0308832e+09 | AB27: 1.0308832e+09 | AC27: =SUM(AD27:AO27) -> 1.0308832e+08 | AD27: 8590693.5 | AE27: 8590693.5 | AF27: 8590693.5 | AG27: 8590693.5 | AH27: 8590693.5 | AI27: 8590693.5 | AJ27: 8590693.5 | AK27: 8590693.5 | AL27: 8590693.5 | AM27: 8590693.5 | AN27: 8590693.5 | AO27: 8590693.5 | AP27: =+AA27+AC27 -> 1.1339715e+09 | AQ27: =IF(AS27=$AS$24,((T27-AP27)*0),T27-AP27) -> 9.277949e+08 | AV27: Ok | AW27: =IFERROR(VLOOKUP(G27,'[70]Detail Deprec_202508'!$D$33:$I$357,6,FALSE),0) -> 8590693.5 | AX27: =AW27-AK27 -> 0.0008333344
A28: 3 | B28: CLC | C28: CLCWH | D28: 152 | E28: WH2 | F28: CLC131-002 | G28: BLD000064 | H28: 42387 | I28: Building | J28: 05 | K28: Lobby & Office Phase 2 | L28: Kawasan Industri Terpadu Indonesia China (KITIC) Kav. 20, Cikarang, West Java | M28: Cikarang Logistic Center | N28: 2016 | R28: 1 | T28: 5000000000 | U28: =+T28/V28 -> 20833333 | V28: 240 | W28: =108+12 -> 120 | X28: =+AC28/U28 -> 12 | Y28: =+W28+X28 -> 132 | Z28: =+V28-Y28 -> 108 | AA28: 2.5e+09 | AB28: 2.5e+09 | AC28: =SUM(AD28:AO28) -> 2.5e+08 | AD28: 20833333 | AE28: 20833333 | AF28: 20833333 | AG28: 20833333 | AH28: 20833333 | AI28: 20833333 | AJ28: 20833333 | AK28: 20833333 | AL28: 20833333 | AM28: 20833333 | AN28: 20833333 | AO28: 20833333 | AP28: =+AA28+AC28 -> 2.75e+09 | AQ28: =IF(AS28=$AS$24,((T28-AP28)*0),T28-AP28) -> 2.25e+09 | AV28: Ok | AW28: =IFERROR(VLOOKUP(G28,'[70]Detail Deprec_202508'!$D$33:$I$357,6,FALSE),0) -> 20833333 | AX28: =AW28-AK28 -> -0.0033333339
A29: 4 | B29: CLC | C29: CLCWH | D29: 152 | E29: WH2 | F29: CLC131-002 | G29: BLD000065 | H29: 42387 | I29: Building | J29: 05 | K29: Warehouse Phase 2 Floor 2 | L29: Kawasan Industri Terpadu Indonesia China (KITIC) Kav. 20, Cikarang, West Java | M29: Cikarang Logistic Center | N29: 2016 | R29: 1 | T29: 44455000000 | U29: =+T29/V29 -> 1.8522917e+08 | V29: 240 | W29: =108+12 -> 120 | X29: =+AC29/U29 -> 12 | Y29: =+W29+X29 -> 132 | Z29: =+V29-Y29 -> 108 | AA29: 2.22275e+10 | AB29: 2.22275e+10 | AC29: =SUM(AD29:AO29) -> 2.22275e+09 | AD29: 1.8522917e+08 | AE29: 1.8522917e+08 | AF29: 1.8522917e+08 | AG29: 1.8522917e+08 | AH29: 1.8522917e+08 | AI29: 1.8522917e+08 | AJ29: 1.8522917e+08 | AK29: 1.8522917e+08 | AL29: 1.8522917e+08 | AM29: 1.8522917e+08 | AN29: 1.8522917e+08 | AO29: 1.8522917e+08 | AP29: =+AA29+AC29 -> 2.445025e+10 | AQ29: =IF(AS29=$AS$24,((T29-AP29)*0),T29-AP29) -> 2.000475e+10 | AV29: Ok | AW29: =IFERROR(VLOOKUP(G29,'[70]Detail Deprec_202508'!$D$33:$I$357,6,FALSE),0) -> 1.8522917e+08 | AX29: =AW29-AK29 -> 0.0033333302
A30: 5 | B30: CLC | C30: CLCWH | D30: 152 | E30: WH2 | F30: CLC131-002 | G30: BLD000066 | H30: 42387 | I30: Building | J30: 05 | K30: Warehouse Phase 2 Floor 1 | L30: Kawasan Industri Terpadu Indonesia China (KITIC) Kav. 20, Cikarang, West Java | M30: Cikarang Logistic Center | N30: 2016 | R30: 1 | T30: 49455000000 | U30: =+T30/V30 -> 206062500 | V30: 240 | W30: =108+12 -> 120 | X30: =+AC30/U30 -> 12 | Y30: =+W30+X30 -> 132 | Z30: =+V30-Y30 -> 108 | AA30: 24727500000 | AB30: 24727500000 | AC30: =SUM(AD30:AO30) -> 2472750000 | AD30: 206062500 | AE30: 206062500 | AF30: 206062500 | AG30: 206062500 | AH30: 206062500 | AI30: 206062500 | AJ30: 206062500 | AK30: 206062500 | AL30: 206062500 | AM30: 206062500 | AN30: 206062500 | AO30: 206062500 | AP30: =+AA30+AC30 -> 27200250000 | AQ30: =IF(AS30=$AS$24,((T30-AP30)*0),T30-AP30) -> 22254750000 | AV30: Ok | AW30: =IFERROR(VLOOKUP(G30,'[70]Detail Deprec_202508'!$D$33:$I$357,6,FALSE),0) -> 206062500 | AX30: =AW30-AK30 -> 0
A31: 6 | B31: CLC | C31: CLCWH | D31: 152 | E31: WH2 | F31: CLC131-002 | G31: BLD000067 | H31: 42387 | I31: Building | J31: 05 | K31: Cold Room Area Phase 2 | L31: Kawasan Industri Terpadu Indonesia China (KITIC) Kav. 20, Cikarang, West Java | M31: Cikarang Logistic Center | N31: 2016 | R31: 1 | T31: 35325000000 | U31: =+T31/V31 -> 147187500 | V31: 240 | W31: =108+12 -> 120 | X31: =+AC31/U31 -> 12 | Y31: =+W31+X31 -> 132 | Z31: =+V31-Y31 -> 108 | AA31: 17662500000 | AB31: 17662500000 | AC31: =SUM(AD31:AO31) -> 1766250000 | AD31: 147187500 | AE31: 147187500 | AF31: 147187500 | AG31: 147187500 | AH31: 147187500 | AI31: 147187500 | AJ31: 147187500 | AK31: 147187500 | AL31: 147187500 | AM31: 147187500 | AN31: 147187500 | AO31: 147187500 | AP31: =+AA31+AC31 -> 19428750000 | AQ31: =IF(AS31=$AS$24,((T31-AP31)*0),T31-AP31) -> 15896250000 | AV31: Ok | AW31: =IFERROR(VLOOKUP(G31,'[70]Detail Deprec_202508'!$D$33:$I$357,6,FALSE),0) -> 147187500 | AX31: =AW31-AK31 -> 0
A32: 7 | B32: CLC | C32: CLCWH | D32: 152 | E32: WH2 | F32: CLC131-002 | G32: BLD000068 | H32: 42387 | I32: Building | J32: 05 | K32: Cargo Lifter Phase 2 | L32: Kawasan Industri Terpadu Indonesia China (KITIC) Kav. 20, Cikarang, West Java | M32: Cikarang Logistic Center | N32: 2016 | R32: 1 | S32: 271320 | T32: 3375220800 | U32: =+T32/V32 -> 14063420 | V32: 240 | W32: =108+12 -> 120 | X32: =+AC32/U32 -> 12 | Y32: =+W32+X32 -> 132 | Z32: =+V32-Y32 -> 108 | AA32: 1687610400 | AB32: 1687610400 | AC32: =SUM(AD32:AO32) -> 168761040 | AD32: 14063420 | AE32: 14063420 | AF32: 14063420 | AG32: 14063420 | AH32: 14063420 | AI32: 14063420 | AJ32: 14063420 | AK32: 14063420 | AL32: 14063420 | AM32: 14063420 | AN32: 14063420 | AO32: 14063420 | AP32: =+AA32+AC32 -> 1856371440 | AQ32: =IF(AS32=$AS$24,((T32-AP32)*0),T32-AP32) -> 1518849360 | AV32: Ok | AW32: =IFERROR(VLOOKUP(G32,'[70]Detail Deprec_202508'!$D$33:$I$357,6,FALSE),0) -> 14063420 | AX32: =AW32-AK32 -> 0
A33: 8 | B33: CLC | C33: CLCWH | D33: 152 | E33: WH2 | F33: CLC131-003 | G33: BLD000069 | H33: 42387 | I33: Building | J33: 05 | K33: Cargo Lifter Phase 2 | L33: Kawasan Industri Terpadu Indonesia China (KITIC) Kav. 20, Cikarang, West Java | M33: Cikarang Logistic Center | N33: 2016 | R33: 1 | S33: 271320 | T33: 3549950880 | U33: =+T33/V33 -> 14791462 | V33: 240 | W33: =108+12 -> 120 | X33: =+AC33/U33 -> 12 | Y33: =+W33+X33 -> 132 | Z33: =+V33-Y33 -> 108 | AA33: 1774975440 | AB33: 1774975440 | AC33: =SUM(AD33:AO33) -> 177497544 | AD33: 14791462 | AE33: 14791462 | AF33: 14791462 | AG33: 14791462 | AH33: 14791462 | AI33: 14791462 | AJ33: 14791462 | AK33: 14791462 | AL33: 14791462 | AM33: 14791462 | AN33: 14791462 | AO33: 14791462 | AP33: =+AA33+AC33 -> 1952472984 | AQ33: =IF(AS33=$AS$24,((T33-AP33)*0),T33-AP33) -> 1597477896 | AV33: Ok | AW33: =IFERROR(VLOOKUP(G33,'[70]Detail Deprec_202508'!$D$33:$I$357,6,FALSE),0) -> 14791462 | AX33: =AW33-AK33 -> 0
A34: 9 | B34: CLC | C34: CLCWH | D34: 152 | E34: WH2 | F34: CLC131-003 | G34: BLD000070 | H34: 42387 | I34: Building | J34: 05 | K34: Canopy Area Phase 2 | L34: Kawasan Industri Terpadu Indonesia China (KITIC) Kav. 20, Cikarang, West Java | M34: Cikarang Logistic Center | N34: 2016 | R34: 1 | S34: 193800 | T34: 2612617800 | U34: =+T34/V34 -> 10885908 | V34: 240 | W34: =108+12 -> 120 | X34: =+AC34/U34 -> 12 | Y34: =+W34+X34 -> 132 | Z34: =+V34-Y34 -> 108 | AA34: 1306308900 | AB34: 1306308900 | AC34: =SUM(AD34:AO34) -> 130630890 | AD34: 10885908 | AE34: 10885908 | AF34: 10885908 | AG34: 10885908 | AH34: 10885908 | AI34: 10885908 | AJ34: 10885908 | AK34: 10885908 | AL34: 10885908 | AM34: 10885908 | AN34: 10885908 | AO34: 10885908 | AP34: =+AA34+AC34 -> 1436939790 | AQ34: =IF(AS34=$AS$24,((T34-AP34)*0),T34-AP34) -> 1175678010 | AV34: Ok | AW34: =IFERROR(VLOOKUP(G34,'[70]Detail Deprec_202508'!$D$33:$I$357,6,FALSE),0) -> 10885908 | AX34: =AW34-AK34 -> 0
A35: 10 | B35: CLC | C35: CLCWH | D35: 152 | E35: WH2 | F35: CLC131-003 | G35: BLD000071 | H35: 42387 | I35: Building | J35: 05 | K35: Omni Lifter Phase 2 | L35: Kawasan Industri Terpadu Indonesia China (KITIC) Kav. 20, Cikarang, West Java | M35: Cikarang Logistic Center | N35: 2016 | R35: 1 | T35: 7065000000 | U35: =+T35/V35 -> 29437500 | V35: 240 | W35: =108+12 -> 120 | X35: =+AC35/U35 -> 12 | Y35: =+W35+X35 -> 132 | Z35: =+V35-Y35 -> 108 | AA35: 3532500000 | AB35: 3532500000 | AC35: =SUM(AD35:AO35) -> 353250000 | AD35: 29437500 | AE35: 29437500 | AF35: 29437500 | AG35: 29437500 | AH35: 29437500 | AI35: 29437500 | AJ35: 29437500 | AK35: 29437500 | AL35: 29437500 | AM35: 29437500 | AN35: 29437500 | AO35: 29437500 | AP35: =+AA35+AC35 -> 3885750000 | AQ35: =IF(AS35=$AS$24,((T35-AP35)*0),T35-AP35) -> 3179250000 | AV35: Ok | AW35: =IFERROR(VLOOKUP(G35,'[70]Detail Deprec_202508'!$D$33:$I$357,6,FALSE),0) -> 29437500 | AX35: =AW35-AK35 -> 0
A36: 11 | B36: CLC | C36: CLCWH | D36: 152 | E36: WH2 | F36: CLC131-003 | G36: BLD000072 | H36: 42387 | I36: Building | J36: 05 | K36: Omni Lifter Phase 2 | L36: Kawasan Industri Terpadu Indonesia China (KITIC) Kav. 20, Cikarang, West Java | M36: Cikarang Logistic Center | N36: 2016 | R36: 1 | S36: 38760 | T36: 534694200 | U36: =+T36/V36 -> 2227892.5 | V36: 240 | W36: =108+12 -> 120 | X36: =+AC36/U36 -> 12 | Y36: =+W36+X36 -> 132 | Z36: =+V36-Y36 -> 108 | AA36: 267347100 | AB36: 267347100 | AC36: =SUM(AD36:AO36) -> 26734710 | AD36: 2227892.5 | AE36: 2227892.5 | AF36: 2227892.5 | AG36: 2227892.5 | AH36: 2227892.5 | AI36: 2227892.5 | AJ36: 2227892.5 | AK36: 2227892.5 | AL36: 2227892.5 | AM36: 2227892.5 | AN36: 2227892.5 | AO36: 2227892.5 | AP36: =+AA36+AC36 -> 294081810 | AQ36: =IF(AS36=$AS$24,((T36-AP36)*0),T36-AP36) -> 240612390 | AV36: Ok | AW36: =IFERROR(VLOOKUP(G36,'[70]Detail Deprec_202508'!$D$33:$I$357,6,FALSE),0) -> 2227892.5 | AX36: =AW36-AK36 -> 0
A37: 12 | B37: CLC | C37: CLCWH | D37: 152 | E37: WH2 | F37: CLC131-003 | G37: BLD000073 | H37: 42387 | I37: Building | J37: 05 | K37: Mezzanine Area Phase 2 | L37: Kawasan Industri Terpadu Indonesia China (KITIC) Kav. 20, Cikarang, West Java | M37: Cikarang Logistic Center | N37: 2016 | R37: 1 | T37: 1338483845 | U37: =+T37/V37 -> 5577016 | V37: 240 | W37: =108+12 -> 120 | X37: =+AC37/U37 -> 12 | Y37: =+W37+X37 -> 132 | Z37: =+V37-Y37 -> 108 | AA37: 6.6924192e+08 | AB37: 6.6924192e+08 | AC37: =SUM(AD37:AO37) -> 66924192 | AD37: 5577016 | AE37: 5577016 | AF37: 5577016 | AG37: 5577016 | AH37: 5577016 | AI37: 5577016 | AJ37: 5577016 | AK37: 5577016 | AL37: 5577016 | AM37: 5577016 | AN37: 5577016 | AO37: 5577016 | AP37: =+AA37+AC37 -> 7.3616611e+08 | AQ37: =IF(AS37=$AS$24,((T37-AP37)*0),T37-AP37) -> 6.0231773e+08 | AV37: Ok | AW37: =IFERROR(VLOOKUP(G37,'[70]Detail Deprec_202508'!$D$33:$I$357,6,FALSE),0) -> 5577016 | AX37: =AW37-AK37 -> -0.00083333347
A38: 13 | B38: CLC | C38: CLCWH | D38: 152 | E38: WH2 | F38: CLC131-005 | G38: BLD000076 | H38: 43830 | I38: Building | J38: 007-12 | K38: Roof for Motorcycle Parking Area (80%) | L38: SII JKC | M38: KITIC Office | N38: 2019 | R38: 1 | T38: 177294305 | U38: =+T38/V38 -> 738726.27 | V38: 240 | W38: =61+12 -> 73 | X38: =+AC38/U38 -> 12 | Y38: =+W38+X38 -> 85 | Z38: =+V38-Y38 -> 155 | AA38: 53927018 | AB38: 1.2336729e+08 | AC38: =SUM(AD38:AO38) -> 8864715.2 | AD38: 738726.27 | AE38: 738726.27 | AF38: 738726.27 | AG38: 738726.27 | AH38: 738726.27 | AI38: 738726.27 | AJ38: 738726.27 | AK38: 738726.27 | AL38: 738726.27 | AM38: 738726.27 | AN38: 738726.27 | AO38: 738726.27 | AP38: =+AA38+AC38 -> 62791733 | AQ38: =IF(AS38=$AS$24,((T38-AP38)*0),T38-AP38) -> 1.1450257e+08 | AV38: Ok | AW38: =IFERROR(VLOOKUP(G38,'[70]Detail Deprec_202508'!$D$33:$I$357,6,FALSE),0) -> 738726.27 | AX38: =AW38-AK38 -> -0.00083333335
A39: 14 | B39: CLC | C39: CLCWH | D39: 153 | E39: WH1 | F39: CLC133-001 | G39: STR000005 | H39: 41639 | I39: Structures | J39: 2005 | K39: Security system & installation | L39: SECOM Indonesia | M39: Cikarang Warehouse & Office | N39: 2013 | R39: 1 | S39: 4082 | T39: 48890114 | U39: =+T39/V39 -> 814835.23 | V39: 60 | W39: 60 | X39: =+AC39/U39 -> 0 | Y39: =+W39+X39 -> 60 | Z39: =+V39-Y39 -> 0 | AA39: 48890114 | AB39: 1.4901161e-08 | AC39: =SUM(AD39:AL39) -> 0 | AP39: =+AA39+AC39 -> 48890114 | AQ39: =IF(AS39=$AS$24,((T39-AP39)*0),T39-AP39) -> 1.4901161e-08 | AV39: Ok | AW39: =IFERROR(VLOOKUP(G39,'[70]Detail Deprec_202508'!$D$33:$I$357,6,FALSE),0) -> 0 | AX39: =AW39-AK39 -> 0
A40: =+A39+1 -> 15 | B40: CLC | C40: CLCWH | D40: 153 | E40: WH1 | F40: CLC133-002 | G40: STR000006 | H40: 41639 | I40: Structures | J40: 2007 | K40: CCTV system WH 1 | L40: SECOM Indonesia | M40: Cikarang Warehouse & Office | N40: 2013 | R40: 1 | S40: 40583.96 | T40: 4.8607409e+08 | U40: =+T40/V40 -> 8101234.8 | V40: 60 | W40: 60 | X40: =+AC40/U40 -> 0 | Y40: =+W40+X40 -> 60 | Z40: =+V40-Y40 -> 0 | AA40: 4.8607409e+08 | AB40: -1.1920929e-07 | AC40: =SUM(AD40:AL40) -> 0 | AP40: =+AA40+AC40 -> 4.8607409e+08 | AQ40: =IF(AS40=$AS$24,((T40-AP40)*0),T40-AP40) -> -1.1920929e-07 | AV40: Ok | AW40: =IFERROR(VLOOKUP(G40,'[70]Detail Deprec_202508'!$D$33:$I$357,6,FALSE),0) -> 0 | AX40: =AW40-AK40 -> 0
A41: =+A40+1 -> 16 | B41: CLC | C41: CLCWH | D41: 153 | E41: WH1 | F41: CLC133-003 | G41: STR000007 | H41: 41639 | I41: Structures | J41: 2008 | K41: Access control | L41: SECOM Indonesia | M41: Cikarang Warehouse & Office | N41: 2013 | R41: 1 | S41: 4246 | T41: 50854342 | U41: =+T41/V41 -> 847572.37 | V41: 60 | W41: 60 | X41: =+AC41/U41 -> 0 | Y41: =+W41+X41 -> 60 | Z41: =+V41-Y41 -> 0 | AA41: 50854342 | AB41: -2.2351742e-08 | AC41: =SUM(AD41:AL41) -> 0 | AP41: =+AA41+AC41 -> 50854342 | AQ41: =IF(AS41=$AS$24,((T41-AP41)*0),T41-AP41) -> -2.2351742e-08 | AV41: Ok | AW41: =IFERROR(VLOOKUP(G41,'[70]Detail Deprec_202508'!$D$33:$I$357,6,FALSE),0) -> 0 | AX41: =AW41-AK41 -> 0
A42: =+A41+1 -> 17 | B42: CLC | C42: CLCWH | D42: 153 | E42: WH1 | F42: CLC133-004 | G42: STR000008 | H42: 41639 | I42: Structures | J42: 2011 | K42: Security system & installation | L42: SECOM Indonesia | M42: Cikarang Warehouse & Office | N42: 2013 | R42: 1 | S42: 519 | T42: 6216063 | U42: =+T42/V42 -> 103601.05 | V42: 60 | W42: 60 | X42: =+AC42/U42 -> 0 | Y42: =+W42+X42 -> 60 | Z42: =+V42-Y42 -> 0 | AA42: 6216063 | AB42: -1.8626451e-09 | AC42: =SUM(AD42:AL42) -> 0 | AP42: =+AA42+AC42 -> 6216063 | AQ42: =IF(AS42=$AS$24,((T42-AP42)*0),T42-AP42) -> -1.8626451e-09 | AV42: Ok | AW42: =IFERROR(VLOOKUP(G42,'[70]Detail Deprec_202508'!$D$33:$I$357,6,FALSE),0) -> 0 | AX42: =AW42-AK42 -> 0
A43: =+A42+1 -> 18 | B43: CLC | C43: CLCWH | D43: 153 | E43: WH1 | F43: CLC133-026 | G43: STR000013 | H43: 41759 | I43: Structures | J43: 64 | K43: Wifi Terminal DG | L43: Dangerous Room (KDDI Indonesia) | N43: 2014 | R43: 1 | T43: 156382893 | U43: =+T43/V43 -> 2606381.5 | V43: 60 | W43: 60 | X43: =+AC43/U43 -> 0 | Y43: =+W43+X43 -> 60 | Z43: =+V43-Y43 -> 0 | AA43: 156382893 | AB43: 0 | AC43: =SUM(AD43:AL43) -> 0 | AP43: =+AA43+AC43 -> 156382893 | AQ43: =IF(AS43=$AS$24,((T43-AP43)*0),T43-AP43) -> 0 | AV43: Ok | AW43: =IFERROR(VLOOKUP(G43,'[70]Detail Deprec_202508'!$D$33:$I$357,6,FALSE),0) -> 0 | AX43: =AW43-AK43 -> 0
A44: =+A43+1 -> 19 | B44: CLC_SBY | C44: CLCWH | D44: 153 | E44: SBY | F44: CLC133-007 | G44: STR000023 | H44: 42366 | I44: Structures | J44: 20 | K44: Wifi Instalation Warehouse Surabaya | L44: KDDI Indonesia | N44: 2015 | R44: 1 | S44: 26310 | T44: 364130400 | U44: =+T44/V44 -> 6068840 | V44: 60 | W44: 60 | X44: =+AC44/U44 -> 0 | Y44: =+W44+X44 -> 60 | Z44: =+V44-Y44 -> 0 | AA44: 364130400 | AB44: 0 | AC44: =SUM(AD44:AL44) -> 0 | AP44: =+AA44+AC44 -> 364130400 | AQ44: =IF(AS44=$AS$24,((T44-AP44)*0),T44-AP44) -> 0 | AV44: Ok | AW44: =IFERROR(VLOOKUP(G44,'[70]Detail Deprec_202508'!$D$33:$I$357,6,FALSE),0) -> 0 | AX44: =AW44-AK44 -> 0
A45: =+A44+1 -> 20 | B45: CLC | C45: CLCWH | D45: 153 | E45: WH1 | F45: CLC133-008 | G45: STR000024 | H45: 42366 | I45: Structures | J45: 22 | K45: Installation High Bay Lighting Warehouse | L45: Seamec Asia | M45: WH 1 | N45: 2015 | R45: 1 | T45: 227000000 | U45: =+T45/V45 -> 3783333.3 | V45: 60 | W45: 60 | X45: =+AC45/U45 -> 0 | Y45: =+W45+X45 -> 60 | Z45: =+V45-Y45 -> 0 | AA45: 2.27e+08 | AB45: -2.9802322e-08 | AC45: =SUM(AD45:AL45) -> 0 | AP45: =+AA45+AC45 -> 2.27e+08 | AQ45: =IF(AS45=$AS$24,((T45-AP45)*0),T45-AP45) -> -2.9802322e-08 | AV45: Ok | AW45: =IFERROR(VLOOKUP(G45,'[70]Detail Deprec_202508'!$D$33:$I$357,6,FALSE),0) -> 0 | AX45: =AW45-AK45 -> 0
A46: =+A45+1 -> 21 | B46: CLC | C46: CLCWH | D46: 153 | E46: WH2 | F46: CLC133-009 | G46: STR000025 | H46: 42397 | I46: Structures | J46: 16 | K46: Internet System | L46: KDDI Indonesia | M46: WH & Office Phase 2 | N46: 2016 | R46: 1 | T46: 745885600 | U46: =+T46/V46 -> 12431427 | V46: 60 | W46: 60 | X46: =+AC46/U46 -> 0 | Y46: =+W46+X46 -> 60 | Z46: =+V46-Y46 -> 0 | AA46: 745885600 | AB46: 0 | AC46: =SUM(AD46:AL46) -> 0 | AP46: =+AA46+AC46 -> 745885600 | AQ46: =IF(AS46=$AS$24,((T46-AP46)*0),T46-AP46) -> 0 | AV46: Ok | AW46: =IFERROR(VLOOKUP(G46,'[70]Detail Deprec_202508'!$D$33:$I$357,6,FALSE),0) -> 0 | AX46: =AW46-AK46 -> 0
A47: =+A46+1 -> 22 | B47: CLC | C47: CLCWH | D47: 153 | E47: OTHERS | F47: CLC133-010 | G47: STR000026 | H47: 42429 | I47: Structures | J47: 27 | K47: Install PABX | L47: KDDI Indonesia | M47: Install New PABX at server room | N47: 2016 | R47: 1 | T47: 45560000 | U47: =+T47/V47 -> 759333.33 | V47: 60 | W47: 60 | X47: =+AC47/U47 -> 0 | Y47: =+W47+X47 -> 60 | Z47: =+V47-Y47 -> 0 | AA47: 45560000 | AB47: 7.4505806e-09 | AC47: =SUM(AD47:AL47) -> 0 | AP47: =+AA47+AC47 -> 45560000 | AQ47: =IF(AS47=$AS$24,((T47-AP47)*0),T47-AP47) -> 7.4505806e-09 | AV47: Ok | AW47: =IFERROR(VLOOKUP(G47,'[70]Detail Deprec_202508'!$D$33:$I$357,6,FALSE),0) -> 0 | AX47: =AW47-AK47 -> 0
A48: =+A47+1 -> 23 | B48: CLC | C48: CLCWH | D48: 153 | E48: WH2 | F48: CLC133-011 | G48: STR000027 | H48: 42489 | I48: Structures | J48: 35 | K48: CCTV system | L48: SECOM Indonesia | M48: WH 2 | N48: 2016 | R48: 1 | S48: 66652.35 | T48: 8.848766e+08 | U48: =+T48/V48 -> 14747943 | V48: 60 | W48: 60 | X48: =+AC48/U48 -> 0 | Y48: =+W48+X48 -> 60 | Z48: =+V48-Y48 -> 0 | AA48: 8.848766e+08 | AB48: 0 | AC48: =SUM(AD48:AL48) -> 0 | AP48: =+AA48+AC48 -> 8.848766e+08 | AQ48: =IF(AS48=$AS$24,((T48-AP48)*0),T48-AP48) -> 0 | AV48: Ok | AW48: =IFERROR(VLOOKUP(G48,'[70]Detail Deprec_202508'!$D$33:$I$357,6,FALSE),0) -> 0 | AX48: =AW48-AK48 -> 0
A49: =+A48+1 -> 24 | B49: CLC | C49: CLCWH | D49: 153 | E49: OTHERS | F49: CLC133-012 | G49: STR000028 | H49: 42489 | I49: Structures | J49: 35 | K49: Pariometer Border System | L49: SECOM Indonesia | N49: 2016 | R49: 1 | T49: 303068283 | U49: =+T49/V49 -> 5051138 | V49: 60 | W49: 60 | X49: =+AC49/U49 -> 0 | Y49: =+W49+X49 -> 60 | Z49: =+V49-Y49 -> 0 | AA49: 3.0306828e+08 | AB49: 5.9604645e-08 | AC49: =SUM(AD49:AL49) -> 0 | AP49: =+AA49+AC49 -> 3.0306828e+08 | AQ49: =IF(AS49=$AS$24,((T49-AP49)*0),T49-AP49) -> 5.9604645e-08 | AV49: Ok | AW49: =IFERROR(VLOOKUP(G49,'[70]Detail Deprec_202508'!$D$33:$I$357,6,FALSE),0) -> 0 | AX49: =AW49-AK49 -> 0
A50: =+A49+1 -> 25 | B50: CLC | C50: CLCWH | D50: 153 | E50: WH2 | F50: CLC133-013 | G50: STR000029 | H50: 42719 | I50: Structures | J50: 08 | K50: CCTV system fr Security Guard House | L50: SECOM Indonesia | N50: 2016 | R50: 1 | S50: 4947.09 | T50: 67097382 | U50: =+T50/V50 -> 1118289.7 | V50: 60 | W50: 60 | X50: =+AC50/U50 -> 0 | Y50: =+W50+X50 -> 60 | Z50: =+V50-Y50 -> 0 | AA50: 67097382 | AB50: 1.4901161e-08 | AC50: =SUM(AD50:AL50) -> 0 | AP50: =+AA50+AC50 -> 67097382 | AQ50: =IF(AS50=$AS$24,((T50-AP50)*0),T50-AP50) -> 1.4901161e-08 | AV50: Ok | AW50: =IFERROR(VLOOKUP(G50,'[70]Detail Deprec_202508'!$D$33:$I$357,6,FALSE),0) -> 0 | AX50: =AW50-AK50 -> 0
A51: =+A50+1 -> 26 | B51: CLC | C51: CLCWH | D51: 153 | E51: WH2 | F51: CLC133-014 | G51: STR000030 | H51: 42719 | I51: Structures | J51: 08 | K51: Finger Scan Acces for W/H Phase 2 | L51: SECOM Indonesia | N51: 2016 | R51: 1 | T51: 36326195 | U51: =+T51/V51 -> 605436.58 | V51: 60 | W51: 60 | X51: =+AC51/U51 -> 0 | Y51: =+W51+X51 -> 60 | Z51: =+V51-Y51 -> 0 | AA51: 36326195 | AB51: 0 | AC51: =SUM(AD51:AL51) -> 0 | AP51: =+AA51+AC51 -> 36326195 | AQ51: =IF(AS51=$AS$24,((T51-AP51)*0),T51-AP51) -> 0 | AV51: Ok | AW51: =IFERROR(VLOOKUP(G51,'[70]Detail Deprec_202508'!$D$33:$I$357,6,FALSE),0) -> 0 | AX51: =AW51-AK51 -> 0
A52: =+A51+1 -> 27 | B52: CLC | C52: CLCWH | D52: 153 | E52: OTHERS | F52: CLC133-015 | G52: STR000031 | H52: 42733 | I52: Structures | J52: 18 | K52: Pariometer Border System in Central Area W/H CLC | L52: SECOM Indonesia | N52: 2016 | R52: 1 | T52: 92140414 | U52: =+T52/V52 -> 1535673.6 | V52: 60 | W52: 60 | X52: =+AC52/U52 -> 0 | Y52: =+W52+X52 -> 60 | Z52: =+V52-Y52 -> 0 | AA52: 92140414 | AB52: 0 | AC52: =SUM(AD52:AL52) -> 0 | AP52: =+AA52+AC52 -> 92140414 | AQ52: =IF(AS52=$AS$24,((T52-AP52)*0),T52-AP52) -> 0 | AV52: Ok | AW52: =IFERROR(VLOOKUP(G52,'[70]Detail Deprec_202508'!$D$33:$I$357,6,FALSE),0) -> 0 | AX52: =AW52-AK52 -> 0
A53: =+A52+1 -> 28 | B53: CLC | C53: CLCWH | D53: 153 | E53: WH1 | F53: CLC133-016 | G53: STR000035 | H53: 42885 | I53: Structures | J53: 15 | K53: New Panic Bar | L53: SMCC Utama | N53: 2017 | R53: 1 | T53: 80000000 | U53: =+T53/V53 -> 1333333.3 | V53: 60 | W53: 60 | X53: =+AC53/U53 -> 0 | Y53: =+W53+X53 -> 60 | Z53: =+V53-Y53 -> 0 | AA53: 80000000 | AB53: 0 | AC53: =SUM(AD53:AL53) -> 0 | AP53: =+AA53+AC53 -> 80000000 | AQ53: =IF(AS53=$AS$24,((T53-AP53)*0),T53-AP53) -> 0 | AV53: Ok | AW53: =IFERROR(VLOOKUP(G53,'[70]Detail Deprec_202508'!$D$33:$I$357,6,FALSE),0) -> 0 | AX53: =AW53-AK53 -> 0
A54: =+A53+1 -> 29 | B54: CLC | C54: CLCWH | D54: 153 | E54: MDN | F54: CLC133-017 | G54: STR000045 | H54: 43006 | I54: Structures | J54: 05 | K54: WIFI Installation Warehouse Medan | L54: KDDI Indonesia | N54: 2017 | R54: 1 | T54: 94507530 | U54: =+T54/V54 -> 1575125.5 | V54: 60 | W54: 60 | X54: =+AC54/U54 -> 0 | Y54: =+W54+X54 -> 60 | Z54: =+V54-Y54 -> 0 | AA54: 94507530 | AB54: 0 | AC54: =SUM(AD54:AL54) -> 0 | AP54: =+AA54+AC54 -> 94507530 | AQ54: =IF(AS54=$AS$24,((T54-AP54)*0),T54-AP54) -> 0 | AV54: Ok | AW54: =IFERROR(VLOOKUP(G54,'[70]Detail Deprec_202508'!$D$33:$I$357,6,FALSE),0) -> 0 | AX54: =AW54-AK54 -> 0
A55: =+A54+1 -> 30 | B55: CLC | C55: CLCWH | D55: 153 | E55: WH1 | F55: CLC133-018 | G55: STR000048 | H55: 43097 | I55: Structures | J55: 25 | K55: Wifi Installation WH 1 | L55: KDDI Indonesia | N55: 2017 | R55: 1 | T55: 76595000 | U55: =+T55/V55 -> 1276583.3 | V55: 60 | W55: 60 | X55: =+AC55/U55 -> 0 | Y55: =+W55+X55 -> 60 | Z55: =+V55-Y55 -> 0 | AA55: 76595000 | AB55: 0 | AC55: =SUM(AD55:AL55) -> 0 | AP55: =+AA55+AC55 -> 76595000 | AQ55: =IF(AS55=$AS$24,((T55-AP55)*0),T55-AP55) -> 0 | AV55: Ok | AW55: =IFERROR(VLOOKUP(G55,'[70]Detail Deprec_202508'!$D$33:$I$357,6,FALSE),0) -> 0 | AX55: =AW55-AK55 -> 0
A56: =+A55+1 -> 31 | B56: CLC | C56: CLCWH | D56: 153 | E56: WH2 | F56: CLC133-019 | G56: STR000050 | H56: 43220 | I56: Structures | K56: CCTV System fr PLB Area WH II | L56: SECOM Indonesia | N56: 2018 | R56: 1 | T56: 214296550 | U56: =+T56/V56 -> 3571609.2 | V56: 60 | W56: 60 | X56: =+AC56/U56 -> 0 | Y56: =+W56+X56 -> 60 | Z56: =+V56-Y56 -> 0 | AA56: 214296550 | AB56: 0 | AC56: =SUM(AD56:AL56) -> 0 | AP56: =+AA56+AC56 -> 214296550 | AQ56: =IF(AS56=$AS$24,((T56-AP56)*0),T56-AP56) -> 0 | AV56: Ok | AX56: =AW56-AK56 -> 0
A57: =+A56+1 -> 32 | B57: CLC | C57: CLCWH | D57: 153 | E57: OTHERS | F57: CLC133-020 | G57: STR000051 | H57: 43403 | I57: Structures | J57: JKT_GL004975 | K57: Wifi Installation at Pekan Baru | L57: KDDI Indonesia | N57: 2018 | R57: 1 | T57: 195741000 | U57: =+T57/V57 -> 3262350 | V57: 60 | W57: 60 | X57: =+AC57/U57 -> 0 | Y57: =+W57+X57 -> 60 | Z57: =+V57-Y57 -> 0 | AA57: 195741000 | AB57: 0 | AC57: =SUM(AD57:AL57) -> 0 | AP57: =+AA57+AC57 -> 195741000 | AQ57: =IF(AS57=$AS$24,((T57-AP57)*0),T57-AP57) -> 0 | AV57: Ok | AW57: =IFERROR(VLOOKUP(G57,'[70]Detail Deprec_202508'!$D$33:$I$357,6,FALSE),0) -> 0 | AX57: =AW57-AK57 -> 0
A58: =+A57+1 -> 33 | B58: CLC | C58: CLCWH | D58: 153 | E58: MDN | F58: CLC133-021 | G58: STR000053 | H58: 43570 | I58: Structures | J58: JKT_GL007420 | K58: Wifi Installation at Medan B7 | L58: KDDI Indonesia | N58: 2019 | R58: 1 | T58: 109550000 | U58: =+T58/V58 -> 1825833.3 | V58: 60 | W58: 60 | X58: =+AC58/U58 -> 0 | Y58: =+W58+X58 -> 60 | Z58: =+V58-Y58 -> 0 | AA58: 109550000 | AB58: 0 | AC58: =SUM(AD58:AL58) -> 0 | AP58: =+AA58+AC58 -> 109550000 | AQ58: =IF(AS58=$AS$24,((T58-AP58)*0),T58-AP58) -> 0 | AV58: Ok | AW58: =IFERROR(VLOOKUP(G58,'[70]Detail Deprec_202508'!$D$33:$I$357,6,FALSE),0) -> 0 | AX58: =AW58-AK58 -> 0
A59: =+A58+1 -> 34 | B59: CLC | C59: CLCWH | D59: 153 | E59: PBG | F59: CLC133-022 | G59: STR000055 | H59: 43827 | I59: Structures | J59: JKT_GL010375 | K59: Wifi Installation at W/H Palembang | L59: KDDI Indonesia | N59: 2019 | R59: 1 | T59: 103960000 | U59: =+T59/V59 -> 1732666.7 | V59: 60 | W59: 60 | X59: =+AC59/U59 -> 0 | Y59: =+W59+X59 -> 60 | Z59: =+V59-Y59 -> 0 | AA59: 103960000 | AB59: 0 | AC59: =SUM(AD59:AL59) -> 0 | AP59: =+AA59+AC59 -> 103960000 | AQ59: =IF(AS59=$AS$24,((T59-AP59)*0),T59-AP59) -> 0 | AV59: Ok | AW59: =IFERROR(VLOOKUP(G59,'[70]Detail Deprec_202508'!$D$33:$I$357,6,FALSE),0) -> 0 | AX59: =AW59-AK59 -> 0
A60: =+A59+1 -> 35 | B60: CLC | C60: CLCWH | D60: 153 | E60: WH1 | F60: CLC134-021 | G60: STR000062 | H60: 44560 | I60: Structures | J60: JKT_GL016704 | K60: Handrail at Loading Dock WH 1 | L60: SMCC Utama | N60: 2021 | R60: 1 | T60: 120000000 | U60: =+T60/V60 -> 3333333.3 | V60: 36 | W60: 36 | X60: =+AC60/U60 -> 0 | Y60: =+W60+X60 -> 36 | Z60: =+V60-Y60 -> 0 | AA60: 120000000 | AB60: 0 | AC60: =SUM(AD60:AL60) -> 0 | AP60: =+AA60+AC60 -> 120000000 | AQ60: =IF(AS60=$AS$24,((T60-AP60)*0),T60-AP60) -> 0 | AV60: Ok | AW60: =IFERROR(VLOOKUP(G60,'[70]Detail Deprec_202508'!$D$33:$I$357,6,FALSE),0) -> 0 | AX60: =AW60-AK60 -> 0
A61: =+A60+1 -> 36 | B61: CLC | C61: CLCWH | D61: 153 | E61: WH2 | F61: CLC134-022 | G61: STR000063 | H61: 44560 | I61: Structures | J61: JKT_GL016759 | K61: Handrail at Loading Dock WH 2 | L61: SMCC Utama | N61: 2021 | R61: 1 | T61: 122900000 | U61: =+T61/V61 -> 3413888.9 | V61: 36 | W61: 36 | X61: =+AC61/U61 -> 0 | Y61: =+W61+X61 -> 36 | Z61: =+V61-Y61 -> 0 | AA61: 1.229e+08 | AB61: 1.4901161e-08 | AC61: =SUM(AD61:AL61) -> 0 | AP61: =+AA61+AC61 -> 1.229e+08 | AQ61: =IF(AS61=$AS$24,((T61-AP61)*0),T61-AP61) -> 1.4901161e-08 | AV61: Ok | AW61: =IFERROR(VLOOKUP(G61,'[70]Detail Deprec_202508'!$D$33:$I$357,6,FALSE),0) -> 0 | AX61: =AW61-AK61 -> 0
A62: =+A61+1 -> 37 | B62: CLC | C62: CLCWH | D62: 153 | E62: OTHERS | F62: CLC134-023 | G62: STR000068 | H62: 44865 | I62: Structures | J62: JKT_GL019011 | K62: Body Harness Hangers | L62: JKTC | N62: 2022 | R62: 1 | T62: 62500000 | U62: =+T62/V62 -> 1041666.7 | V62: 60 | W62: =27+12 -> 39 | X62: =+AC62/U62 -> 12 | Y62: =+W62+X62 -> 51 | Z62: =+V62-Y62 -> 9 | AA62: 40625000 | AB62: 34375000 | AC62: =SUM(AD62:AO62) -> 12500000 | AD62: 1041666.7 | AE62: 1041666.7 | AF62: 1041666.7 | AG62: 1041666.7 | AH62: 1041666.7 | AI62: 1041666.7 | AJ62: 1041666.7 | AK62: 1041666.7 | AL62: 1041666.7 | AM62: 1041666.7 | AN62: 1041666.7 | AO62: 1041666.7 | AP62: =+AA62+AC62 -> 53125000 | AQ62: =IF(AS62=$AS$24,((T62-AP62)*0),T62-AP62) -> 9375000 | AV62: Ok | AW62: =IFERROR(VLOOKUP(G62,'[70]Detail Deprec_202508'!$D$33:$I$357,6,FALSE),0) -> 1041666.7 | AX62: =AW62-AK62 -> 0.0033333334
A63: =+A62+1 -> 38 | B63: CLC | C63: CLCWH | D63: 153 | E63: OTHERS | F63: CLC134-023 | G63: STR000069 | H63: 44865 | I63: Structures | J63: JKT_GL019011 | K63: Body Harness Hangers | L63: JKTC | N63: 2022 | R63: 1 | T63: 62500000 | U63: =+T63/V63 -> 1041666.7 | V63: 60 | W63: =27+12 -> 39 | X63: =+AC63/U63 -> 12 | Y63: =+W63+X63 -> 51 | Z63: =+V63-Y63 -> 9 | AA63: 40625000 | AB63: 34375000 | AC63: =SUM(AD63:AO63) -> 12500000 | AD63: 1041666.7 | AE63: 1041666.7 | AF63: 1041666.7 | AG63: 1041666.7 | AH63: 1041666.7 | AI63: 1041666.7 | AJ63: 1041666.7 | AK63: 1041666.7 | AL63: 1041666.7 | AM63: 1041666.7 | AN63: 1041666.7 | AO63: 1041666.7 | AP63: =+AA63+AC63 -> 53125000 | AQ63: =IF(AS63=$AS$24,((T63-AP63)*0),T63-AP63) -> 9375000 | AV63: Ok | AW63: =IFERROR(VLOOKUP(G63,'[70]Detail Deprec_202508'!$D$33:$I$357,6,FALSE),0) -> 1041666.7 | AX63: =AW63-AK63 -> 0.0033333334
A64: =+A63+1 -> 39 | B64: CLC | C64: CLCWH | D64: 154 | E64: OTHERS | F64: CLC134-016 | G64: MNE000029 | H64: 36980 | I64: Machinary and Equipment | K64: Container | M64: 20 Feet | N64: 2001 | R64: 1 | T64: 10000000 | U64: =+T64/V64 -> 166666.67 | V64: 60 | W64: 60 | X64: =+AC64/U64 -> 0 | Y64: =+W64+X64 -> 60 | Z64: =+V64-Y64 -> 0 | AA64: 10000000 | AB64: 0 | AC64: =SUM(AD64:AL64) -> 0 | AP64: =+AA64+AC64 -> 10000000 | AQ64: =IF(AS64=$AS$24,((T64-AP64)*0),T64-AP64) -> 0 | AV64: Ok | AW64: =IFERROR(VLOOKUP(G64,'[70]Detail Deprec_202508'!$D$33:$I$357,6,FALSE),0) -> 0 | AX64: =AW64-AK64 -> 0
A65: =+A64+1 -> 40 | B65: CLC | C65: CLCWH | D65: 154 | E65: WH1 | F65: CLC134-001 | G65: MNE000131 | H65: 41726 | I65: Machinary and Equipment | J65: 25 | K65: VNA Racking System | L65: VNA | N65: 2014 | R65: 1 | S65: 61170 | T65: 711651780 | U65: =+T65/V65 -> 11860863 | V65: 60 | W65: 60 | X65: =+AC65/U65 -> 0 | Y65: =+W65+X65 -> 60 | Z65: =+V65-Y65 -> 0 | AA65: 711651780 | AB65: 0 | AC65: =SUM(AD65:AL65) -> 0 | AP65: =+AA65+AC65 -> 711651780 | AQ65: =IF(AS65=$AS$24,((T65-AP65)*0),T65-AP65) -> 0 | AV65: Ok | AW65: =IFERROR(VLOOKUP(G65,'[70]Detail Deprec_202508'!$D$33:$I$357,6,FALSE),0) -> 0 | AX65: =AW65-AK65 -> 0
A66: =+A65+1 -> 41 | B66: CLC | C66: CLCWH | D66: 154 | E66: OTHERS | F66: CLC134-003 | G66: MNE000132 | H66: 41759 | I66: Machinary and Equipment | J66: 115 | K66: Racking System | L66: JSR Trading | N66: 2014 | R66: 1 | S66: 21840 | T66: 249063360 | U66: =+T66/V66 -> 4151056 | V66: 60 | W66: 60 | X66: =+AC66/U66 -> 0 | Y66: =+W66+X66 -> 60 | Z66: =+V66-Y66 -> 0 | AA66: 249063360 | AB66: 0 | AC66: =SUM(AD66:AL66) -> 0 | AP66: =+AA66+AC66 -> 249063360 | AQ66: =IF(AS66=$AS$24,((T66-AP66)*0),T66-AP66) -> 0 | AV66: Ok | AW66: =IFERROR(VLOOKUP(G66,'[70]Detail Deprec_202508'!$D$33:$I$357,6,FALSE),0) -> 0 | AX66: =AW66-AK66 -> 0
A67: =+A66+1 -> 42 | B67: CLC | C67: CLCWH | D67: 154 | E67: OTHERS | F67: CLC134-006 | G67: MNE000135 | H67: 41764 | I67: Machinary and Equipment | J67: 7 | K67: Fire Extinguisher & Alarm System | L67: Citra Teknik Safetindo | N67: 2014 | R67: 1 | T67: 66224000 | U67: =+T67/V67 -> 1103733.3 | V67: 60 | W67: 60 | X67: =+AC67/U67 -> 0 | Y67: =+W67+X67 -> 60 | Z67: =+V67-Y67 -> 0 | AA67: 66224000 | AB67: 0 | AC67: =SUM(AD67:AL67) -> 0 | AP67: =+AA67+AC67 -> 66224000 | AQ67: =IF(AS67=$AS$24,((T67-AP67)*0),T67-AP67) -> 0 | AV67: Ok | AW67: =IFERROR(VLOOKUP(G67,'[70]Detail Deprec_202508'!$D$33:$I$357,6,FALSE),0) -> 0 | AX67: =AW67-AK67 -> 0
A68: =+A67+1 -> 43 | B68: CLC | C68: CLCWH | D68: 154 | E68: OTHERS | F68: CLC134-002 | G68: MNE000136 | H68: 41789 | I68: Machinary and Equipment | J68: 112 | K68: Racking System | L68: VNA | N68: 2014 | R68: 1 | S68: 99500 | T68: 1117783000 | U68: =+T68/V68 -> 18629717 | V68: 60 | W68: 60 | X68: =+AC68/U68 -> 0 | Y68: =+W68+X68 -> 60 | Z68: =+V68-Y68 -> 0 | AA68: 1117783000 | AB68: 0 | AC68: =SUM(AD68:AL68) -> 0 | AP68: =+AA68+AC68 -> 1117783000 | AQ68: =IF(AS68=$AS$24,((T68-AP68)*0),T68-AP68) -> 0 | AV68: Ok | AW68: =IFERROR(VLOOKUP(G68,'[70]Detail Deprec_202508'!$D$33:$I$357,6,FALSE),0) -> 0 | AX68: =AW68-AK68 -> 0
A69: =+A68+1 -> 44 | B69: CLC | C69: CLCWH | D69: 154 | E69: OTHERS | F69: CLC134-007 | G69: MNE000137 | H69: 41820 | I69: Machinary and Equipment | J69: 2008 | K69: Racking System | M69: JSR Trading | N69: 2014 | R69: 1 | S69: 31716 | T69: 368254476 | U69: =+T69/V69 -> 6137574.6 | V69: 60 | W69: 60 | X69: =+AC69/U69 -> 0 | Y69: =+W69+X69 -> 60 | Z69: =+V69-Y69 -> 0 | AA69: 368254476 | AB69: 0 | AC69: =SUM(AD69:AL69) -> 0 | AP69: =+AA69+AC69 -> 368254476 | AQ69: =IF(AS69=$AS$24,((T69-AP69)*0),T69-AP69) -> 0 | AV69: Ok | AW69: =IFERROR(VLOOKUP(G69,'[70]Detail Deprec_202508'!$D$33:$I$357,6,FALSE),0) -> 0 | AX69: =AW69-AK69 -> 0
A70: =+A69+1 -> 45 | B70: CLC | C70: CLCWH | D70: 154 | E70: OTHERS | F70: CLC134-008 | G70: MNE000138 | H70: 41828 | I70: Machinary and Equipment | J70: 8 | K70: Racking System | L70: Nutech Industries | N70: 2014 | R70: 1 | S70: 209350 | T70: 2505710150 | U70: =+T70/V70 -> 41761836 | V70: 60 | W70: 60 | X70: =+AC70/U70 -> 0 | Y70: =+W70+X70 -> 60 | Z70: =+V70-Y70 -> 0 | AA70: 2505710150 | AB70: 0 | AC70: =SUM(AD70:AL70) -> 0 | AP70: =+AA70+AC70 -> 2505710150 | AQ70: =IF(AS70=$AS$24,((T70-AP70)*0),T70-AP70) -> 0 | AV70: Ok | AW70: =IFERROR(VLOOKUP(G70,'[70]Detail Deprec_202508'!$D$33:$I$357,6,FALSE),0) -> 0 | AX70: =AW70-AK70 -> 0
A71: =+A70+1 -> 46 | B71: CLC | C71: CLCWH | D71: 154 | E71: OTHERS | F71: CLC-A-001 | G71: MNE000141 | H71: 41866 | I71: Machinary and Equipment | K71: Scruber Dryer | L71: Gaddle GT50 | N71: 2014 | R71: 1 | T71: 41472000 | U71: =+T71/V71 -> 691200 | V71: 60 | W71: 60 | X71: =+AC71/U71 -> 0 | Y71: =+W71+X71 -> 60 | Z71: =+V71-Y71 -> 0 | AA71: 41472000 | AB71: 0 | AC71: =SUM(AD71:AL71) -> 0 | AP71: =+AA71+AC71 -> 41472000 | AQ71: =IF(AS71=$AS$24,((T71-AP71)*0),T71-AP71) -> 0 | AV71: Ok | AW71: =IFERROR(VLOOKUP(G71,'[70]Detail Deprec_202508'!$D$33:$I$357,6,FALSE),0) -> 0 | AX71: =AW71-AK71 -> 0
A72: =+A71+1 -> 47 | B72: CLC | C72: CLCWH | D72: 154 | E72: OTHERS | F72: CLC134-009 | G72: MNE000142 | H72: 41879 | I72: Machinary and Equipment | K72: Racking System | L72: Seamec Asia | N72: 2014 | R72: 1 | S72: 20895 | T72: 242193945 | U72: =+T72/V72 -> 4036565.8 | V72: 60 | W72: 60 | X72: =+AC72/U72 -> 0 | Y72: =+W72+X72 -> 60 | Z72: =+V72-Y72 -> 0 | AA72: 242193945 | AB72: 0 | AC72: =SUM(AD72:AL72) -> 0 | AP72: =+AA72+AC72 -> 242193945 | AQ72: =IF(AS72=$AS$24,((T72-AP72)*0),T72-AP72) -> 0 | AV72: Ok | AW72: =IFERROR(VLOOKUP(G72,'[70]Detail Deprec_202508'!$D$33:$I$357,6,FALSE),0) -> 0 | AX72: =AW72-AK72 -> 0
A73: =+A72+1 -> 48 | B73: CLC | C73: CLCWH | D73: 154 | E73: OTHERS | F73: CLC134-010 | G73: MNE000159 | H73: 41911 | I73: Machinary and Equipment | J73: 17 | K73: Racking System | L73: JSR Trading | N73: 2014 | R73: 1 | T73: 259871343 | U73: =+T73/V73 -> 4331189 | V73: 60 | W73: 60 | X73: =+AC73/U73 -> 0 | Y73: =+W73+X73 -> 60 | Z73: =+V73-Y73 -> 0 | AA73: 2.5987134e+08 | AB73: 5.9604645e-08 | AC73: =SUM(AD73:AL73) -> 0 | AP73: =+AA73+AC73 -> 2.5987134e+08 | AQ73: =IF(AS73=$AS$24,((T73-AP73)*0),T73-AP73) -> 5.9604645e-08 | AV73: Ok | AW73: =IFERROR(VLOOKUP(G73,'[70]Detail Deprec_202508'!$D$33:$I$357,6,FALSE),0) -> 0 | AX73: =AW73-AK73 -> 0
A74: =+A73+1 -> 49 | B74: CLC | C74: CLCWH | D74: 154 | E74: OTHERS | F74: CLC134-011 | G74: MNE000186 | H74: 42143 | I74: Machinary and Equipment | J74: 5 | K74: Nestainer & Joint Pallet | L74: Hanwa Indonesia | N74: 2015 | R74: 381 | T74: 344590000 | U74: =+T74/V74 -> 5743166.7 | V74: 60 | W74: 60 | X74: =+AC74/U74 -> 0 | Y74: =+W74+X74 -> 60 | Z74: =+V74-Y74 -> 0 | AA74: 344590000 | AB74: 0 | AC74: =SUM(AD74:AL74) -> 0 | AP74: =+AA74+AC74 -> 344590000 | AQ74: =IF(AS74=$AS$24,((T74-AP74)*0),T74-AP74) -> 0 | AV74: Ok | AW74: =IFERROR(VLOOKUP(G74,'[70]Detail Deprec_202508'!$D$33:$I$357,6,FALSE),0) -> 0 | AX74: =AW74-AK74 -> 0
A75: =+A74+1 -> 50 | B75: CLC | C75: CLCWH | D75: 154 | E75: SBY | F75: CLC134-013 | G75: MNE000202 | H75: 42338 | I75: Machinary and Equipment | J75: 102 | K75: Lightening Rod | L75: Joko | M75: WH Surabaya | N75: 2015 | R75: 1 | T75: 17300000 | U75: =+T75/V75 -> 288333.33 | V75: 60 | W75: 60 | X75: =+AC75/U75 -> 0 | Y75: =+W75+X75 -> 60 | Z75: =+V75-Y75 -> 0 | AA75: 17300000 | AB75: 0 | AC75: =SUM(AD75:AL75) -> 0 | AP75: =+AA75+AC75 -> 17300000 | AQ75: =IF(AS75=$AS$24,((T75-AP75)*0),T75-AP75) -> 0 | AV75: Ok | AW75: =IFERROR(VLOOKUP(G75,'[70]Detail Deprec_202508'!$D$33:$I$357,6,FALSE),0) -> 0 | AX75: =AW75-AK75 -> 0
A76: =+A75+1 -> 51 | B76: CLC | C76: CLCWH | D76: 154 | E76: SBY | F76: CLC134-014 | G76: MNE000203 | H76: 42338 | I76: Machinary and Equipment | J76: 102 | K76: Fire Alarm | L76: Gagas Mandiri | M76: WH Surabaya | N76: 2015 | R76: 1 | T76: 41500000 | U76: =+T76/V76 -> 691666.67 | V76: 60 | W76: 60 | X76: =+AC76/U76 -> 0 | Y76: =+W76+X76 -> 60 | Z76: =+V76-Y76 -> 0 | AA76: 41500000 | AB76: 0 | AC76: =SUM(AD76:AL76) -> 0 | AP76: =+AA76+AC76 -> 41500000 | AQ76: =IF(AS76=$AS$24,((T76-AP76)*0),T76-AP76) -> 0 | AV76: Ok | AW76: =IFERROR(VLOOKUP(G76,'[70]Detail Deprec_202508'!$D$33:$I$357,6,FALSE),0) -> 0 | AX76: =AW76-AK76 -> 0
A77: =+A76+1 -> 52 | B77: CLC | C77: CLCWH | D77: 154 | E77: WH1 | F77: CLC134-015 | G77: MNE000204 | H77: 42338 | I77: Machinary and Equipment | J77: 102 | K77: Exsposion proof lamp | N77: 2015 | R77: 1 | T77: 23100000 | U77: =+T77/V77 -> 385000 | V77: 60 | W77: 60 | X77: =+AC77/U77 -> 0 | Y77: =+W77+X77 -> 60 | Z77: =+V77-Y77 -> 0 | AA77: 23100000 | AB77: 0 | AC77: =SUM(AD77:AL77) -> 0 | AP77: =+AA77+AC77 -> 23100000 | AQ77: =IF(AS77=$AS$24,((T77-AP77)*0),T77-AP77) -> 0 | AV77: Ok | AW77: =IFERROR(VLOOKUP(G77,'[70]Detail Deprec_202508'!$D$33:$I$357,6,FALSE),0) -> 0 | AX77: =AW77-AK77 -> 0
A78: =+A77+1 -> 53 | B78: CLC | C78: CLCWH | D78: 154 | E78: OTHERS | F78: CLC-R-01 | G78: MNE000208 | H78: 42398 | I78: Machinary and Equipment | J78: 09 | K78: Nestainer & Joint Pallet | L78: Sankyu Construction Jakarta | N78: 2016 | R78: 1 | T78: 202500000 | U78: =+T78/V78 -> 3375000 | V78: 60 | W78: 60 | X78: =+AC78/U78 -> 0 | Y78: =+W78+X78 -> 60 | Z78: =+V78-Y78 -> 0 | AA78: 202500000 | AB78: 0 | AC78: =SUM(AD78:AL78) -> 0 | AP78: =+AA78+AC78 -> 202500000 | AQ78: =IF(AS78=$AS$24,((T78-AP78)*0),T78-AP78) -> 0 | AV78: Ok | AW78: =IFERROR(VLOOKUP(G78,'[70]Detail Deprec_202508'!$D$33:$I$357,6,FALSE),0) -> 0 | AX78: =AW78-AK78 -> 0
A79: =+A78+1 -> 54 | B79: CLC | C79: CLCWH | D79: 154 | E79: OTHERS | F79: CLC-R-02 | G79: MNE000209 | H79: 42398 | I79: Machinary and Equipment | J79: 09 | K79: Nestainer & Joint Pallet | L79: Sankyu Construction Jakarta | N79: 2016 | R79: 1 | T79: 179250000 | U79: =+T79/V79 -> 2987500 | V79: 60 | W79: 60 | X79: =+AC79/U79 -> 0 | Y79: =+W79+X79 -> 60 | Z79: =+V79-Y79 -> 0 | AA79: 179250000 | AB79: 0 | AC79: =SUM(AD79:AL79) -> 0 | AP79: =+AA79+AC79 -> 179250000 | AQ79: =IF(AS79=$AS$24,((T79-AP79)*0),T79-AP79) -> 0 | AV79: Ok | AW79: =IFERROR(VLOOKUP(G79,'[70]Detail Deprec_202508'!$D$33:$I$357,6,FALSE),0) -> 0 | AX79: =AW79-AK79 -> 0
A80: =+A79+1 -> 55 | B80: CLC | C80: CLCWH | D80: 154 | E80: OTHERS | F80: CLC-R-03 | G80: MNE000211 | H80: 42612 | I80: Machinary and Equipment | J80: 22 | K80: Nestainer | L80: Hanwa Indonesia | N80: 2016 | R80: 50 | T80: 82500000 | U80: =+T80/V80 -> 1375000 | V80: 60 | W80: 60 | X80: =+AC80/U80 -> 0 | Y80: =+W80+X80 -> 60 | Z80: =+V80-Y80 -> 0 | AA80: 82500000 | AB80: 0 | AC80: =SUM(AD80:AL80) -> 0 | AP80: =+AA80+AC80 -> 82500000 | AQ80: =IF(AS80=$AS$24,((T80-AP80)*0),T80-AP80) -> 0 | AV80: Ok | AW80: =IFERROR(VLOOKUP(G80,'[70]Detail Deprec_202508'!$D$33:$I$357,6,FALSE),0) -> 0 | AX80: =AW80-AK80 -> 0
A81: =+A80+1 -> 56 | B81: CLC | C81: CLCWH | D81: 154 | E81: OTHERS | F81: CLC-R-04 | G81: MNE000212 | H81: 42613 | I81: Machinary and Equipment | J81: 2025 | K81: Nestainer & Joint Pallet | L81: Hanwa Indonesia | N81: 2016 | R81: 230 | T81: 173355000 | U81: =+T81/V81 -> 2889250 | V81: 60 | W81: 60 | X81: =+AC81/U81 -> 0 | Y81: =+W81+X81 -> 60 | Z81: =+V81-Y81 -> 0 | AA81: 173355000 | AB81: 0 | AC81: =SUM(AD81:AL81) -> 0 | AP81: =+AA81+AC81 -> 173355000 | AQ81: =IF(AS81=$AS$24,((T81-AP81)*0),T81-AP81) -> 0 | AV81: Ok | AW81: =IFERROR(VLOOKUP(G81,'[70]Detail Deprec_202508'!$D$33:$I$357,6,FALSE),0) -> 0 | AX81: =AW81-AK81 -> 0
A82: =+A81+1 -> 57 | B82: CLC | C82: CLCWH | D82: 154 | E82: OTHERS | F82: CLC-R-05 | G82: MNE000215 | H82: 42733 | I82: Machinary and Equipment | J82: 18 | K82: Nestainer Rack | L82: Hanwa Indonesia | N82: 2016 | R82: 1 | T82: 29600000 | U82: =+T82/V82 -> 493333.33 | V82: 60 | W82: 60 | X82: =+AC82/U82 -> 0 | Y82: =+W82+X82 -> 60 | Z82: =+V82-Y82 -> 0 | AA82: 29600000 | AB82: 3.7252903e-09 | AC82: =SUM(AD82:AL82) -> 0 | AP82: =+AA82+AC82 -> 29600000 | AQ82: =IF(AS82=$AS$24,((T82-AP82)*0),T82-AP82) -> 3.7252903e-09 | AV82: Ok | AW82: =IFERROR(VLOOKUP(G82,'[70]Detail Deprec_202508'!$D$33:$I$357,6,FALSE),0) -> 0 | AX82: =AW82-AK82 -> 0
A83: =+A82+1 -> 58 | B83: CLC | C83: CLCWH | D83: 154 | E83: OTHERS | F83: CLC-R-06 | G83: MNE000218 | H83: 42860 | I83: Machinary and Equipment | J83: 03 | K83: Nestainer and Joint Pallet | L83: Hanwa Indonesia | N83: 2017 | R83: 1 | T83: 72000000 | U83: =+T83/V83 -> 1200000 | V83: 60 | W83: 60 | X83: =+AC83/U83 -> 0 | Y83: =+W83+X83 -> 60 | Z83: =+V83-Y83 -> 0 | AA83: 72000000 | AB83: 0 | AC83: =SUM(AD83:AL83) -> 0 | AP83: =+AA83+AC83 -> 72000000 | AQ83: =IF(AS83=$AS$24,((T83-AP83)*0),T83-AP83) -> 0 | AV83: Ok | AW83: =IFERROR(VLOOKUP(G83,'[70]Detail Deprec_202508'!$D$33:$I$357,6,FALSE),0) -> 0 | AX83: =AW83-AK83 -> 0
A84: =+A83+1 -> 59 | B84: CLC | C84: CLCWH | D84: 154 | E84: WH1 | F84: CLC134-017 | G84: MNE000219 | H84: 42885 | I84: Machinary and Equipment | J84: 15 | K84: Modification Eye Washer | L84: SMCC Utama | N84: 2017 | R84: 1 | T84: 180000000 | U84: =+T84/V84 -> 3000000 | V84: 60 | W84: 60 | X84: =+AC84/U84 -> 0 | Y84: =+W84+X84 -> 60 | Z84: =+V84-Y84 -> 0 | AA84: 180000000 | AB84: 0 | AC84: =SUM(AD84:AL84) -> 0 | AP84: =+AA84+AC84 -> 180000000 | AQ84: =IF(AS84=$AS$24,((T84-AP84)*0),T84-AP84) -> 0 | AV84: Ok | AW84: =IFERROR(VLOOKUP(G84,'[70]Detail Deprec_202508'!$D$33:$I$357,6,FALSE),0) -> 0 | AX84: =AW84-AK84 -> 0
A85: =+A84+1 -> 60 | B85: CLC | C85: CLCWH | D85: 154 | E85: OTHERS | F85: CLC-R-07 | G85: MNE000220 | H85: 42908 | I85: Machinary and Equipment | J85: 19 | K85: Nestainer and Joint Pallet | L85: Hanwa Indonesia | N85: 2017 | R85: 393 | T85: 417780000 | U85: =+T85/V85 -> 6963000 | V85: 60 | W85: 60 | X85: =+AC85/U85 -> 0 | Y85: =+W85+X85 -> 60 | Z85: =+V85-Y85 -> 0 | AA85: 417780000 | AB85: 0 | AC85: =SUM(AD85:AL85) -> 0 | AP85: =+AA85+AC85 -> 417780000 | AQ85: =IF(AS85=$AS$24,((T85-AP85)*0),T85-AP85) -> 0 | AV85: Ok | AW85: =IFERROR(VLOOKUP(G85,'[70]Detail Deprec_202508'!$D$33:$I$357,6,FALSE),0) -> 0 | AX85: =AW85-AK85 -> 0
A86: =+A85+1 -> 61 | B86: CLC | C86: CLCWH | D86: 154 | E86: OTHERS | F86: CLC-R-08 | G86: MNE000230 | H86: 43097 | I86: Machinary and Equipment | J86: 23 | K86: Nestainer Rack | L86: Hanwa Indonesia | N86: 2017 | R86: 454 | T86: 588744000 | U86: =+T86/V86 -> 9812400 | V86: 60 | W86: 60 | X86: =+AC86/U86 -> 0 | Y86: =+W86+X86 -> 60 | Z86: =+V86-Y86 -> 0 | AA86: 588744000 | AB86: 0 | AC86: =SUM(AD86:AL86) -> 0 | AP86: =+AA86+AC86 -> 588744000 | AQ86: =IF(AS86=$AS$24,((T86-AP86)*0),T86-AP86) -> 0 | AV86: Ok | AW86: =IFERROR(VLOOKUP(G86,'[70]Detail Deprec_202508'!$D$33:$I$357,6,FALSE),0) -> 0 | AX86: =AW86-AK86 -> 0
A87: =+A86+1 -> 62 | B87: CLC | C87: CLCWH | D87: 154 | E87: OTHERS | F87: CLC-R-09 | G87: MNE000233 | H87: 43158 | I87: Machinary and Equipment | J87: JKT_GL000856 | K87: Nestainer and Joint Pallet | L87: Hanwa Indonesia | N87: 2018 | R87: 848 | T87: 865600000 | U87: =+T87/V87 -> 14426667 | V87: 60 | W87: 60 | X87: =+AC87/U87 -> 0 | Y87: =+W87+X87 -> 60 | Z87: =+V87-Y87 -> 0 | AA87: 865600000 | AB87: 0 | AC87: =SUM(AD87:AL87) -> 0 | AP87: =+AA87+AC87 -> 865600000 | AQ87: =IF(AS87=$AS$24,((T87-AP87)*0),T87-AP87) -> 0 | AU87: Finish 28 Feb 23 | AV87: Ok | AW87: =IFERROR(VLOOKUP(G87,'[70]Detail Deprec_202508'!$D$33:$I$357,6,FALSE),0) -> 0 | AX87: =AW87-AK87 -> 0
A88: =+A87+1 -> 63 | B88: CLC | C88: CLCWH | D88: 154 | E88: OTHERS | F88: CLC134-066 | G88: MNE000236 | H88: 43220 | I88: Machinary and Equipment | K88: Container 40 Ft (Second) | L88: Wahana Bintang Transindo | N88: 2018 | R88: 1 | T88: 29500000 | U88: =+T88/V88 -> 819444.44 | V88: 36 | W88: 36 | X88: =+AC88/U88 -> 0 | Y88: =+W88+X88 -> 36 | Z88: =+V88-Y88 -> 0 | AA88: 29500000 | AB88: 3.7252903e-09 | AC88: =SUM(AD88:AL88) -> 0 | AP88: =+AA88+AC88 -> 29500000 | AQ88: =IF(AS88=$AS$24,((T88-AP88)*0),T88-AP88) -> 3.7252903e-09 | AV88: Ok | AW88: =IFERROR(VLOOKUP(G88,'[70]Detail Deprec_202508'!$D$33:$I$357,6,FALSE),0) -> 0 | AX88: =AW88-AK88 -> 0
A89: =+A88+1 -> 64 | B89: CLC | C89: CLCWH | D89: 154 | E89: OTHERS | F89: CLC134-067 | G89: MNE000237 | H89: 43220 | I89: Machinary and Equipment | K89: Container 40 Ft (Second) | L89: Wahana Bintang Transindo | N89: 2018 | R89: 1 | T89: 29500000 | U89: =+T89/V89 -> 819444.44 | V89: 36 | W89: 36 | X89: =+AC89/U89 -> 0 | Y89: =+W89+X89 -> 36 | Z89: =+V89-Y89 -> 0 | AA89: 29500000 | AB89: 3.7252903e-09 | AC89: =SUM(AD89:AL89) -> 0 | AP89: =+AA89+AC89 -> 29500000 | AQ89: =IF(AS89=$AS$24,((T89-AP89)*0),T89-AP89) -> 3.7252903e-09 | AV89: Ok | AW89: =IFERROR(VLOOKUP(G89,'[70]Detail Deprec_202508'!$D$33:$I$357,6,FALSE),0) -> 0 | AX89: =AW89-AK89 -> 0
A90: =+A89+1 -> 65 | B90: CLC | C90: CLCWH | D90: 154 | E90: OTHERS | F90: CLC134-068 | G90: MNE000238 | H90: 43220 | I90: Machinary and Equipment | K90: Container 40 Ft (Second) | L90: Wahana Bintang Transindo | N90: 2018 | R90: 1 | T90: 29500000 | U90: =+T90/V90 -> 819444.44 | V90: 36 | W90: 36 | X90: =+AC90/U90 -> 0 | Y90: =+W90+X90 -> 36 | Z90: =+V90-Y90 -> 0 | AA90: 29500000 | AB90: 3.7252903e-09 | AC90: =SUM(AD90:AL90) -> 0 | AP90: =+AA90+AC90 -> 29500000 | AQ90: =IF(AS90=$AS$24,((T90-AP90)*0),T90-AP90) -> 3.7252903e-09 | AV90: Ok | AW90: =IFERROR(VLOOKUP(G90,'[70]Detail Deprec_202508'!$D$33:$I$357,6,FALSE),0) -> 0 | AX90: =AW90-AK90 -> 0
A91: =+A90+1 -> 66 | B91: CLC | C91: CLCWH | D91: 154 | E91: OTHERS | F91: CLC134-069 | G91: MNE000239 | H91: 43220 | I91: Machinary and Equipment | K91: Container 40 Ft (Second) | L91: Wahana Bintang Transindo | N91: 2018 | R91: 1 | T91: 29500000 | U91: =+T91/V91 -> 819444.44 | V91: 36 | W91: 36 | X91: =+AC91/U91 -> 0 | Y91: =+W91+X91 -> 36 | Z91: =+V91-Y91 -> 0 | AA91: 29500000 | AB91: 3.7252903e-09 | AC91: =SUM(AD91:AL91) -> 0 | AP91: =+AA91+AC91 -> 29500000 | AQ91: =IF(AS91=$AS$24,((T91-AP91)*0),T91-AP91) -> 3.7252903e-09 | AV91: Ok | AW91: =IFERROR(VLOOKUP(G91,'[70]Detail Deprec_202508'!$D$33:$I$357,6,FALSE),0) -> 0 | AX91: =AW91-AK91 -> 0
A92: =+A91+1 -> 67 | B92: CLC | C92: CLCWH | D92: 154 | E92: OTHERS | F92: CLC-R-10 | G92: MNE000243 | H92: 43343 | I92: Machinary and Equipment | J92: JKT_GL003844 | K92: Nestainer and Joint Pallet | L92: Hanwa Indonesia | N92: 2018 | R92: 701 | T92: 847200000 | U92: =+T92/V92 -> 14120000 | V92: 60 | W92: 60 | X92: =+AC92/U92 -> 0 | Y92: =+W92+X92 -> 60 | Z92: =+V92-Y92 -> 0 | AA92: 847200000 | AB92: 0 | AC92: =SUM(AD92:AL92) -> 0 | AP92: =+AA92+AC92 -> 847200000 | AQ92: =IF(AS92=$AS$24,((T92-AP92)*0),T92-AP92) -> 0 | AV92: Ok | AW92: =IFERROR(VLOOKUP(G92,'[70]Detail Deprec_202508'!$D$33:$I$357,6,FALSE),0) -> 0 | AX92: =AW92-AK92 -> 0
A93: =+A92+1 -> 68 | B93: CLC | C93: CLCWH | D93: 154 | E93: OTHERS | F93: CLC-R-11 | G93: MNE000244 | H93: 43343 | I93: Machinary and Equipment | J93: JKT_GL003850 | K93: Nestainer and Joint Pallet | L93: Hanwa Indonesia | N93: 2018 | R93: 255 | T93: 636750000 | U93: =+T93/V93 -> 10612500 | V93: 60 | W93: 60 | X93: =+AC93/U93 -> 0 | Y93: =+W93+X93 -> 60 | Z93: =+V93-Y93 -> 0 | AA93: 636750000 | AB93: 0 | AC93: =SUM(AD93:AL93) -> 0 | AP93: =+AA93+AC93 -> 636750000 | AQ93: =IF(AS93=$AS$24,((T93-AP93)*0),T93-AP93) -> 0 | AV93: Ok | AW93: =IFERROR(VLOOKUP(G93,'[70]Detail Deprec_202508'!$D$33:$I$357,6,FALSE),0) -> 0 | AX93: =AW93-AK93 -> 0
A94: =+A93+1 -> 69 | B94: CLC_SBY | C94: CLCWH | D94: 154 | E94: SBY | F94: CLC134-018 | G94: MNE000251 | H94: 43370 | I94: Machinary and Equipment | J94: JKT_GL004318 | K94: Fire Alarm System at Surabaya | L94: Panca Jaya Kencana | M94: Surabaya | N94: 2018 | R94: 1 | T94: 70726150 | U94: =+T94/V94 -> 1178769.2 | V94: 60 | W94: 60 | X94: =+AC94/U94 -> 0 | Y94: =+W94+X94 -> 60 | Z94: =+V94-Y94 -> 0 | AA94: 70726150 | AB94: 0 | AC94: =SUM(AD94:AL94) -> 0 | AP94: =+AA94+AC94 -> 70726150 | AQ94: =IF(AS94=$AS$24,((T94-AP94)*0),T94-AP94) -> 0 | AV94: Ok | AW94: =IFERROR(VLOOKUP(G94,'[70]Detail Deprec_202508'!$D$33:$I$357,6,FALSE),0) -> 0 | AX94: =AW94-AK94 -> 0
A95: =+A94+1 -> 70 | B95: CLC_SBY | C95: CLCWH | D95: 154 | E95: SBY | F95: CLC134-019 | G95: MNE000250 | H95: 43370 | I95: Machinary and Equipment | J95: JKT_GL004318 | K95: CCTV Warehouse at Surabaya | L95: Panca Jaya Kencana | M95: Surabaya | N95: 2018 | R95: 1 | T95: 32227800 | U95: =+T95/V95 -> 537130 | V95: 60 | W95: 60 | X95: =+AC95/U95 -> 0 | Y95: =+W95+X95 -> 60 | Z95: =+V95-Y95 -> 0 | AA95: 32227800 | AB95: 0 | AC95: =SUM(AD95:AL95) -> 0 | AP95: =+AA95+AC95 -> 32227800 | AQ95: =IF(AS95=$AS$24,((T95-AP95)*0),T95-AP95) -> 0 | AV95: Ok | AW95: =IFERROR(VLOOKUP(G95,'[70]Detail Deprec_202508'!$D$33:$I$357,6,FALSE),0) -> 0 | AX95: =AW95-AK95 -> 0
A96: =+A95+1 -> 71 | B96: CLC_SBY | C96: CLCWH | D96: 154 | E96: SBY | F96: CLC134-020 | G96: MNE000249 | H96: 43370 | I96: Machinary and Equipment | J96: JKT_GL004318 | K96: Fire Alarm (Smoke Detector) at Surabaya | L96: Panca Jaya Kencana | M96: Surabaya | N96: 2018 | R96: 1 | T96: 228315940 | U96: =+T96/V96 -> 3805265.7 | V96: 60 | W96: 60 | X96: =+AC96/U96 -> 0 | Y96: =+W96+X96 -> 60 | Z96: =+V96-Y96 -> 0 | AA96: 228315940 | AB96: 0 | AC96: =SUM(AD96:AL96) -> 0 | AP96: =+AA96+AC96 -> 228315940 | AQ96: =IF(AS96=$AS$24,((T96-AP96)*0),T96-AP96) -> 0 | AV96: Ok | AW96: =IFERROR(VLOOKUP(G96,'[70]Detail Deprec_202508'!$D$33:$I$357,6,FALSE),0) -> 0 | AX96: =AW96-AK96 -> 0
A97: =+A96+1 -> 72 | B97: CLC | C97: CLCWH | D97: 154 | E97: OTHERS | F97: CLC-R-13 | G97: MNE000290 | H97: 44027 | I97: Machinary and Equipment | J97: JKT_GL012307 | K97: Nestainer | L97: Hanwa Indonesia | N97: 2020 | O97: 344 Unit | P97: 182 Rack Nestainer | Q97: 162 Joint Pallet | R97: 344 | T97: 412700000 | U97: =+T97/V97 -> 6878333.3 | V97: 60 | W97: 60 | X97: =+AC97/U97 -> 0 | Y97: =+W97+X97 -> 60 | Z97: 0 | AA97: 412700000 | AB97: 0 | AC97: =SUM(AD97:AO97) -> 0 | AP97: =+AA97+AC97 -> 412700000 | AQ97: =IF(AS97=$AS$24,((T97-AP97)*0),T97-AP97) -> 0 | AV97: Ok | AW97: =IFERROR(VLOOKUP(G97,'[70]Detail Deprec_202508'!$D$33:$I$357,6,FALSE),0) -> 0 | AX97: =AW97-AK97 -> 0
A98: =+A97+1 -> 73 | B98: CLC | C98: CLCWH | D98: 154 | E98: OTHERS | F98: CLC133-025 | G98: MNE000292 | H98: 44042 | I98: Machinary and Equipment | J98: JKT_GL012424 | K98: Stand Baterry | L98: Jakarta Construction | N98: 2020 | O98: 1 Unit | R98: 1 | T98: 35180636 | U98: =+T98/V98 -> 586343.93 | V98: 60 | W98: 60 | X98: =+AC98/U98 -> 0 | Y98: =+W98+X98 -> 60 | Z98: =+V98-Y98 -> 0 | AA98: 35180636 | AB98: -7.4505806e-09 | AC98: =SUM(AD98:AL98) -> 0 | AP98: =+AA98+AC98 -> 35180636 | AQ98: =IF(AS98=$AS$24,((T98-AP98)*0),T98-AP98) -> -7.4505806e-09 | AV98: Ok | AW98: =IFERROR(VLOOKUP(G98,'[70]Detail Deprec_202508'!$D$33:$I$357,6,FALSE),0) -> 0 | AX98: =AW98-AK98 -> 0
A99: =+A98+1 -> 74 | B99: CLC | C99: CLCWH | D99: 154 | E99: OTHERS | F99: CLC-R-12 | G99: MNE000298 | H99: 44286 | I99: Machinary and Equipment | J99: JKT_GL014337 | K99: Nistainer | L99: JKTC | N99: 2021 | O99: 905 Unit | P99: L1190xW1250xH1250 | Q99: W 1250 (L1250) | R99: 905 | T99: 1487754320 | U99: =+T99/V99 -> 24795905 | V99: 60 | W99: =46+12 -> 58 | X99: =+AC99/U99 -> 2 | Y99: =+W99+X99 -> 60 | Z99: =+V99-Y99 -> 0 | AA99: 1.4381625e+09 | AB99: 49591811 | AC99: =SUM(AD99:AE99) -> 49591811 | AD99: 24795905 | AE99: 24795905 | AP99: =+AA99+AC99 -> 1.4877543e+09 | AQ99: =IF(AS99=$AS$24,((T99-AP99)*0),T99-AP99) -> -2.3841858e-07 | AU99: 44286 | AV99: Ok | AW99: =IFERROR(VLOOKUP(G99,'[70]Detail Deprec_202508'!$D$33:$I$357,6,FALSE),0) -> 24795905 | AX99: =AW99-AK99 -> 24795905
A100: =+A99+1 -> 75 | B100: CLC | C100: CLCWH | D100: 154 | E100: OTHERS | F100: CLC-R-14 | G100: MNE000315 | H100: 44957 | I100: Machinary and Equipment | J100: JKTGL_019643 | K100: Racking System | L100: Jakarta Construction | M100: 445 Set | N100: 2023 | O100: Nestainer 227 Set | P100: Join 218 Set | R100: 445 | T100: 929200000 | U100: =+T100/V100 -> 15486667 | V100: 60 | W100: =24+12 -> 36 | X100: =+AC100/U100 -> 12 | Y100: =+W100+X100 -> 48 | Z100: =+V100-Y100 -> 12 | AA100: 5.5752e+08 | AB100: 3.7168e+08 | AC100: =SUM(AD100:AO100) -> 1.8584e+08 | AD100: 15486667 | AE100: 15486667 | AF100: 15486667 | AG100: 15486667 | AH100: 15486667 | AI100: 15486667 | AJ100: 15486667 | AK100: 15486667 | AL100: 15486667 | AM100: 15486667 | AN100: 15486667 | AO100: 15486667 | AP100: =+AA100+AC100 -> 7.4336e+08 | AQ100: =IF(AS100=$AS$24,((T100-AP100)*0),T100-AP100) -> 1.8584e+08 | AU100: 44925 | AV100: Ok | AW100: =IFERROR(VLOOKUP(G100,'[70]Detail Deprec_202508'!$D$33:$I$357,6,FALSE),0) -> 15486667 | AX100: =AW100-AK100 -> 0.0033333339
A101: =+A100+1 -> 76 | B101: CLC | C101: CLCOWH | D101: 154 | E101: BALI | F101: CLC134-071 | G101: MNE000332 | H101: 45838 | I101: Machinary and Equipment | K101: Loading/Unloading Ramping System | L101: Indotara | M101: 10 T | N101: 2025 | O101: PTR10WM/10T | P101: A825-138 | Q101: DHE-809-80 | R101: 1 | T101: 145223481 | U101: =+T101/V101 -> 4033985.6 | V101: 36 | W101: =7+12 -> 19 | X101: =+AC101/U101 -> 12 | Y101: =+W101+X101 -> 31 | Z101: =+V101-Y101 -> 5 | AA101: 28237899 | AB101: 1.1698558e+08 | AC101: =SUM(AD101:AO101) -> 48407827 | AD101: 4033985.6 | AE101: 4033985.6 | AF101: 4033985.6 | AG101: 4033985.6 | AH101: 4033985.6 | AI101: 4033985.6 | AJ101: 4033985.6 | AK101: 4033985.6 | AL101: 4033985.6 | AM101: 4033985.6 | AN101: 4033985.6 | AO101: 4033985.6 | AP101: =+AA101+AC101 -> 76645726 | AQ101: =IF(AS101=$AS$24,((T101-AP101)*0),T101-AP101) -> 68577755 | AR101: Additional | AV101: OK | AW101: =IFERROR(VLOOKUP(G101,'[70]Detail Deprec_202508'!$D$33:$I$357,6,FALSE),0) -> 4033985.6 | AX101: =AW101-AK101 -> -0.023333333
A102: =+A101+1 -> 77 | B102: CLC | C102: CLCTRP | D102: 155 | E102: TRP | F102: TG-C-015 | G102: VEH000067 | H102: 38541 | I102: Vehicles | J102: 8006 | K102: Head Trucktor | L102: Nissan Diesel | M102: 26T | N102: 2005 | O102: A 9174 RM | P102: PE6195714T | Q102: MHPWM432H5K000005 | R102: 1 | T102: 505454546 | U102: =+T102/V102 -> 8424242.4 | V102: 60 | W102: 60 | X102: =+AC102/U102 -> 0 | Y102: =+W102+X102 -> 60 | Z102: =+V102-Y102 -> 0 | AA102: 505454546 | AB102: 0 | AC102: =SUM(AD102:AL102) -> 0 | AP102: =+AA102+AC102 -> 505454546 | AQ102: =IF(AS102=$AS$24,((T102-AP102)*0),T102-AP102) -> 0 | AS102: Disposals | AU102: 45838 | AV102: Ok | AW102: =IFERROR(VLOOKUP(G102,'[71]Detail Deprec_202501'!$D$246:$I$393,6,FALSE),0) -> 0 | AX102: =AW102-AK102 -> 0
A103: =+A102+1 -> 78 | B103: CLC | C103: CLCTRP | D103: 155 | E103: TRP | F103: TG-C-014 | G103: VEH000068 | H103: 38541 | I103: Vehicles | J103: 8006 | K103: Head Trucktor | L103: Nissan Diesel | M103: 25T | N103: 2005 | O103: A 9173 RM | P103: PE6195713T | Q103: MHPWM432H5K000004 | R103: 1 | T103: 505454546 | U103: =+T103/V103 -> 8424242.4 | V103: 60 | W103: 60 | X103: =+AC103/U103 -> 0 | Y103: =+W103+X103 -> 60 | Z103: =+V103-Y103 -> 0 | AA103: 505454546 | AB103: 0 | AC103: =SUM(AD103:AL103) -> 0 | AP103: =+AA103+AC103 -> 505454546 | AQ103: =IF(AS103=$AS$24,((T103-AP103)*0),T103-AP103) -> 0 | AS103: Disposals | AU103: 45838 | AV103: Ok | AW103: =IFERROR(VLOOKUP(G103,'[71]Detail Deprec_202501'!$D$246:$I$393,6,FALSE),0) -> 0 | AX103: =AW103-AK103 -> 0
...

Sheet Sheet1
D4: Land | E4: 7 Location
D5: Buildings | E5: 78 Office and Workshop
D6: Structures | E6: 61 Structure
D7: Machinery & Equipments | E7: 278 Machine & Equipment
D8: Vehicles | E8: 474 Vehicle
D9: Tools, Furnitures & Fixtures | E9: 181 Tools & Furnitur
D10: Non-Asset | E10: 88 Item Machine, Tools and Vehicle

Sheet List Approval 2022
A1: PT. SANKYU INDONESIA INTERNATIONAL
A2: LIST OF ACQUISITION & DISPOSALS ASSET
A3: JAN - JUN 2022 (1st SEMESTER)
A5: No. | B5: Site | C5: Job | D5: Fixed Asset | F5: Application | H5: Purchase/Disposed Date | I5: Bookslip No. | J5: Name of Fixed Asset | K5: Purchase/Disposal Prices | L5: Status | N5: Vendor/Customer
D6: AX | E6: No. | F6: No. | G6: Date | L6: Acquisition | M6: Disposals
A8: 1 | B8: KS | C8: 7R | D8: VEH000322 | E8: 7R-C-044 | F8: 7R-001 | G8: 44592 | H8: 44608 | I8: 20220225_070-02 | J8: Forklift TCM | K8: 60000000 | M8: Disposals | N8: Rizqi Putra P. | O8: Ok
A9: 2 | B9: KS | C9: 7R | D9: VEH000629 | E9: 7R-C-051 | F9: 7R-001 | G9: 44592 | H9: 44834 | I9: 20220830_006-08 | J9: Forklift 10 Ton | K9: 1075000000 | L9: Acquisition | N9: Kasana | O9: Ok
A10: 3 | B10: CLC | C10: CLCWH | D10: STR000022 | E10: CLC133-006 | F10: CLC1133-006 | G10: 44606 | H10: 44606 | I10: 20220225_071-02 | J10: Floor Harder | K10: - | M10: Disposals | N10: CLCWH | O10: Ok
A11: 4 | B11: CLGC | C11: M10 | D11: VEH000615 | E11: M10-C-054 | G11: 44607 | H11: 44642 | I11: 20220322_009-03 | J11: Toyota Fortuner | K11: 540419432 | L11: Acquisition | N11: Tunas Radean | O11: Ok
B12: ASC | C12: 3A | D12: VEH000614 | E12: 3A-C-263 | F12: 3A-031 | G12: 44607 | H12: 44642 | I12: 20220322_009-03 | J12: Toyota Fortuner | K12: 540419432 | L12: Acquisition | N12: Tunas Radean | O12: Ok
A13: 5 | B13: CLGC | C13: M10 | D13: VEH000138 | E13: M10-C-012 | F13: CLGC-22-001S | G13: 44614 | H13: 44651 | I13: 20220231_034-03 | J13: Hydraulic Crane 45 Ton | K13: 500000000 | M13: Disposals | N13: Fedis Putra U. | O13: Ok
A14: 6 | B14: HO | C14: 502 | D14: STR000064 | F14: 502-001 | G14: 44621 | H14: 44651 | I14: 20220331_012-03 | J14: AC Daikin | K14: 32768000 | L14: Acquisition | N14: Manunggal SD | O14: Ok
C15: 502 | D15: STR000065 | F15: 502-001 | G15: 44621 | H15: 44651 | I15: 20220331_012-03 | J15: AC Daikin | K15: 33700500 | L15: Acquisition | N15: Manunggal SD | O15: Ok
A16: 7 | B16: KS | C16: 7R | D16: VEH000634 | F16: 7R-002 | G16: 44636 | H16: 44880 | I16: 20221115_015-11 | J16: Mini Excavator | K16: 890000000 | L16: Acquisition | N16: Kasana | O16: Ok
A17: 8 | B17: CLGC | C17: M10 | D17: VEH000462 | E17: M10-C-034 | F17: CLGC-22-002S | G17: 44641 | H17: 44651 | I17: 20220331_035-03 | J17: Mitsubishi Fajero | K17: 136363636 | M17: Disposals | N17: Fajar Hikmah | O17: Ok
A18: 9 | B18: ASC | C18: 3A | D18: VEH000463 | E18: 3A-C-208 | F18: 3A-039 | G18: 44641 | H18: 44651 | I18: 20220331_035-03 | J18: Mitsubishi Fajero | K18: 136363636 | M18: Disposals | N18: Fajar Hikmah | O18: OK
A19: 10 | B19: CLG | C19: 7 | D19: STR000066 | E19: 7-A-040 | F19: 7-001 | G19: 44650 | H19: 44665 | I19: 20220414_012-04 | J19: Air Conditioner | K19: 63625000 | L19: Acquisition | N19: Prima Mandiri | O19: Ok
C20: 7 | D20: STR000067 | E20: 7-A-041 | F20: 7-001 | G20: 44650 | H20: 44665 | I20: 20220414_012-04 | J20: Air Conditioner | K20: 63625000 | L20: Acquisition | N20: Prima Mandiri | O20: Ok
A21: 11 | B21: CLGC | C21: M10 | D21: MNE000304 | E21: M10-B-131 | F21: CLGC-22-002P | G21: 12145 | H21: 44694 | I21: 20220513_012-05 | J21: Magnrtic Drilling Machine | K21: 16041200 | L21: Acquisition | N21: Kawan Lama | O21: Ok
B22: CLGC | C22: M10 | D22: MNE000305 | E22: M10-B-132 | F22: CLGC-22-002P | G22: 12145 | H22: 44694 | I22: 20220513_012-05 | J22: Magnrtic Drilling Machine | K22: 16041200 | L22: Acquisition | N22: Kawan Lama | O22: Ok
A23: 12 | B23: HO | C23: 502 | D23: VEH000620 | F23: ADM | G23: 44662 | H23: 44711 | I23: 20220530_005-04 | J23: Avanza E M.T | K23: 192151181 | L23: Acquisition | N23: Auto2000 | O23: Ok
A24: 13 | B24: CLC | C24: CLCTRP | D24: VEH000090 | E24: CLC-C-14T | F24: CLC-C-14T | G24: 44677 | H24: 44712 | I24: 20220531_070-05 | J24: Truck Flat Bad | K24: 58000000 | M24: Disposals | N24: Teguh Arifian | O24: Ok
A25: 14 | B25: CLC | C25: 3ID | D25: VEH000555 | F25: CLC-C-14T | G25: 44704 | H25: 44712 | I25: 20220531_071-05 | J25: Forklift | K25: 160000000 | M25: Disposals | N25: Guzilla | O25: Ok
A26: 15 | B26: CLGA | C26: 7 | D26: VEH000422 | E26: 3A-C-202 | F26: 7-001 | G26: 44691 | H26: 44712 | I26: 20220531_072-05 | J26: Fortuner | K26: 117117117 | M26: Disposals | N26: Mutiara S. K. | O26: Ok
A27: 16 | B27: CLGL | C27: 7CL | D27: VEH000111 | E27: 7C-C-083 | G27: 44706 | H27: 44742 | I27: 20220630_065-06 | J27: Truck Dyna | K27: 54954955 | M27: Disposals | N27: Kranindo Perjaya | O27: Ok
A28: 17 | B28: CLGL | C28: 7CL | D28: VEH000193 | E28: 7C-C-129 | G28: 44719 | H28: 44742 | I28: 20220630_064-06 | J28: CR-V | K28: 67567568 | M28: Disposals | N28: Start Muri Indonesia | O28: Ok
A29: 18 | B29: ASC | C29: 3A | D29: VEH000648 | E29: 3A-C-282 | F29: 3A-034-035 | G29: 44714 | H29: 45085 | I29: 20230608_007-06 | J29: Bulldozer | K29: 2275000000 | L29: Acquisition | N29: United Tractors | O29: Ok
B30: ASC | C30: 3A | D30: VEH000647 | E30: 3A-C-281 | F30: 3A-034-035 | G30: 44714 | H30: 45085 | I30: 20230608_007-06 | J30: Bulldozer | K30: 2275000000 | L30: Acquisition | N30: United Tractors | O30: Ok
B31: ASC | C31: 3A | D31: VEH000650 | E31: 3A-C-184 | F31: 3A-034-035 | G31: 44714 | H31: 45107 | I31: 20230717_006-07 | J31: Bulldozer | K31: 2275000000 | L31: Acquisition | N31: United Tractors | O31: OK
B32: ASC | C32: 3A | D32: VEH000649 | E32: 3A-C-283 | F32: 3A-034-035 | G32: 44714 | H32: 45085 | I32: 20230608_007-06 | J32: Bulldozer | K32: 1530000000 | L32: Acquisition | N32: United Tractors | O32: Ok
B33: ASC | C33: 3A | D33: VEH000640 | E33: 3A-C-280 | F33: 3A-034-035 | G33: 44714 | H33: 44985 | I33: 20230228_087-02 | J33: Bulldozer | K33: 3150000000 | L33: Acquisition | N33: United Tractors | O33: Ok
B34: ASC | C34: 3A | D34: VEH000633 | E34: 3A-C-278 | F34: 3A-034-035 | G34: 44714 | H34: 44819 | I34: 20220915_007-09 | J34: Excavator | K34: 1400000000 | L34: Acquisition | N34: United Tractors | O34: Ok
A35: 19 | B35: ASC | C35: 3A | D35: MNE000306 | E35: 3A-B-071 | F35: 3A-034-033 | G35: 44714 | H35: 44771 | I35: 20220729_102 | J35: Drum Cliper | K35: 39000000 | L35: Acquisition | N35: Sunstream Indonesia | O35: Ok
B36: ASC | C36: 3A | D36: MNE000307 | E36: 3A-B-072 | F36: 3A-034-033 | G36: 44714 | H36: 44771 | I36: 20220729_102 | J36: Drum Cliper | K36: 39000000 | L36: Acquisition | N36: Sunstream Indonesia | O36: Ok
A37: 20 | B37: ASC | C37: 3A | D37: VEH000638 | E37: 3A-C-279 | F37: 3A-032 | G37: 44714 | H37: 44956 | I37: 20230130_046-01 | J37: Forlift Battery | K37: 505000000 | L37: Acquisition | N37: Traktor Nusantara | O37: Ok
A38: 21
A39: 22
A41: No. | B41: Site | C41: Job | D41: Fixed Asset | F41: Application | H41: Purchase/Disposed Date | I41: Bookslip No. | J41: Name of Fixed Asset | K41: Purchase/Disposal Prices | L41: Status | N41: Vendor/Customer
D42: AX | E42: No. | F42: No. | G42: Date | L42: Acquisition | M42: Disposals
A43: 23 | B43: CLGC | C43: M10 | D43: VEH000636 | E43: M10-C-056 | F43: CLGC-22-003P | G43: 44774 | H43: 44925 | I43: 20221230_117 | J43: Unic Crane 10T - Head | K43: 1380000000 | L43: Acquisition | N43: United Tractors | O43: Ok
B44: CLGC | C44: M10 | D44: VEH000637 | E44: M10-C-057 | F44: CLGC-22-003P | G44: 44774 | H44: 44925 | I44: 20221230_118 | J44: Unic Crane 10T - Crane | K44: 810000000 | L44: Acquisition | N44: United Tractors | O44: Ok
A45: 24 | B45: CLGC | C45: M10 | D45: FNF000106 | E45: M10-A-023 | F45: CLGC-22-003S | G45: 44776 | H45: 44804 | I45: 20220831_116-08 | J45: FC Xerox | K45: 11000000 | M45: Disposals | N45: Astra Graphia | O45: Ok
A46: 25 | B46: CLGC | C46: M10 | D46: FNF000209 | E46: M10-A-034 | F46: CLGC-22-004P | G46: 44776 | H46: 44804 | I46: 20220831_115-08 | J46: FC Xerox | K46: 83500000 | L46: Acquisition | N46: Astra Graphia | O46: Ok
A47: 26 | B47: CLC | C47: CLCWH | D47: VEH000632 | E47: CLC135-001 | F47: CLC135-001 | G47: 44781 | H47: 44726 | I47: 20220914_005-09 | J47: Kijang Inova | K47: 328364415 | L47: Acquisition | N47: Auto2000 | O47: Ok
A48: 27 | B48: ASC | C48: 3A | D48: VEH000559 | E48: 3A-C-235 | F48: 3A-036 | G48: 44784 | H48: 44834 | I48: 20220931_044-09 | J48: Bulldozer | K48: 13000000 | M48: Disposals | N48: Ciptamas Persada | O48: Ok
A49: 28 | B49: ASC | C49: 3A | D49: MNE000231 | E49: 3A-B-051 | F49: 3A-037 | G49: 44784 | H49: 44834 | I49: 20220931_044-09 | J49: Drum Dumper | K49: 1000000 | M49: Disposals | N49: Ciptamas Persada | O49: Ok
B50: ASC | C50: 3A | D50: MNE000232 | E50: 3A-B-052 | F50: 3A-037 | G50: 44784 | H50: 44834 | I50: 20220931_044-09 | J50: Drum Dumper | K50: 1000000 | M50: Disposals | N50: Ciptamas Persada | O50: Ok
A51: 29 | B51: CLGC | C51: M10 | D51: VEH000645 | E51: M10-C-059 | F51: CLGC-22-005P | G51: 44788 | H51: 30-4-232 | I51: 20230515_010-05 | J51: UD Truck | K51: 1380000000 | L51: Acquisition | N51: United Tractors | O51: Ok
B52: CLGC | C52: M10 | D52: VEH000646 | E52: M10-C-060 | F52: CLGC-22-005P | G52: 44788 | H52: 30-4-232 | I52: 20230515_010-05 | J52: Truck Loader Crane | K52: 810000000 | L52: Acquisition | N52: United Tractors | O52: Ok
A53: 30 | B53: CLGL | C53: 7CL | D53: FNF000210 | E53: 7C-A-015 | F53: 7CL-2202 | G53: 44798 | H53: 44804 | I53: 20110930_045-09 | J53: IJ-CAD STD (AutoCad) | L53: Acquisition | N53: System Metrix | O53: OK
A54: 31 | B54: CLC | C54: CLCWH | D54: STR000068 | E54: CLC134-023A | G54: 44802 | H54: 44865 | I54: 202241031_086-10 | J54: Body Harness Hangers | K54: 62500000 | L54: Acquisition | N54: JKTC | O54: OK
B55: CLC | C55: CLCWH | D55: STR000069 | E55: CLC134-023B | G55: 44802 | H55: 44865 | I55: 202241031_086-10 | J55: Body Harness Hangers | K55: 62500000 | L55: Acquisition | N55: JKTC | O55: OK
A56: 32 | B56: CLGC | C56: M10 | D56: VEH000635 | E56: M10-C-055 | F56: CLGC-22-007P | G56: 44823 | H56: 44925 | I56: 20221230_116-12 | J56: Tadano Rough Terrain Crane | K56: 6780000000 | L56: Acquisition | N56: United Tractors | O56: Ok
A57: 33 | B57: CLC | C57: CLCWH | D57: MNE000315 | E57: CLC-R-13 | G57: 44837 | H57: 44957 | I57: 20230131-046-01 | J57: Nestainer & Join Pallet | K57: 929200000 | L57: Acquisition | N57: JKTC | O57: Ok
A58: 34 | B58: CLGC | C58: M10 | D58: VEH000639 | E58: M10-C-058 | F58: CLGC-22-006P | G58: 44904 | H58: 44985 | I58: 20230217_009-02 | J58: Avanza 1.5 G CVT | K58: 221050226 | L58: Acquisition | N58: Astra Intl | O58: Ok
A59: 35 | B59: CLGC | C59: M10 | D59: MNE000311 | E59: M10-B-136 | F59: CLGC-22-008P | G59: 44915 | H59: 44925 | I59: 20221230_014-12 | J59: JO-Tech Electric Winch 1 Ton | K59: 49875000 | L59: Acquisition | N59: Mutiara Andalas Strategi | O59: Ok
B60: CLGC | C60: M10 | D60: MNE000312 | E60: M10-B-137 | F60: CLGC-22-008P | G60: 44915 | H60: 44925 | I60: 20221230_014-12 | J60: JO-Tech Electric Winch 1 Ton | K60: 49875000 | L60: Acquisition | N60: Mutiara Andalas Strategi | O60: Ok
A61: 36 | B61: CLGC | C61: M10 | D61: MNE000313 | E61: M10-B-138 | F61: CLGC-22-009P | G61: 44915 | H61: 44925 | I61: 20221230_014-12 | J61: JO-Tech Electric Winch 2 Ton | K61: 92625000 | L61: Acquisition | N61: Mutiara Andalas Strategi | O61: Ok
B62: CLGC | C62: M10 | D62: MNE000314 | E62: M10-B-139 | F62: CLGC-22-009P | G62: 44915 | H62: 44925 | I62: 20221230_014-12 | J62: JO-Tech Electric Winch 2 Ton | K62: 92625000 | L62: Acquisition | N62: Mutiara Andalas Strategi | O62: Ok
A63: 37 | B63: CLGC | C63: M10 | D63: MNE000308 | E63: M10-B-133 | F63: CLGC-22-010P | G63: 44915 | H63: 44925 | I63: 20221230_014-12 | J63: Hyperthem Portable Plasma Cuting | K63: 183000000 | L63: Acquisition | N63: Mutiara Andalas Strategi | O63: Ok
B64: CLGC | C64: M10 | D64: MNE000309 | E64: M10-B-134 | F64: CLGC-22-010P | G64: 44915 | H64: 44925 | I64: 20221230_014-12 | J64: Hyperthem Portable Plasma Cuting | K64: 112000000 | L64: Acquisition | N64: Mutiara Andalas Strategi | O64: Ok
B65: CLGC | C65: M10 | D65: MNE000310 | E65: M10-B-135 | F65: CLGC-22-010P | G65: 44915 | H65: 44925 | I65: 20221230_014-12 | J65: Hyperthem Portable Plasma Cuting | K65: 112000000 | L65: Acquisition | N65: Mutiara Andalas Strategi | O65: Ok

Sheet List Approval 2021
A1: PT. SANKYU INDONESIA INTERNATIONAL
A2: LIST OF ACQUISITION & DISPOSALS ASSET
A3: JAN - JUN 2021 (1st SEMESTER)
A5: No. | B5: Site | C5: Job | D5: Fixed Asset | F5: Application | H5: Purchase/Disposed Date | I5: Bookslip No. | J5: Name of Fixed Asset | K5: Purchase/Disposal Prices | L5: Status | N5: Vendor/Customer
D6: AX | E6: No. | F6: No. | G6: Date | L6: Acquisition | M6: Disposals
A7: 1 | B7: JPO | C7: 7CACA | D7: FNF000089 | F7: JKT-001 | G7: 44209 | H7: 44225 | I7: 20210129_022-01 | J7: Air Purfier | K7: 0 | M7: Disposals | N7: JKT PJ | O7: Ok
A8: =A7+1 -> 2 | B8: JKHO | C8: PJT14 | D8: FNF000099 | F8: JKT-002 | G8: 44209 | H8: 44225 | I8: 20210129_023-01 | J8: Laptop NEC | K8: 0 | M8: Disposals | N8: JKT PJ | O8: Ok
A9: =A8+1 -> 3 | B9: JPO | C9: PJT14 | D9: FNF000100 | F9: JKT-003 | G9: 44209 | H9: 44225 | I9: 20210129_024-01 | J9: Printer Hewlet Packard | K9: 0 | M9: Disposals | N9: JKT PJ | O9: Ok
A10: =A9+1 -> 4 | B10: JPO | C10: PJT14 | D10: FNF000101 | F10: JKT-004 | G10: 44209 | H10: 44225 | I10: 20210129_025-01 | J10: Apple Macbook Pro | K10: 0 | M10: Disposals | N10: JKT PJ | O10: Ok
A11: 5 | B11: ASC | C11: 3A | D11: VEH000330 | E11: 3A-C-178 | F11: 3A-032 | G11: 44243 | H11: 44253 | I11: 20210226_111-02 | J11: Forklift | K11: 45000000 | M11: Disposals | N11: Bintang Timur Musawa | O11: Ok
A12: 6 | B12: ASC | C12: 3A | D12: VEH000384 | E12: 3A-C-188 | F12: 3A-033 | G12: 44243 | H12: 44253 | I12: 20210226_112-02 | J12: Forklift | K12: 45000000 | M12: Disposals | N12: SAN-Swa Equipment | O12: Ok
B13: ASC | C13: 3A | D13: VEH000385 | E13: 3A-C-189 | F13: 3A-033 | G13: 44243 | H13: 44253 | I13: 20210226_112-02 | J13: Forklift | K13: 45000000 | M13: Disposals | N13: SAN-Swa Equipment | O13: Ok
B14: ASC | C14: 3A | D14: VEH000387 | E14: 3A-C-192 | F14: 3A-033 | G14: 44243 | H14: 44253 | I14: 20210226_112-02 | J14: Forklift | K14: 45000000 | M14: Disposals | N14: SAN-Swa Equipment | O14: Ok
A15: 7 | B15: ASC | C15: 3A | D15: VEH000318 | E15: 3A-C-176 | F15: 3A-034 | G15: 44243 | H15: 44253 | I15: 20210226_113-02 | J15: Whell Loader | K15: 30000000 | M15: Disposals | N15: Ciptamas Persada | O15: Ok
B16: ASC | C16: 3A | D16: VEH000448 | E16: 3A-C-206 | F16: 3A-034 | G16: 44243 | H16: 44253 | I16: 20210226_113-02 | J16: Bulldozer | K16: 20000000 | M16: Disposals | N16: Ciptamas Persada | O16: Ok
A17: 8 | B17: ASC | C17: 3A | D17: VEH000172 | E17: 3A-C-145 | F17: 3A-035 | G17: 44243 | H17: 44253 | I17: 20210226_114-02 | J17: Forklift | K17: 25454545 | M17: Disposals | N17: Duta Champion Utama | O17: Ok
B18: ASC | C18: 3A | D18: VEH000207 | E18: 3A-C-156 | F18: 3A-035 | G18: 44243 | H18: 44253 | I18: 20210226_114-02 | J18: Forklift | K18: 27272727 | M18: Disposals | N18: Duta Champion Utama | O18: Ok
B19: ASC | C19: 3A | D19: VEH000263 | E19: 3A-C-169 | F19: 3A-035 | G19: 44243 | H19: 44253 | I19: 20210226_114-02 | J19: Forklift | K19: 31818182 | M19: Disposals | N19: Duta Champion Utama | O19: Ok
B20: ASC | C20: 3A | D20: VEH000332 | E20: 3A-C-197 | F20: 3A-035 | G20: 44243 | H20: 44253 | I20: 20210226_114-02 | J20: Forklift | K20: 44636364 | M20: Disposals | N20: Duta Champion Utama | O20: Ok
B21: ASC | C21: 3A | D21: VEH000386 | E21: 3A-C-180 | F21: 3A-035 | G21: 44243 | H21: 44253 | I21: 20210226_114-02 | J21: Forklift | K21: 32272727 | M21: Disposals | N21: Duta Champion Utama | O21: Ok
B22: ASC | C22: 3A | D22: VEH000400 | E22: 3A-C-187 | F22: 3A-035 | G22: 44243 | H22: 44253 | I22: 20210226_114-02 | J22: Forklift | K22: 29272727 | M22: Disposals | N22: Duta Champion Utama | O22: Ok
A23: 9 | B23: ASC | C23: 3A | D23: VEH000241 | E23: 3A-C-162 | F23: 3A-036 | G23: 44243 | H23: 44253 | I23: 20210226_115-02 | J23: Forklift | K23: 36363636 | M23: Disposals | N23: Biru Reforma Indonesia | O23: Ok
B24: ASC | C24: 3A | D24: VEH000266 | E24: 3A-C-171 | F24: 3A-036 | G24: 44243 | H24: 44253 | I24: 20210226_115-02 | J24: Forklift | K24: 40909091 | M24: Disposals | N24: Biru Reforma Indonesia | O24: Ok
A25: 10 | B25: CLGC | C25: M10 | D25: VEH000029 | E25: M10-C-001 | F25: CLGC-21-001 | G25: 44253 | H25: 44286 | I25: 20210331_098-03 | J25: Forklift | K25: 20000000 | M25: Disposals | N25: Fedis Putra Utama | O25: Ok
B26: CLGC | C26: M10 | D26: VEH000030 | E26: M10-C-006 | F26: CLGC-21-001 | G26: 44253 | H26: 44286 | I26: 20210331_098-03 | J26: Forklift | K26: 20000000 | M26: Disposals | N26: Fedis Putra Utama | O26: Ok
B27: CLGC | C27: M10 | D27: VEH000015 | E27: M10-C-002 | F27: CLGC-21-001 | G27: 44253 | H27: 44286 | I27: 20210331_098-03 | J27: Forklift | K27: 15000000 | M27: Disposals | N27: Fedis Putra Utama | O27: Ok
A28: 11 | B28: HO | C28: 502 | D28: FNF000203 | F28: HO-001 | G28: 44253 | H28: 44286 | I28: 20210531_103-05 | J28: Server SPISy Core Payroll Basic | K28: 587130000 | L28: Acquisition | N28: KDDI | O28: Ok
A29: 12 | B29: CLC | C29: 502 | D29: FNF000204 | E29: CLC | F29: CLC-001 | G29: 44265 | H29: 44286 | I29: 20210729_015-07 | J29: CDMS BLC Software | K29: 337000000 | L29: Acquisition | N29: Solution Manufaktur Teknologi | O29: Ok
A30: 13 | B30: CLGL | C30: 7CL | D30: VEH000003 | E30: 7C-C-044 | F30: 7CL | G30: 44267 | H30: 44286 | I30: 20210331_110-03 | J30: Forklift | K30: 25000000 | M30: Disposals | N30: Fedis Putra Utama | O30: Ok
B31: CLGL | C31: 7CL | D31: VEH000020 | E31: 3B-C-004 | F31: 7CL | G31: 44267 | H31: 44286 | I31: 20210331_110-03 | J31: Forklift | K31: 25000000 | M31: Disposals | N31: Fedis Putra Utama | O31: Ok
A32: 14 | B32: CLC | C32: CLCWH | D32: MNE000298 | E32: CLC | F32: CLC-002 | G32: 44270 | H32: 44286 | I32: 20210331_096-03 | J32: Nestainer | K32: 1487754320 | L32: Acquisition | N32: JKC | O32: Ok
A33: 15 | B33: CLGC | C33: M10 | D33: VEH000590 | E33: M10-C-042 | F33: CLGC-21-001P | G33: 44272 | H33: 44308 | I33: 20210422_002-04 | J33: Avanza 1.3 A/T | K33: 188114886 | L33: Acquisition | N33: Tunas Radian | O33: Ok
B34: CLGC | C34: M10 | D34: VEH000591 | E34: M10-C-043 | F34: CLGC-21-001P | G34: 44272 | H34: 44308 | I34: 20210422_002-04 | J34: Avanza 1.3 A/T | K34: 188114886 | L34: Acquisition | N34: Tunas Radian | O34: Ok
B35: CLGC | C35: M10 | D35: VEH000592 | E35: M10-C-044 | F35: CLGC-21-001P | G35: 44272 | H35: 44308 | I35: 20210422_002-04 | J35: Avanza 1.3 A/T | K35: 188114886 | L35: Acquisition | N35: Tunas Radian | O35: Ok
B36: CLGC | C36: M10 | D36: VEH000593 | E36: M10-C-045 | F36: CLGC-21-001P | G36: 44272 | H36: 44308 | I36: 20210422_002-04 | J36: Avanza 1.3 A/T | K36: 188114886 | L36: Acquisition | N36: Tunas Radian | O36: Ok
A37: 16 | B37: CLGL | C37: 7CL | D37: VEH000595 | E37: 7CL-C-181 | F37: 01-7CL-21 | G37: 44272 | H37: 44286 | I37: 20210317_012-03 20210531_102-05 | J37: Truck Crane | K37: 750000000 | L37: Acquisition | N37: Deugro | O37: Ok
A38: 17 | B38: ASC | C38: 3A | D38: VEH000594 | E38: 3A-C-259 | F38: 3A-026 | G38: 44278 | H38: 44316 | I38: 20210430_041-04 | J38: Avanza 1.3 A/T | K38: 188114886 | L38: Acquisition | N38: Tunas Radian | O38: Ok
A39: 18 | B39: ASC | C39: 3A | D39: VEH000191 | E39: 3A-C-150 | F39: 3A-037 | G39: 44278 | H39: 44286 | I39: 20210331_102-03 | J39: Avanza | K39: 22727273 | M39: Disposals | N39: Biru Reforma Indonesia | O39: Ok
A40: 19 | B40: JKTC | C40: AGC | D40: MNE000123 | F40: JKTC-001 | G40: 44280 | H40: 44286 | I40: 20210331_097-03 | J40: Container 40Ft | K40: 0 | M40: Disposals | N40: JKTC | O40: Ok
A41: 20 | B41: CLGC | C41: M10 | D41: VEH000179 | E41: 3A-C-147 | F41: CLG-21-002S | G41: 44284 | H41: 44316 | I41: 20210430_039-04 | J41: Inova | K41: 73636364 | M41: Disposals | N41: Sahabat Mobilindo | O41: Ok
B42: CLGC | C42: M10 | D42: VEH000233 | E42: M10-C-019 | F42: CLG-21-003S | G42: 44284 | H42: 44316 | I42: 20210430_039-04 | J42: Avanza | K42: 63636364 | M42: Disposals | N42: Sahabat Mobilindo | O42: Ok
B43: CLGC | C43: M10 | D43: VEH000235 | E43: M10-C-022 | F43: CLG-21-004S | G43: 44284 | H43: 44316 | I43: 20210430_039-04 | J43: Avanza | K43: 65909090 | M43: Disposals | N43: Sahabat Mobilindo | O43: Ok
B44: CLGC | C44: M10 | D44: VEH000234 | E44: M10-C-021 | F44: CLG-21-005S | G44: 44284 | H44: 44316 | I44: 20210430_039-04 | J44: Avanza | K44: 63636364 | M44: Disposals | N44: Sahabat Mobilindo | O44: Ok
A45: 21 | B45: CLGC | C45: M10 | D45: MNE000299 | E45: M10-B-128 | F45: CLGC-21-004P | G45: 44295 | H45: 44316 | I45: 20210430_101-04 | J45: 20FT Dry Container | K45: 24000000 | L45: Acquisition | N45: Mutiara Andalas S. | O45: Ok
B46: CLGC | C46: M10 | D46: MNE000300 | E46: M10-B-129 | F46: CLGC-21-004P | G46: 44295 | H46: 44316 | I46: 20210430_101-04 | J46: 20FT Dry Container | K46: 24000000 | L46: Acquisition | N46: Mutiara Andalas S. | O46: Ok
A47: 22 | B47: CLGC | C47: M10 | D47: VEH000596 | E47: M10-C-046 | F47: CLGC-21-003P | G47: 44306 | H47: 44347 | I47: 20210531_110-05 | J47: Tractor Head | K47: 600000000 | L47: Acquisition | N47: Anugrah Wibawa | O47: Ok
B48: CLGC | C48: M10 | D48: VEH000597 | E48: M10-C-047 | F48: CLGC-21-003P | G48: 44306 | H48: 44347 | I48: 20210531_110-05 | J48: Trailer Hight Bed 40F | K48: 147000000 | L48: Acquisition | N48: Anugrah Wibawa | O48: Ok
B49: CLGC | C49: M10 | D49: VEH000598 | E49: M10-C-048 | F49: CLGC-21-003P | G49: 44306 | H49: 44347 | I49: 20210531_110-05 | J49: Tractor Head | K49: 600000000 | L49: Acquisition | N49: Anugrah Wibawa | O49: Ok
B50: CLGC | C50: M10 | D50: VEH000599 | E50: M10-C-049 | F50: CLGC-21-003P | G50: 44306 | H50: 44347 | I50: 20210531_110-05 | J50: Trailer Hight Bed 40F | K50: 147000000 | L50: Acquisition | N50: Anugrah Wibawa | O50: Ok
B51: CLGC | C51: M10 | D51: VEH000600 | E51: M10-C-050 | F51: CLGC-21-003P | G51: 44306 | H51: 44347 | I51: 20210531_110-05 | J51: Tractor Head | K51: 600000000 | L51: Acquisition | N51: Anugrah Wibawa | O51: Ok
B52: CLGC | C52: M10 | D52: VEH000601 | E52: M10-C-051 | F52: CLGC-21-003P | G52: 44306 | H52: 44347 | I52: 20210531_110-05 | J52: Trailer Hight Bed 40F | K52: 147000000 | L52: Acquisition | N52: Anugrah Wibawa | O52: Ok
A53: 23 | B53: CLGC | C53: M10 | D53: VEH000602 | E53: M10-C-052 | F53: CLGC-21-002P | G53: 44306 | H53: 44347 | I53: 20210531_110-05 | J53: 25T Roughter Crane | K53: 1850000000 | L53: Acquisition | N53: Anugrah Wibawa | O53: Ok
A54: 24 | B54: ASC | C54: 3A | D54: VEH000603 | E54: 3A-C-260 | F54: 3A-027 | G54: 44354 | H54: 44452 | I54: 20210913_008-09 | J54: Wheel Loader | K54: 1400000000 | L54: Acquisition | N54: HEXINDO | O54: Ok
B55: ASC | C55: 3A | D55: VEH000611 | E55: 3A-C-262 | F55: 3A-027 | G55: 44354 | H55: 44616 | I55: 20220224_009-02 | J55: Forklift Diesel | K55: 618000000 | L55: Acquisition | N55: Traktor Nusantara | O55: Ok
B56: ASC | C56: 3A | D56: VEH000610 | E56: 3A-C-261 | F56: 3A-027 | G56: 44354 | H56: 44592 | I56: 20220131_081-01 | J56: Forklift Diesel | K56: 400000000 | L56: Acquisition | N56: Traktor Nusantara | O56: OK
A57: 25 | B57: ASC | C57: 3A | D57: VEH000622 | E57: 3A-C-271 | F57: 3A-028 | G57: 44354 | H57: 44712 | I57: 20220531_007-05 | J57: Forklift Batery | K57: 548000000 | L57: Acquisition | N57: Traktor Nusantara | O57: OK
B58: ASC | C58: 3A | D58: VEH000623 | E58: 3A-C-269 | F58: 3A-028 | G58: 44354 | H58: 44712 | I58: 20220531_007-05 | J58: Forklift Batery | K58: 548000000 | L58: Acquisition | N58: Traktor Nusantara | O58: OK
B59: ASC | C59: 3A | D59: VEH000624 | E59: 3A-C-270 | F59: 3A-028 | G59: 44354 | H59: 44712 | I59: 20220531_007-05 | J59: Forklift Batery | K59: 548000000 | L59: Acquisition | N59: Traktor Nusantara | O59: OK
B60: ASC | C60: 3A | D60: CIP000093 | F60: 3A-028 | G60: 44354 | J60: Forklift Batery | L60: Acquisition | N60: Traktor Nusantara | O60: 20220330_010-03 (Paid to Traktor Nusantara_asset)
A61: 26 | B61: MCCI | C61: 3G | D61: VEH000123 | E61: 3G-C-053 | F61: CLG-MCCI-21-001 S | G61: 44368 | H61: 44377 | I61: 20210631_058-06 | J61: Forklift | K61: 19500000 | M61: Disposals | N61: Multi Akses Kreasitama | O61: Ok
B62: MCCI | C62: 3G | D62: VEH000167 | E62: 3G-C-057 | F62: CLG-MCCI-21-002 S | G62: 44368 | H62: 44377 | I62: 20210631_058-06 | J62: Forklift | K62: 51500000 | M62: Disposals | N62: Multi Akses Kreasitama | O62: Ok
A63: 27 | B63: CLG | C63: 7 | D63: FNF000205 | E63: 7-A-039 | F63: 7- | G63: 44287 | H63: 44407 | I63: 20210730_118-07 | J63: Tera Neo Post | K63: 39545455 | L63: Acquisition | N63: Inti Warna Sentosa | O63: Ok
A66: No. | B66: Site | C66: Job | D66: Fixed Asset | F66: Application | H66: Purchase/Disposed Date | I66: Bookslip No. | J66: Name of Fixed Asset | K66: Purchase/Disposal Prices | L66: Status | N66: Vendor/Customer
D67: AX | E67: No. | F67: No. | G67: Date | L67: Acquisition | M67: Disposals
A68: 1 | B68: ASH | C68: MGASH | D68: VEH000041 | F68: MGASH-001-2021-S | G68: 44382 | H68: 44439 | I68: 20210831_041-08 | J68: Motorcycle | K68: 1000000 | M68: Disposals | N68: Cahaya Indah Purnama | O68: OK
B69: ASH | C69: MGASH | D69: VEH000042 | F69: MGASH-002-2021-S | G69: 44382 | H69: 44439 | I69: 20210831_041-08 | J69: Motorcycle | K69: 1000000 | M69: Disposals | N69: Cahaya Indah Purnama | O69: OK
B70: ASH | C70: MGASH | D70: VEH000043 | F70: MGASH-003-2021-S | G70: 44382 | H70: 44439 | I70: 20210831_041-08 | J70: Motorcycle | K70: 1000000 | M70: Disposals | N70: Cahaya Indah Purnama | O70: OK
B71: ASH | C71: MGASH | D71: VEH000044 | F71: MGASH-004-2021-S | G71: 44382 | H71: 44439 | I71: 20210831_041-08 | J71: Motorcycle | K71: 1000000 | M71: Disposals | N71: Cahaya Indah Purnama | O71: OK
A72: 2 | B72: KS | C72: 7R | D72: VEH000006 | E72: 7S-C-014 | F72: 7BF-002 | G72: 44398 | H72: 44407 | I72: 20210730_116-07 | J72: Track Loader | K72: 35000000 | M72: Disposals | N72: Rizqi Putra Pribumi | O72: OK
B73: KS | C73: 7BF | D73: VEH000115 | E73: 7R-C-031 | F73: 7R-004 | G73: 44398 | H73: 44407 | I73: 20210730_116-07 | J73: Forklift | K73: 33000000 | M73: Disposals | N73: Rizqi Putra Pribumi | O73: OK
B74: KS | C74: 7R | D74: VEH000102 | E74: 7R-C-040 | F74: 7R-003 | G74: 44398 | H74: 44407 | I74: 20210730_116-07 | J74: Forklift | K74: 25000000 | M74: Disposals | N74: Rizqi Putra Pribumi | O74: OK
B75: KS | C75: 7R | D75: VEH000131 | E75: 7S-C-032 | F75: 7BF-001 | G75: 44398 | H75: 44407 | I75: 20210730_116-07 | J75: Forklift | K75: 22000000 | M75: Disposals | N75: Rizqi Putra Pribumi | O75: OK
B76: KS | C76: 7R | D76: VEH000056 | E76: 3A-C-097 | F76: 7R-002 | G76: 44398 | H76: 44407 | I76: 20210730_116-07 | J76: Forklift | K76: 15000000 | M76: Disposals | N76: Rizqi Putra Pribumi | O76: OK
B77: KS | C77: 7BF | D77: VEH000120 | E77: 7R-C-037 | F77: 7R-001 | G77: 44398 | H77: 44407 | I77: 20210730_116-07 | J77: Forklift | K77: 15000000 | M77: Disposals | N77: Rizqi Putra Pribumi | O77: OK
A78: 3 | B78: CLGC | C78: M10 | D78: MNE000301 | E78: M10-C-130 | F78: CLGC-21-004P | G78: 44403 | H78: 44407 | I78: 20210730_117-07 | J78: Load Cell for Unich | K78: 115000000 | L78: Acquisition | N78: Multi Sentosa Teknik | O78: OK
A79: 4 | B79: KS | C79: 7R | D79: MNE000302 | E79: 7R-B-004 | F79: 7R-005 | G79: 44405 | H79: 44426 | I79: 20210818_005-08 | J79: Jet Cleaner Assy | K79: 28215000 | L79: Acquisition | N79: Duta Champion Utama | O79: OK
A80: 5 | B80: ASC | C80: 3A | D80: VEH000628 | E80: 3A-C-275 | F80: 3A-032 | G80: 44459 | H80: 44741 | I80: 20220629_005-06 | J80: Bulldozer | K80: 3100000000 | L80: Acquisition | N80: United Tractor | O80: Ok
A81: 6 | B81: CLGC | C81: M10 | D81: MNE000303 | E81: M10-C-053 | F81: CLGC-21-006P | G81: 44461 | H81: 44592 | I81: 20220331_007-01 | J81: Tadano Crane | K81: 6780000000 | L81: Acquisition | N81: United Tractor | O81: Ok
A82: 7 | B82: ASC | C82: 3A | D82: VEH000612 | E82: 3A-B-069 | F82: 3A-031 | G82: 44470 | H82: 44651 | I82: 20220331_017-03 | J82: Taiyu Drum Dumper | K82: 146288477 | L82: Acquisition | N82: Assurich | O82: Ok
D83: VEH000613 | E83: 3A-B-070 | F83: 3A-031 | G83: 44470 | H83: 44651 | I83: 20220331_017-03 | J83: Taiyu Drum Dumper | K83: 146288477 | L83: Acquisition | N83: Assurich | O83: Ok
A84: 8 | B84: ASC | C84: 3A | D84: VEH000223 | E84: 3A-C-161 | F84: 3A-038 | G84: 44470 | H84: 44498 | I84: 20211029_092-10 | J84: Wheeloader | K84: 50000000 | M84: Disposals | N84: Multi Akses Kreasitama | O84: Ok
A85: 9 | B85: ACS | C85: 3A | D85: VEH000604 | E85: 3A-B-063 | F85: 3A-030 | G85: 44477 | H85: 44592 | I85: 20211028_007-10 | J85: Push Pull | K85: 161500000 | L85: Acquisition | N85: A&T Engineering | O85: Ok
B86: ACS | C86: 3A | D86: VEH000605 | E86: 3A-B-064 | F86: 3A-030 | G86: 44477 | H86: 44592 | I86: 20211028_007-10 | J86: Push Pull | K86: 161500000 | L86: Acquisition | N86: A&T Engineering | O86: Ok
B87: ACS | C87: 3A | D87: VEH000606 | E87: 3A-B-065 | F87: 3A-030 | G87: 44477 | H87: 44592 | I87: 20211028_007-10 | J87: Push Pull | K87: 161500000 | L87: Acquisition | N87: A&T Engineering | O87: Ok
B88: ACS | C88: 3A | D88: VEH000607 | E88: 3A-B-066 | F88: 3A-030 | G88: 44477 | H88: 44592 | I88: 20211028_007-10 | J88: Push Pull | K88: 161500000 | L88: Acquisition | N88: A&T Engineering | O88: Ok
B89: ACS | C89: 3A | D89: VEH000608 | E89: 3A-B-067 | F89: 3A-030 | G89: 44477 | H89: 44592 | I89: 20211028_007-10 | J89: Push Pull | K89: 161500000 | L89: Acquisition | N89: A&T Engineering | O89: Ok
B90: ACS | C90: 3A | D90: VEH000609 | E90: 3A-B-068 | F90: 3A-030 | G90: 44477 | H90: 44592 | I90: 20211028_007-10 | J90: Push Pull | K90: 161500000 | L90: Acquisition | N90: A&T Engineering | O90: Ok
A91: 10 | B91: ACS | C91: 3A | D91: VEH000625 | E91: 3A-C-273 | F91: 3A-029 | G91: 44477 | H91: 44727 | I91: 20220615_008-06 | J91: Forklift | K91: 570000000 | L91: Acquisition | N91: Traktor Nusantara | O91: OK
B92: ACS | C92: 3A | D92: VEH000626 | E92: 3A-C-274 | F92: 3A-029 | G92: 44477 | H92: 44727 | I92: 20220615_008-06 | J92: Forklift | K92: 570000000 | L92: Acquisition | N92: Traktor Nusantara | O92: OK
B93: ACS | C93: 3A | D93: VEH000621 | E93: 3A-C-268 | F93: 3A-029 | G93: 44477 | H93: 44727 | I93: 20220531_007-05 | J93: Forklift | K93: 548000000 | L93: Acquisition | N93: Traktor Nusantara | O93: OK
B94: ACS | C94: 3A | D94: VEH000627 | E94: 3A-C-272 | F94: 3A-029 | G94: 44477 | H94: 44727 | I94: 20220615_008-06 | J94: Forklift | K94: 548000000 | L94: Acquisition | N94: Traktor Nusantara | O94: OK
B95: ACS | C95: 3A | D95: VEH000619 | E95: 3A-C-267 | F95: 3A-029 | G95: 44477 | H95: 44665 | I95: 20220414_013-09 | J95: Forklift | K95: 456000000 | L95: Acquisition | N95: Traktor Nusantara | O95: OK
B96: ACS | C96: 3A | D96: VEH000630 | E96: 3A-C-277 | F96: 3A-029 | G96: 44477 | H96: 44811 | I96: 20211028_008-10 | J96: Forklift | K96: 456000000 | L96: Acquisition | N96: Traktor Nusantara | O96: OK
B97: ACS | C97: 3A | D97: VEH000631 | E97: 3A-C-276 | F97: 3A-029 | G97: 44477 | H97: 44812 | I97: 20220908_006-09 | J97: Forklift | K97: 456000000 | L97: Acquisition | N97: Traktor Nusantara | O97: OK
B98: ACS | C98: 3A | D98: VEH000617 | E98: 3A-C-265 | F98: 3A-029 | G98: 44477 | H98: 44665 | I98: 20220414_013-09 | J98: Forklift | K98: 456000000 | L98: Acquisition | N98: Traktor Nusantara | O98: OK
B99: ACS | C99: 3A | D99: VEH000618 | E99: 3A-C-266 | F99: 3A-029 | G99: 44477 | H99: 44665 | I99: 20220414_013-09 | J99: Forklift | K99: 456000000 | L99: Acquisition | N99: Traktor Nusantara | O99: OK
A100: 11 | B100: CLC | C100: CLCWH | D100: STR000062 | E100: CLC134-021 | F100: CLC-016 | G100: 44518 | H100: 44560 | I100: 20211230_046-12 | J100: Handrail WH 1 | K100: 120000000 | L100: Acquisition | N100: SMCC | O100: Ok
A101: 12 | B101: CLC | C101: CLCWH | D101: STR000063 | E101: CLC134-022 | F101: CLC-016 | G101: 44518 | H101: 44560 | I101: 20211230_047-12 | J101: Handrail WH 2 | K101: 122900000 | L101: Acquisition | N101: SMCC | O101: Ok
A102: 13 | B102: CLC | C102: CLCWH | D102: FNF000206 | E102: CLC133-024 | F102: CLC-017 | G102: 44522 | H102: 44592 | I102: 20220131_082-01 | J102: Access Point WH 1 | K102: 282660000 | L102: Acquisition | N102: KDDI | O102: Ok
A103: 14 | B103: CLC | C103: CLCWH | D103: FNF000207 | E103: CLC133-023 | F103: CLC-018 | G103: 44522 | H103: 44592 | I103: 20220131_082-01 | J103: Access Point WH 2 | K103: 337790000 | L103: Acquisition | N103: KDDI | O103: Ok
...
