Workbook
Name \0: #N/A
Name \a: #REF!
Name \c: #REF!
Name \p: #REF!
Name \q: [1]FRYPROD!#REF!
Name ___RSE2: '[2]CMA Calculations'!$H$1066
Name __DAT1: "$#REF!.$A$1:$A$394"
Name __DAT10: #REF!
Name __DAT11: #REF!
Name __DAT12: #REF!
Name __DAT13: #REF!
Name __DAT14: #REF!
Name __DAT15: #REF!
Name __DAT16: #REF!
Name __DAT2: "$#REF!.$B$1:$B$394"
Name __DAT3: "$#REF!.$#REF!$#REF!:$#REF!$#REF!"
Name __DAT6: #REF!
Name __DAT7: #REF!
Name __DAT8: #REF!
Name __DAT9: #REF!
Name __NPW1: '[3]Permanent info'!$E$5
Name __NPW10: '[3]Permanent info'!$R$5
Name __NPW11: '[3]Permanent info'!$S$5
Name __NPW2: '[3]Permanent info'!$G$5
Name __NPW3: '[3]Permanent info'!$H$5
Name __NPW4: '[3]Permanent info'!$I$5
Name __NPW5: '[3]Permanent info'!$K$5
Name __NPW6: '[3]Permanent info'!$L$5
Name __NPW7: '[3]Permanent info'!$M$5
Name __NPW8: '[3]Permanent info'!$O$5
Name __NPW9: '[3]Permanent info'!$Q$5
Name __poc01: #REF!
Name __poc02: #REF!
Name __poc03: #REF!
Name __poc04: #REF!
Name __poc05: #REF!
Name __PPH25: #REF!
Name __RSE2: '[2]CMA Calculations'!$H$1066
Name __vib01: #REF!
Name __vib02: #REF!
Name __vib03: #REF!
Name __vib04: #REF!
Name __vib05: #REF!
Name __vib06: #REF!
Name __vib07: #REF!
Name __WS1: #REF!
Name __WS2: #REF!
Name _1: #REF!
Name _15: #REF!
Name _15_2: #REF!
Name _3: #REF!
Name _CDD763: #REF!
Name _DAT1: "$#REF!.$A$1:$A$394"
Name _DAT10: #REF!
Name _DAT11: #REF!
Name _DAT12: #REF!
Name _DAT13: #REF!
Name _DAT14: #REF!
Name _DAT15: #REF!
Name _DAT16: #REF!

Sheet TB
B1: TB July 2020
B3: Ledger account | C3: Name | D3: Opening balance | E3: Debit | F3: Credit | G3: Closing balance | I3: MainAccount | J3: Name | K3: Opening balance | L3: Debit | M3: Credit | N3: Closing balance
B4: 1510000 | C4: Land | G4: =IFERROR(VLOOKUP(B4,$I$4:$N$29,6,FALSE),0) -> 102037368651 | H4: =LEFT(I4,3) -> 151 | I4: 1510000 | J4: Land | K4: 102037368651 | L4: 0 | M4: 0 | N4: 102037368651 | P4: 102037368651 | Q4: =P4-N4 -> 0
B5: 1520000 | C5: Buildings | G5: =IFERROR(VLOOKUP(B5,$I$4:$N$29,6,FALSE),0) -> 2.8312631e+11 | H5: =LEFT(I5,3) -> 152 | I5: 1520000 | J5: Buildings | K5: 2.8312631e+11 | L5: 0 | M5: 0 | N5: 2.8312631e+11 | P5: 2.8331437e+11 | Q5: =P5-N5 -> 188052750
B6: 1530000 | C6: Structures | G6: =IFERROR(VLOOKUP(B6,$I$4:$N$29,6,FALSE),0) -> 9.7607306e+09 | H6: =LEFT(I6,3) -> 153 | I6: 1530000 | J6: Structures | K6: 9.7607306e+09 | L6: 0 | M6: 0 | N6: 9.7607306e+09 | P6: 9.4307277e+09 | Q6: =P6-N6 -> -330002944
B7: 1540000 | C7: Machinery & Equipment | G7: =IFERROR(VLOOKUP(B7,$I$4:$N$29,6,FALSE),0) -> 7.7916025e+10 | H7: =LEFT(I7,3) -> 154 | I7: 1540000 | J7: Machinery & Equipment | K7: 7.7916025e+10 | L7: 0 | M7: 0 | N7: 7.7916025e+10 | P7: 7.8722001e+10 | Q7: =P7-N7 -> 8.0597534e+08
B8: 1550000 | C8: Vehicles | G8: =IFERROR(VLOOKUP(B8,$I$4:$N$29,6,FALSE),0) -> 4.257898e+11 | H8: =LEFT(I8,3) -> 155 | I8: 1550000 | J8: Vehicles | K8: 4.2930926e+11 | L8: 1154788214 | M8: 4674244400 | N8: 4.257898e+11 | P8: 4.4178311e+11 | Q8: =P8-N8 -> 1.5993311e+10
B9: 1560000 | C9: Tools, Furniture & Fixtures | G9: =IFERROR(VLOOKUP(B9,$I$4:$N$29,6,FALSE),0) -> 1.4359284e+10 | H9: =LEFT(I9,3) -> 156 | I9: 1560000 | J9: Tools, Furniture & Fixtures | K9: 1.4359284e+10 | L9: 0 | M9: 0 | N9: 1.4359284e+10 | P9: 1.3614925e+10 | Q9: =P9-N9 -> -7.4435809e+08
B10: 1585400 | C10: Lease Hold Improvement Machine& Equipment | G10: =IFERROR(VLOOKUP(B10,$I$4:$N$29,6,FALSE),0) -> 0 | H10: =LEFT(I10,3) -> 161 | I10: 1615500 | J10: Down Payment: Vehicles | K10: 533400001 | L10: 0 | M10: 339600000 | N10: 193800001 | P10: 620000000 | Q10: =P10-N10 -> 426199999
B11: 1585500 | C11: Lease Hold Improvement Vehicle | G11: =IFERROR(VLOOKUP(B11,$I$4:$N$29,6,FALSE),0) -> 0 | H11: =LEFT(I11,3) -> 172 | I11: 1720000 | J11: System & Software | K11: 588800000 | L11: 0 | M11: 0 | N11: 588800000 | P11: 1434345000 | Q11: =P11-N11 -> 845545000
B12: 1615200 | C12: Down Payment: Building | G12: =IFERROR(VLOOKUP(B12,$I$4:$N$29,6,FALSE),0) -> 0 | H12: =LEFT(I12,3) -> 251 | I12: 2515200 | J12: Accumulated Depreciation: Building | K12: -1.674119e+11 | L12: 0 | M12: 1.1347742e+09 | N12: -1.6854668e+11 | P12: 0 | Q12: =P12-N12 -> 1.6854668e+11
B13: 1615300 | C13: Down Payment: Structures | G13: =IFERROR(VLOOKUP(B13,$I$4:$N$29,6,FALSE),0) -> 0 | H13: =LEFT(I13,3) -> 251 | I13: 2515300 | J13: Accumulated Depreciation: Structures | K13: -9.0335391e+09 | L13: 0 | M13: 25060967 | N13: -9.0586e+09 | P13: -1.1295559e+11 | Q13: =P13-N13 -> -1.0389699e+11
B14: 1615400 | C14: Down Payment: Machinary & Equipment | G14: =IFERROR(VLOOKUP(B14,$I$4:$N$29,6,FALSE),0) -> 0 | H14: =LEFT(I14,3) -> 251 | I14: 2515400 | J14: Accumulated Depreciation: Machine | K14: -6.9740764e+10 | L14: 0 | M14: 1.4068039e+08 | N14: -6.9881444e+10 | P14: -7.9542433e+09 | Q14: =P14-N14 -> 6.1927201e+10
B15: 1615500 | C15: Down Payment: Vehicles | G15: =IFERROR(VLOOKUP(B15,$I$4:$N$29,6,FALSE),0) -> 193800001 | H15: =LEFT(I15,3) -> 251 | I15: 2515500 | J15: Accumulated Depreciation: Vehicles | K15: -3.2151482e+11 | L15: 4674244400 | M15: 2.2399987e+09 | N15: -3.1908058e+11 | P15: -6.5588325e+10 | Q15: =P15-N15 -> 2.5349225e+11
... B18: 2515400 | C18: Accumulated Depreciation: Machine | G18: =IFERROR(VLOOKUP(B18,$I$4:$N$29,6,FALSE),0) -> -6.9881444e+10 | H18: =LEFT(I18,3) -> 421 | I18: 4215500 | J18: Gain from Sold FA Vehicles | K18: -3199549552 | L18: 0 | M18: 569621622 | N18: -3769171174 | P18: -1.1221614e+09 | Q18: =P18-N18 -> 2.6470097e+09
B19: 2515500 | C19: Accumulated Depreciation: Vehicles | G19: =IFERROR(VLOOKUP(B19,$I$4:$N$29,6,FALSE),0) -> -3.1908058e+11 | H19: =LEFT(I19,3)
B20: 2515600 | C20: Accumulated Depreciation: Tools, Furniture & Fixtures | G20: =IFERROR(VLOOKUP(B20,$I$4:$N$29,6,FALSE),0) -> -1.1956838e+10 | H20: =LEFT(I20,3)
B21: 1615600 | C21: Down Payment: Tools, Furniture & Fixtures | G21: =IFERROR(VLOOKUP(B21,$I$4:$N$29,6,FALSE),0) -> 0 | H21: =LEFT(I21,3)
B22: 4215500 | C22: Gain from Sold FA Vehicles | G22: =IFERROR(VLOOKUP(B22,$I$4:$N$29,6,FALSE),0) -> -3769171174
B23: 4215600 | C23: Gain from Sold FA Tools, Furniture & Fixtures | G23: =IFERROR(VLOOKUP(B23,$I$4:$N$29,6,FALSE),0) -> 0
B24: 4215400 | C24: Gain from Sold FA Machinary & Equipment | G24: =IFERROR(VLOOKUP(B24,$I$4:$N$29,6,FALSE),0) -> 0
B25: 4215200 | C25: Gain from Sold FA Building | G25: =IFERROR(VLOOKUP(B25,$I$4:$N$29,6,FALSE),0) -> 0
B26: 1720000 | C26: System & Software | G26: =IFERROR(VLOOKUP(B26,$I$4:$N$29,6,FALSE),0) -> 588800000
B27: 2540000 | C27: Accumulated Depreciation: System & Software | G27: =IFERROR(VLOOKUP(B27,$I$4:$N$29,6,FALSE),0) -> -1.1310567e+08
B28: 5215500 | G28: =IFERROR(VLOOKUP(B28,$I$4:$N$29,6,FALSE),0) -> 0
B29: 5215600 | G29: =IFERROR(VLOOKUP(B29,$I$4:$N$29,6,FALSE),0) -> 0
D32: =H4&"*,"&H5&"*,"&H6&"*,"&H7&"*,"&H8&"*,"&H9&"*,"&H10&"*,"&H11&"*,"&H13&"*,"&H14&"*,"&H15&"*,"&H16&"*,"&H17&"*,"&H18&"*,"&H19&"*,"&H20&"*,"&H12 -> 151*,152*,153*,154*,155*,156*,161*,172*,251*,251*,251*,251*,254*,421*,*,*,251
D33: 151*,152*,153*,154*,155*,156*,161*,251*,161*158*,42*,17*,254*,52*
J39: MNE000001
J40: MNE000002
J41: MNE000003
J42: MNE000004
J43: MNE000005
J44: MNE000006
J45: MNE000007
J46: MNE000008
J47: FNF000002
J48: FNF000003
J49: FNF000004
J50: FNF000005
... J57: FNF000047

Sheet TOTAL
A1: PT. Sankyu Indonesia International
A2: Total of Fixed Asset
A3: 30 Jun 2026
A5: No. | B5: Name of Fixed Assets | C5: Fixed Asset (List) | I5: D365
C6: Beginning Balance | D6: Additional | E6: Disposals | F6: Adjustment | G6: Ending Balace | I6: Total | J6: Different
G7: a | I7: b | J7: c = a - b
A8: Purchase Price | M8: TB | N8: List | O8: Diff TB | P8: Diff List
A9: 152 | B9: Buildings | C9: 2.8312631e+11 | D9: =SUMIFS(FA_2026!$S$10:$S$80,FA_2026!$D$10:$D$80,TOTAL!$A$9,FA_2026!$AQ$10:$AQ$80,TOTAL!$D$6) -> 0 | E9: =-SUMIFS(FA_2026!$S$10:$S$78,FA_2026!$D$10:$D$78,TOTAL!$A$9,FA_2026!$AR$10:$AR$78,TOTAL!$E$6) -> 0 | G9: =+C9+D9+E9+F9 -> 2.8312631e+11 | I9: =TB!G5 -> 2.8312631e+11 | J9: =+G9-I9 -> 0 | M9: 2.8312631e+11 | N9: =FA_2026!S81 -> 2.8312631e+11 | O9: =M9-C9 -> 0 | P9: =(C9+D9)-N9 -> 0
A10: 153 | B10: Structures | C10: 9.8908306e+09 | D10: =SUMIFS(FA_2026!$S$82:$S$147,FA_2026!$D$82:$D$147,TOTAL!$A$10,FA_2026!$AQ$82:$AQ$147,TOTAL!$D$6) -> 59325000 | E10: =-SUMIFS(FA_2026!$S$82:$S$147,FA_2026!$D$82:$D$147,TOTAL!$A$10,FA_2026!$AR$82:$AR$147,TOTAL!$E$6) -> -189425000 | G10: =+C10+D10+E10+F10 -> 9.7607306e+09 | I10: =TB!G6 -> 9.7607306e+09 | J10: =+G10-I10 -> 0 | M10: 9.8908306e+09 | N10: =FA_2026!S148 -> 9.9501556e+09 | O10: =M10-C10 -> 0 | P10: =(C10+D10)-N10 -> 0
A11: 154 | B11: Machinery & Equipments | C11: 7.7752435e+10 | D11: =SUMIFS(FA_2026!$S$149:$S$521,FA_2026!$D$149:$D$521,TOTAL!$A$11,FA_2026!$AQ$149:$AQ$521,TOTAL!$D$6) -> 180890000 | E11: =-SUMIFS(FA_2026!$S$149:$S$521,FA_2026!$D$149:$D$521,TOTAL!$A$11,FA_2026!$AR$149:$AR$521,TOTAL!$E$6) -> -17300000 | G11: =+C11+D11+E11+F11 -> 7.7916025e+10 | I11: =TB!G7 -> 7.7916025e+10 | J11: =+G11-I11 -> 0 | M11: 7.7752435e+10 | N11: =FA_2026!S522 -> 7.7933325e+10 | O11: =M11-C11 -> 0 | P11: =(C11+D11)-N11 -> 0
A12: 159 | B12: Vessels | C12: 0 | D12: 0 | E12: 0 | G12: =+C12+D12+E12+F12 -> 0 | I12: 0 | J12: =+G12-I12 -> 0 | O12: =M12-C12 -> 0 | P12: =(C12+D12)-N12 -> 0
A13: 155 | B13: Vehicles | C13: 4.3479287e+11 | D13: =SUMIFS(FA_2026!$S$523:$S$936,FA_2026!$D$523:$D$936,TOTAL!$A$13,FA_2026!$AQ$523:$AQ$936,TOTAL!$D$6) -> 14181941541 | E13: =-SUMIFS(FA_2026!$S$523:$S$936,FA_2026!$D$523:$D$936,TOTAL!$A$13,FA_2026!$AR$523:$AR$936,TOTAL!$E$6) -> -2.318501e+10 | G13: =C13+D13+E13+F13 -> 4.257898e+11 | I13: =TB!G8 -> 4.257898e+11 | J13: =+G13-I13 -> 1.000061 | M13: 4.3479287e+11 | N13: =FA_2026!S937 -> 4.4897481e+11 | O13: =M13-C13 -> -1.000061 | P13: =(C13+D13)-N13 -> 0
A14: 156 | B14: Tools, Furnitures & Fixtures | C14: 1.4282999e+10 | D14: =SUMIFS(FA_2026!$S$938:$S$1143,FA_2026!$D$938:$D$1143,TOTAL!$A$14,FA_2026!$AQ$938:$AQ$1143,TOTAL!$D$6) -> 107379000 | E14: =-SUMIFS(FA_2026!$S$938:$S$1143,FA_2026!$D$938:$D$1143,TOTAL!$A$14,FA_2026!$AR$938:$AR$1143,TOTAL!$E$6) -> -31094062 | G14: =+C14+D14+E14+F14 -> 1.4359284e+10 | I14: =TB!G9 -> 1.4359284e+10 | J14: =+G14-I14 -> -0.059997559 | M14: 1.4282999e+10 | N14: =FA_2026!S1144 -> 1.4390378e+10 | O14: =M14-C14 -> 0.059997559 | P14: =(C14+D14)-N14 -> -0.059997559
A15: 172 | B15: System | C15: 588800000 | D15: =SUMIFS(FA_2026!$S$938:$S$1152,FA_2026!$D$938:$D$1152,TOTAL!$A$15,FA_2026!$AQ$938:$AQ$1152,TOTAL!$D$6) -> 0 | E15: =-SUMIFS(FA_2026!$S$938:$S$1152,FA_2026!$D$938:$D$1152,TOTAL!$A$15,FA_2026!$AR$938:$AR$1152,TOTAL!$E$6) -> 0 | G15: =+C15+D15+E15+F15 -> 588800000 | I15: =TB!G26 -> 588800000 | J15: =+G15-I15 -> 0 | M15: 588800000 | N15: =FA_2026!S1152 -> 588800000 | O15: =M15-C15 -> 0 | P15: =(C15+D15)-N15 -> 0
A16: 151 | B16: Land | C16: 102037368651 | D16: =-SUMIFS(FA_2026!$S$1153:$S$1246,FA_2026!$D$1153:$D$1246,TOTAL!$A$16,FA_2026!$AQ$1153:$AQ$1246,TOTAL!$D$6) -> 0 | E16: =-SUMIFS(FA_2026!$S$1153:$S$1159,FA_2026!$D$1153:$D$1159,TOTAL!$A$16,FA_2026!$AR$1153:$AR$1159,TOTAL!$E$6) -> 0 | G16: =+C16+D16+E16+F16 -> 102037368651 | I16: 102037368651 | J16: =+G16-I16 -> 0 | M16: 102037368651 | N16: =FA_2026!S1161 -> 102037368651 | O16: =M16-C16 -> 0 | P16: =(C16+D16)-N16 -> 0
A17: 161 | B17: Construction In Process | C17: 2668541541 | D17: =SUMIFS(FA_2026!$S$1162:$S$1172,FA_2026!$D$1162:$D$1172,TOTAL!$A$17,FA_2026!$AQ$1162:$AQ$1172,TOTAL!$D$6) -> 1079550000 | E17: =-SUMIFS(FA_2026!$AA$1162:$AA$1172,FA_2026!$D$1162:$D$1172,TOTAL!$A$17,FA_2026!$AR$1162:$AR$1172,TOTAL!$E$6) -> -3554291541 | G17: =+C17+D17+E17+F17 -> 193800000 | I17: =SUM(TB!G12:G15,TB!G21) -> 193800001 | J17: =+G17-I17 -> -1 | M17: 2668541542 | N17: =FA_2026!S1172 -> 3748091541 | O17: =M17-C17 -> 1 | P17: =(C17+D17)-N17 -> 0
B18: Grand Total | C18: 9.2501902e+11 | D18: =SUM(D9:D17) -> 15609085541 | E18: =SUM(E9:E17) -> -2.697712e+10 | F18: =SUM(F9:F17) -> 0 | G18: =SUM(G9:G17) -> 9.1377212e+11 | I18: =SUM(I9:I17) -> 9.1377212e+11 | J18: =SUM(J9:J17) -> -0.059936523
C19: 9.134756e+11 | G19: =G18-G17 -> 9.1357832e+11
A20: Accumulated Depreciation (251)
A21: 152 | B21: Buildings | C21: 1.6173803e+11 | D21: =SUM(FA_2026!AB81) -> 6.8086453e+09 | E21: =-SUMIFS(FA_2026!$AO$10:$AO$1952,FA_2026!$D$10:$D$1952,TOTAL!$A21,FA_2026!$AR$10:$AR$1952,TOTAL!$E$6) -> 0 | G21: =SUM(C21:E21) -> 1.6854668e+11 | I21: =TB!G16 -> -1.6854668e+11 | J21: =+G21+I21 -> -0.31115723
A22: 153 | B22: Structures | C22: 9.0976592e+09 | D22: =SUM(FA_2026!AB148) -> 1.503658e+08 | E22: =-SUMIFS(FA_2026!$AO$10:$AO$1952,FA_2026!$D$10:$D$1952,TOTAL!$A22,FA_2026!$AR$10:$AR$1952,TOTAL!$E$6) -> -189425000 | G22: =SUM(C22:E22) -> 9.0586e+09 | I22: =TB!G17 -> -9.0586e+09 | J22: =+G22+I22 -> 0.92000198
A23: 154 | B23: Machinery & Equipments | C23: 6.9012211e+10 | D23: =SUM(FA_2026!AB522) -> 8.8653249e+08 | E23: =-SUMIFS(FA_2026!$AO$10:$AO$1952,FA_2026!$D$10:$D$1952,TOTAL!$A23,FA_2026!$AR$10:$AR$1952,TOTAL!$E$6) -> -17300000 | G23: =SUM(C23:E23) -> 6.9881444e+10 | I23: =TB!G18 -> -6.9881444e+10 | J23: =+G23+I23 -> -5.6826935
A24: 159 | B24: Vessels | C24: 0 | D24: 0 | E24: =-SUMIFS(FA_2026!$AO$10:$AO$1952,FA_2026!$D$10:$D$1952,TOTAL!$A24,FA_2026!$AR$10:$AR$1952,TOTAL!$E$6) -> 0 | G24: =SUM(C24:E24) -> 0 | J24: =+G24+I24 -> 0
A25: 155 | B25: Vehicles | C25: 3.2864007e+11 | D25: =SUM(FA_2026!AB937) -> 1.3625518e+10 | E25: =-SUMIFS(FA_2026!$AO$10:$AO$1952,FA_2026!$D$10:$D$1952,TOTAL!$A25,FA_2026!$AR$10:$AR$1952,TOTAL!$E$6) -> -2.318501e+10 | G25: =SUM(C25:E25) -> 3.1908058e+11 | I25: =TB!G19 -> -3.1908058e+11 | J25: =+G25+I25 -> -1.4338989
A26: 156 | B26: Tools, Furnitures & Fixtures | C26: 1.1435715e+10 | D26: =SUM(FA_2026!AB1144) -> 5.5221737e+08 | E26: =-SUMIFS(FA_2026!$AO$10:$AO$1952,FA_2026!$D$10:$D$1952,TOTAL!$A26,FA_2026!$AR$10:$AR$1952,TOTAL!$E$6) -> -31094062 | G26: =SUM(C26:E26) -> 1.1956838e+10 | I26: =TB!G20 -> -1.1956838e+10 | J26: =+G26+I26 -> 6.4783344
A27: 172 | B27: System | C27: 53475667 | D27: =SUM(FA_2026!AB1152) -> 59630000 | E27: =-SUMIFS(FA_2026!$AO$10:$AO$1952,FA_2026!$D$10:$D$1952,TOTAL!$A27,FA_2026!$AR$10:$AR$1952,TOTAL!$E$6) -> 0 | G27: =SUM(C27:E27) -> 1.1310567e+08 | I27: =TB!G27 -> -1.1310567e+08 | J27: =+G27+I27 -> 0.46666665
B28: Grand Total | C28: 5.7996202e+11 | D28: =SUM(D21:D27) -> 2.2082909e+10 | E28: =SUM(E21:E27) -> -2.3422829e+10 | F28: =SUM(F21:F27) -> 0 | G28: =SUM(G21:G27) -> 5.7863724e+11 | I28: =SUM(I21:I27) -> -5.7863724e+11 | J28: =SUM(J21:J26) -> -0.029413223
C30: =C18-C28 -> 3.45057e+11 | E30: Fixed Asset (Net) | G30: =+G18-G28 -> 3.3513488e+11
A31: Net Book Value (251) | C31: =C30+C40 -> 6.7999808e+11
A32: 151 | B32: Land | C32: =G16 -> 102037368651
A33: 152 | B33: Buildings | C33: =G9-G21 -> 1.1457964e+11 | D33: =FA_2026!AP81 -> 1.1457964e+11 | E33: =D33-C33 -> -0.33139038
A34: 153 | B34: Structures | C34: =G10-G22 -> 7.0213059e+08 | D34: =FA_2026!AP148 -> 7.0213059e+08 | E34: =D34-C34 -> -5.3666638
A35: 154 | B35: Machinery & Equipments | C35: =G11-G23 -> 8.0345815e+09 | D35: =FA_2026!AP522 -> 8.0345815e+09 | E35: =D35-C35 -> -11.967809
A36: 159 | B36: Vessels | C36: =G12-G24 -> 0 | E36: =D36-C36 -> 0
A37: 155 | B37: Vehicles | C37: =G13-G25 -> 1.0670922e+11 | D37: =FA_2026!AP937 -> 1.0670922e+11 | E37: =D37-C37 -> -30.003891
A38: 156 | B38: Tools, Furnitures & Fixtures | C38: =G14-G26 -> 2.4024452e+09 | D38: =FA_2026!AP1144 -> 2.4024452e+09 | E38: =D38-C38 -> -8.2083335
A39: 172 | B39: System | C39: =G15-G27 -> 4.7569433e+08 | D39: =FA_2026!AP1152 -> 4.7569433e+08 | E39: =D39-C39 -> 0
C40: =SUM(C32:C39) -> 3.3494108e+11 | D40: =FA_2026!AP1173+FA_2026!AA1161 -> 3.3494108e+11 | E40: =D40-C40 -> -55.877991 | G40: Land

Sheet FA_2026
A1: PT. SANKYU INDONESIA INTERNATIONAL
A2: LIST OF FIXED ASSETS AND DEPRECIATION SCHEDULE
A3: =TOTAL!A3 -> 30 Jun 2026
S4: =#REF!/#REF! -> #REF!
A7: No. | B7: Site/ Location | C7: Job | D7: Account | E7: Asset | F7: Fixed asset number | G7: Purchase Date | H7: Group | I7: Voucher | J7: Name of Fixed Asset | K7: Maker/Type/Location | L7: Capacity/Size/User | M7: Year | N7: Police | O7: Machine | P7: Chasis | Q7: Quantity | R7: Valas | S7: Purchase Price | T7: Monthly Depreciation | U7: Depreciation Period | Z7: Accumulated Depreciation | AA7: Net Book Value | AB7: Depreciation Expense Current | AC7: DEPRECIATION 2025 ( MONTHLY ) | AO7: Accumulated Depreciation | AP7: Net Book Value | AQ7: Status | AS7: Acquisition | AT7: Remark | AU7: Photo Status | AW7: Checker Name ( A ) | AY7: Existing ( B ) | BA7: If Yes (Existing) ( C ) | BC7: If Not Used ( D ) | BE7: Sticker ( E ) | BL7: Asset
D8: No. | E8: No. | F8: AX | I8: No. | N8: No. | O8: No. | P8: No. | U8: Total | V8: Acc. 2025 | W8: Yearly 2026 | X8: Until 2026 | Y8: Remain > 2026 | Z8: 31 December 2025 | AA8: 31 December 2025 | AB8: =+A3 -> 30 Jun 2026 | AC8: Jan | AD8: Feb | AE8: Mar | AF8: Apr | AG8: May | AH8: Jun | AI8: Jul | AJ8: Aug | AK8: Sep | AL8: Oct | AM8: Nov | AN8: Dec | AO8: =A3 -> 30 Jun 2026 | AP8: =+AO8 -> 30 Jun 2026 | AQ8: Additional | AR8: Disposals | AS8: Condition | AW8: Site | AX8: HO | AY8: Yes | AZ8: No | BA8: Still Used | BB8: Not Used | BC8: Repair | BD8: Disposals | BE8: Good | BF8: Bad | BL8: No.
S9: a | T9: b=a:c | U9: c | V9: d=h:b | W9: e=j:b | X9: f=d+e | Y9: g=c-f | Z9: l=h+j | AA9: m=a-l | AB9: j=total k (jAC-des) | AC9: k | AD9: k | AE9: k | AF9: k | AG9: k | AH9: k | AI9: k | AJ9: k | AK9: k | AL9: k | AM9: k | AN9: k | AO9: l=h+j | AP9: m=a-l | AV9: Check
A10: 1 | B10: HCT | C10: D30 | D10: 152 | E10: 3B-E-002 | F10: BLD000006 | G10: 35430 | H10: Building | I10: - | J10: Additional warehouse at Cilegon branch | K10: Jl. Raya Anyer Km. 121, Gunung Sugih, Ciwandan, Banten | Q10: 1 | S10: 41500000 | T10: =+S10/U10 -> 172916.67 | U10: 240 | V10: 0 | W10: =+AB10/T10 -> 0 | X10: =+V10+W10 -> 0 | Y10: =+U10-X10 -> 240 | Z10: 41500000 | AA10: 0 | AB10: =SUM(AC10:AH10) -> 0 | AO10: =+Z10+AB10 -> 41500000 | AP10: =IF(AR10=$AR$8,((S10-AO10)*0),S10-AO10) -> 0 | AU10: Ok | AV10: =VLOOKUP(F10,[78]!D365FinOps_API_Table[[FixedAssetNumber]:[Department]],80,FALSE) -> #REF! | BL10: 3B-E-002
A11: =+A10+1 -> 2 | B11: HCT | C11: D30 | D11: 152 | E11: 3B-E-001 | F11: BLD000007 | G11: 35430 | H11: Building | I11: - | J11: Warehouse at Cilegon branch | K11: Jl. Raya Anyer Km. 121, Gunung Sugih, Ciwandan, Banten | Q11: 1 | S11: 1890319104 | T11: =+S11/U11 -> 7876329.6 | U11: 240 | V11: 240 | W11: =+AB11/T11 -> 0 | X11: =+V11+W11 -> 240 | Y11: =+U11-X11 -> 0 | Z11: 1890319104 | AA11: 0 | AB11: =SUM(AC11:AH11) -> 0 | AO11: =+Z11+AB11 -> 1890319104 | AP11: =IF(AR11=$AR$8,((S11-AO11)*0),S11-AO11) -> 0 | AU11: Ok | AV11: =VLOOKUP(F11,[78]!D365FinOps_API_Table[[FixedAssetNumber]:[Department]],80,FALSE) -> #REF! | BL11: 3B-E-001
A12: =+A11+1 -> 3 | B12: JKTC | C12: D10 | D12: 152 | E12: - | F12: BLD000009 | G12: 36145 | H12: Building | I12: 10 | J12: Building for Construction at Kawasan Jababeka | K12: Kawasan Industri Jababeka, Jl Industri Selatan 2 Blok JJ no. 5, Cikarang West Java | Q12: 1 | S12: 373983750 | T12: =+S12/U12 -> 1558265.6 | U12: 240 | V12: 240 | W12: =+AB12/T12 -> 0 | X12: =+V12+W12 -> 240 | Y12: =+U12-X12 -> 0 | Z12: 373983750 | AA12: 0 | AB12: =SUM(AC12:AH12) -> 0 | AO12: =+Z12+AB12 -> 373983750 | AP12: =IF(AR12=$AR$8,((S12-AO12)*0),S12-AO12) -> 0 | AU12: Ok | AV12: =VLOOKUP(F12,[78]!D365FinOps_API_Table[[FixedAssetNumber]:[Department]],80,FALSE) -> #REF! | BL12: -
A13: =+A12+1 -> 4 | B13: JKTC | C13: D10 | D13: 152 | E13: - | F13: BLD000010 | G13: 36250 | H13: Building | I13: 4012 | J13: Renovation of building at Kawasan Jababeka | K13: Kawasan Industri Jababeka, Jl Industri Selatan 2 Blok JJ no. 5, Cikarang West Java | Q13: 1 | S13: 373993200 | T13: =+S13/U13 -> 1558305 | U13: 240 | V13: 240 | W13: =+AB13/T13 -> 0 | X13: =+V13+W13 -> 240 | Y13: =+U13-X13 -> 0 | Z13: 373993200 | AA13: 0 | AB13: =SUM(AC13:AH13) -> 0 | AO13: =+Z13+AB13 -> 373993200 | AP13: =IF(AR13=$AR$8,((S13-AO13)*0),S13-AO13) -> 0 | AU13: Ok | AV13: =VLOOKUP(F13,[78]!D365FinOps_API_Table[[FixedAssetNumber]:[Department]],80,FALSE) -> #REF! | BL13: -
A14: =+A13+1 -> 5 | B14: CLGC | C14: D30 | D14: 152 | E14: 7-E-005 | F14: BLD000015 | G14: 38579 | H14: Building | I14: 3066 | J14: Office at Bojonegoro (40 M2) | K14: Jl. Bojonegara Salira I, RT. 018/08, Margagiri, Bojonegara, Banten | Q14: 1 | S14: 52475000 | T14: =+S14/U14 -> 874583.33 | U14: 60 | V14: 60 | W14: =+AB14/T14 -> 0 | X14: =+V14+W14 -> 60 | Y14: =+U14-X14 -> 0 | Z14: 52475000 | AA14: 0 | AB14: =SUM(AC14:AH14) -> 0 | AO14: =+Z14+AB14 -> 52475000 | AP14: =IF(AR14=$AR$8,((S14-AO14)*0),S14-AO14) -> 0 | AU14: Ok | AV14: =VLOOKUP(F14,[78]!D365FinOps_API_Table[[FixedAssetNumber]:[Department]],80,FALSE) -> #REF! | BL14: 7-E-005
A15: =+A14+1 -> 6 | B15: HCT | C15: D30 | D15: 152 | E15: 3B-E-003 | F15: BLD000016 | G15: 38715 | H15: Building | I15: 17 | J15: Expansion Canopy for Warehouse | K15: Jl. Raya Anyer Km. 121, Gunung Sugih, Ciwandan, Banten | Q15: 1 | S15: 692000000 | T15: =+S15/U15 -> 2883333.3 | U15: 240 | V15: 240 | W15: =+AB15/T15 -> 0 | X15: =+V15+W15 -> 240 | Y15: =+U15-X15 -> 0 | Z15: 6.92e+08 | AA15: -2.3841858e-07 | AB15: =SUM(AC15:AH15) -> 0 | AO15: =+Z15+AB15 -> 6.92e+08 | AP15: =IF(AR15=$AR$8,((S15-AO15)*0),S15-AO15) -> -2.3841858e-07 | AU15: Ok | AV15: =VLOOKUP(F15,[78]!D365FinOps_API_Table[[FixedAssetNumber]:[Department]],80,FALSE) -> #REF! | BL15: 3B-E-003
A16: =+A15+1 -> 7 | B16: JOIN | C16: D30 | D16: 152 | E16: 3B-E-003 | F16: BLD000017 | G16: 38715 | H16: Building | I16: 17 | J16: Expansion Canopy for Warehouse | K16: Jl. Raya Anyer Km. 121, Gunung Sugih, Ciwandan, Banten | Q16: 1 | S16: 173000000 | T16: =+S16/U16 -> 720833.33 | U16: 240 | V16: 240 | W16: =+AB16/T16 -> 0 | X16: =+V16+W16 -> 240 | Y16: =+U16-X16 -> 0 | Z16: 1.73e+08 | AA16: -5.9604645e-08 | AB16: =SUM(AC16:AH16) -> 0 | AO16: =+Z16+AB16 -> 1.73e+08 | AP16: =IF(AR16=$AR$8,((S16-AO16)*0),S16-AO16) -> -5.9604645e-08 | AU16: Ok | AV16: =VLOOKUP(F16,[78]!D365FinOps_API_Table[[FixedAssetNumber]:[Department]],80,FALSE) -> #REF! | BL16: 3B-E-003
A17: =+A16+1 -> 8 | B17: JKTC | C17: D10 | D17: 152 | F17: BLD000018 | G17: 38980 | H17: Building | I17: 2 | J17: Workshop at Jababeka Cikarang | K17: Kawasan Industri Jababeka, Jl Industri Selatan 2 Blok JJ no. 6, Cikarang West Java | Q17: 1 | S17: 153336000 | T17: =+S17/U17 -> 638900 | U17: 240 | V17: 231 | W17: =+AB17/T17 -> 6 | X17: =+V17+W17 -> 237 | Y17: =+U17-X17 -> 3 | Z17: 147585900 | AA17: 5750100 | AB17: =SUM(AC17:AH17) -> 3833400 | AC17: 638900 | AD17: 638900 | AE17: 638900 | AF17: 638900 | AG17: 638900 | AH17: 638900 | AI17: 638900 | AJ17: 638900 | AK17: 638900 | AL17: 638900 | AM17: 638900 | AN17: 638900 | AO17: =+Z17+AB17 -> 151419300 | AP17: =IF(AR17=$AR$8,((S17-AO17)*0),S17-AO17) -> 1916700 | AU17: Ok | AV17: =VLOOKUP(F17,[78]!D365FinOps_API_Table[[FixedAssetNumber]:[Department]],80,FALSE) -> #REF!
A18: =+A17+1 -> 9 | B18: JKTC | C18: D10 | D18: 152 | F18: BLD000019 | G18: 38981 | H18: Building | I18: 2 | J18: Workshop at Jababeka Cikarang | K18: Kawasan Industri Jababeka, Jl Industri Selatan 2 Blok JJ no. 6, Cikarang West Java | Q18: 1 | S18: 727290000 | T18: =+S18/U18 -> 3030375 | U18: 240 | V18: 231 | W18: =+AB18/T18 -> 6 | X18: =+V18+W18 -> 237 | Y18: =+U18-X18 -> 3 | Z18: 700016625 | AA18: 27273375 | AB18: =SUM(AC18:AH18) -> 18182250 | AC18: 3030375 | AD18: 3030375 | AE18: 3030375 | AF18: 3030375 | AG18: 3030375 | AH18: 3030375 | AI18: 3030375 | AJ18: 3030375 | AK18: 3030375 | AL18: 3030375 | AM18: 3030375 | AN18: 3030375 | AO18: =+Z18+AB18 -> 718198875 | AP18: =IF(AR18=$AR$8,((S18-AO18)*0),S18-AO18) -> 9091125 | AU18: Ok | AV18: =VLOOKUP(F18,[78]!D365FinOps_API_Table[[FixedAssetNumber]:[Department]],80,FALSE) -> #REF!
A19: =+A18+1 -> 10 | B19: JKTC | C19: D10 | D19: 152 | F19: BLD000020 | G19: 39051 | H19: Building | I19: 125 | J19: Renovation of New Workshop at Cikarang | K19: Kawasan Industri Jababeka, Jl Industri Selatan 2 Blok JJ no. 6, Cikarang West Java | Q19: 1 | S19: 36100000 | T19: =+S19/U19 -> 150416.67 | U19: 240 | V19: 229 | W19: =+AB19/T19 -> 6 | X19: =+V19+W19 -> 235 | Y19: =+U19-X19 -> 5 | Z19: 34445417 | AA19: 1654583.3 | AB19: =SUM(AC19:AH19) -> 902500 | AC19: 150416.67 | AD19: 150416.67 | AE19: 150416.67 | AF19: 150416.67 | AG19: 150416.67 | AH19: 150416.67 | AI19: 150416.67 | AJ19: 150416.67 | AK19: 150416.67 | AL19: 150416.67 | AM19: 150416.67 | AN19: 150416.67 | AO19: =+Z19+AB19 -> 35347917 | AP19: =IF(AR19=$AR$8,((S19-AO19)*0),S19-AO19) -> 752083.33 | AU19: Ok | AV19: =VLOOKUP(F19,[78]!D365FinOps_API_Table[[FixedAssetNumber]:[Department]],80,FALSE) -> #REF!
A20: =+A19+1 -> 11 | B20: JKTC | C20: D10 | D20: 152 | F20: BLD000021 | G20: 39051 | H20: Building | I20: 4005 | J20: Renovation of New Workshop at Cikarang | K20: Kawasan Industri Jababeka, Jl Industri Selatan 2 Blok JJ no. 6, Cikarang West Java | Q20: 1 | S20: 24253500 | T20: =+S20/U20 -> 101056.25 | U20: 240 | V20: 229 | W20: =+AB20/T20 -> 6 | X20: =+V20+W20 -> 235 | Y20: =+U20-X20 -> 5 | Z20: 23141881 | AA20: 1111618.8 | AB20: =SUM(AC20:AH20) -> 606337.5 | AC20: 101056.25 | AD20: 101056.25 | AE20: 101056.25 | AF20: 101056.25 | AG20: 101056.25 | AH20: 101056.25 | AI20: 101056.25 | AJ20: 101056.25 | AK20: 101056.25 | AL20: 101056.25 | AM20: 101056.25 | AN20: 101056.25 | AO20: =+Z20+AB20 -> 23748219 | AP20: =IF(AR20=$AR$8,((S20-AO20)*0),S20-AO20) -> 505281.25 | AU20: Ok | AV20: =VLOOKUP(F20,[78]!D365FinOps_API_Table[[FixedAssetNumber]:[Department]],80,FALSE) -> #REF!
A21: =+A20+1 -> 12 | B21: JKTC | C21: D10 | D21: 152 | F21: BLD000022 | G21: 39051 | H21: Building | I21: 4058 | J21: Renovation of New Workshop at Cikarang | K21: Kawasan Industri Jababeka, Jl Industri Selatan 2 Blok JJ no. 6, Cikarang West Java | Q21: 1 | S21: 64080000 | T21: =+S21/U21 -> 267000 | U21: 240 | V21: 229 | W21: =+AB21/T21 -> 6 | X21: =+V21+W21 -> 235 | Y21: =+U21-X21 -> 5 | Z21: 61143000 | AA21: 2937000 | AB21: =SUM(AC21:AH21) -> 1602000 | AC21: 267000 | AD21: 267000 | AE21: 267000 | AF21: 267000 | AG21: 267000 | AH21: 267000 | AI21: 267000 | AJ21: 267000 | AK21: 267000 | AL21: 267000 | AM21: 267000 | AN21: 267000 | AO21: =+Z21+AB21 -> 62745000 | AP21: =IF(AR21=$AR$8,((S21-AO21)*0),S21-AO21) -> 1335000 | AU21: Ok | AV21: =VLOOKUP(F21,[78]!D365FinOps_API_Table[[FixedAssetNumber]:[Department]],80,FALSE) -> #REF!
A22: =+A21+1 -> 13 | B22: JKTC | C22: D10 | D22: 152 | F22: BLD000023 | G22: 39051 | H22: Building | I22: 4058 | J22: Renovation of New Workshop at Cikarang | K22: Kawasan Industri Jababeka, Jl Industri Selatan 2 Blok JJ no. 6, Cikarang West Java | Q22: 1 | S22: 42720000 | T22: =+S22/U22 -> 178000 | U22: 240 | V22: 229 | W22: =+AB22/T22 -> 6 | X22: =+V22+W22 -> 235 | Y22: =+U22-X22 -> 5 | Z22: 40762000 | AA22: 1958000 | AB22: =SUM(AC22:AH22) -> 1068000 | AC22: 178000 | AD22: 178000 | AE22: 178000 | AF22: 178000 | AG22: 178000 | AH22: 178000 | AI22: 178000 | AJ22: 178000 | AK22: 178000 | AL22: 178000 | AM22: 178000 | AN22: 178000 | AO22: =+Z22+AB22 -> 41830000 | AP22: =IF(AR22=$AR$8,((S22-AO22)*0),S22-AO22) -> 890000 | AU22: Ok | AV22: =VLOOKUP(F22,[78]!D365FinOps_API_Table[[FixedAssetNumber]:[Department]],80,FALSE) -> #REF!
A23: =+A22+1 -> 14 | B23: JKTC | C23: D10 | D23: 152 | F23: BLD000024 | G23: 39080 | H23: Building | I23: 4013 | J23: Additional work for New warehouse at Cikarang | K23: Kawasan Industri Jababeka, Jl Industri Selatan 2 Blok JJ no. 6, Cikarang West Java | Q23: 1 | S23: 22000000 | T23: =+S23/U23 -> 91666.667 | U23: 240 | V23: 229 | W23: =+AB23/T23 -> 6 | X23: =+V23+W23 -> 235 | Y23: =+U23-X23 -> 5 | Z23: 20991667 | AA23: 1008333.3 | AB23: =SUM(AC23:AH23) -> 550000 | AC23: 91666.667 | AD23: 91666.667 | AE23: 91666.667 | AF23: 91666.667 | AG23: 91666.667 | AH23: 91666.667 | AI23: 91666.667 | AJ23: 91666.667 | AK23: 91666.667 | AL23: 91666.667 | AM23: 91666.667 | AN23: 91666.667 | AO23: =+Z23+AB23 -> 21541667 | AP23: =IF(AR23=$AR$8,((S23-AO23)*0),S23-AO23) -> 458333.33 | AU23: Ok | AV23: =VLOOKUP(F23,[78]!D365FinOps_API_Table[[FixedAssetNumber]:[Department]],80,FALSE) -> #REF!
A24: =+A23+1 -> 15 | B24: JKTC | C24: D10 | D24: 152 | F24: BLD000025 | G24: 39080 | H24: Building | I24: 4029 | J24: Additional work for New warehouse at Cikarang | K24: Kawasan Industri Jababeka, Jl Industri Selatan 2 Blok JJ no. 6, Cikarang West Java | Q24: 1 | S24: 16169000 | T24: =+S24/U24 -> 67370.833 | U24: 240 | V24: 229 | W24: =+AB24/T24 -> 6 | X24: =+V24+W24 -> 235 | Y24: =+U24-X24 -> 5 | Z24: 15427921 | AA24: 741079.17 | AB24: =SUM(AC24:AH24) -> 404225 | AC24: 67370.833 | AD24: 67370.833 | AE24: 67370.833 | AF24: 67370.833 | AG24: 67370.833 | AH24: 67370.833 | AI24: 67370.833 | AJ24: 67370.833 | AK24: 67370.833 | AL24: 67370.833 | AM24: 67370.833 | AN24: 67370.833 | AO24: =+Z24+AB24 -> 15832146 | AP24: =IF(AR24=$AR$8,((S24-AO24)*0),S24-AO24) -> 336854.17 | AU24: Ok | AV24: =VLOOKUP(F24,[78]!D365FinOps_API_Table[[FixedAssetNumber]:[Department]],80,FALSE) -> #REF!
A25: =+A24+1 -> 16 | B25: JKTC | C25: D10 | D25: 152 | F25: BLD000026 | G25: 39080 | H25: Building | I25: 4033 | J25: Additional work for New warehouse at Cikarang | K25: Kawasan Industri Jababeka, Jl Industri Selatan 2 Blok JJ no. 6, Cikarang West Java | Q25: 1 | S25: 51901000 | T25: =+S25/U25 -> 216254.17 | U25: 240 | V25: 229 | W25: =+AB25/T25 -> 6 | X25: =+V25+W25 -> 235 | Y25: =+U25-X25 -> 5 | Z25: 49522204 | AA25: 2378795.8 | AB25: =SUM(AC25:AH25) -> 1297525 | AC25: 216254.17 | AD25: 216254.17 | AE25: 216254.17 | AF25: 216254.17 | AG25: 216254.17 | AH25: 216254.17 | AI25: 216254.17 | AJ25: 216254.17 | AK25: 216254.17 | AL25: 216254.17 | AM25: 216254.17 | AN25: 216254.17 | AO25: =+Z25+AB25 -> 50819729 | AP25: =IF(AR25=$AR$8,((S25-AO25)*0),S25-AO25) -> 1081270.8 | AU25: Ok | AV25: =VLOOKUP(F25,[78]!D365FinOps_API_Table[[FixedAssetNumber]:[Department]],80,FALSE) -> #REF!
A26: =+A25+1 -> 17 | B26: JKTC | C26: D10 | D26: 152 | F26: BLD000027 | G26: 39080 | H26: Building | I26: 4053 | J26: Additional work for New warehouse at Cikarang | K26: Kawasan Industri Jababeka, Jl Industri Selatan 2 Blok JJ no. 6, Cikarang West Java | Q26: 1 | S26: 37640000 | T26: =+S26/U26 -> 156833.33 | U26: 240 | V26: 229 | W26: =+AB26/T26 -> 6 | X26: =+V26+W26 -> 235 | Y26: =+U26-X26 -> 5 | Z26: 35914833 | AA26: 1725166.7 | AB26: =SUM(AC26:AH26) -> 941000 | AC26: 156833.33 | AD26: 156833.33 | AE26: 156833.33 | AF26: 156833.33 | AG26: 156833.33 | AH26: 156833.33 | AI26: 156833.33 | AJ26: 156833.33 | AK26: 156833.33 | AL26: 156833.33 | AM26: 156833.33 | AN26: 156833.33 | AO26: =+Z26+AB26 -> 36855833 | AP26: =IF(AR26=$AR$8,((S26-AO26)*0),S26-AO26) -> 784166.67 | AU26: Ok | AV26: =VLOOKUP(F26,[78]!D365FinOps_API_Table[[FixedAssetNumber]:[Department]],80,FALSE) -> #REF!
A27: =+A26+1 -> 18 | B27: JKTC | C27: D10 | D27: 152 | F27: BLD000028 | G27: 39113 | H27: Building | I27: 4022 | J27: Renovation of New Workshop at Cikarang | K27: Kawasan Industri Jababeka, Jl Industri Selatan 2 Blok JJ no. 6, Cikarang West Java | Q27: 1 | S27: 50340000 | T27: =+S27/U27 -> 209750 | U27: 240 | V27: 228 | W27: =+AB27/T27 -> 6 | X27: =+V27+W27 -> 234 | Y27: =+U27-X27 -> 6 | Z27: 47823000 | AA27: 2517000 | AB27: =SUM(AC27:AH27) -> 1258500 | AC27: 209750 | AD27: 209750 | AE27: 209750 | AF27: 209750 | AG27: 209750 | AH27: 209750 | AI27: 209750 | AJ27: 209750 | AK27: 209750 | AL27: 209750 | AM27: 209750 | AN27: 209750 | AO27: =+Z27+AB27 -> 49081500 | AP27: =IF(AR27=$AR$8,((S27-AO27)*0),S27-AO27) -> 1258500 | AU27: Ok | AV27: =VLOOKUP(F27,[78]!D365FinOps_API_Table[[FixedAssetNumber]:[Department]],80,FALSE) -> #REF!
A28: =+A27+1 -> 19 | B28: JKTC | C28: D10 | D28: 152 | F28: BLD000029 | G28: 39113 | H28: Building | I28: 4026 | J28: Renovation of New Workshop at Cikarang | K28: Kawasan Industri Jababeka, Jl Industri Selatan 2 Blok JJ no. 6, Cikarang West Java | Q28: 1 | S28: 23735290 | T28: =+S28/U28 -> 98897.042 | U28: 240 | V28: 228 | W28: =+AB28/T28 -> 6 | X28: =+V28+W28 -> 234 | Y28: =+U28-X28 -> 6 | Z28: 22548526 | AA28: 1186764.5 | AB28: =SUM(AC28:AH28) -> 593382.25 | AC28: 98897.042 | AD28: 98897.042 | AE28: 98897.042 | AF28: 98897.042 | AG28: 98897.042 | AH28: 98897.042 | AI28: 98897.042 | AJ28: 98897.042 | AK28: 98897.042 | AL28: 98897.042 | AM28: 98897.042 | AN28: 98897.042 | AO28: =+Z28+AB28 -> 23141908 | AP28: =IF(AR28=$AR$8,((S28-AO28)*0),S28-AO28) -> 593382.25 | AU28: Ok | AV28: =VLOOKUP(F28,[78]!D365FinOps_API_Table[[FixedAssetNumber]:[Department]],80,FALSE) -> #REF!
... A37: =+A36+1 -> 28 | B37: JKTC | C37: D10 | D37: 152 | F37: BLD000038 | G37: 39171 | H37: Building | I37: 4049 | J37: Renovation of New Workshop at Cikarang | K37: Kawasan Industri Jababeka, Jl Industri Selatan 2 Blok JJ no. 6, Cikarang West Java | Q37: 1 | S37: 13800000 | T37: =+S37/U37 -> 57500 | U37: 240 | V37: 226 | W37: =+AB37/T37 -> 6 | X37: =+V37+W37 -> 232 | Y37: =+U37-X37 -> 8 | Z37: 12995000 | AA37: 805000 | AB37: =SUM(AC37:AH37) -> 345000 | AC37: 57500 | AD37: 57500 | AE37: 57500 | AF37: 57500 | AG37: 57500 | AH37: 57500 | AI37: 57500 | AJ37: 57500 | AK37: 57500 | AL37: 57500 | AM37: 57500 | AN37: 57500 | AO37: =+Z37+AB37 -> 13340000 | AP37: =IF(AR37=$AR$8,((S37-AO37)*0),S37-AO37) -> 460000 | AU37: Ok | AV37: =VLOOKUP(F37,[78]!D365FinOps_API_Table[[FixedAssetNumber]:[Department]],80,FALSE) -> #REF!
A38: =+A37+1 -> 29 | B38: CLGA | C38: AD_CGADM | D38: 152 | E38: 7-E-008 | F38: BLD000039 | G38: 39660 | H38: Building | I38: 3051 | J38: New mess for Japanesse | K38: Jl. TB. Ismail, Bendungan, Cilegon, Banten | Q38: 1 | S38: 3000000000 | T38: =+S38/U38 -> 12500000 | U38: 240 | V38: 210 | W38: =+AB38/T38 -> 6 | X38: =+V38+W38 -> 216 | Y38: =+U38-X38 -> 24 | Z38: 2625000000 | AA38: 375000000 | AB38: =SUM(AC38:AH38) -> 75000000 | AC38: 12500000 | AD38: 12500000 | AE38: 12500000 | AF38: 12500000 | AG38: 12500000 | AH38: 12500000 | AI38: 12500000 | AJ38: 12500000 | AK38: 12500000 | AL38: 12500000 | AM38: 12500000 | AN38: 12500000 | AO38: =+Z38+AB38 -> 2700000000 | AP38: =IF(AR38=$AR$8,((S38-AO38)*0),S38-AO38) -> 300000000 | AU38: Ok | AV38: =VLOOKUP(F38,[78]!D365FinOps_API_Table[[FixedAssetNumber]:[Department]],80,FALSE) -> #REF! | BL38: 7-E-008
A39: =+A38+1 -> 30 | B39: CLGA | C39: AD_CGADM | D39: 152 | E39: 7C-E-002 | F39: BLD000040 | G39: 39660 | H39: Building | I39: 3052 | J39: Cilegon New Office | K39: Jl. Raya Anyer Km. 121, Gunung Sugih, Ciwandan, Banten | S39: 540406125 | T39: 2251692.2 | U39: 240 | V39: 210 | W39: =+AB39/T39 -> 6 | X39: =+V39+W39 -> 216 | Y39: =+U39-X39 -> 24 | Z39: 4.7285536e+08 | AA39: 67550766 | AB39: =SUM(AC39:AH39) -> 13510153 | AC39: 2251692.2 | AD39: 2251692.2 | AE39: 2251692.2 | AF39: 2251692.2 | AG39: 2251692.2 | AH39: 2251692.2 | AI39: 2251692.2 | AJ39: 2251692.2 | AK39: 2251692.2 | AL39: 2251692.2 | AM39: 2251692.2 | AN39: 2251692.2 | AO39: =+Z39+AB39 -> 4.8636551e+08 | AP39: =IF(AR39=$AR$8,((S39-AO39)*0),S39-AO39) -> 54040612 | AU39: Ok | AV39: =VLOOKUP(F39,[78]!D365FinOps_API_Table[[FixedAssetNumber]:[Department]],80,FALSE) -> #REF! | BL39: 7C-E-002
A40: =+A39+1 -> 31 | B40: CLGA | C40: AD_CGADM | D40: 152 | E40: 7C-E-002 | F40: BLD000041 | G40: 39660 | H40: Building | I40: 3052 | J40: Cilegon New Office | K40: Jl. Raya Anyer Km. 121, Gunung Sugih, Ciwandan, Banten | Q40: 1 | S40: 2161624500 | T40: 10132615 | U40: 240 | V40: 200.66667 | W40: =+AB40/T40 -> 6 | X40: =+V40+W40 -> 206.66667 | Y40: =+U40-X40 -> 33.333333 | Z40: 2.033278e+09 | AA40: 1.2834645e+08 | AB40: =SUM(AC40:AH40) -> 60795689 | AC40: 10132615 | AD40: 10132615 | AE40: 10132615 | AF40: 10132615 | AG40: 10132615 | AH40: 10132615 | AI40: 10132615 | AJ40: 10132615 | AK40: 10132615 | AL40: 10132615 | AM40: 10132615 | AN40: 10132615 | AO40: =+Z40+AB40 -> 2.0940737e+09 | AP40: =IF(AR40=$AR$8,((S40-AO40)*0),S40-AO40) -> 67550766 | AU40: Ok | AV40: =VLOOKUP(F40,[78]!D365FinOps_API_Table[[FixedAssetNumber]:[Department]],80,FALSE) -> #REF! | BL40: 7C-E-002
A41: =+A40+1 -> 32 | B41: CLGA | C41: AD_CGADM | D41: 152 | E41: 7C-E-002 | F41: BLD000042 | G41: 39660 | H41: Building | I41: 3052 | J41: Cilegon New Office | K41: Jl. Raya Anyer Km. 121, Gunung Sugih, Ciwandan, Banten | S41: 2702030625 | T41: 10132615 | U41: 240 | V41: 219.33333 | W41: =+AB41/T41 -> 6 | X41: =+V41+W41 -> 225.33333 | Y41: =+U41-X41 -> 14.666667 | Z41: 2.2224202e+09 | AA41: 4.7961044e+08 | AB41: =SUM(AC41:AH41) -> 60795689 | AC41: 10132615 | AD41: 10132615 | AE41: 10132615 | AF41: 10132615 | AG41: 10132615 | AH41: 10132615 | AI41: 10132615 | AJ41: 10132615 | AK41: 10132615 | AL41: 10132615 | AM41: 10132615 | AN41: 10132615 | AO41: =+Z41+AB41 -> 2.2832159e+09 | AP41: =IF(AR41=$AR$8,((S41-AO41)*0),S41-AO41) -> 4.1881475e+08 | AU41: Ok | AV41: =VLOOKUP(F41,[78]!D365FinOps_API_Table[[FixedAssetNumber]:[Department]],80,FALSE) -> #REF! | BL41: 7C-E-002
A42: =+A41+1 -> 33 | B42: JOIN | C42: D30 | D42: 152 | E42: 3B-E-004 | F42: BLD000043 | G42: 39717 | H42: Building | I42: 3041 | J42: Renovation for Warehouse Cilegon | K42: Jl. Raya Anyer Km. 121, Gunung Sugih, Ciwandan, Banten | Q42: 1 | S42: 114000000 | T42: =+S42/U42 -> 950000 | U42: 120 | V42: 120 | W42: =+AB42/T42 -> 0 | X42: =+V42+W42 -> 120 | Y42: =+U42-X42 -> 0 | Z42: 114000000 | AA42: 0 | AB42: =SUM(AC42:AH42) -> 0 | AO42: =+Z42+AB42 -> 114000000 | AP42: =IF(AR42=$AR$8,((S42-AO42)*0),S42-AO42) -> 0 | AU42: Ok | AV42: =VLOOKUP(F42,[78]!D365FinOps_API_Table[[FixedAssetNumber]:[Department]],80,FALSE) -> #REF! | BL42: 3B-E-004
A43: =+A42+1 -> 34 | B43: HCT | C43: D30 | D43: 152 | E43: 3B-E-004 | F43: BLD000044 | G43: 39717 | H43: Building | I43: 3041 | J43: Renovation for Warehouse Cilegon | K43: Jl. Raya Anyer Km. 121, Gunung Sugih, Ciwandan, Banten | S43: 456000000 | T43: =+S43/U43 -> 3800000 | U43: 120 | V43: 120 | W43: =+AB43/T43 -> 0 | X43: =+V43+W43 -> 120 | Y43: =+U43-X43 -> 0 | Z43: 456000000 | AA43: 0 | AB43: =SUM(AC43:AH43) -> 0 | AO43: =+Z43+AB43 -> 456000000 | AP43: =IF(AR43=$AR$8,((S43-AO43)*0),S43-AO43) -> 0 | AU43: Ok | AV43: =VLOOKUP(F43,[78]!D365FinOps_API_Table[[FixedAssetNumber]:[Department]],80,FALSE) -> #REF! | BL43: 3B-E-004
A44: =+A43+1 -> 35 | B44: CLGC | C44: D30 | D44: 152 | E44: M10-E-003 | F44: BLD000045 | G44: 40907 | H44: Building | I44: 3031 | J44: Warehouse Canopy | K44: Jl. Raya Anyer Km. 121, Gunung Sugih, Ciwandan, Banten | Q44: 1 | S44: 950000000 | T44: =+S44/U44 -> 15833333 | U44: 60 | V44: 60 | W44: =+AB44/T44 -> 0 | X44: =+V44+W44 -> 60 | Y44: =+U44-X44 -> 0 | Z44: 950000000 | AA44: 0 | AB44: =SUM(AC44:AH44) -> 0 | AO44: =+Z44+AB44 -> 950000000 | AP44: =IF(AR44=$AR$8,((S44-AO44)*0),S44-AO44) -> 0 | AU44: Ok | AV44: =VLOOKUP(F44,[78]!D365FinOps_API_Table[[FixedAssetNumber]:[Department]],80,FALSE) -> #REF! | BG44: 1 | BL44: M10-E-003
A45: =+A44+1 -> 36 | B45: SLI | C45: AD_HO | D45: 152 | E45: JKL-131-001 | F45: BLD000046 | G45: 41163 | H45: Building | I45: 5 | J45: Tanjung Priok Office | K45: Jl. Enggano no. 40B Jakarta Utara | L45: Jakarta Logistic | M45: 2012 | Q45: 1 | S45: 570190000 | T45: =+S45/U45 -> 2375791.7 | U45: 240 | V45: 162 | W45: =+AB45/T45 -> 6 | X45: =+V45+W45 -> 168 | Y45: =+U45-X45 -> 72 | Z45: 384878250 | AA45: 185311750 | AB45: =SUM(AC45:AH45) -> 14254750 | AC45: 2375791.7 | AD45: 2375791.7 | AE45: 2375791.7 | AF45: 2375791.7 | AG45: 2375791.7 | AH45: 2375791.7 | AI45: 2375791.7 | AJ45: 2375791.7 | AK45: 2375791.7 | AL45: 2375791.7 | AM45: 2375791.7 | AN45: 2375791.7 | AO45: =+Z45+AB45 -> 399133000 | AP45: =IF(AR45=$AR$8,((S45-AO45)*0),S45-AO45) -> 171057000 | AU45: Ok | AV45: =VLOOKUP(F45,[78]!D365FinOps_API_Table[[FixedAssetNumber]:[Department]],80,FALSE) -> #REF! | BL45: JKL-131-001
A46: =+A45+1 -> 37 | B46: CKR | C46: AD_HO | D46: 152 | E46: BLD000047 | F46: BLD000047 | G46: 41639 | H46: Building | I46: 111 | J46: Cikarang Warehouse and Office | K46: Kawasan Industri Terpadu Indonesia China (KITIC) Kav. 20, Cikarang, West Java | L46: Head Ofice & Cikarang Logistic | M46: 2013 | Q46: 1 | S46: 17412922966 | T46: =+S46/U46 -> 72553846 | U46: 240 | V46: 145 | W46: =+AB46/T46 -> 6 | X46: =+V46+W46 -> 151 | Y46: =+U46-X46 -> 89 | Z46: 1.0520308e+10 | AA46: 6.8926153e+09 | AB46: =SUM(AC46:AH46) -> 4.3532307e+08 | AC46: 72553846 | AD46: 72553846 | AE46: 72553846 | AF46: 72553846 | AG46: 72553846 | AH46: 72553846 | AI46: 72553846 | AJ46: 72553846 | AK46: 72553846 | AL46: 72553846 | AM46: 72553846 | AN46: 72553846 | AO46: =+Z46+AB46 -> 1.0955631e+10 | AP46: =IF(AR46=$AR$8,((S46-AO46)*0),S46-AO46) -> 6.4572923e+09 | AU46: Ok | AV46: =VLOOKUP(F46,[78]!D365FinOps_API_Table[[FixedAssetNumber]:[Department]],80,FALSE) -> #REF! | BL46: BLD000047
A47: =+A46+1 -> 38 | B47: CLC | C47: CLCWH | D47: 152 | E47: CLC131-001 | F47: BLD000048 | G47: 41639 | H47: Building | I47: 111 | J47: Cikarang Warehouse and Office | K47: Kawasan Industri Terpadu Indonesia China (KITIC) Kav. 20, Cikarang, West Java | L47: Head Ofice & Cikarang Logistic | M47: 2013 | Q47: 1 | S47: 7.1701319e+10 | T47: =+S47/U47 -> 2.987555e+08 | U47: 240 | V47: 145 | W47: =+AB47/T47 -> 6 | X47: =+V47+W47 -> 151 | Y47: =+U47-X47 -> 89 | Z47: 4.3319547e+10 | AA47: 2.8381772e+10 | AB47: =SUM(AC47:AH47) -> 1.792533e+09 | AC47: 2.987555e+08 | AD47: 2.987555e+08 | AE47: 2.987555e+08 | AF47: 2.987555e+08 | AG47: 2.987555e+08 | AH47: 2.987555e+08 | AI47: 2.987555e+08 | AJ47: 2.987555e+08 | AK47: 2.987555e+08 | AL47: 2.987555e+08 | AM47: 2.987555e+08 | AN47: 2.987555e+08 | AO47: =+Z47+AB47 -> 4.511208e+10 | AP47: =IF(AR47=$AR$8,((S47-AO47)*0),S47-AO47) -> 2.6589239e+10 | AU47: Ok | AV47: =VLOOKUP(F47,[78]!D365FinOps_API_Table[[FixedAssetNumber]:[Department]],80,FALSE) -> #REF! | AW47: =AV47-AJ47 -> #REF! | BL47: CLC131-001
A48: =+A47+1 -> 39 | B48: CLGC | C48: D30 | D48: 152 | E48: M10-E-004 | F48: BLD000049 | G48: 41696 | H48: Building | I48: 3152 | J48: Fencing | K48: Bojonegara Land | M48: 2014 | Q48: 1 | S48: 1129260000 | T48: =+S48/U48 -> 18821000 | U48: 60 | V48: 60 | W48: =+AB48/T48 -> 0 | X48: =+V48+W48 -> 60 | Y48: =+U48-X48 -> 0 | Z48: 1129260000 | AA48: 0 | AB48: =SUM(AC48:AH48) -> 0 | AO48: =+Z48+AB48 -> 1129260000 | AP48: =IF(AR48=$AR$8,((S48-AO48)*0),S48-AO48) -> 0 | AU48: Ok | AV48: =VLOOKUP(F48,[78]!D365FinOps_API_Table[[FixedAssetNumber]:[Department]],80,FALSE) -> #REF! | AW48: =AV48-AJ48 -> #REF! | BL48: M10-E-004
A49: =+A48+1 -> 40 | B49: CLGC | C49: D30 | D49: 152 | E49: M10-E-005 | F49: BLD000050 | G49: 41757 | H49: Building | I49: 13 | J49: Clearing and compacting Land at Bojonegara | M49: 2014 | Q49: 1 | S49: 1167000000 | T49: =+S49/U49 -> 19450000 | U49: 60 | V49: 60 | W49: =+AB49/T49 -> 0 | X49: =+V49+W49 -> 60 | Y49: =+U49-X49 -> 0 | Z49: 1167000000 | AA49: 0 | AB49: =SUM(AC49:AH49) -> 0 | AO49: =+Z49+AB49 -> 1167000000 | AP49: =IF(AR49=$AR$8,((S49-AO49)*0),S49-AO49) -> 0 | AU49: Ok | AV49: =VLOOKUP(F49,[78]!D365FinOps_API_Table[[FixedAssetNumber]:[Department]],80,FALSE) -> #REF! | AW49: =AV49-AJ49 -> #REF! | BL49: M10-E-005
A50: =+A49+1 -> 41 | B50: CLGC | C50: D30 | D50: 152 | E50: M10-E-005 | F50: BLD000051 | G50: 41757 | H50: Building | I50: 13 | J50: Clearing and compacting Land at Bojonegara | M50: 2014 | S50: 1167000000 | T50: =+S50/U50 -> 19450000 | U50: 60 | V50: 60 | W50: =+AB50/T50 -> 0 | X50: =+V50+W50 -> 60 | Y50: =+U50-X50 -> 0 | Z50: 1167000000 | AA50: 0 | AB50: =SUM(AC50:AH50) -> 0 | AO50: =+Z50+AB50 -> 1167000000 | AP50: =IF(AR50=$AR$8,((S50-AO50)*0),S50-AO50) -> 0 | AU50: Ok | AV50: =VLOOKUP(F50,[78]!D365FinOps_API_Table[[FixedAssetNumber]:[Department]],80,FALSE) -> #REF! | AW50: =AV50-AJ50 -> #REF! | BL50: M10-E-005
A51: =+A50+1 -> 42 | B51: MESS | C51: AD_HO | D51: 152 | E51: BLD000052 | F51: BLD000052 | G51: 41881 | H51: Building | I51: 51 | J51: Dormitory (Building Work) | K51: Kota Deltamas Cluster Pasadena Blok B, Cikarang Pusat, Jawa Barat | M51: 2014 | N51: B11-B12-B15-B16-B17 | O51: B50-B51-B52-B53-B55 | Q51: 1 | S51: 8500000000 | T51: =+S51/U51 -> 35416667 | U51: 240 | V51: 137 | W51: =+AB51/T51 -> 6 | X51: =+V51+W51 -> 143 | Y51: =+U51-X51 -> 97 | Z51: 4.8520833e+09 | AA51: 3.6479167e+09 | AB51: =SUM(AC51:AH51) -> 2.125e+08 | AC51: 35416667 | AD51: 35416667 | AE51: 35416667 | AF51: 35416667 | AG51: 35416667 | AH51: 35416667 | AI51: 35416667 | AJ51: 35416667 | AK51: 35416667 | AL51: 35416667 | AM51: 35416667 | AN51: 35416667 | AO51: =+Z51+AB51 -> 5.0645833e+09 | AP51: =IF(AR51=$AR$8,((S51-AO51)*0),S51-AO51) -> 3.4354167e+09 | AU51: Ok | AV51: =VLOOKUP(F51,[78]!D365FinOps_API_Table[[FixedAssetNumber]:[Department]],80,FALSE) -> #REF! | AW51: =AV51-AJ51 -> #REF! | BL51: BLD000052
A52: =+A51+1 -> 43 | B52: MESS | C52: AD_HO | D52: 152 | E52: BLD000053 | F52: BLD000053 | G52: 41881 | H52: Building | I52: 51 | J52: Dormitory (M&E Work) | K52: Kota Deltamas Cluster Pasadena Blok B, Cikarang Pusat, Jawa Barat | M52: 2014 | N52: B11-B12-B15-B16-B17 | O52: B50-B51-B52-B53-B55 | Q52: 1 | S52: 5500000000 | T52: =+S52/U52 -> 22916667 | U52: 240 | V52: 137 | W52: =+AB52/T52 -> 6 | X52: =+V52+W52 -> 143 | Y52: =+U52-X52 -> 97 | Z52: 3.1395833e+09 | AA52: 2.3604167e+09 | AB52: =SUM(AC52:AH52) -> 137500000 | AC52: 22916667 | AD52: 22916667 | AE52: 22916667 | AF52: 22916667 | AG52: 22916667 | AH52: 22916667 | AI52: 22916667 | AJ52: 22916667 | AK52: 22916667 | AL52: 22916667 | AM52: 22916667 | AN52: 22916667 | AO52: =+Z52+AB52 -> 3.2770833e+09 | AP52: =IF(AR52=$AR$8,((S52-AO52)*0),S52-AO52) -> 2.2229167e+09 | AU52: Ok | AV52: =VLOOKUP(F52,[78]!D365FinOps_API_Table[[FixedAssetNumber]:[Department]],80,FALSE) -> #REF! | AW52: =AV52-AJ52 -> #REF! | BL52: BLD000053
A53: =+A52+1 -> 44 | B53: MESS | C53: AD_HO | D53: 152 | E53: BLD000054 | F53: BLD000054 | G53: 41881 | H53: Building | I53: 51 | J53: Dormitory (Building Work) | K53: Kota Deltamas Cluster Pasadena Blok B, Cikarang Pusat, Jawa Barat | M53: 2014 | N53: B11-B12-B15-B16-B17 | O53: B50-B51-B52-B53-B55 | Q53: 1 | S53: 500000000 | T53: =+S53/U53 -> 2083333.3 | U53: 240 | V53: 137 | W53: =+AB53/T53 -> 6 | X53: =+V53+W53 -> 143 | Y53: =+U53-X53 -> 97 | Z53: 2.8541667e+08 | AA53: 2.1458333e+08 | AB53: =SUM(AC53:AH53) -> 12500000 | AC53: 2083333.3 | AD53: 2083333.3 | AE53: 2083333.3 | AF53: 2083333.3 | AG53: 2083333.3 | AH53: 2083333.3 | AI53: 2083333.3 | AJ53: 2083333.3 | AK53: 2083333.3 | AL53: 2083333.3 | AM53: 2083333.3 | AN53: 2083333.3 | AO53: =+Z53+AB53 -> 2.9791667e+08 | AP53: =IF(AR53=$AR$8,((S53-AO53)*0),S53-AO53) -> 2.0208333e+08 | AU53: Ok | AV53: =VLOOKUP(F53,[78]!D365FinOps_API_Table[[FixedAssetNumber]:[Department]],80,FALSE) -> #REF! | AW53: =AV53-AJ53 -> #REF! | BL53: BLD000054
A54: =+A53+1 -> 45 | B54: MESS | C54: AD_HO | D54: 152 | E54: BLD000055 | F54: BLD000055 | G54: 41745 | H54: Building | I54: 20 | J54: Building Permit (IMB) | K54: Kota Deltamas Cluster Pasadena Blok B, Cikarang Pusat, Jawa Barat | M54: 2014 | N54: 503/088/B/BPMPPT | Q54: 1 | S54: 61175000 | T54: =+S54/U54 -> 254895.83 | U54: 240 | V54: 137 | W54: =+AB54/T54 -> 6 | X54: =+V54+W54 -> 143 | Y54: =+U54-X54 -> 97 | Z54: 34920729 | AA54: 26254271 | AB54: =SUM(AC54:AH54) -> 1529375 | AC54: 254895.83 | AD54: 254895.83 | AE54: 254895.83 | AF54: 254895.83 | AG54: 254895.83 | AH54: 254895.83 | AI54: 254895.83 | AJ54: 254895.83 | AK54: 254895.83 | AL54: 254895.83 | AM54: 254895.83 | AN54: 254895.83 | AO54: =+Z54+AB54 -> 36450104 | AP54: =IF(AR54=$AR$8,((S54-AO54)*0),S54-AO54) -> 24724896 | AU54: Ok | AV54: =VLOOKUP(F54,[78]!D365FinOps_API_Table[[FixedAssetNumber]:[Department]],80,FALSE) -> #REF! | AW54: =AV54-AJ54 -> #REF! | BL54: BLD000055
A55: =+A54+1 -> 46 | B55: MESS | C55: AD_HO | D55: 152 | E55: BLD000056 | F55: BLD000056 | G55: 41881 | H55: Building | I55: 51 | J55: Building | K55: Kota Deltamas Cluster Pasadena Blok B, Cikarang Pusat, Jawa Barat | M55: 2014 | N55: B11-B12-B15-B16-B17 | O55: B50-B51-B52-B53-B55 | Q55: 1 | S55: 165469683 | T55: =+S55/U55 -> 689457.01 | U55: 240 | V55: 137 | W55: =+AB55/T55 -> 6 | X55: =+V55+W55 -> 143 | Y55: =+U55-X55 -> 97 | Z55: 94455611 | AA55: 71014072 | AB55: =SUM(AC55:AH55) -> 4136742.1 | AC55: 689457.01 | AD55: 689457.01 | AE55: 689457.01 | AF55: 689457.01 | AG55: 689457.01 | AH55: 689457.01 | AI55: 689457.01 | AJ55: 689457.01 | AK55: 689457.01 | AL55: 689457.01 | AM55: 689457.01 | AN55: 689457.01 | AO55: =+Z55+AB55 -> 98592353 | AP55: =IF(AR55=$AR$8,((S55-AO55)*0),S55-AO55) -> 66877330 | AU55: Ok | AV55: =VLOOKUP(F55,[78]!D365FinOps_API_Table[[FixedAssetNumber]:[Department]],80,FALSE) -> #REF! | AW55: =AV55-AJ55 -> #REF! | BL55: BLD000056
A56: =+A55+1 -> 47 | B56: CLGC | C56: D30 | D56: 152 | E56: M10-E-006 | F56: BLD000057 | G56: 41880 | H56: Building | I56: 3028 | J56: Drainage at Sankyu Yard Bojonegara | K56: Bojonegara Land | M56: 2014 | Q56: 1 | S56: 317500000 | T56: =+S56/U56 -> 5291666.7 | U56: 60 | V56: 60 | W56: =+AB56/T56 -> 0 | X56: =+V56+W56 -> 60 | Y56: =+U56-X56 -> 0 | Z56: 3.175e+08 | AA56: 1.7881393e-07 | AB56: =SUM(AC56:AH56) -> 0 | AO56: =+Z56+AB56 -> 3.175e+08 | AP56: =IF(AR56=$AR$8,((S56-AO56)*0),S56-AO56) -> 1.7881393e-07 | AU56: Ok | AV56: =VLOOKUP(F56,[78]!D365FinOps_API_Table[[FixedAssetNumber]:[Department]],80,FALSE) -> #REF! | AW56: =AV56-AJ56 -> #REF! | BL56: M10-E-006
A57: =+A56+1 -> 48 | B57: CLGC | C57: D30 | D57: 152 | E57: M10-E-006 | F57: BLD000058 | G57: 41880 | H57: Building | I57: 3028 | J57: Drainage at Sankyu Yard Bojonegara | K57: Bojonegara Land | M57: 2014 | S57: 317500000 | T57: =+S57/U57 -> 5291666.7 | U57: 60 | V57: 60 | W57: =+AB57/T57 -> 0 | X57: =+V57+W57 -> 60 | Y57: =+U57-X57 -> 0 | Z57: 3.175e+08 | AA57: 1.7881393e-07 | AB57: =SUM(AC57:AH57) -> 0 | AO57: =+Z57+AB57 -> 3.175e+08 | AP57: =IF(AR57=$AR$8,((S57-AO57)*0),S57-AO57) -> 1.7881393e-07 | AU57: Ok | AV57: =VLOOKUP(F57,[78]!D365FinOps_API_Table[[FixedAssetNumber]:[Department]],80,FALSE) -> #REF! | AW57: =AV57-AJ57 -> #REF! | BL57: M10-E-006
A58: =+A57+1 -> 49 | B58: MESS | C58: AD_HO | D58: 152 | E58: BLD000059 | F58: BLD000059 | G58: 41900 | H58: Building | I58: 8 | J58: Legalization Document (AJB) | K58: Kota Deltamas Cluster Pasadena Blok B, Cikarang Pusat, Jawa Barat | M58: 2014 | Q58: 1 | S58: 83958170 | T58: =+S58/U58 -> 349825.71 | U58: 240 | V58: 135 | W58: =+AB58/T58 -> 6 | X58: =+V58+W58 -> 141 | Y58: =+U58-X58 -> 99 | Z58: 47226471 | AA58: 36731699 | AB58: =SUM(AC58:AH58) -> 2098954.2 | AC58: 349825.71 | AD58: 349825.71 | AE58: 349825.71 | AF58: 349825.71 | AG58: 349825.71 | AH58: 349825.71 | AI58: 349825.71 | AJ58: 349825.71 | AK58: 349825.71 | AL58: 349825.71 | AM58: 349825.71 | AN58: 349825.71 | AO58: =+Z58+AB58 -> 49325425 | AP58: =IF(AR58=$AR$8,((S58-AO58)*0),S58-AO58) -> 34632745 | AU58: Ok | AV58: =VLOOKUP(F58,[78]!D365FinOps_API_Table[[FixedAssetNumber]:[Department]],80,FALSE) -> #REF! | AW58: =AV58-AJ58 -> #REF! | BL58: BLD000059
A59: =+A58+1 -> 50 | B59: MESS | C59: AD_HO | D59: 152 | E59: BLD000060 | F59: BLD000060 | G59: 41900 | H59: Building | I59: 8 | J59: Legalization Document (BPHTB) | K59: Kota Deltamas Cluster Pasadena Blok B, Cikarang Pusat, Jawa Barat | M59: 2014 | Q59: 1 | S59: 392390850 | T59: =+S59/U59 -> 1634961.9 | U59: 240 | V59: 135 | W59: =+AB59/T59 -> 6 | X59: =+V59+W59 -> 141 | Y59: =+U59-X59 -> 99 | Z59: 2.2071985e+08 | AA59: 1.71671e+08 | AB59: =SUM(AC59:AH59) -> 9809771.2 | AC59: 1634961.9 | AD59: 1634961.9 | AE59: 1634961.9 | AF59: 1634961.9 | AG59: 1634961.9 | AH59: 1634961.9 | AI59: 1634961.9 | AJ59: 1634961.9 | AK59: 1634961.9 | AL59: 1634961.9 | AM59: 1634961.9 | AN59: 1634961.9 | AO59: =+Z59+AB59 -> 2.3052962e+08 | AP59: =IF(AR59=$AR$8,((S59-AO59)*0),S59-AO59) -> 1.6186123e+08 | AU59: Ok | AV59: =VLOOKUP(F59,[78]!D365FinOps_API_Table[[FixedAssetNumber]:[Department]],80,FALSE) -> #REF! | AW59: =AV59-AJ59 -> #REF! | BL59: BLD000060
A60: =+A59+1 -> 51 | B60: CLGC | C60: D30 | D60: 152 | E60: M10-E-007 | F60: BLD000061 | G60: 42124 | H60: Building | I60: 3030 | J60: Modification Fencing of Sankyu Land Bojonegara | K60: Bintang Cahaya Utama | M60: 2015 | Q60: 1 | S60: 735000000 | T60: =+S60/U60 -> 12250000 | U60: 60 | V60: 60 | W60: =+AB60/T60 -> 0 | X60: =+V60+W60 -> 60 | Y60: =+U60-X60 -> 0 | Z60: 735000000 | AA60: 0 | AB60: =SUM(AC60:AH60) -> 0 | AO60: =+Z60+AB60 -> 735000000 | AP60: =IF(AR60=$AR$8,((S60-AO60)*0),S60-AO60) -> 0 | AU60: Ok | AV60: =VLOOKUP(F60,[78]!D365FinOps_API_Table[[FixedAssetNumber]:[Department]],80,FALSE) -> #REF! | AW60: =AV60-AJ60 -> #REF! | BL60: M10-E-007
A61: =+A60+1 -> 52 | B61: CLGC | C61: D30 | D61: 152 | E61: M10-E-007 | F61: BLD000062 | G61: 42124 | H61: Building | I61: 3030 | J61: Modification Fencing of Sankyu Land Bojonegara | K61: Bintang Cahaya Utama | M61: 2015 | S61: 735000000 | T61: =+S61/U61 -> 12250000 | U61: 60 | V61: 60 | W61: =+AB61/T61 -> 0 | X61: =+V61+W61 -> 60 | Y61: =+U61-X61 -> 0 | Z61: 735000000 | AA61: 0 | AB61: =SUM(AC61:AH61) -> 0 | AO61: =+Z61+AB61 -> 735000000 | AP61: =IF(AR61=$AR$8,((S61-AO61)*0),S61-AO61) -> 0 | AU61: Ok | AV61: =VLOOKUP(F61,[78]!D365FinOps_API_Table[[FixedAssetNumber]:[Department]],80,FALSE) -> #REF! | AW61: =AV61-AJ61 -> #REF! | BL61: M10-E-007
A62: =+A61+1 -> 53 | B62: CLC | C62: CLCWH | D62: 152 | E62: CLC131-004 | F62: BLD000063 | G62: 42398 | H62: Building | I62: 84 | J62: IMB Tax Warehouse Phase II | K62: Kawasan Industri Terpadu Indonesia China (KITIC) Kav. 20, Cikarang, West Java | L62: Cikarang Logistic Center | M62: 2016 | Q62: 1 | S62: 2061766435 | T62: =+S62/U62 -> 8590693.5 | U62: 240 | V62: 120 | W62: =+AB62/T62 -> 6 | X62: =+V62+W62 -> 126 | Y62: =+U62-X62 -> 114 | Z62: 1.0308832e+09 | AA62: 1.0308832e+09 | AB62: =SUM(AC62:AH62) -> 51544161 | AC62: 8590693.5 | AD62: 8590693.5 | AE62: 8590693.5 | AF62: 8590693.5 | AG62: 8590693.5 | AH62: 8590693.5 | AI62: 8590693.5 | AJ62: 8590693.5 | AK62: 8590693.5 | AL62: 8590693.5 | AM62: 8590693.5 | AN62: 8590693.5 | AO62: =+Z62+AB62 -> 1.0824274e+09 | AP62: =IF(AR62=$AR$8,((S62-AO62)*0),S62-AO62) -> 9.7933906e+08 | AU62: Ok | AV62: =VLOOKUP(F62,[78]!D365FinOps_API_Table[[FixedAssetNumber]:[Department]],80,FALSE) -> #REF! | AW62: =AV62-AJ62 -> #REF! | BL62: CLC131-004
A63: =+A62+1 -> 54 | B63: CLC | C63: CLCWH | D63: 152 | E63: CLC131-002 | F63: BLD000064 | G63: 42387 | H63: Building | I63: 05 | J63: Lobby & Office Phase 2 | K63: Kawasan Industri Terpadu Indonesia China (KITIC) Kav. 20, Cikarang, West Java | L63: Cikarang Logistic Center | M63: 2016 | Q63: 1 | S63: 5000000000 | T63: =+S63/U63 -> 20833333 | U63: 240 | V63: 120 | W63: =+AB63/T63 -> 6 | X63: =+V63+W63 -> 126 | Y63: =+U63-X63 -> 114 | Z63: 2.5e+09 | AA63: 2.5e+09 | AB63: =SUM(AC63:AH63) -> 1.25e+08 | AC63: 20833333 | AD63: 20833333 | AE63: 20833333 | AF63: 20833333 | AG63: 20833333 | AH63: 20833333 | AI63: 20833333 | AJ63: 20833333 | AK63: 20833333 | AL63: 20833333 | AM63: 20833333 | AN63: 20833333 | AO63: =+Z63+AB63 -> 2.625e+09 | AP63: =IF(AR63=$AR$8,((S63-AO63)*0),S63-AO63) -> 2.375e+09 | AU63: Ok | AV63: =VLOOKUP(F63,[78]!D365FinOps_API_Table[[FixedAssetNumber]:[Department]],80,FALSE) -> #REF! | AW63: =AV63-AJ63 -> #REF! | BL63: CLC131-002
A64: =+A63+1 -> 55 | B64: CLC | C64: CLCWH | D64: 152 | E64: CLC131-002 | F64: BLD000065 | G64: 42387 | H64: Building | I64: 05 | J64: Warehouse Phase 2 Floor 2 | K64: Kawasan Industri Terpadu Indonesia China (KITIC) Kav. 20, Cikarang, West Java | L64: Cikarang Logistic Center | M64: 2016 | Q64: 1 | S64: 44455000000 | T64: =+S64/U64 -> 1.8522917e+08 | U64: 240 | V64: 120 | W64: =+AB64/T64 -> 6 | X64: =+V64+W64 -> 126 | Y64: =+U64-X64 -> 114 | Z64: 2.22275e+10 | AA64: 2.22275e+10 | AB64: =SUM(AC64:AH64) -> 1111375000 | AC64: 1.8522917e+08 | AD64: 1.8522917e+08 | AE64: 1.8522917e+08 | AF64: 1.8522917e+08 | AG64: 1.8522917e+08 | AH64: 1.8522917e+08 | AI64: 1.8522917e+08 | AJ64: 1.8522917e+08 | AK64: 1.8522917e+08 | AL64: 1.8522917e+08 | AM64: 1.8522917e+08 | AN64: 1.8522917e+08 | AO64: =+Z64+AB64 -> 2.3338875e+10 | AP64: =IF(AR64=$AR$8,((S64-AO64)*0),S64-AO64) -> 2.1116125e+10 | AU64: Ok | AV64: =VLOOKUP(F64,[78]!D365FinOps_API_Table[[FixedAssetNumber]:[Department]],80,FALSE) -> #REF! | AW64: =AV64-AJ64 -> #REF! | BL64: CLC131-002
A65: =+A64+1 -> 56 | B65: CLC | C65: CLCWH | D65: 152 | E65: CLC131-002 | F65: BLD000066 | G65: 42387 | H65: Building | I65: 05 | J65: Warehouse Phase 2 Floor 1 | K65: Kawasan Industri Terpadu Indonesia China (KITIC) Kav. 20, Cikarang, West Java | L65: Cikarang Logistic Center | M65: 2016 | Q65: 1 | S65: 49455000000 | T65: =+S65/U65 -> 206062500 | U65: 240 | V65: 120 | W65: =+AB65/T65 -> 6 | X65: =+V65+W65 -> 126 | Y65: =+U65-X65 -> 114 | Z65: 24727500000 | AA65: 24727500000 | AB65: =SUM(AC65:AH65) -> 1236375000 | AC65: 206062500 | AD65: 206062500 | AE65: 206062500 | AF65: 206062500 | AG65: 206062500 | AH65: 206062500 | AI65: 206062500 | AJ65: 206062500 | AK65: 206062500 | AL65: 206062500 | AM65: 206062500 | AN65: 206062500 | AO65: =+Z65+AB65 -> 25963875000 | AP65: =IF(AR65=$AR$8,((S65-AO65)*0),S65-AO65) -> 23491125000 | AU65: Ok | AV65: =VLOOKUP(F65,[78]!D365FinOps_API_Table[[FixedAssetNumber]:[Department]],80,FALSE) -> #REF! | AW65: =AV65-AJ65 -> #REF! | BL65: CLC131-002
A66: =+A65+1 -> 57 | B66: CLC | C66: CLCWH | D66: 152 | E66: CLC131-002 | F66: BLD000067 | G66: 42387 | H66: Building | I66: 05 | J66: Cold Room Area Phase 2 | K66: Kawasan Industri Terpadu Indonesia China (KITIC) Kav. 20, Cikarang, West Java | L66: Cikarang Logistic Center | M66: 2016 | Q66: 1 | S66: 35325000000 | T66: =+S66/U66 -> 147187500 | U66: 240 | V66: 120 | W66: =+AB66/T66 -> 6 | X66: =+V66+W66 -> 126 | Y66: =+U66-X66 -> 114 | Z66: 17662500000 | AA66: 17662500000 | AB66: =SUM(AC66:AH66) -> 883125000 | AC66: 147187500 | AD66: 147187500 | AE66: 147187500 | AF66: 147187500 | AG66: 147187500 | AH66: 147187500 | AI66: 147187500 | AJ66: 147187500 | AK66: 147187500 | AL66: 147187500 | AM66: 147187500 | AN66: 147187500 | AO66: =+Z66+AB66 -> 18545625000 | AP66: =IF(AR66=$AR$8,((S66-AO66)*0),S66-AO66) -> 16779375000 | AU66: Ok | AV66: =VLOOKUP(F66,[78]!D365FinOps_API_Table[[FixedAssetNumber]:[Department]],80,FALSE) -> #REF! | AW66: =AV66-AJ66 -> #REF! | BL66: CLC131-002
A67: =+A66+1 -> 58 | B67: CLC | C67: CLCWH | D67: 152 | E67: CLC131-002 | F67: BLD000068 | G67: 42387 | H67: Building | I67: 05 | J67: Cargo Lifter Phase 2 | K67: Kawasan Industri Terpadu Indonesia China (KITIC) Kav. 20, Cikarang, West Java | L67: Cikarang Logistic Center | M67: 2016 | Q67: 1 | R67: 271320 | S67: 3375220800 | T67: =+S67/U67 -> 14063420 | U67: 240 | V67: 120 | W67: =+AB67/T67 -> 6 | X67: =+V67+W67 -> 126 | Y67: =+U67-X67 -> 114 | Z67: 1687610400 | AA67: 1687610400 | AB67: =SUM(AC67:AH67) -> 84380520 | AC67: 14063420 | AD67: 14063420 | AE67: 14063420 | AF67: 14063420 | AG67: 14063420 | AH67: 14063420 | AI67: 14063420 | AJ67: 14063420 | AK67: 14063420 | AL67: 14063420 | AM67: 14063420 | AN67: 14063420 | AO67: =+Z67+AB67 -> 1771990920 | AP67: =IF(AR67=$AR$8,((S67-AO67)*0),S67-AO67) -> 1603229880 | AU67: Ok | AV67: =VLOOKUP(F67,[78]!D365FinOps_API_Table[[FixedAssetNumber]:[Department]],80,FALSE) -> #REF! | AW67: =AV67-AJ67 -> #REF! | BL67: CLC131-002
A68: =+A67+1 -> 59 | B68: CLC | C68: CLCWH | D68: 152 | E68: CLC131-003 | F68: BLD000069 | G68: 42387 | H68: Building | I68: 05 | J68: Cargo Lifter Phase 2 | K68: Kawasan Industri Terpadu Indonesia China (KITIC) Kav. 20, Cikarang, West Java | L68: Cikarang Logistic Center | M68: 2016 | Q68: 1 | R68: 271320 | S68: 3549950880 | T68: =+S68/U68 -> 14791462 | U68: 240 | V68: 120 | W68: =+AB68/T68 -> 6 | X68: =+V68+W68 -> 126 | Y68: =+U68-X68 -> 114 | Z68: 1774975440 | AA68: 1774975440 | AB68: =SUM(AC68:AH68) -> 88748772 | AC68: 14791462 | AD68: 14791462 | AE68: 14791462 | AF68: 14791462 | AG68: 14791462 | AH68: 14791462 | AI68: 14791462 | AJ68: 14791462 | AK68: 14791462 | AL68: 14791462 | AM68: 14791462 | AN68: 14791462 | AO68: =+Z68+AB68 -> 1863724212 | AP68: =IF(AR68=$AR$8,((S68-AO68)*0),S68-AO68) -> 1686226668 | AU68: Ok | AV68: =VLOOKUP(F68,[78]!D365FinOps_API_Table[[FixedAssetNumber]:[Department]],80,FALSE) -> #REF! | AW68: =AV68-AJ68 -> #REF! | BL68: CLC131-003
A69: =+A68+1 -> 60 | B69: CLC | C69: CLCWH | D69: 152 | E69: CLC131-003 | F69: BLD000070 | G69: 42387 | H69: Building | I69: 05 | J69: Canopy Area Phase 2 | K69: Kawasan Industri Terpadu Indonesia China (KITIC) Kav. 20, Cikarang, West Java | L69: Cikarang Logistic Center | M69: 2016 | Q69: 1 | R69: 193800 | S69: 2612617800 | T69: =+S69/U69 -> 10885908 | U69: 240 | V69: 120 | W69: =+AB69/T69 -> 6 | X69: =+V69+W69 -> 126 | Y69: =+U69-X69 -> 114 | Z69: 1306308900 | AA69: 1306308900 | AB69: =SUM(AC69:AH69) -> 65315445 | AC69: 10885908 | AD69: 10885908 | AE69: 10885908 | AF69: 10885908 | AG69: 10885908 | AH69: 10885908 | AI69: 10885908 | AJ69: 10885908 | AK69: 10885908 | AL69: 10885908 | AM69: 10885908 | AN69: 10885908 | AO69: =+Z69+AB69 -> 1371624345 | AP69: =IF(AR69=$AR$8,((S69-AO69)*0),S69-AO69) -> 1240993455 | AU69: Ok | AV69: =VLOOKUP(F69,[78]!D365FinOps_API_Table[[FixedAssetNumber]:[Department]],80,FALSE) -> #REF! | AW69: =AV69-AJ69 -> #REF! | BL69: CLC131-003
A70: =+A69+1 -> 61 | B70: CLC | C70: CLCWH | D70: 152 | E70: CLC131-003 | F70: BLD000071 | G70: 42387 | H70: Building | I70: 05 | J70: Omni Lifter Phase 2 | K70: Kawasan Industri Terpadu Indonesia China (KITIC) Kav. 20, Cikarang, West Java | L70: Cikarang Logistic Center | M70: 2016 | Q70: 1 | S70: 7065000000 | T70: =+S70/U70 -> 29437500 | U70: 240 | V70: 120 | W70: =+AB70/T70 -> 6 | X70: =+V70+W70 -> 126 | Y70: =+U70-X70 -> 114 | Z70: 3532500000 | AA70: 3532500000 | AB70: =SUM(AC70:AH70) -> 176625000 | AC70: 29437500 | AD70: 29437500 | AE70: 29437500 | AF70: 29437500 | AG70: 29437500 | AH70: 29437500 | AI70: 29437500 | AJ70: 29437500 | AK70: 29437500 | AL70: 29437500 | AM70: 29437500 | AN70: 29437500 | AO70: =+Z70+AB70 -> 3709125000 | AP70: =IF(AR70=$AR$8,((S70-AO70)*0),S70-AO70) -> 3355875000 | AU70: Ok | AV70: =VLOOKUP(F70,[78]!D365FinOps_API_Table[[FixedAssetNumber]:[Department]],80,FALSE) -> #REF! | AW70: =AV70-AJ70 -> #REF! | BL70: CLC131-003
A71: =+A70+1 -> 62 | B71: CLC | C71: CLCWH | D71: 152 | E71: CLC131-003 | F71: BLD000072 | G71: 42387 | H71: Building | I71: 05 | J71: Omni Lifter Phase 2 | K71: Kawasan Industri Terpadu Indonesia China (KITIC) Kav. 20, Cikarang, West Java | L71: Cikarang Logistic Center | M71: 2016 | Q71: 1 | R71: 38760 | S71: 534694200 | T71: =+S71/U71 -> 2227892.5 | U71: 240 | V71: 120 | W71: =+AB71/T71 -> 6 | X71: =+V71+W71 -> 126 | Y71: =+U71-X71 -> 114 | Z71: 267347100 | AA71: 267347100 | AB71: =SUM(AC71:AH71) -> 13367355 | AC71: 2227892.5 | AD71: 2227892.5 | AE71: 2227892.5 | AF71: 2227892.5 | AG71: 2227892.5 | AH71: 2227892.5 | AI71: 2227892.5 | AJ71: 2227892.5 | AK71: 2227892.5 | AL71: 2227892.5 | AM71: 2227892.5 | AN71: 2227892.5 | AO71: =+Z71+AB71 -> 280714455 | AP71: =IF(AR71=$AR$8,((S71-AO71)*0),S71-AO71) -> 253979745 | AU71: Ok | AV71: =VLOOKUP(F71,[78]!D365FinOps_API_Table[[FixedAssetNumber]:[Department]],80,FALSE) -> #REF! | AW71: =AV71-AJ71 -> #REF! | BL71: CLC131-003
A72: =+A71+1 -> 63 | B72: CLC | C72: CLCWH | D72: 152 | E72: CLC131-003 | F72: BLD000073 | G72: 42387 | H72: Building | I72: 05 | J72: Mezzanine Area Phase 2 | K72: Kawasan Industri Terpadu Indonesia China (KITIC) Kav. 20, Cikarang, West Java | L72: Cikarang Logistic Center | M72: 2016 | Q72: 1 | S72: 1338483845 | T72: =+S72/U72 -> 5577016 | U72: 240 | V72: 120 | W72: =+AB72/T72 -> 6 | X72: =+V72+W72 -> 126 | Y72: =+U72-X72 -> 114 | Z72: 6.6924192e+08 | AA72: 6.6924192e+08 | AB72: =SUM(AC72:AH72) -> 33462096 | AC72: 5577016 | AD72: 5577016 | AE72: 5577016 | AF72: 5577016 | AG72: 5577016 | AH72: 5577016 | AI72: 5577016 | AJ72: 5577016 | AK72: 5577016 | AL72: 5577016 | AM72: 5577016 | AN72: 5577016 | AO72: =+Z72+AB72 -> 7.0270402e+08 | AP72: =IF(AR72=$AR$8,((S72-AO72)*0),S72-AO72) -> 6.3577983e+08 | AU72: Ok | AV72: =VLOOKUP(F72,[78]!D365FinOps_API_Table[[FixedAssetNumber]:[Department]],80,FALSE) -> #REF! | AW72: =AV72-AJ72 -> #REF! | BL72: CLC131-003
A73: =+A72+1 -> 64 | B73: SLI | C73: AD_HO | D73: 152 | E73: JKL-131-002 | F73: BLD000074 | G73: 42580 | H73: Building | I73: 102 | J73: Fencing at Port Office | K73: Jl. Enggano no. 40B Jakarta Utara | M73: 2016 | Q73: 1 | S73: 21300000 | T73: =+S73/U73 -> 355000 | U73: 60 | V73: 60 | W73: =+AB73/T73 -> 0 | X73: =+V73+W73 -> 60 | Y73: =+U73-X73 -> 0 | Z73: 21300000 | AA73: 0 | AB73: =SUM(AC73:AH73) -> 0 | AO73: =+Z73+AB73 -> 21300000 | AP73: =IF(AR73=$AR$8,((S73-AO73)*0),S73-AO73) -> 0 | AU73: Ok | AV73: =VLOOKUP(F73,[78]!D365FinOps_API_Table[[FixedAssetNumber]:[Department]],80,FALSE) -> #REF! | AW73: =AV73-AJ73 -> #REF! | BL73: JKL-131-002
A74: =+A73+1 -> 65 | B74: CLGC | C74: D30 | D74: 152 | E74: M10-E-008 | F74: BLD000075 | G74: 42943 | H74: Building | I74: 3164 | J74: Workshop at Bojonegara | K74: Bojonegara Land | M74: 2017 | Q74: 1 | S74: 1430000000 | T74: =+S74/U74 -> 23833333 | U74: 60 | V74: 60 | W74: =+AB74/T74 -> 0 | X74: =+V74+W74 -> 60 | Y74: =+U74-X74 -> 0 | Z74: 1.43e+09 | AA74: -2.3841858e-07 | AB74: =SUM(AC74:AH74) -> 0 | AO74: =+Z74+AB74 -> 1.43e+09 | AP74: =IF(AR74=$AR$8,((S74-AO74)*0),S74-AO74) -> -2.3841858e-07 | AU74: Ok | AV74: =VLOOKUP(F74,[78]!D365FinOps_API_Table[[FixedAssetNumber]:[Department]],80,FALSE) -> #REF! | AW74: =AV74-AJ74 -> #REF! | BL74: M10-E-008
A75: =+A74+1 -> 66 | B75: CLC | C75: CLCWH | D75: 152 | E75: CLC131-005 | F75: BLD000076 | G75: 43830 | H75: Building | I75: 007-12 | J75: Roof for Motorcycle Parking Area (80%) | K75: SII JKC | L75: KITIC Office | M75: 2019 | Q75: 1 | S75: 177294305 | T75: =+S75/U75 -> 738726.27 | U75: 240 | V75: 73 | W75: =+AB75/T75 -> 6 | X75: =+V75+W75 -> 79 | Y75: =+U75-X75 -> 161 | Z75: 53927018 | AA75: 1.2336729e+08 | AB75: =SUM(AC75:AH75) -> 4432357.6 | AC75: 738726.27 | AD75: 738726.27 | AE75: 738726.27 | AF75: 738726.27 | AG75: 738726.27 | AH75: 738726.27 | AI75: 738726.27 | AJ75: 738726.27 | AK75: 738726.27 | AL75: 738726.27 | AM75: 738726.27 | AN75: 738726.27 | AO75: =+Z75+AB75 -> 58359375 | AP75: =IF(AR75=$AR$8,((S75-AO75)*0),S75-AO75) -> 1.1893493e+08 | AU75: Ok | AV75: =VLOOKUP(F75,[78]!D365FinOps_API_Table[[FixedAssetNumber]:[Department]],80,FALSE) -> #REF! | AW75: =AV75-AJ75 -> #REF! | BL75: CLC131-005
A76: =+A75+1 -> 67 | B76: CKR | C76: AD_HO | D76: 152 | E76: BLD000077 | F76: BLD000077 | G76: 43830 | H76: Building | I76: 007-12 | J76: Roof for Motorcycle Parking Area (20%) | K76: SII JKC | L76: KITIC Office | M76: 2019 | Q76: 1 | S76: 44323576 | T76: =+S76/U76 -> 184681.57 | U76: 240 | V76: 73 | W76: =+AB76/T76 -> 6 | X76: =+V76+W76 -> 79 | Y76: =+U76-X76 -> 161 | Z76: 13481754 | AA76: 30841822 | AB76: =SUM(AC76:AH76) -> 1108089.4 | AC76: 184681.57 | AD76: 184681.57 | AE76: 184681.57 | AF76: 184681.57 | AG76: 184681.57 | AH76: 184681.57 | AI76: 184681.57 | AJ76: 184681.57 | AK76: 184681.57 | AL76: 184681.57 | AM76: 184681.57 | AN76: 184681.57 | AO76: =+Z76+AB76 -> 14589844 | AP76: =IF(AR76=$AR$8,((S76-AO76)*0),S76-AO76) -> 29733732 | AU76: Ok | AV76: =VLOOKUP(F76,[78]!D365FinOps_API_Table[[FixedAssetNumber]:[Department]],80,FALSE) -> #REF! | AW76: =AV76-AJ76 -> #REF! | BL76: BLD000077
A77: =+A76+1 -> 68 | B77: CLGC | C77: D30 | D77: 152 | E77: M10-E-009 | F77: BLD000078 | G77: 44195 | H77: Building | I77: JKT_GL013691 | J77: Bojonegara Renovation Site Office | K77: Watu Lawang | M77: 2020 | Q77: 1 | S77: 105000000 | T77: =+S77/U77 -> 875000 | U77: 120 | V77: 61 | W77: =+AB77/T77 -> 6 | X77: =+V77+W77 -> 67 | Y77: =+U77-X77 -> 53 | Z77: 53375000 | AA77: 51625000 | AB77: =SUM(AC77:AH77) -> 5250000 | AC77: 875000 | AD77: 875000 | AE77: 875000 | AF77: 875000 | AG77: 875000 | AH77: 875000 | AI77: 875000 | AJ77: 875000 | AK77: 875000 | AL77: 875000 | AM77: 875000 | AN77: 875000 | AO77: =+Z77+AB77 -> 58625000 | AP77: =IF(AR77=$AR$8,((S77-AO77)*0),S77-AO77) -> 46375000 | AU77: Ok | AV77: =VLOOKUP(F77,[78]!D365FinOps_API_Table[[FixedAssetNumber]:[Department]],80,FALSE) -> #REF! | AW77: =AV77-AJ77 -> #REF! | BL77: M10-E-009
A78: =+A77+1 -> 69 | B78: CLGC | C78: D30 | D78: 152 | E78: M10-E-010 | F78: BLD000079 | G78: 44195 | H78: Building | I78: JKT_GL013691 | J78: Bojonegara Tempat B3 | K78: Sumur Gunung | M78: 2020 | Q78: 1 | S78: 99000000 | T78: =+S78/U78 -> 825000 | U78: 120 | V78: 61 | W78: =+AB78/T78 -> 6 | X78: =+V78+W78 -> 67 | Y78: =+U78-X78 -> 53 | Z78: 50325000 | AA78: 48675000 | AB78: =SUM(AC78:AH78) -> 4950000 | AC78: 825000 | AD78: 825000 | AE78: 825000 | AF78: 825000 | AG78: 825000 | AH78: 825000 | AI78: 825000 | AJ78: 825000 | AK78: 825000 | AL78: 825000 | AM78: 825000 | AN78: 825000 | AO78: =+Z78+AB78 -> 55275000 | AP78: =IF(AR78=$AR$8,((S78-AO78)*0),S78-AO78) -> 43725000 | AU78: Ok | AV78: =VLOOKUP(F78,[78]!D365FinOps_API_Table[[FixedAssetNumber]:[Department]],80,FALSE) -> #REF! | AW78: =AV78-AJ78 -> #REF! | BL78: M10-E-010
A79: =+A78+1 -> 70 | B79: CLGC | C79: D30 | D79: 152 | E79: M10-E-011 | F79: BLD000080 | G79: 44469 | H79: Building | I79: JKT_GL015971 | J79: Sandblast Painting & Shop | K79: CLG Cons | M79: 2021 | Q79: 1 | S79: 1152329235 | T79: =+S79/U79 -> 9602743.6 | U79: 120 | V79: 52 | W79: =+AB79/T79 -> 6 | X79: =+V79+W79 -> 58 | Y79: =+U79-X79 -> 62 | Z79: 4.9934267e+08 | AA79: 6.5298657e+08 | AB79: =SUM(AC79:AH79) -> 57616462 | AC79: 9602743.6 | AD79: 9602743.6 | AE79: 9602743.6 | AF79: 9602743.6 | AG79: 9602743.6 | AH79: 9602743.6 | AI79: 9602743.6 | AJ79: 9602743.6 | AK79: 9602743.6 | AL79: 9602743.6 | AM79: 9602743.6 | AN79: 9602743.6 | AO79: =+Z79+AB79 -> 5.5695913e+08 | AP79: =IF(AR79=$AR$8,((S79-AO79)*0),S79-AO79) -> 5.953701e+08 | AU79: Ok | AV79: =VLOOKUP(F79,[78]!D365FinOps_API_Table[[FixedAssetNumber]:[Department]],80,FALSE) -> #REF! | AW79: =AV79-AJ79 -> #REF! | BL79: M10-E-011
AV80: =VLOOKUP(F80,[78]!D365FinOps_API_Table[[FixedAssetNumber]:[Department]],80,FALSE) -> #REF! | AW80: =AV80-AJ80 -> #REF!
E81: =H81 -> Building Total | H81: Building Total | S81: =SUM(S10:S80) -> 2.8312631e+11 | T81: =SUM(T10:T80) -> 1.2879948e+09 | Z81: 1.6173803e+11 | AA81: 1.2138828e+11 | AB81: =SUM(AB10:AB80) -> 6.8086453e+09 | AC81: =SUM(AC10:AC80) -> 1.1347742e+09 | AD81: =SUM(AD10:AD80) -> 1.1347742e+09 | AE81: =SUM(AE10:AE80) -> 1.1347742e+09 | AF81: =SUM(AF10:AF80) -> 1.1347742e+09 | AG81: =SUM(AG10:AG80) -> 1.1347742e+09 | AH81: =SUM(AH10:AH80) -> 1.1347742e+09 | AI81: =SUM(AI10:AI80) -> 1.1347742e+09 | ... AP81: =SUM(AP10:AP80) -> 1.1457964e+11 | AU81: ToT | AV81: =VLOOKUP(F81,[78]!D365FinOps_API_Table[[FixedAssetNumber]:[Department]],80,FALSE) -> #REF! | AW81: =AV81-AN81 -> #REF! | BL81: =BO81 -> 0
A82: =A79+1 -> 71 | B82: JKTC | C82: D10 | D82: 153 | E82: - | F82: STR000003 | G82: 36217 | H82: Structures | I82: 4016 | J82: Electric installation | K82: Cikarang Office | Q82: 1 | S82: 34540000 | T82: =+S82/U82 -> 575666.67 | U82: 60 | V82: 60 | W82: =+AB82/T82 -> 0 | X82: =+V82+W82 -> 60 | Y82: =+U82-X82 -> 0 | Z82: 34540000 | AA82: 0 | AB82: =SUM(AC82:AH82) -> 0 | AO82: =+Z82+AB82 -> 34540000 | AP82: =IF(AR82=$AR$8,((S82-AO82)*0),S82-AO82) -> 0 | AU82: Ok | AV82: =VLOOKUP(F82,[78]!D365FinOps_API_Table[[FixedAssetNumber]:[Department]],80,FALSE) -> #REF! | AW82: =AV82-AN82 -> #REF! | BL82: -
A83: =+A82+1 -> 72 | B83: JKTC | C83: D10 | D83: 153 | E83: - | F83: STR000004 | G83: 36250 | H83: Structures | I83: 4042 | J83: Electric installation | K83: Cikarang Office | Q83: 1 | S83: 11541384 | T83: =+S83/U83 -> 192356.4 | U83: 60 | V83: 60 | W83: =+AB83/T83 -> 0 | X83: =+V83+W83 -> 60 | Y83: =+U83-X83 -> 0 | Z83: 11541384 | AA83: 0 | AB83: =SUM(AC83:AH83) -> 0 | AO83: =+Z83+AB83 -> 11541384 | AP83: =IF(AR83=$AR$8,((S83-AO83)*0),S83-AO83) -> 0 | AU83: Ok | AV83: =VLOOKUP(F83,[78]!D365FinOps_API_Table[[FixedAssetNumber]:[Department]],80,FALSE) -> #REF! | AW83: =AV83-AN83 -> #REF! | BL83: -
A84: =+A83+1 -> 73 | B84: CLC | C84: CLCWH | D84: 153 | E84: CLC133-001 | F84: STR000005 | G84: 41639 | H84: Structures | I84: 2005 | J84: Security system & installation | K84: SECOM Indonesia | L84: Cikarang Warehouse & Office | M84: 2013 | Q84: 1 | R84: 4082 | S84: 48890114 | T84: =+S84/U84 -> 814835.23 | U84: 60 | V84: 60 | W84: =+AB84/T84 -> 0 | X84: =+V84+W84 -> 60 | Y84: =+U84-X84 -> 0 | Z84: 48890114 | AA84: 1.4901161e-08 | AB84: =SUM(AC84:AH84) -> 0 | AO84: =+Z84+AB84 -> 48890114 | AP84: =IF(AR84=$AR$8,((S84-AO84)*0),S84-AO84) -> 1.4901161e-08 | AU84: Ok | AV84: =VLOOKUP(F84,[78]!D365FinOps_API_Table[[FixedAssetNumber]:[Department]],80,FALSE) -> #REF! | AW84: =AV84-AN84 -> #REF! | BL84: CLC133-001
A85: =+A84+1 -> 74 | B85: CLC | C85: CLCWH | D85: 153 | E85: CLC133-002 | F85: STR000006 | G85: 41639 | H85: Structures | I85: 2007 | J85: CCTV system WH 1 | K85: SECOM Indonesia | L85: Cikarang Warehouse & Office | M85: 2013 | Q85: 1 | R85: 40583.96 | S85: 4.8607409e+08 | T85: =+S85/U85 -> 8101234.8 | U85: 60 | V85: 60 | W85: =+AB85/T85 -> 0 | X85: =+V85+W85 -> 60 | Y85: =+U85-X85 -> 0 | Z85: 4.8607409e+08 | AA85: -1.1920929e-07 | AB85: =SUM(AC85:AH85) -> 0 | AO85: =+Z85+AB85 -> 4.8607409e+08 | AP85: =IF(AR85=$AR$8,((S85-AO85)*0),S85-AO85) -> -1.1920929e-07 | AU85: Ok | AV85: =VLOOKUP(F85,[78]!D365FinOps_API_Table[[FixedAssetNumber]:[Department]],80,FALSE) -> #REF! | AW85: =AV85-AN85 -> #REF! | BL85: CLC133-002
A86: =+A85+1 -> 75 | B86: CLC | C86: CLCWH | D86: 153 | E86: CLC133-003 | F86: STR000007 | G86: 41639 | H86: Structures | I86: 2008 | J86: Access control | K86: SECOM Indonesia | L86: Cikarang Warehouse & Office | M86: 2013 | Q86: 1 | R86: 4246 | S86: 50854342 | T86: =+S86/U86 -> 847572.37 | U86: 60 | V86: 60 | W86: =+AB86/T86 -> 0 | X86: =+V86+W86 -> 60 | Y86: =+U86-X86 -> 0 | Z86: 50854342 | AA86: -2.2351742e-08 | AB86: =SUM(AC86:AH86) -> 0 | AO86: =+Z86+AB86 -> 50854342 | AP86: =IF(AR86=$AR$8,((S86-AO86)*0),S86-AO86) -> -2.2351742e-08 | AU86: Ok | AV86: =VLOOKUP(F86,[78]!D365FinOps_API_Table[[FixedAssetNumber]:[Department]],80,FALSE) -> #REF! | AW86: =AV86-AN86 -> #REF! | BL86: CLC133-003
A87: =+A86+1 -> 76 | B87: CLC | C87: CLCWH | D87: 153 | E87: CLC133-004 | F87: STR000008 | G87: 41639 | H87: Structures | I87: 2011 | J87: Security system & installation | K87: SECOM Indonesia | L87: Cikarang Warehouse & Office | M87: 2013 | Q87: 1 | R87: 519 | S87: 6216063 | T87: =+S87/U87 -> 103601.05 | U87: 60 | V87: 60 | W87: =+AB87/T87 -> 0 | X87: =+V87+W87 -> 60 | Y87: =+U87-X87 -> 0 | Z87: 6216063 | AA87: -1.8626451e-09 | AB87: =SUM(AC87:AH87) -> 0 | AO87: =+Z87+AB87 -> 6216063 | AP87: =IF(AR87=$AR$8,((S87-AO87)*0),S87-AO87) -> -1.8626451e-09 | AU87: Ok | AV87: =VLOOKUP(F87,[78]!D365FinOps_API_Table[[FixedAssetNumber]:[Department]],80,FALSE) -> #REF! | AW87: =AV87-AN87 -> #REF! | BL87: CLC133-004
A88: =+A87+1 -> 77 | B88: CKR | C88: AD_HO | D88: 153 | E88: HO-133-001 | F88: STR000009 | G88: 41726 | H88: Structures | I88: 87 | J88: Sever | K88: KDDI Indonesia | M88: 2014 | Q88: 1 | R88: 9987 | S88: 116188758 | T88: =+S88/U88 -> 1936479.3 | U88: 60 | V88: 60 | W88: =+AB88/T88 -> 0 | X88: =+V88+W88 -> 60 | Y88: =+U88-X88 -> 0 | Z88: 1.1618876e+08 | AA88: -4.4703484e-08 | AB88: =SUM(AC88:AH88) -> 0 | AO88: =+Z88+AB88 -> 1.1618876e+08 | AP88: =IF(AR88=$AR$8,((S88-AO88)*0),S88-AO88) -> -4.4703484e-08 | AU88: Ok | AV88: =VLOOKUP(F88,[78]!D365FinOps_API_Table[[FixedAssetNumber]:[Department]],80,FALSE) -> #REF! | AW88: =AV88-AN88 -> #REF! | BL88: HO-133-001
A89: =+A88+1 -> 78 | B89: CKR | C89: AD_HO | D89: 153 | E89: HO-133-002 | F89: STR000010 | G89: 41726 | H89: Structures | I89: 87 | J89: LAN Wireless | K89: KDDI Indonesia | M89: 2014 | Q89: 1 | R89: 24303 | S89: 282741102 | T89: =+S89/U89 -> 4712351.7 | U89: 60 | V89: 60 | W89: =+AB89/T89 -> 0 | X89: =+V89+W89 -> 60 | Y89: =+U89-X89 -> 0 | Z89: 2.827411e+08 | AA89: -5.9604645e-08 | AB89: =SUM(AC89:AH89) -> 0 | AO89: =+Z89+AB89 -> 2.827411e+08 | AP89: =IF(AR89=$AR$8,((S89-AO89)*0),S89-AO89) -> -5.9604645e-08 | AU89: Ok | AV89: =VLOOKUP(F89,[78]!D365FinOps_API_Table[[FixedAssetNumber]:[Department]],80,FALSE) -> #REF! | AW89: =AV89-AN89 -> #REF! | BL89: HO-133-002
A90: =+A89+1 -> 79 | B90: CKR | C90: AD_HO | D90: 153 | E90: HO-133-003 | F90: STR000011 | G90: 41726 | H90: Structures | I90: 87 | J90: Telephone Terminal | K90: KDDI Indonesia | M90: 2014 | Q90: 1 | R90: 1384 | S90: 16101456 | T90: =+S90/U90 -> 268357.6 | U90: 60 | V90: 60 | W90: =+AB90/T90 -> 0 | X90: =+V90+W90 -> 60 | Y90: =+U90-X90 -> 0 | Z90: 16101456 | AA90: -5.5879354e-09 | AB90: =SUM(AC90:AH90) -> 0 | AO90: =+Z90+AB90 -> 16101456 | AP90: =IF(AR90=$AR$8,((S90-AO90)*0),S90-AO90) -> -5.5879354e-09 | AU90: Ok | AV90: =VLOOKUP(F90,[78]!D365FinOps_API_Table[[FixedAssetNumber]:[Department]],80,FALSE) -> #REF! | AW90: =AV90-AN90 -> #REF! | BL90: HO-133-003
A91: =+A90+1 -> 80 | B91: CLC | C91: CLCWH | D91: 153 | E91: CLC133-026 | F91: STR000013 | G91: 41759 | H91: Structures | I91: 64 | J91: Wifi Terminal DG | K91: Dangerous Room (KDDI Indonesia) | M91: 2014 | Q91: 1 | S91: 156382893 | T91: =+S91/U91 -> 2606381.5 | U91: 60 | V91: 60 | W91: =+AB91/T91 -> 0 | X91: =+V91+W91 -> 60 | Y91: =+U91-X91 -> 0 | Z91: 156382893 | AA91: 0 | AB91: =SUM(AC91:AH91) -> 0 | AO91: =+Z91+AB91 -> 156382893 | AP91: =IF(AR91=$AR$8,((S91-AO91)*0),S91-AO91) -> 0 | AU91: Ok | AV91: =VLOOKUP(F91,[78]!D365FinOps_API_Table[[FixedAssetNumber]:[Department]],80,FALSE) -> #REF! | AW91: =AV91-AN91 -> #REF! | BL91: CLC133-026
A92: =+A91+1 -> 81 | B92: CKR | C92: AD_HO | D92: 153 | E92: HO-133-004 | F92: STR000014 | G92: 41817 | H92: Structures | I92: 28 | J92: Telephone Installation | K92: KDDI Indonesia | M92: 2014 | Q92: 1 | S92: 26867854 | T92: =+S92/U92 -> 447797.57 | U92: 60 | V92: 60 | W92: =+AB92/T92 -> 0 | X92: =+V92+W92 -> 60 | Y92: =+U92-X92 -> 0 | Z92: 26867854 | AA92: 1.1175871e-08 | AB92: =SUM(AC92:AH92) -> 0 | AO92: =+Z92+AB92 -> 26867854 | AP92: =IF(AR92=$AR$8,((S92-AO92)*0),S92-AO92) -> 1.1175871e-08 | AU92: Ok | AV92: =VLOOKUP(F92,[78]!D365FinOps_API_Table[[FixedAssetNumber]:[Department]],80,FALSE) -> #REF! | AW92: =AV92-AN92 -> #REF! | BL92: HO-133-004
A93: =+A92+1 -> 82 | B93: MESS | C93: AD_HO | D93: 153 | E93: HO-133-005 | F93: STR000018 | G93: 41881 | H93: Structures | I93: 51 | J93: Water Installation | K93: Kota Deltamas Cluster Pasadena Blok B, Cikarang Pusat, Jawa Barat | M93: 2014 | Q93: 1 | S93: 25000000 | T93: =+S93/U93 -> 416666.67 | U93: 60 | V93: 60 | W93: =+AB93/T93 -> 0 | X93: =+V93+W93 -> 60 | Y93: =+U93-X93 -> 0 | Z93: 25000000 | AA93: -3.7252903e-09 | AB93: =SUM(AC93:AH93) -> 0 | AO93: =+Z93+AB93 -> 25000000 | AP93: =IF(AR93=$AR$8,((S93-AO93)*0),S93-AO93) -> -3.7252903e-09 | AU93: Ok | AV93: =VLOOKUP(F93,[78]!D365FinOps_API_Table[[FixedAssetNumber]:[Department]],80,FALSE) -> #REF! | AW93: =AV93-AN93 -> #REF! | BL93: HO-133-005
A94: =+A93+1 -> 83 | B94: CKR | C94: AD_HO | D94: 153 | E94: HO-133-006 | F94: STR000019 | G94: 41880 | H94: Structures | I94: 60 | J94: Hardware Reinforce at KITIC - Staircase | K94: KDDI Indonesia | M94: 2014 | Q94: 1 | S94: 185618275 | T94: =+S94/U94 -> 3093637.9 | U94: 60 | V94: 60 | W94: =+AB94/T94 -> 0 | X94: =+V94+W94 -> 60 | Y94: =+U94-X94 -> 0 | Z94: 185618275 | AA94: 0 | AB94: =SUM(AC94:AH94) -> 0 | AO94: =+Z94+AB94 -> 185618275 | AP94: =IF(AR94=$AR$8,((S94-AO94)*0),S94-AO94) -> 0 | AU94: Ok | AV94: =VLOOKUP(F94,[78]!D365FinOps_API_Table[[FixedAssetNumber]:[Department]],80,FALSE) -> #REF! | AW94: =AV94-AN94 -> #REF! | BL94: HO-133-006
A95: =+A94+1 -> 84 | B95: MESS | C95: AD_HO | D95: 153 | E95: HO-133-007 | F95: STR000020 | G95: 41911 | H95: Structures | I95: 16 | J95: Wi Fi infrastruktur for Dormitory Building | K95: Sarana Utama Mandiri | M95: 2014 | Q95: 1 | S95: 68739000 | T95: =+S95/U95 -> 1145650 | U95: 60 | V95: 60 | W95: =+AB95/T95 -> 0 | X95: =+V95+W95 -> 60 | Y95: =+U95-X95 -> 0 | Z95: 68739000 | AA95: 0 | AB95: =SUM(AC95:AH95) -> 0 | AO95: =+Z95+AB95 -> 68739000 | AP95: =IF(AR95=$AR$8,((S95-AO95)*0),S95-AO95) -> 0 | AU95: Ok | AV95: =VLOOKUP(F95,[78]!D365FinOps_API_Table[[FixedAssetNumber]:[Department]],80,FALSE) -> #REF! | AW95: =AV95-AN95 -> #REF! | BL95: HO-133-007
A96: =+A95+1 -> 85 | B96: CKR | C96: AD_HO | D96: 153 | E96: HO-133-008 | F96: STR000021 | G96: 42080 | H96: Structures | I96: 17 | J96: Installation KWH Meter and Water Supply Matering | K96: Seamec Asia | M96: 2015 | Q96: 1 | S96: 90480000 | T96: =+S96/U96 -> 1508000 | U96: 60 | V96: 60 | W96: =+AB96/T96 -> 0 | X96: =+V96+W96 -> 60 | Y96: =+U96-X96 -> 0 | Z96: 90480000 | AA96: 0 | AB96: =SUM(AC96:AH96) -> 0 | AO96: =+Z96+AB96 -> 90480000 | AP96: =IF(AR96=$AR$8,((S96-AO96)*0),S96-AO96) -> 0 | AU96: Ok | AV96: =VLOOKUP(F96,[78]!D365FinOps_API_Table[[FixedAssetNumber]:[Department]],80,FALSE) -> #REF! | AW96: =AV96-AN96 -> #REF! | BL96: HO-133-008
A97: =+A96+1 -> 86 | B97: CLC_SBY | C97: CLCWH | D97: 153 | E97: CLC133-007 | F97: STR000023 | G97: 42366 | H97: Structures | I97: 20 | J97: Wifi Instalation Warehouse Surabaya | K97: KDDI Indonesia | M97: 2015 | Q97: 1 | R97: 26310 | S97: 364130400 | T97: =+S97/U97 -> 6068840 | U97: 60 | V97: 60 | W97: =+AB97/T97 -> 0 | X97: =+V97+W97 -> 60 | Y97: =+U97-X97 -> 0 | Z97: 364130400 | AA97: 0 | AB97: =SUM(AC97:AH97) -> 0 | AO97: =+Z97+AB97 -> 364130400 | AP97: =IF(AR97=$AR$8,((S97-AO97)*0),S97-AO97) -> 0 | AU97: Ok | AV97: =VLOOKUP(F97,[78]!D365FinOps_API_Table[[FixedAssetNumber]:[Department]],80,FALSE) -> #REF! | AW97: =AV97-AN97 -> #REF! | BL97: CLC133-007
A98: =+A97+1 -> 87 | B98: CLC | C98: CLCWH | D98: 153 | E98: CLC133-008 | F98: STR000024 | G98: 42366 | H98: Structures | I98: 22 | J98: Installation High Bay Lighting Warehouse | K98: Seamec Asia | L98: WH 1 | M98: 2015 | Q98: 1 | S98: 227000000 | T98: =+S98/U98 -> 3783333.3 | U98: 60 | V98: 60 | W98: =+AB98/T98 -> 0 | X98: =+V98+W98 -> 60 | Y98: =+U98-X98 -> 0 | Z98: 2.27e+08 | AA98: -2.9802322e-08 | AB98: =SUM(AC98:AH98) -> 0 | AO98: =+Z98+AB98 -> 2.27e+08 | AP98: =IF(AR98=$AR$8,((S98-AO98)*0),S98-AO98) -> -2.9802322e-08 | AU98: Ok | AV98: =VLOOKUP(F98,[78]!D365FinOps_API_Table[[FixedAssetNumber]:[Department]],80,FALSE) -> #REF! | AW98: =AV98-AN98 -> #REF! | BL98: CLC133-008
A99: =+A98+1 -> 88 | B99: CLC | C99: CLCWH | D99: 153 | E99: CLC133-009 | F99: STR000025 | G99: 42397 | H99: Structures | I99: 16 | J99: Internet System | K99: KDDI Indonesia | L99: WH & Office Phase 2 | M99: 2016 | Q99: 1 | S99: 745885600 | T99: =+S99/U99 -> 12431427 | U99: 60 | V99: 60 | W99: =+AB99/T99 -> 0 | X99: =+V99+W99 -> 60 | Y99: =+U99-X99 -> 0 | Z99: 745885600 | AA99: 0 | AB99: =SUM(AC99:AH99) -> 0 | AO99: =+Z99+AB99 -> 745885600 | AP99: =IF(AR99=$AR$8,((S99-AO99)*0),S99-AO99) -> 0 | AU99: Ok | AV99: =VLOOKUP(F99,[78]!D365FinOps_API_Table[[FixedAssetNumber]:[Department]],80,FALSE) -> #REF! | AW99: =AV99-AN99 -> #REF! | BL99: CLC133-009
A100: =+A99+1 -> 89 | B100: CLC | C100: CLCWH | D100: 153 | E100: CLC133-010 | F100: STR000026 | G100: 42429 | H100: Structures | I100: 27 | J100: Install PABX | K100: KDDI Indonesia | L100: Install New PABX at server room | M100: 2016 | Q100: 1 | S100: 45560000 | T100: =+S100/U100 -> 759333.33 | U100: 60 | V100: 60 | W100: =+AB100/T100 -> 0 | X100: =+V100+W100 -> 60 | Y100: =+U100-X100 -> 0 | Z100: 45560000 | AA100: 7.4505806e-09 | AB100: =SUM(AC100:AH100) -> 0 | AO100: =+Z100+AB100 -> 45560000 | AP100: =IF(AR100=$AR$8,((S100-AO100)*0),S100-AO100) -> 7.4505806e-09 | AU100: Ok | AV100: =VLOOKUP(F100,[78]!D365FinOps_API_Table[[FixedAssetNumber]:[Department]],80,FALSE) -> #REF! | AW100: =AV100-AN100 -> #REF! | BL100: CLC133-010
A101: =+A100+1 -> 90 | B101: CLC | C101: CLCWH | D101: 153 | E101: CLC133-011 | F101: STR000027 | G101: 42489 | H101: Structures | I101: 35 | J101: CCTV system | K101: SECOM Indonesia | L101: WH 2 | M101: 2016 | Q101: 1 | R101: 66652.35 | S101: 8.848766e+08 | T101: =+S101/U101 -> 14747943 | U101: 60 | V101: 60 | W101: =+AB101/T101 -> 0 | X101: =+V101+W101 -> 60 | Y101: =+U101-X101 -> 0 | Z101: 8.848766e+08 | AA101: 0 | AB101: =SUM(AC101:AH101) -> 0 | AO101: =+Z101+AB101 -> 8.848766e+08 | AP101: =IF(AR101=$AR$8,((S101-AO101)*0),S101-AO101) -> 0 | AU101: Ok | AV101: =VLOOKUP(F101,[78]!D365FinOps_API_Table[[FixedAssetNumber]:[Department]],80,FALSE) -> #REF! | AW101: =AV101-AN101 -> #REF! | BL101: CLC133-011
A102: =+A101+1 -> 91 | B102: CLC | C102: CLCWH | D102: 153 | E102: CLC133-012 | F102: STR000028 | G102: 42489 | H102: Structures | I102: 35 | J102: Pariometer Border System | K102: SECOM Indonesia | M102: 2016 | Q102: 1 | S102: 303068283 | T102: =+S102/U102 -> 5051138 | U102: 60 | V102: 60 | W102: =+AB102/T102 -> 0 | X102: =+V102+W102 -> 60 | Y102: =+U102-X102 -> 0 | Z102: 3.0306828e+08 | AA102: 5.9604645e-08 | AB102: =SUM(AC102:AH102) -> 0 | AO102: =+Z102+AB102 -> 3.0306828e+08 | AP102: =IF(AR102=$AR$8,((S102-AO102)*0),S102-AO102) -> 5.9604645e-08 | AU102: Ok | AV102: =VLOOKUP(F102,[78]!D365FinOps_API_Table[[FixedAssetNumber]:[Department]],80,FALSE) -> #REF! | AW102: =AV102-AN102 -> #REF! | BL102: CLC133-012
A103: =+A102+1 -> 92 | B103: CLC | C103: CLCWH | D103: 153 | E103: CLC133-013 | F103: STR000029 | G103: 42719 | H103: Structures | I103: 08 | J103: CCTV system fr Security Guard House | K103: SECOM Indonesia | M103: 2016 | Q103: 1 | R103: 4947.09 | S103: 67097382 | T103: =+S103/U103 -> 1118289.7 | U103: 60 | V103: 60 | W103: =+AB103/T103 -> 0 | X103: =+V103+W103 -> 60 | Y103: =+U103-X103 -> 0 | Z103: 67097382 | AA103: 1.4901161e-08 | AB103: =SUM(AC103:AH103) -> 0 | AO103: =+Z103+AB103 -> 67097382 | AP103: =IF(AR103=$AR$8,((S103-AO103)*0),S103-AO103) -> 1.4901161e-08 | AU103: Ok | AV103: =VLOOKUP(F103,[78]!D365FinOps_API_Table[[FixedAssetNumber]:[Department]],80,FALSE) -> #REF! | AW103: =AV103-AN103 -> #REF! | BL103: CLC133-013
A104: =+A103+1 -> 93 | B104: CLC | C104: CLCWH | D104: 153 | E104: CLC133-014 | F104: STR000030 | G104: 42719 | H104: Structures | I104: 08 | J104: Finger Scan Acces for W/H Phase 2 | K104: SECOM Indonesia | M104: 2016 | Q104: 1 | S104: 36326195 | T104: =+S104/U104 -> 605436.58 | U104: 60 | V104: 60 | W104: =+AB104/T104 -> 0 | X104: =+V104+W104 -> 60 | Y104: =+U104-X104 -> 0 | Z104: 36326195 | AA104: 0 | AB104: =SUM(AC104:AH104) -> 0 | AO104: =+Z104+AB104 -> 36326195 | AP104: =IF(AR104=$AR$8,((S104-AO104)*0),S104-AO104) -> 0 | AU104: Ok | AV104: =VLOOKUP(F104,[78]!D365FinOps_API_Table[[FixedAssetNumber]:[Department]],80,FALSE) -> #REF! | AW104: =AV104-AN104 -> #REF! | BL104: CLC133-014
A105: =+A104+1 -> 94 | B105: CLC | C105: CLCWH | D105: 153 | E105: CLC133-015 | F105: STR000031 | G105: 42733 | H105: Structures | I105: 18 | J105: Pariometer Border System in Central Area W/H CLC | K105: SECOM Indonesia | M105: 2016 | Q105: 1 | S105: 92140414 | T105: =+S105/U105 -> 1535673.6 | U105: 60 | V105: 60 | W105: =+AB105/T105 -> 0 | X105: =+V105+W105 -> 60 | Y105: =+U105-X105 -> 0 | Z105: 92140414 | AA105: 0 | AB105: =SUM(AC105:AH105) -> 0 | AO105: =+Z105+AB105 -> 92140414 | AP105: =IF(AR105=$AR$8,((S105-AO105)*0),S105-AO105) -> 0 | AU105: Ok | AV105: =VLOOKUP(F105,[78]!D365FinOps_API_Table[[FixedAssetNumber]:[Department]],80,FALSE) -> #REF! | AW105: =AV105-AN105 -> #REF! | BL105: CLC133-015
A106: =+A105+1 -> 95 | B106: CKR | C106: AD_HO | D106: 153 | F106: STR000032 | G106: 42733 | H106: Structures | I106: 18 | J106: Repair Concrete Panel Fence | K106: SMCC Utama | M106: 2016 | Q106: 1 | S106: 56000000 | T106: =+S106/U106 -> 933333.33 | U106: 60 | V106: 60 | W106: =+AB106/T106 -> 0 | X106: =+V106+W106 -> 60 | Y106: =+U106-X106 -> 0 | Z106: 56000000 | AA106: -7.4505806e-09 | AB106: =SUM(AC106:AH106) -> 0 | AO106: =+Z106+AB106 -> 56000000 | AP106: =IF(AR106=$AR$8,((S106-AO106)*0),S106-AO106) -> -7.4505806e-09 | AU106: Ok | AV106: =VLOOKUP(F106,[78]!D365FinOps_API_Table[[FixedAssetNumber]:[Department]],80,FALSE) -> #REF! | AW106: =AV106-AN106 -> #REF!
A107: =+A106+1 -> 96 | B107: CLC | C107: CLCWH | D107: 153 | E107: CLC133-016 | F107: STR000035 | G107: 42885 | H107: Structures | I107: 15 | J107: New Panic Bar | K107: SMCC Utama | M107: 2017 | Q107: 1 | S107: 80000000 | T107: =+S107/U107 -> 1333333.3 | U107: 60 | V107: 60 | W107: =+AB107/T107 -> 0 | X107: =+V107+W107 -> 60 | Y107: =+U107-X107 -> 0 | Z107: 80000000 | AA107: 0 | AB107: =SUM(AC107:AH107) -> 0 | AO107: =+Z107+AB107 -> 80000000 | AP107: =IF(AR107=$AR$8,((S107-AO107)*0),S107-AO107) -> 0 | AU107: Ok | AV107: =VLOOKUP(F107,[78]!D365FinOps_API_Table[[FixedAssetNumber]:[Department]],80,FALSE) -> #REF! | AW107: =AV107-AN107 -> #REF! | BL107: CLC133-016
A108: =+A107+1 -> 97 | B108: SLI | C108: AD_HO | D108: 153 | F108: STR000036 | G108: 42915 | H108: Structures | I108: 5045 | J108: Interior and Company Logo of Tanjung Priuk | K108: SMCC Utama | M108: 2017 | Q108: 1 | S108: 217000000 | T108: =+S108/U108 -> 3616666.7 | U108: 60 | V108: 60 | W108: =+AB108/T108 -> 0 | X108: =+V108+W108 -> 60 | Y108: =+U108-X108 -> 0 | Z108: 217000000 | AA108: 0 | AB108: =SUM(AC108:AH108) -> 0 | AO108: =+Z108+AB108 -> 217000000 | AP108: =IF(AR108=$AR$8,((S108-AO108)*0),S108-AO108) -> 0 | AU108: Ok | AV108: =VLOOKUP(F108,[78]!D365FinOps_API_Table[[FixedAssetNumber]:[Department]],80,FALSE) -> #REF! | AW108: =AV108-AN108 -> #REF!
A109: =+A108+1 -> 98 | B109: SLI | C109: AD_HO | D109: 153 | F109: STR000037 | G109: 42915 | H109: Structures | I109: 5045 | J109: Mechanical and Demolish Work | K109: SMCC Utama | M109: 2017 | Q109: 1 | S109: 124000000 | T109: =+S109/U109 -> 2066666.7 | U109: 60 | V109: 60 | W109: =+AB109/T109 -> 0 | X109: =+V109+W109 -> 60 | Y109: =+U109-X109 -> 0 | Z109: 124000000 | AA109: 0 | AB109: =SUM(AC109:AH109) -> 0 | AO109: =+Z109+AB109 -> 124000000 | AP109: =IF(AR109=$AR$8,((S109-AO109)*0),S109-AO109) -> 0 | AU109: Ok | AV109: =VLOOKUP(F109,[78]!D365FinOps_API_Table[[FixedAssetNumber]:[Department]],80,FALSE) -> #REF! | AW109: =AV109-AN109 -> #REF!
A110: =+A109+1 -> 99 | B110: SLI | C110: AD_HO | D110: 153 | F110: STR000038 | G110: 42915 | H110: Structures | I110: 5045 | J110: Electrical Work at Tanjung Priuk | K110: SMCC Utama | M110: 2017 | Q110: 1 | S110: 211000000 | T110: =+S110/U110 -> 3516666.7 | U110: 60 | V110: 60 | W110: =+AB110/T110 -> 0 | X110: =+V110+W110 -> 60 | Y110: =+U110-X110 -> 0 | Z110: 211000000 | AA110: 0 | AB110: =SUM(AC110:AH110) -> 0 | AO110: =+Z110+AB110 -> 211000000 | AP110: =IF(AR110=$AR$8,((S110-AO110)*0),S110-AO110) -> 0 | AU110: Ok | AV110: =VLOOKUP(F110,[78]!D365FinOps_API_Table[[FixedAssetNumber]:[Department]],80,FALSE) -> #REF! | AW110: =AV110-AN110 -> #REF!
...

Sheet Sheet1
D4: Land | E4: 7 Location
D5: Buildings | E5: 78 Office and Workshop
D6: Structures | E6: 61 Structure
D7: Machinery & Equipments | E7: 278 Machine & Equipment
D8: Vehicles | E8: 474 Vehicle
D9: Tools, Furnitures & Fixtures | E9: 181 Tools & Furnitur
D10: Non-Asset | E10: 88 Item Machine, Tools and Vehicle

Sheet Disposal 2026
A1: PT. Sankyu Indonesia International
A2: Disposals of Fixed Asset
A3: =TOTAL!A3 -> 30 Jun 2026
A6: No | B6: Name of Asset | C6: Fix Asset Number AX | D6: Maker/Type/Location | E6: Capacity | F6: Police No. | G6: Machine No. | H6: Chasis No. | I6: Site | J6: Job | K6: Date | M6: Purchase | N6: Acc. Depr. | O6: Net Book Value | P6: Proceed | Q6: Gain on Sale | R6: Lose on Sale | T6: Vc. | U6: Buyer
K7: Purchase | L7: Disposal | M7: Price | N7: upto Disposal | Q7: ( 421 ) | R7: ( 521 )
A9: 1 | B9: =IF(IFERROR(VLOOKUP(C9,FA_2026!$F$10:$AT$65451,5,FALSE),0)=0,"-",IFERROR(VLOOKUP(C9,FA_2026!$F$10:$AT$65451,5,FALSE),0)) -> Lightening Rod | C9: MNE000202 | D9: =IF(IFERROR(VLOOKUP(C9,FA_2026!$F$10:$AT$65451,6,FALSE),0)=0,"-",IFERROR(VLOOKUP(C9,FA_2026!$F$10:$AT$65451,6,FALSE),0)) -> Joko | E9: =IF(IFERROR(VLOOKUP(C9,FA_2026!$F$10:$AT$65451,7,FALSE),0)=0,"-",IFERROR(VLOOKUP(C9,FA_2026!$F$10:$AT$65451,7,FALSE),0)) -> WH Surabaya | F9: =IF(IFERROR(VLOOKUP(C9,FA_2026!$F$10:$AT$65451,9,FALSE),0)=0,"-",IFERROR(VLOOKUP(C9,FA_2026!$F$10:$AT$65451,9,FALSE),0)) -> - | G9: =IF(IFERROR(VLOOKUP(C9,FA_2026!$F$10:$AT$65451,10,FALSE),0)=0,"-",IFERROR(VLOOKUP(C9,FA_2026!$F$10:$AT$65451,10,FALSE),0)) -> - | H9: =IF(IFERROR(VLOOKUP(C9,FA_2026!$F$10:$AT$65451,11,FALSE),0)=0,"-",IFERROR(VLOOKUP(C9,FA_2026!$F$10:$AT$65451,11,FALSE),0)) -> - | I9: =IFERROR(INDEX(FA_2026!$B$10:$B$1159,MATCH('Disposal 2026'!C9,FA_2026!$F$10:$F$1159,0)),0) -> CLC | J9: =IFERROR(INDEX(FA_2026!$C$10:$C$1159,MATCH('Disposal 2026'!C9,FA_2026!$F$10:$F$1159,0)),0) -> CLCWH | K9: =IF(IFERROR(VLOOKUP(C9,FA_2026!$F$10:$AT$65451,2,FALSE),0)=0,"-",IFERROR(VLOOKUP(C9,FA_2026!$F$10:$AT$65451,2,FALSE),0)) -> 42338 | L9: =IF(IFERROR(VLOOKUP(C9,'List Approval 2025'!$D$7:$M$65624,5,FALSE),0)=0,"-",IFERROR(VLOOKUP(C9,'List Approval 2025'!$D$7:$M$65624,5,FALSE),0)) -> - | M9: =IF(IFERROR(VLOOKUP(C9,FA_2026!$F$10:$AT$65451,14,FALSE),0)=0,"-",IFERROR(VLOOKUP(C9,FA_2026!$F$10:$AT$65451,14,FALSE),0)) -> 17300000 | N9: =IF(IFERROR(VLOOKUP(C9,FA_2026!$F$10:$AT$65451,36,FALSE),0)=0,"-",IFERROR(VLOOKUP(C9,FA_2026!$F$10:$AT$65451,36,FALSE),0)) -> 17300000 | O9: =ROUND(IFERROR(+M9-N9,0),0) -> 0 | P9: =IFERROR(VLOOKUP(C9,'List Approval 2026'!$D$7:$M$276,10,FALSE),0) -> 0 | Q9: =(IFERROR(IF(+P9-O9<0,"-",+P9-O9),0)) -> 0 | R9: =(IFERROR(IF(P9-O9>=0,"-",O9-P9),0)) -> - | U9: =IFERROR(VLOOKUP(C9,'List Approval 2026'!$D$7:$P$225,13,FALSE),"-") -> Sankyu CLC
A10: =+A9+1 -> 2 | B10: =IF(IFERROR(VLOOKUP(C10,FA_2026!$F$10:$AT$65451,5,FALSE),0)=0,"-",IFERROR(VLOOKUP(C10,FA_2026!$F$10:$AT$65451,5,FALSE),0)) -> Crowler Crane | C10: VEH000054 | D10: =IF(IFERROR(VLOOKUP(C10,FA_2026!$F$10:$AT$65451,6,FALSE),0)=0,"-",IFERROR(VLOOKUP(C10,FA_2026!$F$10:$AT$65451,6,FALSE),0)) -> Sumitomo | E10: =IF(IFERROR(VLOOKUP(C10,FA_2026!$F$10:$AT$65451,7,FALSE),0)=0,"-",IFERROR(VLOOKUP(C10,FA_2026!$F$10:$AT$65451,7,FALSE),0)) -> 200T | F10: =IF(IFERROR(VLOOKUP(C10,FA_2026!$F$10:$AT$65451,9,FALSE),0)=0,"-",IFERROR(VLOOKUP(C10,FA_2026!$F$10:$AT$65451,9,FALSE),0)) -> - | G10: =IF(IFERROR(VLOOKUP(C10,FA_2026!$F$10:$AT$65451,10,FALSE),0)=0,"-",IFERROR(VLOOKUP(C10,FA_2026!$F$10:$AT$65451,10,FALSE),0)) -> K13C-TJ10782 | H10: =IF(IFERROR(VLOOKUP(C10,FA_2026!$F$10:$AT$65451,11,FALSE),0)=0,"-",IFERROR(VLOOKUP(C10,FA_2026!$F$10:$AT$65451,11,FALSE),0)) -> - | I10: =IFERROR(INDEX(FA_2026!$B$10:$B$1159,MATCH('Disposal 2026'!C10,FA_2026!$F$10:$F$1159,0)),0) -> CLGC | J10: =IFERROR(INDEX(FA_2026!$C$10:$C$1159,MATCH('Disposal 2026'!C10,FA_2026!$F$10:$F$1159,0)),0) -> D30 | K10: =IF(IFERROR(VLOOKUP(C10,FA_2026!$F$10:$AT$65451,2,FALSE),0)=0,"-",IFERROR(VLOOKUP(C10,FA_2026!$F$10:$AT$65451,2,FALSE),0)) -> 38228 | L10: =IF(IFERROR(VLOOKUP(C10,'List Approval 2025'!$D$7:$M$65624,5,FALSE),0)=0,"-",IFERROR(VLOOKUP(C10,'List Approval 2025'!$D$7:$M$65624,5,FALSE),0)) -> 1 | M10: =IF(IFERROR(VLOOKUP(C10,FA_2026!$F$10:$AT$65451,14,FALSE),0)=0,"-",IFERROR(VLOOKUP(C10,FA_2026!$F$10:$AT$65451,14,FALSE),0)) -> 7634037281 | N10: =IF(IFERROR(VLOOKUP(C10,FA_2026!$F$10:$AT$65451,36,FALSE),0)=0,"-",IFERROR(VLOOKUP(C10,FA_2026!$F$10:$AT$65451,36,FALSE),0)) -> 7634037281 | O10: =ROUND(IFERROR(+M10-N10,0),0) -> 0 | P10: =IFERROR(VLOOKUP(C10,'List Approval 2025'!$D$7:$M$277,10,FALSE),0) -> 1400000000 | Q10: =(IFERROR(IF(+P10-O10<0,"-",+P10-O10),0)) -> 1400000000 | R10: =(IFERROR(IF(P10-O10>=0,"-",O10-P10),0)) -> - | U10: =IFERROR(VLOOKUP(C10,'List Approval 2025'!$D$7:$P$226,13,FALSE),"-") -> - | V10: CAJE
A11: =+A10+1 -> 3 | B11: =IF(IFERROR(VLOOKUP(C11,FA_2026!$F$10:$AT$65451,5,FALSE),0)=0,"-",IFERROR(VLOOKUP(C11,FA_2026!$F$10:$AT$65451,5,FALSE),0)) -> Chassis High Bed | C11: VEH000083 | D11: =IF(IFERROR(VLOOKUP(C11,FA_2026!$F$10:$AT$65451,6,FALSE),0)=0,"-",IFERROR(VLOOKUP(C11,FA_2026!$F$10:$AT$65451,6,FALSE),0)) -> Masana (for Nissan) | E11: =IF(IFERROR(VLOOKUP(C11,FA_2026!$F$10:$AT$65451,7,FALSE),0)=0,"-",IFERROR(VLOOKUP(C11,FA_2026!$F$10:$AT$65451,7,FALSE),0)) -> 40 feet; 3 axcle | F11: =IF(IFERROR(VLOOKUP(C11,FA_2026!$F$10:$AT$65451,9,FALSE),0)=0,"-",IFERROR(VLOOKUP(C11,FA_2026!$F$10:$AT$65451,9,FALSE),0)) -> MS-04 | G11: =IF(IFERROR(VLOOKUP(C11,FA_2026!$F$10:$AT$65451,10,FALSE),0)=0,"-",IFERROR(VLOOKUP(C11,FA_2026!$F$10:$AT$65451,10,FALSE),0)) -> - | H11: =IF(IFERROR(VLOOKUP(C11,FA_2026!$F$10:$AT$65451,11,FALSE),0)=0,"-",IFERROR(VLOOKUP(C11,FA_2026!$F$10:$AT$65451,11,FALSE),0)) -> MTR0605128443 | I11: =IFERROR(INDEX(FA_2026!$B$10:$B$1159,MATCH('Disposal 2026'!C11,FA_2026!$F$10:$F$1159,0)),0) -> CLC | J11: =IFERROR(INDEX(FA_2026!$C$10:$C$1159,MATCH('Disposal 2026'!C11,FA_2026!$F$10:$F$1159,0)),0) -> CLCTRP | K11: =IF(IFERROR(VLOOKUP(C11,FA_2026!$F$10:$AT$65451,2,FALSE),0)=0,"-",IFERROR(VLOOKUP(C11,FA_2026!$F$10:$AT$65451,2,FALSE),0)) -> 38548 | L11: =IF(IFERROR(VLOOKUP(C11,'List Approval 2025'!$D$7:$M$65624,5,FALSE),0)=0,"-",IFERROR(VLOOKUP(C11,'List Approval 2025'!$D$7:$M$65624,5,FALSE),0)) -> - | M11: =IF(IFERROR(VLOOKUP(C11,FA_2026!$F$10:$AT$65451,14,FALSE),0)=0,"-",IFERROR(VLOOKUP(C11,FA_2026!$F$10:$AT$65451,14,FALSE),0)) -> 105000000 | N11: =IF(IFERROR(VLOOKUP(C11,FA_2026!$F$10:$AT$65451,36,FALSE),0)=0,"-",IFERROR(VLOOKUP(C11,FA_2026!$F$10:$AT$65451,36,FALSE),0)) -> 105000000 | O11: =ROUND(IFERROR(+M11-N11,0),0) -> 0 | P11: =IFERROR(VLOOKUP(C11,'List Approval 2026'!$D$7:$M$276,10,FALSE),0) -> 45045045 | Q11: =(IFERROR(IF(+P11-O11<0,"-",+P11-O11),0)) -> 45045045 | R11: =(IFERROR(IF(P11-O11>=0,"-",O11-P11),0)) -> - | U11: =IFERROR(VLOOKUP(C11,'List Approval 2026'!$D$7:$P$225,13,FALSE),"-") -> Citra Seraya Pratama
A12: =+A11+1 -> 4 | B12: =IF(IFERROR(VLOOKUP(C12,FA_2026!$F$10:$AT$65451,5,FALSE),0)=0,"-",IFERROR(VLOOKUP(C12,FA_2026!$F$10:$AT$65451,5,FALSE),0)) -> Head Tractor | C12: VEH000211 | D12: =IF(IFERROR(VLOOKUP(C12,FA_2026!$F$10:$AT$65451,6,FALSE),0)=0,"-",IFERROR(VLOOKUP(C12,FA_2026!$F$10:$AT$65451,6,FALSE),0)) -> Hino | E12: =IF(IFERROR(VLOOKUP(C12,FA_2026!$F$10:$AT$65451,7,FALSE),0)=0,"-",IFERROR(VLOOKUP(C12,FA_2026!$F$10:$AT$65451,7,FALSE),0)) -> 26T | F12: =IF(IFERROR(VLOOKUP(C12,FA_2026!$F$10:$AT$65451,9,FALSE),0)=0,"-",IFERROR(VLOOKUP(C12,FA_2026!$F$10:$AT$65451,9,FALSE),0)) -> A 9155 TZ | G12: =IF(IFERROR(VLOOKUP(C12,FA_2026!$F$10:$AT$65451,10,FALSE),0)=0,"-",IFERROR(VLOOKUP(C12,FA_2026!$F$10:$AT$65451,10,FALSE),0)) -> P11CUBJ-15323 | H12: =IF(IFERROR(VLOOKUP(C12,FA_2026!$F$10:$AT$65451,11,FALSE),0)=0,"-",IFERROR(VLOOKUP(C12,FA_2026!$F$10:$AT$65451,11,FALSE),0)) -> MJEFM2PKKCJZ-14141 | I12: =IFERROR(INDEX(FA_2026!$B$10:$B$1159,MATCH('Disposal 2026'!C12,FA_2026!$F$10:$F$1159,0)),0) -> CLC | J12: =IFERROR(INDEX(FA_2026!$C$10:$C$1159,MATCH('Disposal 2026'!C12,FA_2026!$F$10:$F$1159,0)),0) -> CLCTRP | K12: =IF(IFERROR(VLOOKUP(C12,FA_2026!$F$10:$AT$65451,2,FALSE),0)=0,"-",IFERROR(VLOOKUP(C12,FA_2026!$F$10:$AT$65451,2,FALSE),0)) -> 41016 | L12: =IF(IFERROR(VLOOKUP(C12,'List Approval 2025'!$D$7:$M$65624,5,FALSE),0)=0,"-",IFERROR(VLOOKUP(C12,'List Approval 2025'!$D$7:$M$65624,5,FALSE),0)) -> - | M12: =IF(IFERROR(VLOOKUP(C12,FA_2026!$F$10:$AT$65451,14,FALSE),0)=0,"-",IFERROR(VLOOKUP(C12,FA_2026!$F$10:$AT$65451,14,FALSE),0)) -> 832727273 | N12: =IF(IFERROR(VLOOKUP(C12,FA_2026!$F$10:$AT$65451,36,FALSE),0)=0,"-",IFERROR(VLOOKUP(C12,FA_2026!$F$10:$AT$65451,36,FALSE),0)) -> 8.3272727e+08 | O12: =ROUND(IFERROR(+M12-N12,0),0) -> 0 | P12: =IFERROR(VLOOKUP(C12,'List Approval 2026'!$D$7:$M$276,10,FALSE),0) -> 211711712 | Q12: =(IFERROR(IF(+P12-O12<0,"-",+P12-O12),0)) -> 211711712 | R12: =(IFERROR(IF(P12-O12>=0,"-",O12-P12),0)) -> - | U12: =IFERROR(VLOOKUP(C12,'List Approval 2026'!$D$7:$P$225,13,FALSE),"-") -> Citra Seraya Pratama
A13: =+A12+1 -> 5 | B13: =IF(IFERROR(VLOOKUP(C13,FA_2026!$F$10:$AT$65451,5,FALSE),0)=0,"-",IFERROR(VLOOKUP(C13,FA_2026!$F$10:$AT$65451,5,FALSE),0)) -> Forklift Sumitomo | C13: VEH000290 | D13: =IF(IFERROR(VLOOKUP(C13,FA_2026!$F$10:$AT$65451,6,FALSE),0)=0,"-",IFERROR(VLOOKUP(C13,FA_2026!$F$10:$AT$65451,6,FALSE),0)) -> Sumitomo | E13: =IF(IFERROR(VLOOKUP(C13,FA_2026!$F$10:$AT$65451,7,FALSE),0)=0,"-",IFERROR(VLOOKUP(C13,FA_2026!$F$10:$AT$65451,7,FALSE),0)) -> 1,5T | F13: =IF(IFERROR(VLOOKUP(C13,FA_2026!$F$10:$AT$65451,9,FALSE),0)=0,"-",IFERROR(VLOOKUP(C13,FA_2026!$F$10:$AT$65451,9,FALSE),0)) -> - | G13: =IF(IFERROR(VLOOKUP(C13,FA_2026!$F$10:$AT$65451,10,FALSE),0)=0,"-",IFERROR(VLOOKUP(C13,FA_2026!$F$10:$AT$65451,10,FALSE),0)) -> U2283 | H13: =IF(IFERROR(VLOOKUP(C13,FA_2026!$F$10:$AT$65451,11,FALSE),0)=0,"-",IFERROR(VLOOKUP(C13,FA_2026!$F$10:$AT$65451,11,FALSE),0)) -> R1H-04425 | I13: =IFERROR(INDEX(FA_2026!$B$10:$B$1159,MATCH('Disposal 2026'!C13,FA_2026!$F$10:$F$1159,0)),0) -> CLC | J13: =IFERROR(INDEX(FA_2026!$C$10:$C$1159,MATCH('Disposal 2026'!C13,FA_2026!$F$10:$F$1159,0)),0) -> CLCWH | K13: =IF(IFERROR(VLOOKUP(C13,FA_2026!$F$10:$AT$65451,2,FALSE),0)=0,"-",IFERROR(VLOOKUP(C13,FA_2026!$F$10:$AT$65451,2,FALSE),0)) -> 41715 | L13: =IF(IFERROR(VLOOKUP(C13,'List Approval 2025'!$D$7:$M$65624,5,FALSE),0)=0,"-",IFERROR(VLOOKUP(C13,'List Approval 2025'!$D$7:$M$65624,5,FALSE),0)) -> - | M13: =IF(IFERROR(VLOOKUP(C13,FA_2026!$F$10:$AT$65451,14,FALSE),0)=0,"-",IFERROR(VLOOKUP(C13,FA_2026!$F$10:$AT$65451,14,FALSE),0)) -> 253184243 | N13: =IF(IFERROR(VLOOKUP(C13,FA_2026!$F$10:$AT$65451,36,FALSE),0)=0,"-",IFERROR(VLOOKUP(C13,FA_2026!$F$10:$AT$65451,36,FALSE),0)) -> 253184243 | O13: =ROUND(IFERROR(+M13-N13,0),0) -> 0 | P13: =IFERROR(VLOOKUP(C13,'List Approval 2026'!$D$7:$M$276,10,FALSE),0) -> 15765766 | Q13: =(IFERROR(IF(+P13-O13<0,"-",+P13-O13),0)) -> 15765766 | R13: =(IFERROR(IF(P13-O13>=0,"-",O13-P13),0)) -> - | U13: =IFERROR(VLOOKUP(C13,'List Approval 2026'!$D$7:$P$225,13,FALSE),"-") -> Najwa Jaya
A14: =+A13+1 -> 6 | B14: =IF(IFERROR(VLOOKUP(C14,FA_2026!$F$10:$AT$65451,5,FALSE),0)=0,"-",IFERROR(VLOOKUP(C14,FA_2026!$F$10:$AT$65451,5,FALSE),0)) -> Pick Up | C14: VEH000300 | D14: =IF(IFERROR(VLOOKUP(C14,FA_2026!$F$10:$AT$65451,6,FALSE),0)=0,"-",IFERROR(VLOOKUP(C14,FA_2026!$F$10:$AT$65451,6,FALSE),0)) -> Daihatsu Grand Max | E14: =IF(IFERROR(VLOOKUP(C14,FA_2026!$F$10:$AT$65451,7,FALSE),0)=0,"-",IFERROR(VLOOKUP(C14,FA_2026!$F$10:$AT$65451,7,FALSE),0)) -> 2,1T | F14: =IF(IFERROR(VLOOKUP(C14,FA_2026!$F$10:$AT$65451,9,FALSE),0)=0,"-",IFERROR(VLOOKUP(C14,FA_2026!$F$10:$AT$65451,9,FALSE),0)) -> B 9971 SYM | G14: =IF(IFERROR(VLOOKUP(C14,FA_2026!$F$10:$AT$65451,10,FALSE),0)=0,"-",IFERROR(VLOOKUP(C14,FA_2026!$F$10:$AT$65451,10,FALSE),0)) -> DEH7723 | H14: =IF(IFERROR(VLOOKUP(C14,FA_2026!$F$10:$AT$65451,11,FALSE),0)=0,"-",IFERROR(VLOOKUP(C14,FA_2026!$F$10:$AT$65451,11,FALSE),0)) -> MHKP3CA1JEK056935 | I14: =IFERROR(INDEX(FA_2026!$B$10:$B$1159,MATCH('Disposal 2026'!C14,FA_2026!$F$10:$F$1159,0)),0) -> CLC | J14: =IFERROR(INDEX(FA_2026!$C$10:$C$1159,MATCH('Disposal 2026'!C14,FA_2026!$F$10:$F$1159,0)),0) -> CLCTRP | K14: =IF(IFERROR(VLOOKUP(C14,FA_2026!$F$10:$AT$65451,2,FALSE),0)=0,"-",IFERROR(VLOOKUP(C14,FA_2026!$F$10:$AT$65451,2,FALSE),0)) -> 41768 | L14: =IF(IFERROR(VLOOKUP(C14,'List Approval 2025'!$D$7:$M$65624,5,FALSE),0)=0,"-",IFERROR(VLOOKUP(C14,'List Approval 2025'!$D$7:$M$65624,5,FALSE),0)) -> 2 | M14: =IF(IFERROR(VLOOKUP(C14,FA_2026!$F$10:$AT$65451,14,FALSE),0)=0,"-",IFERROR(VLOOKUP(C14,FA_2026!$F$10:$AT$65451,14,FALSE),0)) -> 110400000 | N14: =IF(IFERROR(VLOOKUP(C14,FA_2026!$F$10:$AT$65451,36,FALSE),0)=0,"-",IFERROR(VLOOKUP(C14,FA_2026!$F$10:$AT$65451,36,FALSE),0)) -> 110400000 | O14: =ROUND(IFERROR(+M14-N14,0),0) -> 0 | P14: =IFERROR(VLOOKUP(C14,'List Approval 2025'!$D$7:$M$277,10,FALSE),0) -> 36036036 | Q14: =(IFERROR(IF(+P14-O14<0,"-",+P14-O14),0)) -> 36036036 | R14: =(IFERROR(IF(P14-O14>=0,"-",O14-P14),0)) -> - | U14: =IFERROR(VLOOKUP(C14,'List Approval 2025'!$D$7:$P$226,13,FALSE),"-") -> CV. TIRTO KENCONO | V14: 2025
A15: =+A14+1 -> 7 | B15: =IF(IFERROR(VLOOKUP(C15,FA_2026!$F$10:$AT$65451,5,FALSE),0)=0,"-",IFERROR(VLOOKUP(C15,FA_2026!$F$10:$AT$65451,5,FALSE),0)) -> Reach Truck Forklift | C15: VEH000372 | D15: =IF(IFERROR(VLOOKUP(C15,FA_2026!$F$10:$AT$65451,6,FALSE),0)=0,"-",IFERROR(VLOOKUP(C15,FA_2026!$F$10:$AT$65451,6,FALSE),0)) -> Toyota | E15: =IF(IFERROR(VLOOKUP(C15,FA_2026!$F$10:$AT$65451,7,FALSE),0)=0,"-",IFERROR(VLOOKUP(C15,FA_2026!$F$10:$AT$65451,7,FALSE),0)) -> 1,8 T | F15: =IF(IFERROR(VLOOKUP(C15,FA_2026!$F$10:$AT$65451,9,FALSE),0)=0,"-",IFERROR(VLOOKUP(C15,FA_2026!$F$10:$AT$65451,9,FALSE),0)) -> - | G15: =IF(IFERROR(VLOOKUP(C15,FA_2026!$F$10:$AT$65451,10,FALSE),0)=0,"-",IFERROR(VLOOKUP(C15,FA_2026!$F$10:$AT$65451,10,FALSE),0)) -> 7FBR18-52585 | H15: =IF(IFERROR(VLOOKUP(C15,FA_2026!$F$10:$AT$65451,11,FALSE),0)=0,"-",IFERROR(VLOOKUP(C15,FA_2026!$F$10:$AT$65451,11,FALSE),0)) -> RC22430 | I15: =IFERROR(INDEX(FA_2026!$B$10:$B$1159,MATCH('Disposal 2026'!C15,FA_2026!$F$10:$F$1159,0)),0) -> CLC | J15: =IFERROR(INDEX(FA_2026!$C$10:$C$1159,MATCH('Disposal 2026'!C15,FA_2026!$F$10:$F$1159,0)),0) -> CLCWH | K15: =IF(IFERROR(VLOOKUP(C15,FA_2026!$F$10:$AT$65451,2,FALSE),0)=0,"-",IFERROR(VLOOKUP(C15,FA_2026!$F$10:$AT$65451,2,FALSE),0)) -> 42276 | L15: =IF(IFERROR(VLOOKUP(C15,'List Approval 2025'!$D$7:$M$65624,5,FALSE),0)=0,"-",IFERROR(VLOOKUP(C15,'List Approval 2025'!$D$7:$M$65624,5,FALSE),0)) -> - | M15: =IF(IFERROR(VLOOKUP(C15,FA_2026!$F$10:$AT$65451,14,FALSE),0)=0,"-",IFERROR(VLOOKUP(C15,FA_2026!$F$10:$AT$65451,14,FALSE),0)) -> 229360800 | N15: =IF(IFERROR(VLOOKUP(C15,FA_2026!$F$10:$AT$65451,36,FALSE),0)=0,"-",IFERROR(VLOOKUP(C15,FA_2026!$F$10:$AT$65451,36,FALSE),0)) -> 229360800 | O15: =ROUND(IFERROR(+M15-N15,0),0) -> 0 | P15: =IFERROR(VLOOKUP(C15,'List Approval 2026'!$D$7:$M$276,10,FALSE),0) -> 15765766 | Q15: =(IFERROR(IF(+P15-O15<0,"-",+P15-O15),0)) -> 15765766 | R15: =(IFERROR(IF(P15-O15>=0,"-",O15-P15),0)) -> - | U15: =IFERROR(VLOOKUP(C15,'List Approval 2026'!$D$7:$P$225,13,FALSE),"-") -> Najwa Jaya
A16: =+A15+1 -> 8 | B16: =IF(IFERROR(VLOOKUP(C16,FA_2026!$F$10:$AT$65451,5,FALSE),0)=0,"-",IFERROR(VLOOKUP(C16,FA_2026!$F$10:$AT$65451,5,FALSE),0)) -> Counter Balance Forklift | C16: VEH000378 | D16: =IF(IFERROR(VLOOKUP(C16,FA_2026!$F$10:$AT$65451,6,FALSE),0)=0,"-",IFERROR(VLOOKUP(C16,FA_2026!$F$10:$AT$65451,6,FALSE),0)) -> Toyota | E16: =IF(IFERROR(VLOOKUP(C16,FA_2026!$F$10:$AT$65451,7,FALSE),0)=0,"-",IFERROR(VLOOKUP(C16,FA_2026!$F$10:$AT$65451,7,FALSE),0)) -> 2,5T | F16: =IF(IFERROR(VLOOKUP(C16,FA_2026!$F$10:$AT$65451,9,FALSE),0)=0,"-",IFERROR(VLOOKUP(C16,FA_2026!$F$10:$AT$65451,9,FALSE),0)) -> - | G16: =IF(IFERROR(VLOOKUP(C16,FA_2026!$F$10:$AT$65451,10,FALSE),0)=0,"-",IFERROR(VLOOKUP(C16,FA_2026!$F$10:$AT$65451,10,FALSE),0)) -> 7FB25-56215 | H16: =IF(IFERROR(VLOOKUP(C16,FA_2026!$F$10:$AT$65451,11,FALSE),0)=0,"-",IFERROR(VLOOKUP(C16,FA_2026!$F$10:$AT$65451,11,FALSE),0)) -> AP15-B62894 | I16: =IFERROR(INDEX(FA_2026!$B$10:$B$1159,MATCH('Disposal 2026'!C16,FA_2026!$F$10:$F$1159,0)),0) -> CLC | J16: =IFERROR(INDEX(FA_2026!$C$10:$C$1159,MATCH('Disposal 2026'!C16,FA_2026!$F$10:$F$1159,0)),0) -> CLCWH | K16: =IF(IFERROR(VLOOKUP(C16,FA_2026!$F$10:$AT$65451,2,FALSE),0)=0,"-",IFERROR(VLOOKUP(C16,FA_2026!$F$10:$AT$65451,2,FALSE),0)) -> 42276 | L16: =IF(IFERROR(VLOOKUP(C16,'List Approval 2025'!$D$7:$M$65624,5,FALSE),0)=0,"-",IFERROR(VLOOKUP(C16,'List Approval 2025'!$D$7:$M$65624,5,FALSE),0)) -> - | M16: =IF(IFERROR(VLOOKUP(C16,FA_2026!$F$10:$AT$65451,14,FALSE),0)=0,"-",IFERROR(VLOOKUP(C16,FA_2026!$F$10:$AT$65451,14,FALSE),0)) -> 287109600 | N16: =IF(IFERROR(VLOOKUP(C16,FA_2026!$F$10:$AT$65451,36,FALSE),0)=0,"-",IFERROR(VLOOKUP(C16,FA_2026!$F$10:$AT$65451,36,FALSE),0)) -> 287109600 | O16: =ROUND(IFERROR(+M16-N16,0),0) -> 0 | P16: =IFERROR(VLOOKUP(C16,'List Approval 2026'!$D$7:$M$276,10,FALSE),0) -> 18018017 | Q16: =(IFERROR(IF(+P16-O16<0,"-",+P16-O16),0)) -> 18018017 | R16: =(IFERROR(IF(P16-O16>=0,"-",O16-P16),0)) -> - | U16: =IFERROR(VLOOKUP(C16,'List Approval 2026'!$D$7:$P$225,13,FALSE),"-") -> Najwa Jaya
A17: =+A16+1 -> 9 | B17: =IF(IFERROR(VLOOKUP(C17,FA_2026!$F$10:$AT$65451,5,FALSE),0)=0,"-",IFERROR(VLOOKUP(C17,FA_2026!$F$10:$AT$65451,5,FALSE),0)) -> Chassis High Bed | C17: VEH000392 | D17: =IF(IFERROR(VLOOKUP(C17,FA_2026!$F$10:$AT$65451,6,FALSE),0)=0,"-",IFERROR(VLOOKUP(C17,FA_2026!$F$10:$AT$65451,6,FALSE),0)) -> Simojoyo | E17: =IF(IFERROR(VLOOKUP(C17,FA_2026!$F$10:$AT$65451,7,FALSE),0)=0,"-",IFERROR(VLOOKUP(C17,FA_2026!$F$10:$AT$65451,7,FALSE),0)) -> 40 Feet | F17: =IF(IFERROR(VLOOKUP(C17,FA_2026!$F$10:$AT$65451,9,FALSE),0)=0,"-",IFERROR(VLOOKUP(C17,FA_2026!$F$10:$AT$65451,9,FALSE),0)) -> - | G17: =IF(IFERROR(VLOOKUP(C17,FA_2026!$F$10:$AT$65451,10,FALSE),0)=0,"-",IFERROR(VLOOKUP(C17,FA_2026!$F$10:$AT$65451,10,FALSE),0)) -> - | H17: =IF(IFERROR(VLOOKUP(C17,FA_2026!$F$10:$AT$65451,11,FALSE),0)=0,"-",IFERROR(VLOOKUP(C17,FA_2026!$F$10:$AT$65451,11,FALSE),0)) -> - | I17: =IFERROR(INDEX(FA_2026!$B$10:$B$1159,MATCH('Disposal 2026'!C17,FA_2026!$F$10:$F$1159,0)),0) -> CLC | J17: =IFERROR(INDEX(FA_2026!$C$10:$C$1159,MATCH('Disposal 2026'!C17,FA_2026!$F$10:$F$1159,0)),0) -> CLCTRP | K17: =IF(IFERROR(VLOOKUP(C17,FA_2026!$F$10:$AT$65451,2,FALSE),0)=0,"-",IFERROR(VLOOKUP(C17,FA_2026!$F$10:$AT$65451,2,FALSE),0)) -> 42321 | L17: =IF(IFERROR(VLOOKUP(C17,'List Approval 2025'!$D$7:$M$65624,5,FALSE),0)=0,"-",IFERROR(VLOOKUP(C17,'List Approval 2025'!$D$7:$M$65624,5,FALSE),0)) -> - | M17: =IF(IFERROR(VLOOKUP(C17,FA_2026!$F$10:$AT$65451,14,FALSE),0)=0,"-",IFERROR(VLOOKUP(C17,FA_2026!$F$10:$AT$65451,14,FALSE),0)) -> 235000000 | N17: =IF(IFERROR(VLOOKUP(C17,FA_2026!$F$10:$AT$65451,36,FALSE),0)=0,"-",IFERROR(VLOOKUP(C17,FA_2026!$F$10:$AT$65451,36,FALSE),0)) -> 2.35e+08 | O17: =ROUND(IFERROR(+M17-N17,0),0) -> 0 | P17: =IFERROR(VLOOKUP(C17,'List Approval 2026'!$D$7:$M$276,10,FALSE),0) -> 45045045 | Q17: =(IFERROR(IF(+P17-O17<0,"-",+P17-O17),0)) -> 45045045 | R17: =(IFERROR(IF(P17-O17>=0,"-",O17-P17),0)) -> - | U17: =IFERROR(VLOOKUP(C17,'List Approval 2026'!$D$7:$P$225,13,FALSE),"-") -> Citra Seraya Pratama
A18: =+A17+1 -> 10 | B18: =IF(IFERROR(VLOOKUP(C18,FA_2026!$F$10:$AT$65451,5,FALSE),0)=0,"-",IFERROR(VLOOKUP(C18,FA_2026!$F$10:$AT$65451,5,FALSE),0)) -> Chassis High Bed | C18: VEH000393 | D18: =IF(IFERROR(VLOOKUP(C18,FA_2026!$F$10:$AT$65451,6,FALSE),0)=0,"-",IFERROR(VLOOKUP(C18,FA_2026!$F$10:$AT$65451,6,FALSE),0)) -> Simojoyo | E18: =IF(IFERROR(VLOOKUP(C18,FA_2026!$F$10:$AT$65451,7,FALSE),0)=0,"-",IFERROR(VLOOKUP(C18,FA_2026!$F$10:$AT$65451,7,FALSE),0)) -> 40 Feet | F18: =IF(IFERROR(VLOOKUP(C18,FA_2026!$F$10:$AT$65451,9,FALSE),0)=0,"-",IFERROR(VLOOKUP(C18,FA_2026!$F$10:$AT$65451,9,FALSE),0)) -> - | G18: =IF(IFERROR(VLOOKUP(C18,FA_2026!$F$10:$AT$65451,10,FALSE),0)=0,"-",IFERROR(VLOOKUP(C18,FA_2026!$F$10:$AT$65451,10,FALSE),0)) -> - | H18: =IF(IFERROR(VLOOKUP(C18,FA_2026!$F$10:$AT$65451,11,FALSE),0)=0,"-",IFERROR(VLOOKUP(C18,FA_2026!$F$10:$AT$65451,11,FALSE),0)) -> - | I18: =IFERROR(INDEX(FA_2026!$B$10:$B$1159,MATCH('Disposal 2026'!C18,FA_2026!$F$10:$F$1159,0)),0) -> CLC | J18: =IFERROR(INDEX(FA_2026!$C$10:$C$1159,MATCH('Disposal 2026'!C18,FA_2026!$F$10:$F$1159,0)),0) -> CLCTRP | K18: =IF(IFERROR(VLOOKUP(C18,FA_2026!$F$10:$AT$65451,2,FALSE),0)=0,"-",IFERROR(VLOOKUP(C18,FA_2026!$F$10:$AT$65451,2,FALSE),0)) -> 42321 | L18: =IF(IFERROR(VLOOKUP(C18,'List Approval 2025'!$D$7:$M$65624,5,FALSE),0)=0,"-",IFERROR(VLOOKUP(C18,'List Approval 2025'!$D$7:$M$65624,5,FALSE),0)) -> - | M18: =IF(IFERROR(VLOOKUP(C18,FA_2026!$F$10:$AT$65451,14,FALSE),0)=0,"-",IFERROR(VLOOKUP(C18,FA_2026!$F$10:$AT$65451,14,FALSE),0)) -> 235000000 | N18: =IF(IFERROR(VLOOKUP(C18,FA_2026!$F$10:$AT$65451,36,FALSE),0)=0,"-",IFERROR(VLOOKUP(C18,FA_2026!$F$10:$AT$65451,36,FALSE),0)) -> 2.35e+08 | O18: =ROUND(IFERROR(+M18-N18,0),0) -> 0 | P18: =IFERROR(VLOOKUP(C18,'List Approval 2026'!$D$7:$M$276,10,FALSE),0) -> 45045045 | Q18: =(IFERROR(IF(+P18-O18<0,"-",+P18-O18),0)) -> 45045045 | R18: =(IFERROR(IF(P18-O18>=0,"-",O18-P18),0)) -> - | U18: =IFERROR(VLOOKUP(C18,'List Approval 2026'!$D$7:$P$225,13,FALSE),"-") -> Citra Seraya Pratama
A19: =+A18+1 -> 11 | B19: =IF(IFERROR(VLOOKUP(C19,FA_2026!$F$10:$AT$65451,5,FALSE),0)=0,"-",IFERROR(VLOOKUP(C19,FA_2026!$F$10:$AT$65451,5,FALSE),0)) -> Head Truck | C19: VEH000395 | D19: =IF(IFERROR(VLOOKUP(C19,FA_2026!$F$10:$AT$65451,6,FALSE),0)=0,"-",IFERROR(VLOOKUP(C19,FA_2026!$F$10:$AT$65451,6,FALSE),0)) -> UD TRUCK | E19: =IF(IFERROR(VLOOKUP(C19,FA_2026!$F$10:$AT$65451,7,FALSE),0)=0,"-",IFERROR(VLOOKUP(C19,FA_2026!$F$10:$AT$65451,7,FALSE),0)) -> 34T | F19: =IF(IFERROR(VLOOKUP(C19,FA_2026!$F$10:$AT$65451,9,FALSE),0)=0,"-",IFERROR(VLOOKUP(C19,FA_2026!$F$10:$AT$65451,9,FALSE),0)) -> B 9692 SEH | G19: =IF(IFERROR(VLOOKUP(C19,FA_2026!$F$10:$AT$65451,10,FALSE),0)=0,"-",IFERROR(VLOOKUP(C19,FA_2026!$F$10:$AT$65451,10,FALSE),0)) -> GH8*417121*A1*P | H19: =IF(IFERROR(VLOOKUP(C19,FA_2026!$F$10:$AT$65451,11,FALSE),0)=0,"-",IFERROR(VLOOKUP(C19,FA_2026!$F$10:$AT$65451,11,FALSE),0)) -> JPCZXY0DXFT011891 | I19: =IFERROR(INDEX(FA_2026!$B$10:$B$1159,MATCH('Disposal 2026'!C19,FA_2026!$F$10:$F$1159,0)),0) -> CLC | J19: =IFERROR(INDEX(FA_2026!$C$10:$C$1159,MATCH('Disposal 2026'!C19,FA_2026!$F$10:$F$1159,0)),0) -> CLCTRP | K19: =IF(IFERROR(VLOOKUP(C19,FA_2026!$F$10:$AT$65451,2,FALSE),0)=0,"-",IFERROR(VLOOKUP(C19,FA_2026!$F$10:$AT$65451,2,FALSE),0)) -> 42366 | L19: =IF(IFERROR(VLOOKUP(C19,'List Approval 2025'!$D$7:$M$65624,5,FALSE),0)=0,"-",IFERROR(VLOOKUP(C19,'List Approval 2025'!$D$7:$M$65624,5,FALSE),0)) -> - | M19: =IF(IFERROR(VLOOKUP(C19,FA_2026!$F$10:$AT$65451,14,FALSE),0)=0,"-",IFERROR(VLOOKUP(C19,FA_2026!$F$10:$AT$65451,14,FALSE),0)) -> 905181818 | N19: =IF(IFERROR(VLOOKUP(C19,FA_2026!$F$10:$AT$65451,36,FALSE),0)=0,"-",IFERROR(VLOOKUP(C19,FA_2026!$F$10:$AT$65451,36,FALSE),0)) -> 9.0518182e+08 | O19: =ROUND(IFERROR(+M19-N19,0),0) -> 0 | P19: =IFERROR(VLOOKUP(C19,'List Approval 2026'!$D$7:$M$276,10,FALSE),0) -> 175675676 | Q19: =(IFERROR(IF(+P19-O19<0,"-",+P19-O19),0)) -> 175675676 | R19: =(IFERROR(IF(P19-O19>=0,"-",O19-P19),0)) -> - | U19: =IFERROR(VLOOKUP(C19,'List Approval 2026'!$D$7:$P$225,13,FALSE),"-") -> Citra Seraya Pratama
A20: =+A19+1 -> 12 | B20: =IF(IFERROR(VLOOKUP(C20,FA_2026!$F$10:$AT$65451,5,FALSE),0)=0,"-",IFERROR(VLOOKUP(C20,FA_2026!$F$10:$AT$65451,5,FALSE),0)) -> Head Tractor | C20: VEH000443 | D20: =IF(IFERROR(VLOOKUP(C20,FA_2026!$F$10:$AT$65451,6,FALSE),0)=0,"-",IFERROR(VLOOKUP(C20,FA_2026!$F$10:$AT$65451,6,FALSE),0)) -> HINO | E20: =IF(IFERROR(VLOOKUP(C20,FA_2026!$F$10:$AT$65451,7,FALSE),0)=0,"-",IFERROR(VLOOKUP(C20,FA_2026!$F$10:$AT$65451,7,FALSE),0)) -> 26T | F20: =IF(IFERROR(VLOOKUP(C20,FA_2026!$F$10:$AT$65451,9,FALSE),0)=0,"-",IFERROR(VLOOKUP(C20,FA_2026!$F$10:$AT$65451,9,FALSE),0)) -> B 9980 SYM | G20: =IF(IFERROR(VLOOKUP(C20,FA_2026!$F$10:$AT$65451,10,FALSE),0)=0,"-",IFERROR(VLOOKUP(C20,FA_2026!$F$10:$AT$65451,10,FALSE),0)) -> - | H20: =IF(IFERROR(VLOOKUP(C20,FA_2026!$F$10:$AT$65451,11,FALSE),0)=0,"-",IFERROR(VLOOKUP(C20,FA_2026!$F$10:$AT$65451,11,FALSE),0)) -> - | I20: =IFERROR(INDEX(FA_2026!$B$10:$B$1159,MATCH('Disposal 2026'!C20,FA_2026!$F$10:$F$1159,0)),0) -> CLC | J20: =IFERROR(INDEX(FA_2026!$C$10:$C$1159,MATCH('Disposal 2026'!C20,FA_2026!$F$10:$F$1159,0)),0) -> CLCTRP | K20: =IF(IFERROR(VLOOKUP(C20,FA_2026!$F$10:$AT$65451,2,FALSE),0)=0,"-",IFERROR(VLOOKUP(C20,FA_2026!$F$10:$AT$65451,2,FALSE),0)) -> 42727 | L20: =IF(IFERROR(VLOOKUP(C20,'List Approval 2025'!$D$7:$M$65624,5,FALSE),0)=0,"-",IFERROR(VLOOKUP(C20,'List Approval 2025'!$D$7:$M$65624,5,FALSE),0)) -> - | M20: =IF(IFERROR(VLOOKUP(C20,FA_2026!$F$10:$AT$65451,14,FALSE),0)=0,"-",IFERROR(VLOOKUP(C20,FA_2026!$F$10:$AT$65451,14,FALSE),0)) -> 6.2931235e+08 | N20: =IF(IFERROR(VLOOKUP(C20,FA_2026!$F$10:$AT$65451,36,FALSE),0)=0,"-",IFERROR(VLOOKUP(C20,FA_2026!$F$10:$AT$65451,36,FALSE),0)) -> 6.2931235e+08 | O20: =ROUND(IFERROR(+M20-N20,0),0) -> 0 | P20: =IFERROR(VLOOKUP(C20,'List Approval 2026'!$D$7:$M$276,10,FALSE),0) -> 198198198 | Q20: =(IFERROR(IF(+P20-O20<0,"-",+P20-O20),0)) -> 198198198 | R20: =(IFERROR(IF(P20-O20>=0,"-",O20-P20),0)) -> - | U20: =IFERROR(VLOOKUP(C20,'List Approval 2026'!$D$7:$P$225,13,FALSE),"-") -> Citra Seraya Pratama
A21: =+A20+1 -> 13 | B21: =IF(IFERROR(VLOOKUP(C21,FA_2026!$F$10:$AT$65451,5,FALSE),0)=0,"-",IFERROR(VLOOKUP(C21,FA_2026!$F$10:$AT$65451,5,FALSE),0)) -> Head Tractor | C21: VEH000446 | D21: =IF(IFERROR(VLOOKUP(C21,FA_2026!$F$10:$AT$65451,6,FALSE),0)=0,"-",IFERROR(VLOOKUP(C21,FA_2026!$F$10:$AT$65451,6,FALSE),0)) -> HINO | E21: =IF(IFERROR(VLOOKUP(C21,FA_2026!$F$10:$AT$65451,7,FALSE),0)=0,"-",IFERROR(VLOOKUP(C21,FA_2026!$F$10:$AT$65451,7,FALSE),0)) -> 26T | F21: =IF(IFERROR(VLOOKUP(C21,FA_2026!$F$10:$AT$65451,9,FALSE),0)=0,"-",IFERROR(VLOOKUP(C21,FA_2026!$F$10:$AT$65451,9,FALSE),0)) -> B 9983 SYM | G21: =IF(IFERROR(VLOOKUP(C21,FA_2026!$F$10:$AT$65451,10,FALSE),0)=0,"-",IFERROR(VLOOKUP(C21,FA_2026!$F$10:$AT$65451,10,FALSE),0)) -> - | H21: =IF(IFERROR(VLOOKUP(C21,FA_2026!$F$10:$AT$65451,11,FALSE),0)=0,"-",IFERROR(VLOOKUP(C21,FA_2026!$F$10:$AT$65451,11,FALSE),0)) -> - | I21: =IFERROR(INDEX(FA_2026!$B$10:$B$1159,MATCH('Disposal 2026'!C21,FA_2026!$F$10:$F$1159,0)),0) -> CLC | J21: =IFERROR(INDEX(FA_2026!$C$10:$C$1159,MATCH('Disposal 2026'!C21,FA_2026!$F$10:$F$1159,0)),0) -> CLCTRP | K21: =IF(IFERROR(VLOOKUP(C21,FA_2026!$F$10:$AT$65451,2,FALSE),0)=0,"-",IFERROR(VLOOKUP(C21,FA_2026!$F$10:$AT$65451,2,FALSE),0)) -> 42727 | L21: =IF(IFERROR(VLOOKUP(C21,'List Approval 2025'!$D$7:$M$65624,5,FALSE),0)=0,"-",IFERROR(VLOOKUP(C21,'List Approval 2025'!$D$7:$M$65624,5,FALSE),0)) -> 1 | M21: =IF(IFERROR(VLOOKUP(C21,FA_2026!$F$10:$AT$65451,14,FALSE),0)=0,"-",IFERROR(VLOOKUP(C21,FA_2026!$F$10:$AT$65451,14,FALSE),0)) -> 6.2931235e+08 | N21: =IF(IFERROR(VLOOKUP(C21,FA_2026!$F$10:$AT$65451,36,FALSE),0)=0,"-",IFERROR(VLOOKUP(C21,FA_2026!$F$10:$AT$65451,36,FALSE),0)) -> 6.2931235e+08 | O21: =ROUND(IFERROR(+M21-N21,0),0) -> 0 | P21: =IFERROR(VLOOKUP(C21,'List Approval 2025'!$D$7:$M$277,10,FALSE),0) -> 162162162 | Q21: =(IFERROR(IF(+P21-O21<0,"-",+P21-O21),0)) -> 162162162 | R21: =(IFERROR(IF(P21-O21>=0,"-",O21-P21),0)) -> - | U21: =IFERROR(VLOOKUP(C21,'List Approval 2025'!$D$7:$P$226,13,FALSE),"-") -> CV. TIRTO KENCONO | V21: 2025
A22: =+A21+1 -> 14 | B22: =IF(IFERROR(VLOOKUP(C22,FA_2026!$F$10:$AT$65451,5,FALSE),0)=0,"-",IFERROR(VLOOKUP(C22,FA_2026!$F$10:$AT$65451,5,FALSE),0)) -> Forklift Sumitomo | C22: VEH000287 | D22: =IF(IFERROR(VLOOKUP(C22,FA_2026!$F$10:$AT$65451,6,FALSE),0)=0,"-",IFERROR(VLOOKUP(C22,FA_2026!$F$10:$AT$65451,6,FALSE),0)) -> Sumitomo | E22: =IF(IFERROR(VLOOKUP(C22,FA_2026!$F$10:$AT$65451,7,FALSE),0)=0,"-",IFERROR(VLOOKUP(C22,FA_2026!$F$10:$AT$65451,7,FALSE),0)) -> 1,5T | F22: =IF(IFERROR(VLOOKUP(C22,FA_2026!$F$10:$AT$65451,9,FALSE),0)=0,"-",IFERROR(VLOOKUP(C22,FA_2026!$F$10:$AT$65451,9,FALSE),0)) -> - | G22: =IF(IFERROR(VLOOKUP(C22,FA_2026!$F$10:$AT$65451,10,FALSE),0)=0,"-",IFERROR(VLOOKUP(C22,FA_2026!$F$10:$AT$65451,10,FALSE),0)) -> U2254 | H22: =IF(IFERROR(VLOOKUP(C22,FA_2026!$F$10:$AT$65451,11,FALSE),0)=0,"-",IFERROR(VLOOKUP(C22,FA_2026!$F$10:$AT$65451,11,FALSE),0)) -> R1H-4389 | I22: =IFERROR(INDEX(FA_2026!$B$10:$B$1159,MATCH('Disposal 2026'!C22,FA_2026!$F$10:$F$1159,0)),0) -> CLC | J22: =IFERROR(INDEX(FA_2026!$C$10:$C$1159,MATCH('Disposal 2026'!C22,FA_2026!$F$10:$F$1159,0)),0) -> CLCWH | K22: =IF(IFERROR(VLOOKUP(C22,FA_2026!$F$10:$AT$65451,2,FALSE),0)=0,"-",IFERROR(VLOOKUP(C22,FA_2026!$F$10:$AT$65451,2,FALSE),0)) -> 41715 | L22: =IF(IFERROR(VLOOKUP(C22,'List Approval 2025'!$D$7:$M$65624,5,FALSE),0)=0,"-",IFERROR(VLOOKUP(C22,'List Approval 2025'!$D$7:$M$65624,5,FALSE),0)) -> - | M22: =IF(IFERROR(VLOOKUP(C22,FA_2026!$F$10:$AT$65451,14,FALSE),0)=0,"-",IFERROR(VLOOKUP(C22,FA_2026!$F$10:$AT$65451,14,FALSE),0)) -> 253184243 | N22: =IF(IFERROR(VLOOKUP(C22,FA_2026!$F$10:$AT$65451,36,FALSE),0)=0,"-",IFERROR(VLOOKUP(C22,FA_2026!$F$10:$AT$65451,36,FALSE),0)) -> 253184243 | O22: =ROUND(IFERROR(+M22-N22,0),0) -> 0 | P22: =IFERROR(VLOOKUP(C22,'List Approval 2026'!$D$7:$M$276,10,FALSE),0) -> 15765766 | Q22: =(IFERROR(IF(+P22-O22<0,"-",+P22-O22),0)) -> 15765766 | R22: =(IFERROR(IF(P22-O22>=0,"-",O22-P22),0)) -> - | U22: =IFERROR(VLOOKUP(C22,'List Approval 2026'!$D$7:$P$225,13,FALSE),"-") -> Najwa Jaya
A23: =+A22+1 -> 15 | B23: =IF(IFERROR(VLOOKUP(C23,FA_2026!$F$10:$AT$65451,5,FALSE),0)=0,"-",IFERROR(VLOOKUP(C23,FA_2026!$F$10:$AT$65451,5,FALSE),0)) -> CCTV | C23: STR000057 | D23: =IF(IFERROR(VLOOKUP(C23,FA_2026!$F$10:$AT$65451,6,FALSE),0)=0,"-",IFERROR(VLOOKUP(C23,FA_2026!$F$10:$AT$65451,6,FALSE),0)) -> Sundara Putra Prima | E23: =IF(IFERROR(VLOOKUP(C23,FA_2026!$F$10:$AT$65451,7,FALSE),0)=0,"-",IFERROR(VLOOKUP(C23,FA_2026!$F$10:$AT$65451,7,FALSE),0)) -> Bojonegara | F23: =IF(IFERROR(VLOOKUP(C23,FA_2026!$F$10:$AT$65451,9,FALSE),0)=0,"-",IFERROR(VLOOKUP(C23,FA_2026!$F$10:$AT$65451,9,FALSE),0)) -> HIK Vision | G23: =IF(IFERROR(VLOOKUP(C23,FA_2026!$F$10:$AT$65451,10,FALSE),0)=0,"-",IFERROR(VLOOKUP(C23,FA_2026!$F$10:$AT$65451,10,FALSE),0)) -> - | H23: =IF(IFERROR(VLOOKUP(C23,FA_2026!$F$10:$AT$65451,11,FALSE),0)=0,"-",IFERROR(VLOOKUP(C23,FA_2026!$F$10:$AT$65451,11,FALSE),0)) -> - | I23: =IFERROR(INDEX(FA_2026!$B$10:$B$1159,MATCH('Disposal 2026'!C23,FA_2026!$F$10:$F$1159,0)),0) -> HCT | J23: =IFERROR(INDEX(FA_2026!$C$10:$C$1159,MATCH('Disposal 2026'!C23,FA_2026!$F$10:$F$1159,0)),0) -> D30 | K23: =IF(IFERROR(VLOOKUP(C23,FA_2026!$F$10:$AT$65451,2,FALSE),0)=0,"-",IFERROR(VLOOKUP(C23,FA_2026!$F$10:$AT$65451,2,FALSE),0)) -> 43998 | L23: =IF(IFERROR(VLOOKUP(C23,'List Approval 2025'!$D$7:$M$65624,5,FALSE),0)=0,"-",IFERROR(VLOOKUP(C23,'List Approval 2025'!$D$7:$M$65624,5,FALSE),0)) -> 1 | M23: =IF(IFERROR(VLOOKUP(C23,FA_2026!$F$10:$AT$65451,14,FALSE),0)=0,"-",IFERROR(VLOOKUP(C23,FA_2026!$F$10:$AT$65451,14,FALSE),0)) -> 73425000 | N23: =IF(IFERROR(VLOOKUP(C23,FA_2026!$F$10:$AT$65451,36,FALSE),0)=0,"-",IFERROR(VLOOKUP(C23,FA_2026!$F$10:$AT$65451,36,FALSE),0)) -> 73425000 | O23: =ROUND(IFERROR(+M23-N23,0),0) -> 0 | P23: =IFERROR(VLOOKUP(C23,'List Approval 2026'!$D$7:$M$276,10,FALSE),0) -> 0 | Q23: =(IFERROR(IF(+P23-O23<0,"-",+P23-O23),0)) -> 0 | R23: =(IFERROR(IF(P23-O23>=0,"-",O23-P23),0)) -> - | U23: =IFERROR(VLOOKUP(C23,'List Approval 2026'!$D$7:$P$225,13,FALSE),"-") -> SII
A24: =+A23+1 -> 16 | B24: =IF(IFERROR(VLOOKUP(C24,FA_2026!$F$10:$AT$65451,5,FALSE),0)=0,"-",IFERROR(VLOOKUP(C24,FA_2026!$F$10:$AT$65451,5,FALSE),0)) -> Bojonegara CCTV Camera System | C24: STR000061 | D24: =IF(IFERROR(VLOOKUP(C24,FA_2026!$F$10:$AT$65451,6,FALSE),0)=0,"-",IFERROR(VLOOKUP(C24,FA_2026!$F$10:$AT$65451,6,FALSE),0)) -> Tiga Putra Pandawa | E24: =IF(IFERROR(VLOOKUP(C24,FA_2026!$F$10:$AT$65451,7,FALSE),0)=0,"-",IFERROR(VLOOKUP(C24,FA_2026!$F$10:$AT$65451,7,FALSE),0)) -> - | F24: =IF(IFERROR(VLOOKUP(C24,FA_2026!$F$10:$AT$65451,9,FALSE),0)=0,"-",IFERROR(VLOOKUP(C24,FA_2026!$F$10:$AT$65451,9,FALSE),0)) -> 14 MP | G24: =IF(IFERROR(VLOOKUP(C24,FA_2026!$F$10:$AT$65451,10,FALSE),0)=0,"-",IFERROR(VLOOKUP(C24,FA_2026!$F$10:$AT$65451,10,FALSE),0)) -> 14 MP | H24: =IF(IFERROR(VLOOKUP(C24,FA_2026!$F$10:$AT$65451,11,FALSE),0)=0,"-",IFERROR(VLOOKUP(C24,FA_2026!$F$10:$AT$65451,11,FALSE),0)) -> 14 MP | I24: =IFERROR(INDEX(FA_2026!$B$10:$B$1159,MATCH('Disposal 2026'!C24,FA_2026!$F$10:$F$1159,0)),0) -> CLGC | J24: =IFERROR(INDEX(FA_2026!$C$10:$C$1159,MATCH('Disposal 2026'!C24,FA_2026!$F$10:$F$1159,0)),0) -> D30 | K24: =IF(IFERROR(VLOOKUP(C24,FA_2026!$F$10:$AT$65451,2,FALSE),0)=0,"-",IFERROR(VLOOKUP(C24,FA_2026!$F$10:$AT$65451,2,FALSE),0)) -> 44195 | L24: =IF(IFERROR(VLOOKUP(C24,'List Approval 2025'!$D$7:$M$65624,5,FALSE),0)=0,"-",IFERROR(VLOOKUP(C24,'List Approval 2025'!$D$7:$M$65624,5,FALSE),0)) -> - | M24: =IF(IFERROR(VLOOKUP(C24,FA_2026!$F$10:$AT$65451,14,FALSE),0)=0,"-",IFERROR(VLOOKUP(C24,FA_2026!$F$10:$AT$65451,14,FALSE),0)) -> 116000000 | N24: =IF(IFERROR(VLOOKUP(C24,FA_2026!$F$10:$AT$65451,36,FALSE),0)=0,"-",IFERROR(VLOOKUP(C24,FA_2026!$F$10:$AT$65451,36,FALSE),0)) -> 1.16e+08 | O24: =ROUND(IFERROR(+M24-N24,0),0) -> 0 | P24: =IFERROR(VLOOKUP(C24,'List Approval 2026'!$D$7:$M$276,10,FALSE),0) -> 0 | Q24: =(IFERROR(IF(+P24-O24<0,"-",+P24-O24),0)) -> 0 | R24: =(IFERROR(IF(P24-O24>=0,"-",O24-P24),0)) -> - | U24: =IFERROR(VLOOKUP(C24,'List Approval 2026'!$D$7:$P$225,13,FALSE),"-") -> 0
A25: =+A24+1 -> 17 | B25: =IF(IFERROR(VLOOKUP(C25,FA_2026!$F$10:$AT$65451,5,FALSE),0)=0,"-",IFERROR(VLOOKUP(C25,FA_2026!$F$10:$AT$65451,5,FALSE),0)) -> Avanza Veloz A/T | C25: VEH000550 | D25: =IF(IFERROR(VLOOKUP(C25,FA_2026!$F$10:$AT$65451,6,FALSE),0)=0,"-",IFERROR(VLOOKUP(C25,FA_2026!$F$10:$AT$65451,6,FALSE),0)) -> Tunas Ridean | E25: =IF(IFERROR(VLOOKUP(C25,FA_2026!$F$10:$AT$65451,7,FALSE),0)=0,"-",IFERROR(VLOOKUP(C25,FA_2026!$F$10:$AT$65451,7,FALSE),0)) -> Cilegon Admin | F25: =IF(IFERROR(VLOOKUP(C25,FA_2026!$F$10:$AT$65451,9,FALSE),0)=0,"-",IFERROR(VLOOKUP(C25,FA_2026!$F$10:$AT$65451,9,FALSE),0)) -> A 1417 RG | G25: =IF(IFERROR(VLOOKUP(C25,FA_2026!$F$10:$AT$65451,10,FALSE),0)=0,"-",IFERROR(VLOOKUP(C25,FA_2026!$F$10:$AT$65451,10,FALSE),0)) -> 1 NR G012568 | H25: =IF(IFERROR(VLOOKUP(C25,FA_2026!$F$10:$AT$65451,11,FALSE),0)=0,"-",IFERROR(VLOOKUP(C25,FA_2026!$F$10:$AT$65451,11,FALSE),0)) -> MHKM5EB4JKK011440 | I25: =IFERROR(INDEX(FA_2026!$B$10:$B$1159,MATCH('Disposal 2026'!C25,FA_2026!$F$10:$F$1159,0)),0) -> CLGA | J25: =IFERROR(INDEX(FA_2026!$C$10:$C$1159,MATCH('Disposal 2026'!C25,FA_2026!$F$10:$F$1159,0)),0) -> AD_CGADM | K25: =IF(IFERROR(VLOOKUP(C25,FA_2026!$F$10:$AT$65451,2,FALSE),0)=0,"-",IFERROR(VLOOKUP(C25,FA_2026!$F$10:$AT$65451,2,FALSE),0)) -> 43614 | L25: =IF(IFERROR(VLOOKUP(C25,'List Approval 2025'!$D$7:$M$65624,5,FALSE),0)=0,"-",IFERROR(VLOOKUP(C25,'List Approval 2025'!$D$7:$M$65624,5,FALSE),0)) -> - | M25: =IF(IFERROR(VLOOKUP(C25,FA_2026!$F$10:$AT$65451,14,FALSE),0)=0,"-",IFERROR(VLOOKUP(C25,FA_2026!$F$10:$AT$65451,14,FALSE),0)) -> 210725114 | N25: =IF(IFERROR(VLOOKUP(C25,FA_2026!$F$10:$AT$65451,36,FALSE),0)=0,"-",IFERROR(VLOOKUP(C25,FA_2026!$F$10:$AT$65451,36,FALSE),0)) -> 2.1072511e+08 | O25: =ROUND(IFERROR(+M25-N25,0),0) -> 0 | P25: =IFERROR(VLOOKUP(C25,'List Approval 2026'!$D$7:$M$276,10,FALSE),0) -> 31531532 | Q25: =(IFERROR(IF(+P25-O25<0,"-",+P25-O25),0)) -> 31531532 | R25: =(IFERROR(IF(P25-O25>=0,"-",O25-P25),0)) -> - | U25: =IFERROR(VLOOKUP(C25,'List Approval 2026'!$D$7:$P$225,13,FALSE),"-") -> Fajar Hikmah
A26: =+A25+1 -> 18 | B26: =IF(IFERROR(VLOOKUP(C26,FA_2026!$F$10:$AT$65451,5,FALSE),0)=0,"-",IFERROR(VLOOKUP(C26,FA_2026!$F$10:$AT$65451,5,FALSE),0)) -> Computer | C26: FNF000109 | D26: =IF(IFERROR(VLOOKUP(C26,FA_2026!$F$10:$AT$65451,6,FALSE),0)=0,"-",IFERROR(VLOOKUP(C26,FA_2026!$F$10:$AT$65451,6,FALSE),0)) -> Sony SVF15N1A1J | E26: =IF(IFERROR(VLOOKUP(C26,FA_2026!$F$10:$AT$65451,7,FALSE),0)=0,"-",IFERROR(VLOOKUP(C26,FA_2026!$F$10:$AT$65451,7,FALSE),0)) -> Mr, Tomita | F26: =IF(IFERROR(VLOOKUP(C26,FA_2026!$F$10:$AT$65451,9,FALSE),0)=0,"-",IFERROR(VLOOKUP(C26,FA_2026!$F$10:$AT$65451,9,FALSE),0)) -> - | G26: =IF(IFERROR(VLOOKUP(C26,FA_2026!$F$10:$AT$65451,10,FALSE),0)=0,"-",IFERROR(VLOOKUP(C26,FA_2026!$F$10:$AT$65451,10,FALSE),0)) -> - | H26: =IF(IFERROR(VLOOKUP(C26,FA_2026!$F$10:$AT$65451,11,FALSE),0)=0,"-",IFERROR(VLOOKUP(C26,FA_2026!$F$10:$AT$65451,11,FALSE),0)) -> - | I26: =IFERROR(INDEX(FA_2026!$B$10:$B$1159,MATCH('Disposal 2026'!C26,FA_2026!$F$10:$F$1159,0)),0) -> JPO | J26: =IFERROR(INDEX(FA_2026!$C$10:$C$1159,MATCH('Disposal 2026'!C26,FA_2026!$F$10:$F$1159,0)),0) -> PJT14 | K26: =IF(IFERROR(VLOOKUP(C26,FA_2026!$F$10:$AT$65451,2,FALSE),0)=0,"-",IFERROR(VLOOKUP(C26,FA_2026!$F$10:$AT$65451,2,FALSE),0)) -> 41667 | L26: =IF(IFERROR(VLOOKUP(C26,'List Approval 2025'!$D$7:$M$65624,5,FALSE),0)=0,"-",IFERROR(VLOOKUP(C26,'List Approval 2025'!$D$7:$M$65624,5,FALSE),0)) -> - | M26: =IF(IFERROR(VLOOKUP(C26,FA_2026!$F$10:$AT$65451,14,FALSE),0)=0,"-",IFERROR(VLOOKUP(C26,FA_2026!$F$10:$AT$65451,14,FALSE),0)) -> 31094062 | N26: =IF(IFERROR(VLOOKUP(C26,FA_2026!$F$10:$AT$65451,36,FALSE),0)=0,"-",IFERROR(VLOOKUP(C26,FA_2026!$F$10:$AT$65451,36,FALSE),0)) -> 31094062 | O26: =ROUND(IFERROR(+M26-N26,0),0) -> 0 | P26: =IFERROR(VLOOKUP(C26,'List Approval 2026'!$D$7:$M$276,10,FALSE),0) -> 0 | Q26: =(IFERROR(IF(+P26-O26<0,"-",+P26-O26),0)) -> 0 | R26: =(IFERROR(IF(P26-O26>=0,"-",O26-P26),0)) -> - | U26: =IFERROR(VLOOKUP(C26,'List Approval 2026'!$D$7:$P$225,13,FALSE),"-") -> 0
A27: =+A26+1 -> 19 | B27: =IF(IFERROR(VLOOKUP(C27,FA_2026!$F$10:$AT$65451,5,FALSE),0)=0,"-",IFERROR(VLOOKUP(C27,FA_2026!$F$10:$AT$65451,5,FALSE),0)) -> Tractor Head | C27: VEH000430 | D27: =IF(IFERROR(VLOOKUP(C27,FA_2026!$F$10:$AT$65451,6,FALSE),0)=0,"-",IFERROR(VLOOKUP(C27,FA_2026!$F$10:$AT$65451,6,FALSE),0)) -> Nissan | E27: =IF(IFERROR(VLOOKUP(C27,FA_2026!$F$10:$AT$65451,7,FALSE),0)=0,"-",IFERROR(VLOOKUP(C27,FA_2026!$F$10:$AT$65451,7,FALSE),0)) -> 370HP | F27: =IF(IFERROR(VLOOKUP(C27,FA_2026!$F$10:$AT$65451,9,FALSE),0)=0,"-",IFERROR(VLOOKUP(C27,FA_2026!$F$10:$AT$65451,9,FALSE),0)) -> A 9167 TY | G27: =IF(IFERROR(VLOOKUP(C27,FA_2026!$F$10:$AT$65451,10,FALSE),0)=0,"-",IFERROR(VLOOKUP(C27,FA_2026!$F$10:$AT$65451,10,FALSE),0)) -> GH11371455A2L | H27: =IF(IFERROR(VLOOKUP(C27,FA_2026!$F$10:$AT$65451,11,FALSE),0)=0,"-",IFERROR(VLOOKUP(C27,FA_2026!$F$10:$AT$65451,11,FALSE),0)) -> JPCZM3OD6GT013165 | I27: =IFERROR(INDEX(FA_2026!$B$10:$B$1159,MATCH('Disposal 2026'!C27,FA_2026!$F$10:$F$1159,0)),0) -> KOS | J27: =IFERROR(INDEX(FA_2026!$C$10:$C$1159,MATCH('Disposal 2026'!C27,FA_2026!$F$10:$F$1159,0)),0) -> 3KO | K27: =IF(IFERROR(VLOOKUP(C27,FA_2026!$F$10:$AT$65451,2,FALSE),0)=0,"-",IFERROR(VLOOKUP(C27,FA_2026!$F$10:$AT$65451,2,FALSE),0)) -> 42654 | L27: =IF(IFERROR(VLOOKUP(C27,'List Approval 2025'!$D$7:$M$65624,5,FALSE),0)=0,"-",IFERROR(VLOOKUP(C27,'List Approval 2025'!$D$7:$M$65624,5,FALSE),0)) -> - | M27: =IF(IFERROR(VLOOKUP(C27,FA_2026!$F$10:$AT$65451,14,FALSE),0)=0,"-",IFERROR(VLOOKUP(C27,FA_2026!$F$10:$AT$65451,14,FALSE),0)) -> 945000000 | N27: =IF(IFERROR(VLOOKUP(C27,FA_2026!$F$10:$AT$65451,36,FALSE),0)=0,"-",IFERROR(VLOOKUP(C27,FA_2026!$F$10:$AT$65451,36,FALSE),0)) -> 945000000 | O27: =ROUND(IFERROR(+M27-N27,0),0) -> 0 | P27: =IFERROR(VLOOKUP(C27,'List Approval 2026'!$D$7:$M$276,10,FALSE),0) -> 175675676 | Q27: =(IFERROR(IF(+P27-O27<0,"-",+P27-O27),0)) -> 175675676 | R27: =(IFERROR(IF(P27-O27>=0,"-",O27-P27),0)) -> - | U27: =IFERROR(VLOOKUP(C27,'List Approval 2026'!$D$7:$P$225,13,FALSE),"-") -> Cahaya Said
A28: =+A27+1 -> 20 | B28: =IF(IFERROR(VLOOKUP(C28,FA_2026!$F$10:$AT$65451,5,FALSE),0)=0,"-",IFERROR(VLOOKUP(C28,FA_2026!$F$10:$AT$65451,5,FALSE),0)) -> Dumptruck | C28: VEH000432 | D28: =IF(IFERROR(VLOOKUP(C28,FA_2026!$F$10:$AT$65451,6,FALSE),0)=0,"-",IFERROR(VLOOKUP(C28,FA_2026!$F$10:$AT$65451,6,FALSE),0)) -> Mitsubishi | E28: =IF(IFERROR(VLOOKUP(C28,FA_2026!$F$10:$AT$65451,7,FALSE),0)=0,"-",IFERROR(VLOOKUP(C28,FA_2026!$F$10:$AT$65451,7,FALSE),0)) -> 10T | F28: =IF(IFERROR(VLOOKUP(C28,FA_2026!$F$10:$AT$65451,9,FALSE),0)=0,"-",IFERROR(VLOOKUP(C28,FA_2026!$F$10:$AT$65451,9,FALSE),0)) -> A 9150 TY | G28: =IF(IFERROR(VLOOKUP(C28,FA_2026!$F$10:$AT$65451,10,FALSE),0)=0,"-",IFERROR(VLOOKUP(C28,FA_2026!$F$10:$AT$65451,10,FALSE),0)) -> 6D16-P29916 | H28: =IF(IFERROR(VLOOKUP(C28,FA_2026!$F$10:$AT$65451,11,FALSE),0)=0,"-",IFERROR(VLOOKUP(C28,FA_2026!$F$10:$AT$65451,11,FALSE),0)) -> MHMFM517AGK010908 | I28: =IFERROR(INDEX(FA_2026!$B$10:$B$1159,MATCH('Disposal 2026'!C28,FA_2026!$F$10:$F$1159,0)),0) -> KOS | J28: =IFERROR(INDEX(FA_2026!$C$10:$C$1159,MATCH('Disposal 2026'!C28,FA_2026!$F$10:$F$1159,0)),0) -> 3KO | K28: =IF(IFERROR(VLOOKUP(C28,FA_2026!$F$10:$AT$65451,2,FALSE),0)=0,"-",IFERROR(VLOOKUP(C28,FA_2026!$F$10:$AT$65451,2,FALSE),0)) -> 42682 | L28: =IF(IFERROR(VLOOKUP(C28,'List Approval 2025'!$D$7:$M$65624,5,FALSE),0)=0,"-",IFERROR(VLOOKUP(C28,'List Approval 2025'!$D$7:$M$65624,5,FALSE),0)) -> - | M28: =IF(IFERROR(VLOOKUP(C28,FA_2026!$F$10:$AT$65451,14,FALSE),0)=0,"-",IFERROR(VLOOKUP(C28,FA_2026!$F$10:$AT$65451,14,FALSE),0)) -> 545815545 | N28: =IF(IFERROR(VLOOKUP(C28,FA_2026!$F$10:$AT$65451,36,FALSE),0)=0,"-",IFERROR(VLOOKUP(C28,FA_2026!$F$10:$AT$65451,36,FALSE),0)) -> 545815545 | O28: =ROUND(IFERROR(+M28-N28,0),0) -> 0 | P28: =IFERROR(VLOOKUP(C28,'List Approval 2026'!$D$7:$M$276,10,FALSE),0) -> 45045045 | Q28: =(IFERROR(IF(+P28-O28<0,"-",+P28-O28),0)) -> 45045045 | R28: =(IFERROR(IF(P28-O28>=0,"-",O28-P28),0)) -> - | U28: =IFERROR(VLOOKUP(C28,'List Approval 2026'!$D$7:$P$225,13,FALSE),"-") -> Cahaya Said
A29: =+A28+1 -> 21 | B29: =IF(IFERROR(VLOOKUP(C29,FA_2026!$F$10:$AT$65451,5,FALSE),0)=0,"-",IFERROR(VLOOKUP(C29,FA_2026!$F$10:$AT$65451,5,FALSE),0)) -> Chassis High Bed | C29: VEH000437 | D29: =IF(IFERROR(VLOOKUP(C29,FA_2026!$F$10:$AT$65451,6,FALSE),0)=0,"-",IFERROR(VLOOKUP(C29,FA_2026!$F$10:$AT$65451,6,FALSE),0)) -> Simojoyo | E29: =IF(IFERROR(VLOOKUP(C29,FA_2026!$F$10:$AT$65451,7,FALSE),0)=0,"-",IFERROR(VLOOKUP(C29,FA_2026!$F$10:$AT$65451,7,FALSE),0)) -> 40 feet; 3 axcle | F29: =IF(IFERROR(VLOOKUP(C29,FA_2026!$F$10:$AT$65451,9,FALSE),0)=0,"-",IFERROR(VLOOKUP(C29,FA_2026!$F$10:$AT$65451,9,FALSE),0)) -> A 9167 TY | G29: =IF(IFERROR(VLOOKUP(C29,FA_2026!$F$10:$AT$65451,10,FALSE),0)=0,"-",IFERROR(VLOOKUP(C29,FA_2026!$F$10:$AT$65451,10,FALSE),0)) -> - | H29: =IF(IFERROR(VLOOKUP(C29,FA_2026!$F$10:$AT$65451,11,FALSE),0)=0,"-",IFERROR(VLOOKUP(C29,FA_2026!$F$10:$AT$65451,11,FALSE),0)) -> SJE-40-1569 | I29: =IFERROR(INDEX(FA_2026!$B$10:$B$1159,MATCH('Disposal 2026'!C29,FA_2026!$F$10:$F$1159,0)),0) -> KOS | J29: =IFERROR(INDEX(FA_2026!$C$10:$C$1159,MATCH('Disposal 2026'!C29,FA_2026!$F$10:$F$1159,0)),0) -> 3KO | K29: =IF(IFERROR(VLOOKUP(C29,FA_2026!$F$10:$AT$65451,2,FALSE),0)=0,"-",IFERROR(VLOOKUP(C29,FA_2026!$F$10:$AT$65451,2,FALSE),0)) -> 42705 | L29: =IF(IFERROR(VLOOKUP(C29,'List Approval 2025'!$D$7:$M$65624,5,FALSE),0)=0,"-",IFERROR(VLOOKUP(C29,'List Approval 2025'!$D$7:$M$65624,5,FALSE),0)) -> - | M29: =IF(IFERROR(VLOOKUP(C29,FA_2026!$F$10:$AT$65451,14,FALSE),0)=0,"-",IFERROR(VLOOKUP(C29,FA_2026!$F$10:$AT$65451,14,FALSE),0)) -> 327000000 | N29: =IF(IFERROR(VLOOKUP(C29,FA_2026!$F$10:$AT$65451,36,FALSE),0)=0,"-",IFERROR(VLOOKUP(C29,FA_2026!$F$10:$AT$65451,36,FALSE),0)) -> 327000000 | O29: =ROUND(IFERROR(+M29-N29,0),0) -> 0 | P29: =IFERROR(VLOOKUP(C29,'List Approval 2026'!$D$7:$M$276,10,FALSE),0) -> 45045045 | Q29: =(IFERROR(IF(+P29-O29<0,"-",+P29-O29),0)) -> 45045045 | R29: =(IFERROR(IF(P29-O29>=0,"-",O29-P29),0)) -> - | U29: =IFERROR(VLOOKUP(C29,'List Approval 2026'!$D$7:$P$225,13,FALSE),"-") -> Cahaya Said
A30: =+A29+1 -> 22 | B30: =IF(IFERROR(VLOOKUP(C30,FA_2026!$F$10:$AT$65451,5,FALSE),0)=0,"-",IFERROR(VLOOKUP(C30,FA_2026!$F$10:$AT$65451,5,FALSE),0)) -> Alphard | C30: VEH000460 | D30: =IF(IFERROR(VLOOKUP(C30,FA_2026!$F$10:$AT$65451,6,FALSE),0)=0,"-",IFERROR(VLOOKUP(C30,FA_2026!$F$10:$AT$65451,6,FALSE),0)) -> Toyota | E30: =IF(IFERROR(VLOOKUP(C30,FA_2026!$F$10:$AT$65451,7,FALSE),0)=0,"-",IFERROR(VLOOKUP(C30,FA_2026!$F$10:$AT$65451,7,FALSE),0)) -> Mr, Harada | F30: =IF(IFERROR(VLOOKUP(C30,FA_2026!$F$10:$AT$65451,9,FALSE),0)=0,"-",IFERROR(VLOOKUP(C30,FA_2026!$F$10:$AT$65451,9,FALSE),0)) -> B 1487 FZK | G30: =IF(IFERROR(VLOOKUP(C30,FA_2026!$F$10:$AT$65451,10,FALSE),0)=0,"-",IFERROR(VLOOKUP(C30,FA_2026!$F$10:$AT$65451,10,FALSE),0)) -> 2AR-H854704 | H30: =IF(IFERROR(VLOOKUP(C30,FA_2026!$F$10:$AT$65451,11,FALSE),0)=0,"-",IFERROR(VLOOKUP(C30,FA_2026!$F$10:$AT$65451,11,FALSE),0)) -> JTNGF3DH6H8008501 | I30: =IFERROR(INDEX(FA_2026!$B$10:$B$1159,MATCH('Disposal 2026'!C30,FA_2026!$F$10:$F$1159,0)),0) -> CKR | J30: =IFERROR(INDEX(FA_2026!$C$10:$C$1159,MATCH('Disposal 2026'!C30,FA_2026!$F$10:$F$1159,0)),0) -> AD_HO | K30: =IF(IFERROR(VLOOKUP(C30,FA_2026!$F$10:$AT$65451,2,FALSE),0)=0,"-",IFERROR(VLOOKUP(C30,FA_2026!$F$10:$AT$65451,2,FALSE),0)) -> 42817 | L30: =IF(IFERROR(VLOOKUP(C30,'List Approval 2025'!$D$7:$M$65624,5,FALSE),0)=0,"-",IFERROR(VLOOKUP(C30,'List Approval 2025'!$D$7:$M$65624,5,FALSE),0)) -> - | M30: =IF(IFERROR(VLOOKUP(C30,FA_2026!$F$10:$AT$65451,14,FALSE),0)=0,"-",IFERROR(VLOOKUP(C30,FA_2026!$F$10:$AT$65451,14,FALSE),0)) -> 935705545 | N30: =IF(IFERROR(VLOOKUP(C30,FA_2026!$F$10:$AT$65451,36,FALSE),0)=0,"-",IFERROR(VLOOKUP(C30,FA_2026!$F$10:$AT$65451,36,FALSE),0)) -> 935705545 | O30: =ROUND(IFERROR(+M30-N30,0),0) -> 0 | P30: =IFERROR(VLOOKUP(C30,'List Approval 2026'!$D$7:$M$276,10,FALSE),0) -> 216216216 | Q30: =(IFERROR(IF(+P30-O30<0,"-",+P30-O30),0)) -> 216216216 | R30: =(IFERROR(IF(P30-O30>=0,"-",O30-P30),0)) -> - | U30: =IFERROR(VLOOKUP(C30,'List Approval 2026'!$D$7:$P$225,13,FALSE),"-") -> Biru Revorma Indonesia
A31: =+A30+1 -> 23 | B31: =IF(IFERROR(VLOOKUP(C31,FA_2026!$F$10:$AT$65451,5,FALSE),0)=0,"-",IFERROR(VLOOKUP(C31,FA_2026!$F$10:$AT$65451,5,FALSE),0)) -> Dumptruck | C31: VEH000476 | D31: =IF(IFERROR(VLOOKUP(C31,FA_2026!$F$10:$AT$65451,6,FALSE),0)=0,"-",IFERROR(VLOOKUP(C31,FA_2026!$F$10:$AT$65451,6,FALSE),0)) -> Setia Kawan Motor | E31: =IF(IFERROR(VLOOKUP(C31,FA_2026!$F$10:$AT$65451,7,FALSE),0)=0,"-",IFERROR(VLOOKUP(C31,FA_2026!$F$10:$AT$65451,7,FALSE),0)) -> - | F31: =IF(IFERROR(VLOOKUP(C31,FA_2026!$F$10:$AT$65451,9,FALSE),0)=0,"-",IFERROR(VLOOKUP(C31,FA_2026!$F$10:$AT$65451,9,FALSE),0)) -> A 9035 S | G31: =IF(IFERROR(VLOOKUP(C31,FA_2026!$F$10:$AT$65451,10,FALSE),0)=0,"-",IFERROR(VLOOKUP(C31,FA_2026!$F$10:$AT$65451,10,FALSE),0)) -> 6016-1284442 | H31: =IF(IFERROR(VLOOKUP(C31,FA_2026!$F$10:$AT$65451,11,FALSE),0)=0,"-",IFERROR(VLOOKUP(C31,FA_2026!$F$10:$AT$65451,11,FALSE),0)) -> MHMFM517AHK011869 | I31: =IFERROR(INDEX(FA_2026!$B$10:$B$1159,MATCH('Disposal 2026'!C31,FA_2026!$F$10:$F$1159,0)),0) -> KOS | J31: =IFERROR(INDEX(FA_2026!$C$10:$C$1159,MATCH('Disposal 2026'!C31,FA_2026!$F$10:$F$1159,0)),0) -> 3KO | K31: =IF(IFERROR(VLOOKUP(C31,FA_2026!$F$10:$AT$65451,2,FALSE),0)=0,"-",IFERROR(VLOOKUP(C31,FA_2026!$F$10:$AT$65451,2,FALSE),0)) -> 43039 | L31: =IF(IFERROR(VLOOKUP(C31,'List Approval 2025'!$D$7:$M$65624,5,FALSE),0)=0,"-",IFERROR(VLOOKUP(C31,'List Approval 2025'!$D$7:$M$65624,5,FALSE),0)) -> - | M31: =IF(IFERROR(VLOOKUP(C31,FA_2026!$F$10:$AT$65451,14,FALSE),0)=0,"-",IFERROR(VLOOKUP(C31,FA_2026!$F$10:$AT$65451,14,FALSE),0)) -> 567113655 | N31: =IF(IFERROR(VLOOKUP(C31,FA_2026!$F$10:$AT$65451,36,FALSE),0)=0,"-",IFERROR(VLOOKUP(C31,FA_2026!$F$10:$AT$65451,36,FALSE),0)) -> 567113655 | O31: =ROUND(IFERROR(+M31-N31,0),0) -> 0 | P31: =IFERROR(VLOOKUP(C31,'List Approval 2026'!$D$7:$M$276,10,FALSE),0) -> 90090090 | Q31: =(IFERROR(IF(+P31-O31<0,"-",+P31-O31),0)) -> 90090090 | R31: =(IFERROR(IF(P31-O31>=0,"-",O31-P31),0)) -> - | U31: =IFERROR(VLOOKUP(C31,'List Approval 2026'!$D$7:$P$225,13,FALSE),"-") -> Cahaya Said
A32: =+A31+1 -> 24 | B32: =IF(IFERROR(VLOOKUP(C32,FA_2026!$F$10:$AT$65451,5,FALSE),0)=0,"-",IFERROR(VLOOKUP(C32,FA_2026!$F$10:$AT$65451,5,FALSE),0)) -> Avanza Toyota 1.3 G M/T | C32: VEH000503 | D32: =IF(IFERROR(VLOOKUP(C32,FA_2026!$F$10:$AT$65451,6,FALSE),0)=0,"-",IFERROR(VLOOKUP(C32,FA_2026!$F$10:$AT$65451,6,FALSE),0)) -> Tunas Ridean | E32: =IF(IFERROR(VLOOKUP(C32,FA_2026!$F$10:$AT$65451,7,FALSE),0)=0,"-",IFERROR(VLOOKUP(C32,FA_2026!$F$10:$AT$65451,7,FALSE),0)) -> - | F32: =IF(IFERROR(VLOOKUP(C32,FA_2026!$F$10:$AT$65451,9,FALSE),0)=0,"-",IFERROR(VLOOKUP(C32,FA_2026!$F$10:$AT$65451,9,FALSE),0)) -> A 1341 RC | G32: =IF(IFERROR(VLOOKUP(C32,FA_2026!$F$10:$AT$65451,10,FALSE),0)=0,"-",IFERROR(VLOOKUP(C32,FA_2026!$F$10:$AT$65451,10,FALSE),0)) -> 1NRF386675 | H32: =IF(IFERROR(VLOOKUP(C32,FA_2026!$F$10:$AT$65451,11,FALSE),0)=0,"-",IFERROR(VLOOKUP(C32,FA_2026!$F$10:$AT$65451,11,FALSE),0)) -> MHKM5EA3JJK099233 | I32: =IFERROR(INDEX(FA_2026!$B$10:$B$1159,MATCH('Disposal 2026'!C32,FA_2026!$F$10:$F$1159,0)),0) -> HCT | J32: =IFERROR(INDEX(FA_2026!$C$10:$C$1159,MATCH('Disposal 2026'!C32,FA_2026!$F$10:$F$1159,0)),0) -> D30 | K32: =IF(IFERROR(VLOOKUP(C32,FA_2026!$F$10:$AT$65451,2,FALSE),0)=0,"-",IFERROR(VLOOKUP(C32,FA_2026!$F$10:$AT$65451,2,FALSE),0)) -> 43192 | L32: =IF(IFERROR(VLOOKUP(C32,'List Approval 2025'!$D$7:$M$65624,5,FALSE),0)=0,"-",IFERROR(VLOOKUP(C32,'List Approval 2025'!$D$7:$M$65624,5,FALSE),0)) -> 1 | M32: =IF(IFERROR(VLOOKUP(C32,FA_2026!$F$10:$AT$65451,14,FALSE),0)=0,"-",IFERROR(VLOOKUP(C32,FA_2026!$F$10:$AT$65451,14,FALSE),0)) -> 179874182 | N32: =IF(IFERROR(VLOOKUP(C32,FA_2026!$F$10:$AT$65451,36,FALSE),0)=0,"-",IFERROR(VLOOKUP(C32,FA_2026!$F$10:$AT$65451,36,FALSE),0)) -> 1.7987418e+08 | O32: =ROUND(IFERROR(+M32-N32,0),0) -> 0 | P32: =IFERROR(VLOOKUP(C32,'List Approval 2026'!$D$7:$M$276,10,FALSE),0) -> 90090090 | Q32: =(IFERROR(IF(+P32-O32<0,"-",+P32-O32),0)) -> 90090090 | R32: =(IFERROR(IF(P32-O32>=0,"-",O32-P32),0)) -> - | U32: =IFERROR(VLOOKUP(C32,'List Approval 2026'!$D$7:$P$225,13,FALSE),"-") -> Cahaya Said
A33: =+A32+1 -> 25 | B33: =IF(IFERROR(VLOOKUP(C33,FA_2026!$F$10:$AT$65451,5,FALSE),0)=0,"-",IFERROR(VLOOKUP(C33,FA_2026!$F$10:$AT$65451,5,FALSE),0)) -> Forklift Toyota | C33: VEH000331 | D33: =IF(IFERROR(VLOOKUP(C33,FA_2026!$F$10:$AT$65451,6,FALSE),0)=0,"-",IFERROR(VLOOKUP(C33,FA_2026!$F$10:$AT$65451,6,FALSE),0)) -> Toyota | E33: =IF(IFERROR(VLOOKUP(C33,FA_2026!$F$10:$AT$65451,7,FALSE),0)=0,"-",IFERROR(VLOOKUP(C33,FA_2026!$F$10:$AT$65451,7,FALSE),0)) -> 2,5T | F33: =IF(IFERROR(VLOOKUP(C33,FA_2026!$F$10:$AT$65451,9,FALSE),0)=0,"-",IFERROR(VLOOKUP(C33,FA_2026!$F$10:$AT$65451,9,FALSE),0)) -> 62-8FD25-48170 | G33: =IF(IFERROR(VLOOKUP(C33,FA_2026!$F$10:$AT$65451,10,FALSE),0)=0,"-",IFERROR(VLOOKUP(C33,FA_2026!$F$10:$AT$65451,10,FALSE),0)) -> 1DZ-0292281 | H33: =IF(IFERROR(VLOOKUP(C33,FA_2026!$F$10:$AT$65451,11,FALSE),0)=0,"-",IFERROR(VLOOKUP(C33,FA_2026!$F$10:$AT$65451,11,FALSE),0)) -> 62-8FD25-48170 | I33: =IFERROR(INDEX(FA_2026!$B$10:$B$1159,MATCH('Disposal 2026'!C33,FA_2026!$F$10:$F$1159,0)),0) -> SMI | J33: =IFERROR(INDEX(FA_2026!$C$10:$C$1159,MATCH('Disposal 2026'!C33,FA_2026!$F$10:$F$1159,0)),0) -> 3SM | K33: =IF(IFERROR(VLOOKUP(C33,FA_2026!$F$10:$AT$65451,2,FALSE),0)=0,"-",IFERROR(VLOOKUP(C33,FA_2026!$F$10:$AT$65451,2,FALSE),0)) -> 41996 | L33: =IF(IFERROR(VLOOKUP(C33,'List Approval 2025'!$D$7:$M$65624,5,FALSE),0)=0,"-",IFERROR(VLOOKUP(C33,'List Approval 2025'!$D$7:$M$65624,5,FALSE),0)) -> - | M33: =IF(IFERROR(VLOOKUP(C33,FA_2026!$F$10:$AT$65451,14,FALSE),0)=0,"-",IFERROR(VLOOKUP(C33,FA_2026!$F$10:$AT$65451,14,FALSE),0)) -> 400721400 | N33: =IF(IFERROR(VLOOKUP(C33,FA_2026!$F$10:$AT$65451,36,FALSE),0)=0,"-",IFERROR(VLOOKUP(C33,FA_2026!$F$10:$AT$65451,36,FALSE),0)) -> 400721400 | O33: =ROUND(IFERROR(+M33-N33,0),0) -> 0 | P33: =IFERROR(VLOOKUP(C33,'List Approval 2026'!$D$7:$M$276,10,FALSE),0) -> 31531532 | Q33: =(IFERROR(IF(+P33-O33<0,"-",+P33-O33),0)) -> 31531532 | R33: =(IFERROR(IF(P33-O33>=0,"-",O33-P33),0)) -> - | U33: =IFERROR(VLOOKUP(C33,'List Approval 2026'!$D$7:$P$225,13,FALSE),"-") -> Cahaya Said
... A44: =+A43+1 -> 36 | B44: =IF(IFERROR(VLOOKUP(C44,FA_2026!$F$10:$AT$65451,5,FALSE),0)=0,"-",IFERROR(VLOOKUP(C44,FA_2026!$F$10:$AT$65451,5,FALSE),0)) -> Bulldozer | C44: VEH000649 | D44: =IF(IFERROR(VLOOKUP(C44,FA_2026!$F$10:$AT$65451,6,FALSE),0)=0,"-",IFERROR(VLOOKUP(C44,FA_2026!$F$10:$AT$65451,6,FALSE),0)) -> KOMATSU | E44: =IF(IFERROR(VLOOKUP(C44,FA_2026!$F$10:$AT$65451,7,FALSE),0)=0,"-",IFERROR(VLOOKUP(C44,FA_2026!$F$10:$AT$65451,7,FALSE),0)) -> 1,61 M3 | F44: =IF(IFERROR(VLOOKUP(C44,FA_2026!$F$10:$AT$65451,9,FALSE),0)=0,"-",IFERROR(VLOOKUP(C44,FA_2026!$F$10:$AT$65451,9,FALSE),0)) -> D31EX-22 | G44: =IF(IFERROR(VLOOKUP(C44,FA_2026!$F$10:$AT$65451,10,FALSE),0)=0,"-",IFERROR(VLOOKUP(C44,FA_2026!$F$10:$AT$65451,10,FALSE),0)) -> KMTOD111CNA | H44: =IF(IFERROR(VLOOKUP(C44,FA_2026!$F$10:$AT$65451,11,FALSE),0)=0,"-",IFERROR(VLOOKUP(C44,FA_2026!$F$10:$AT$65451,11,FALSE),0)) -> 062020 | I44: =IFERROR(INDEX(FA_2026!$B$10:$B$1159,MATCH('Disposal 2026'!C44,FA_2026!$F$10:$F$1159,0)),0) -> ASC | J44: =IFERROR(INDEX(FA_2026!$C$10:$C$1159,MATCH('Disposal 2026'!C44,FA_2026!$F$10:$F$1159,0)),0) -> 3A1 | K44: =IF(IFERROR(VLOOKUP(C44,FA_2026!$F$10:$AT$65451,2,FALSE),0)=0,"-",IFERROR(VLOOKUP(C44,FA_2026!$F$10:$AT$65451,2,FALSE),0)) -> 45046 | L44: =IF(IFERROR(VLOOKUP(C44,'List Approval 2025'!$D$7:$M$65624,5,FALSE),0)=0,"-",IFERROR(VLOOKUP(C44,'List Approval 2025'!$D$7:$M$65624,5,FALSE),0)) -> - | M44: =IF(IFERROR(VLOOKUP(C44,FA_2026!$F$10:$AT$65451,14,FALSE),0)=0,"-",IFERROR(VLOOKUP(C44,FA_2026!$F$10:$AT$65451,14,FALSE),0)) -> 1530000000 | N44: =IF(IFERROR(VLOOKUP(C44,FA_2026!$F$10:$AT$65451,36,FALSE),0)=0,"-",IFERROR(VLOOKUP(C44,FA_2026!$F$10:$AT$65451,36,FALSE),0)) -> 1530000000 | O44: =ROUND(IFERROR(+M44-N44,0),0) -> 0 | P44: =IFERROR(VLOOKUP(C44,'List Approval 2026'!$D$7:$M$276,10,FALSE),0) -> 20000000 | Q44: =(IFERROR(IF(+P44-O44<0,"-",+P44-O44),0)) -> 20000000 | R44: =(IFERROR(IF(P44-O44>=0,"-",O44-P44),0)) -> - | U44: =IFERROR(VLOOKUP(C44,'List Approval 2026'!$D$7:$P$225,13,FALSE),"-") -> Biru Revorma Indonesia
A45: =+A44+1 -> 37 | B45: =IF(IFERROR(VLOOKUP(C45,FA_2026!$F$10:$AT$65451,5,FALSE),0)=0,"-",IFERROR(VLOOKUP(C45,FA_2026!$F$10:$AT$65451,5,FALSE),0)) -> - | D45: =IF(IFERROR(VLOOKUP(C45,FA_2026!$F$10:$AT$65451,6,FALSE),0)=0,"-",IFERROR(VLOOKUP(C45,FA_2026!$F$10:$AT$65451,6,FALSE),0)) -> - | E45: =IF(IFERROR(VLOOKUP(C45,FA_2026!$F$10:$AT$65451,7,FALSE),0)=0,"-",IFERROR(VLOOKUP(C45,FA_2026!$F$10:$AT$65451,7,FALSE),0)) -> - | F45: =IF(IFERROR(VLOOKUP(C45,FA_2026!$F$10:$AT$65451,9,FALSE),0)=0,"-",IFERROR(VLOOKUP(C45,FA_2026!$F$10:$AT$65451,9,FALSE),0)) -> - | G45: =IF(IFERROR(VLOOKUP(C45,FA_2026!$F$10:$AT$65451,10,FALSE),0)=0,"-",IFERROR(VLOOKUP(C45,FA_2026!$F$10:$AT$65451,10,FALSE),0)) -> - | H45: =IF(IFERROR(VLOOKUP(C45,FA_2026!$F$10:$AT$65451,11,FALSE),0)=0,"-",IFERROR(VLOOKUP(C45,FA_2026!$F$10:$AT$65451,11,FALSE),0)) -> - | I45: =IFERROR(INDEX(FA_2026!$B$10:$B$1159,MATCH('Disposal 2026'!C45,FA_2026!$F$10:$F$1159,0)),0) -> 0 | J45: =IFERROR(INDEX(FA_2026!$C$10:$C$1159,MATCH('Disposal 2026'!C45,FA_2026!$F$10:$F$1159,0)),0) -> 0 | K45: =IF(IFERROR(VLOOKUP(C45,FA_2026!$F$10:$AT$65451,2,FALSE),0)=0,"-",IFERROR(VLOOKUP(C45,FA_2026!$F$10:$AT$65451,2,FALSE),0)) -> - | L45: =IF(IFERROR(VLOOKUP(C45,'List Approval 2025'!$D$7:$M$65624,5,FALSE),0)=0,"-",IFERROR(VLOOKUP(C45,'List Approval 2025'!$D$7:$M$65624,5,FALSE),0)) -> - | M45: =IF(IFERROR(VLOOKUP(C45,FA_2026!$F$10:$AT$65451,14,FALSE),0)=0,"-",IFERROR(VLOOKUP(C45,FA_2026!$F$10:$AT$65451,14,FALSE),0)) -> - | N45: =IF(IFERROR(VLOOKUP(C45,FA_2026!$F$10:$AT$65451,36,FALSE),0)=0,"-",IFERROR(VLOOKUP(C45,FA_2026!$F$10:$AT$65451,36,FALSE),0)) -> - | O45: =ROUND(IFERROR(+M45-N45,0),0) -> 0 | P45: =IFERROR(VLOOKUP(C45,'List Approval 2026'!$D$7:$M$276,10,FALSE),0) -> 0 | Q45: =(IFERROR(IF(+P45-O45<0,"-",+P45-O45),0)) -> 0 | R45: =(IFERROR(IF(P45-O45>=0,"-",O45-P45),0)) -> - | U45: =IFERROR(VLOOKUP(C45,'List Approval 2026'!$D$7:$P$225,13,FALSE),"-") -> -
A46: =+A45+1 -> 38 | B46: =IF(IFERROR(VLOOKUP(C46,FA_2026!$F$10:$AT$65451,5,FALSE),0)=0,"-",IFERROR(VLOOKUP(C46,FA_2026!$F$10:$AT$65451,5,FALSE),0)) -> - | D46: =IF(IFERROR(VLOOKUP(C46,FA_2026!$F$10:$AT$65451,6,FALSE),0)=0,"-",IFERROR(VLOOKUP(C46,FA_2026!$F$10:$AT$65451,6,FALSE),0)) -> - | E46: =IF(IFERROR(VLOOKUP(C46,FA_2026!$F$10:$AT$65451,7,FALSE),0)=0,"-",IFERROR(VLOOKUP(C46,FA_2026!$F$10:$AT$65451,7,FALSE),0)) -> - | F46: =IF(IFERROR(VLOOKUP(C46,FA_2026!$F$10:$AT$65451,9,FALSE),0)=0,"-",IFERROR(VLOOKUP(C46,FA_2026!$F$10:$AT$65451,9,FALSE),0)) -> - | G46: =IF(IFERROR(VLOOKUP(C46,FA_2026!$F$10:$AT$65451,10,FALSE),0)=0,"-",IFERROR(VLOOKUP(C46,FA_2026!$F$10:$AT$65451,10,FALSE),0)) -> - | H46: =IF(IFERROR(VLOOKUP(C46,FA_2026!$F$10:$AT$65451,11,FALSE),0)=0,"-",IFERROR(VLOOKUP(C46,FA_2026!$F$10:$AT$65451,11,FALSE),0)) -> - | I46: =IFERROR(INDEX(FA_2026!$B$10:$B$1159,MATCH('Disposal 2026'!C46,FA_2026!$F$10:$F$1159,0)),0) -> 0 | J46: =IFERROR(INDEX(FA_2026!$C$10:$C$1159,MATCH('Disposal 2026'!C46,FA_2026!$F$10:$F$1159,0)),0) -> 0 | K46: =IF(IFERROR(VLOOKUP(C46,FA_2026!$F$10:$AT$65451,2,FALSE),0)=0,"-",IFERROR(VLOOKUP(C46,FA_2026!$F$10:$AT$65451,2,FALSE),0)) -> - | L46: =IF(IFERROR(VLOOKUP(C46,'List Approval 2025'!$D$7:$M$65624,5,FALSE),0)=0,"-",IFERROR(VLOOKUP(C46,'List Approval 2025'!$D$7:$M$65624,5,FALSE),0)) -> - | M46: =IF(IFERROR(VLOOKUP(C46,FA_2026!$F$10:$AT$65451,14,FALSE),0)=0,"-",IFERROR(VLOOKUP(C46,FA_2026!$F$10:$AT$65451,14,FALSE),0)) -> - | N46: =IF(IFERROR(VLOOKUP(C46,FA_2026!$F$10:$AT$65451,36,FALSE),0)=0,"-",IFERROR(VLOOKUP(C46,FA_2026!$F$10:$AT$65451,36,FALSE),0)) -> - | O46: =ROUND(IFERROR(+M46-N46,0),0) -> 0 | P46: =IFERROR(VLOOKUP(C46,'List Approval 2026'!$D$7:$M$276,10,FALSE),0) -> 0 | Q46: =(IFERROR(IF(+P46-O46<0,"-",+P46-O46),0)) -> 0 | R46: =(IFERROR(IF(P46-O46>=0,"-",O46-P46),0)) -> - | U46: =IFERROR(VLOOKUP(C46,'List Approval 2026'!$D$7:$P$225,13,FALSE),"-") -> -
A47: =+A46+1 -> 39 | B47: =IF(IFERROR(VLOOKUP(C47,FA_2026!$F$10:$AT$65451,5,FALSE),0)=0,"-",IFERROR(VLOOKUP(C47,FA_2026!$F$10:$AT$65451,5,FALSE),0)) -> - | D47: =IF(IFERROR(VLOOKUP(C47,FA_2026!$F$10:$AT$65451,6,FALSE),0)=0,"-",IFERROR(VLOOKUP(C47,FA_2026!$F$10:$AT$65451,6,FALSE),0)) -> - | E47: =IF(IFERROR(VLOOKUP(C47,FA_2026!$F$10:$AT$65451,7,FALSE),0)=0,"-",IFERROR(VLOOKUP(C47,FA_2026!$F$10:$AT$65451,7,FALSE),0)) -> - | F47: =IF(IFERROR(VLOOKUP(C47,FA_2026!$F$10:$AT$65451,9,FALSE),0)=0,"-",IFERROR(VLOOKUP(C47,FA_2026!$F$10:$AT$65451,9,FALSE),0)) -> - | G47: =IF(IFERROR(VLOOKUP(C47,FA_2026!$F$10:$AT$65451,10,FALSE),0)=0,"-",IFERROR(VLOOKUP(C47,FA_2026!$F$10:$AT$65451,10,FALSE),0)) -> - | H47: =IF(IFERROR(VLOOKUP(C47,FA_2026!$F$10:$AT$65451,11,FALSE),0)=0,"-",IFERROR(VLOOKUP(C47,FA_2026!$F$10:$AT$65451,11,FALSE),0)) -> - | I47: =IFERROR(INDEX(FA_2026!$B$10:$B$1159,MATCH('Disposal 2026'!C47,FA_2026!$F$10:$F$1159,0)),0) -> 0 | J47: =IFERROR(INDEX(FA_2026!$C$10:$C$1159,MATCH('Disposal 2026'!C47,FA_2026!$F$10:$F$1159,0)),0) -> 0 | K47: =IF(IFERROR(VLOOKUP(C47,FA_2026!$F$10:$AT$65451,2,FALSE),0)=0,"-",IFERROR(VLOOKUP(C47,FA_2026!$F$10:$AT$65451,2,FALSE),0)) -> - | L47: =IF(IFERROR(VLOOKUP(C47,'List Approval 2025'!$D$7:$M$65624,5,FALSE),0)=0,"-",IFERROR(VLOOKUP(C47,'List Approval 2025'!$D$7:$M$65624,5,FALSE),0)) -> - | M47: =IF(IFERROR(VLOOKUP(C47,FA_2026!$F$10:$AT$65451,14,FALSE),0)=0,"-",IFERROR(VLOOKUP(C47,FA_2026!$F$10:$AT$65451,14,FALSE),0)) -> - | N47: =IF(IFERROR(VLOOKUP(C47,FA_2026!$F$10:$AT$65451,36,FALSE),0)=0,"-",IFERROR(VLOOKUP(C47,FA_2026!$F$10:$AT$65451,36,FALSE),0)) -> - | O47: =ROUND(IFERROR(+M47-N47,0),0) -> 0 | P47: =IFERROR(VLOOKUP(C47,'List Approval 2026'!$D$7:$M$276,10,FALSE),0) -> 0 | Q47: =(IFERROR(IF(+P47-O47<0,"-",+P47-O47),0)) -> 0 | R47: =(IFERROR(IF(P47-O47>=0,"-",O47-P47),0)) -> - | U47: =IFERROR(VLOOKUP(C47,'List Approval 2026'!$D$7:$P$225,13,FALSE),"-") -> -
A48: =+A47+1 -> 40 | B48: =IF(IFERROR(VLOOKUP(C48,FA_2026!$F$10:$AT$65451,5,FALSE),0)=0,"-",IFERROR(VLOOKUP(C48,FA_2026!$F$10:$AT$65451,5,FALSE),0)) -> - | D48: =IF(IFERROR(VLOOKUP(C48,FA_2026!$F$10:$AT$65451,6,FALSE),0)=0,"-",IFERROR(VLOOKUP(C48,FA_2026!$F$10:$AT$65451,6,FALSE),0)) -> - | E48: =IF(IFERROR(VLOOKUP(C48,FA_2026!$F$10:$AT$65451,7,FALSE),0)=0,"-",IFERROR(VLOOKUP(C48,FA_2026!$F$10:$AT$65451,7,FALSE),0)) -> - | F48: =IF(IFERROR(VLOOKUP(C48,FA_2026!$F$10:$AT$65451,9,FALSE),0)=0,"-",IFERROR(VLOOKUP(C48,FA_2026!$F$10:$AT$65451,9,FALSE),0)) -> - | G48: =IF(IFERROR(VLOOKUP(C48,FA_2026!$F$10:$AT$65451,10,FALSE),0)=0,"-",IFERROR(VLOOKUP(C48,FA_2026!$F$10:$AT$65451,10,FALSE),0)) -> - | H48: =IF(IFERROR(VLOOKUP(C48,FA_2026!$F$10:$AT$65451,11,FALSE),0)=0,"-",IFERROR(VLOOKUP(C48,FA_2026!$F$10:$AT$65451,11,FALSE),0)) -> - | I48: =IFERROR(INDEX(FA_2026!$B$10:$B$1159,MATCH('Disposal 2026'!C48,FA_2026!$F$10:$F$1159,0)),0) -> 0 | J48: =IFERROR(INDEX(FA_2026!$C$10:$C$1159,MATCH('Disposal 2026'!C48,FA_2026!$F$10:$F$1159,0)),0) -> 0 | K48: =IF(IFERROR(VLOOKUP(C48,FA_2026!$F$10:$AT$65451,2,FALSE),0)=0,"-",IFERROR(VLOOKUP(C48,FA_2026!$F$10:$AT$65451,2,FALSE),0)) -> - | L48: =IF(IFERROR(VLOOKUP(C48,'List Approval 2025'!$D$7:$M$65624,5,FALSE),0)=0,"-",IFERROR(VLOOKUP(C48,'List Approval 2025'!$D$7:$M$65624,5,FALSE),0)) -> - | M48: =IF(IFERROR(VLOOKUP(C48,FA_2026!$F$10:$AT$65451,14,FALSE),0)=0,"-",IFERROR(VLOOKUP(C48,FA_2026!$F$10:$AT$65451,14,FALSE),0)) -> - | N48: =IF(IFERROR(VLOOKUP(C48,FA_2026!$F$10:$AT$65451,36,FALSE),0)=0,"-",IFERROR(VLOOKUP(C48,FA_2026!$F$10:$AT$65451,36,FALSE),0)) -> - | O48: =ROUND(IFERROR(+M48-N48,0),0) -> 0 | P48: =IFERROR(VLOOKUP(C48,'List Approval 2026'!$D$7:$M$276,10,FALSE),0) -> 0 | Q48: =(IFERROR(IF(+P48-O48<0,"-",+P48-O48),0)) -> 0 | R48: =(IFERROR(IF(P48-O48>=0,"-",O48-P48),0)) -> - | U48: =IFERROR(VLOOKUP(C48,'List Approval 2026'!$D$7:$P$225,13,FALSE),"-") -> -
A49: =+A48+1 -> 41 | B49: =IF(IFERROR(VLOOKUP(C49,FA_2026!$F$10:$AT$65451,5,FALSE),0)=0,"-",IFERROR(VLOOKUP(C49,FA_2026!$F$10:$AT$65451,5,FALSE),0)) -> - | D49: =IF(IFERROR(VLOOKUP(C49,FA_2026!$F$10:$AT$65451,6,FALSE),0)=0,"-",IFERROR(VLOOKUP(C49,FA_2026!$F$10:$AT$65451,6,FALSE),0)) -> - | E49: =IF(IFERROR(VLOOKUP(C49,FA_2026!$F$10:$AT$65451,7,FALSE),0)=0,"-",IFERROR(VLOOKUP(C49,FA_2026!$F$10:$AT$65451,7,FALSE),0)) -> - | F49: =IF(IFERROR(VLOOKUP(C49,FA_2026!$F$10:$AT$65451,9,FALSE),0)=0,"-",IFERROR(VLOOKUP(C49,FA_2026!$F$10:$AT$65451,9,FALSE),0)) -> - | G49: =IF(IFERROR(VLOOKUP(C49,FA_2026!$F$10:$AT$65451,10,FALSE),0)=0,"-",IFERROR(VLOOKUP(C49,FA_2026!$F$10:$AT$65451,10,FALSE),0)) -> - | H49: =IF(IFERROR(VLOOKUP(C49,FA_2026!$F$10:$AT$65451,11,FALSE),0)=0,"-",IFERROR(VLOOKUP(C49,FA_2026!$F$10:$AT$65451,11,FALSE),0)) -> - | I49: =IFERROR(INDEX(FA_2026!$B$10:$B$1159,MATCH('Disposal 2026'!C49,FA_2026!$F$10:$F$1159,0)),0) -> 0 | J49: =IFERROR(INDEX(FA_2026!$C$10:$C$1159,MATCH('Disposal 2026'!C49,FA_2026!$F$10:$F$1159,0)),0) -> 0 | K49: =IF(IFERROR(VLOOKUP(C49,FA_2026!$F$10:$AT$65451,2,FALSE),0)=0,"-",IFERROR(VLOOKUP(C49,FA_2026!$F$10:$AT$65451,2,FALSE),0)) -> - | L49: =IF(IFERROR(VLOOKUP(C49,'List Approval 2025'!$D$7:$M$65624,5,FALSE),0)=0,"-",IFERROR(VLOOKUP(C49,'List Approval 2025'!$D$7:$M$65624,5,FALSE),0)) -> - | M49: =IF(IFERROR(VLOOKUP(C49,FA_2026!$F$10:$AT$65451,14,FALSE),0)=0,"-",IFERROR(VLOOKUP(C49,FA_2026!$F$10:$AT$65451,14,FALSE),0)) -> - | N49: =IF(IFERROR(VLOOKUP(C49,FA_2026!$F$10:$AT$65451,36,FALSE),0)=0,"-",IFERROR(VLOOKUP(C49,FA_2026!$F$10:$AT$65451,36,FALSE),0)) -> - | O49: =ROUND(IFERROR(+M49-N49,0),0) -> 0 | P49: =IFERROR(VLOOKUP(C49,'List Approval 2026'!$D$7:$M$276,10,FALSE),0) -> 0 | Q49: =(IFERROR(IF(+P49-O49<0,"-",+P49-O49),0)) -> 0 | R49: =(IFERROR(IF(P49-O49>=0,"-",O49-P49),0)) -> - | U49: =IFERROR(VLOOKUP(C49,'List Approval 2026'!$D$7:$P$225,13,FALSE),"-") -> -
A50: =+A49+1 -> 42 | B50: =IF(IFERROR(VLOOKUP(C50,FA_2026!$F$10:$AT$65451,5,FALSE),0)=0,"-",IFERROR(VLOOKUP(C50,FA_2026!$F$10:$AT$65451,5,FALSE),0)) -> - | D50: =IF(IFERROR(VLOOKUP(C50,FA_2026!$F$10:$AT$65451,6,FALSE),0)=0,"-",IFERROR(VLOOKUP(C50,FA_2026!$F$10:$AT$65451,6,FALSE),0)) -> - | E50: =IF(IFERROR(VLOOKUP(C50,FA_2026!$F$10:$AT$65451,7,FALSE),0)=0,"-",IFERROR(VLOOKUP(C50,FA_2026!$F$10:$AT$65451,7,FALSE),0)) -> - | F50: =IF(IFERROR(VLOOKUP(C50,FA_2026!$F$10:$AT$65451,9,FALSE),0)=0,"-",IFERROR(VLOOKUP(C50,FA_2026!$F$10:$AT$65451,9,FALSE),0)) -> - | G50: =IF(IFERROR(VLOOKUP(C50,FA_2026!$F$10:$AT$65451,10,FALSE),0)=0,"-",IFERROR(VLOOKUP(C50,FA_2026!$F$10:$AT$65451,10,FALSE),0)) -> - | H50: =IF(IFERROR(VLOOKUP(C50,FA_2026!$F$10:$AT$65451,11,FALSE),0)=0,"-",IFERROR(VLOOKUP(C50,FA_2026!$F$10:$AT$65451,11,FALSE),0)) -> - | I50: =IFERROR(INDEX(FA_2026!$B$10:$B$1159,MATCH('Disposal 2026'!C50,FA_2026!$F$10:$F$1159,0)),0) -> 0 | J50: =IFERROR(INDEX(FA_2026!$C$10:$C$1159,MATCH('Disposal 2026'!C50,FA_2026!$F$10:$F$1159,0)),0) -> 0 | K50: =IF(IFERROR(VLOOKUP(C50,FA_2026!$F$10:$AT$65451,2,FALSE),0)=0,"-",IFERROR(VLOOKUP(C50,FA_2026!$F$10:$AT$65451,2,FALSE),0)) -> - | L50: =IF(IFERROR(VLOOKUP(C50,'List Approval 2025'!$D$7:$M$65624,5,FALSE),0)=0,"-",IFERROR(VLOOKUP(C50,'List Approval 2025'!$D$7:$M$65624,5,FALSE),0)) -> - | M50: =IF(IFERROR(VLOOKUP(C50,FA_2026!$F$10:$AT$65451,14,FALSE),0)=0,"-",IFERROR(VLOOKUP(C50,FA_2026!$F$10:$AT$65451,14,FALSE),0)) -> - | N50: =IF(IFERROR(VLOOKUP(C50,FA_2026!$F$10:$AT$65451,36,FALSE),0)=0,"-",IFERROR(VLOOKUP(C50,FA_2026!$F$10:$AT$65451,36,FALSE),0)) -> - | O50: =ROUND(IFERROR(+M50-N50,0),0) -> 0 | P50: =IFERROR(VLOOKUP(C50,'List Approval 2026'!$D$7:$M$276,10,FALSE),0) -> 0 | Q50: =(IFERROR(IF(+P50-O50<0,"-",+P50-O50),0)) -> 0 | R50: =(IFERROR(IF(P50-O50>=0,"-",O50-P50),0)) -> - | U50: =IFERROR(VLOOKUP(C50,'List Approval 2026'!$D$7:$P$225,13,FALSE),"-") -> -
A51: =+A50+1 -> 43 | B51: =IF(IFERROR(VLOOKUP(C51,FA_2026!$F$10:$AT$65451,5,FALSE),0)=0,"-",IFERROR(VLOOKUP(C51,FA_2026!$F$10:$AT$65451,5,FALSE),0)) -> - | D51: =IF(IFERROR(VLOOKUP(C51,FA_2026!$F$10:$AT$65451,6,FALSE),0)=0,"-",IFERROR(VLOOKUP(C51,FA_2026!$F$10:$AT$65451,6,FALSE),0)) -> - | E51: =IF(IFERROR(VLOOKUP(C51,FA_2026!$F$10:$AT$65451,7,FALSE),0)=0,"-",IFERROR(VLOOKUP(C51,FA_2026!$F$10:$AT$65451,7,FALSE),0)) -> - | F51: =IF(IFERROR(VLOOKUP(C51,FA_2026!$F$10:$AT$65451,9,FALSE),0)=0,"-",IFERROR(VLOOKUP(C51,FA_2026!$F$10:$AT$65451,9,FALSE),0)) -> - | G51: =IF(IFERROR(VLOOKUP(C51,FA_2026!$F$10:$AT$65451,10,FALSE),0)=0,"-",IFERROR(VLOOKUP(C51,FA_2026!$F$10:$AT$65451,10,FALSE),0)) -> - | H51: =IF(IFERROR(VLOOKUP(C51,FA_2026!$F$10:$AT$65451,11,FALSE),0)=0,"-",IFERROR(VLOOKUP(C51,FA_2026!$F$10:$AT$65451,11,FALSE),0)) -> - | I51: =IFERROR(INDEX(FA_2026!$B$10:$B$1159,MATCH('Disposal 2026'!C51,FA_2026!$F$10:$F$1159,0)),0) -> 0 | J51: =IFERROR(INDEX(FA_2026!$C$10:$C$1159,MATCH('Disposal 2026'!C51,FA_2026!$F$10:$F$1159,0)),0) -> 0 | K51: =IF(IFERROR(VLOOKUP(C51,FA_2026!$F$10:$AT$65451,2,FALSE),0)=0,"-",IFERROR(VLOOKUP(C51,FA_2026!$F$10:$AT$65451,2,FALSE),0)) -> - | L51: =IF(IFERROR(VLOOKUP(C51,'List Approval 2025'!$D$7:$M$65624,5,FALSE),0)=0,"-",IFERROR(VLOOKUP(C51,'List Approval 2025'!$D$7:$M$65624,5,FALSE),0)) -> - | M51: =IF(IFERROR(VLOOKUP(C51,FA_2026!$F$10:$AT$65451,14,FALSE),0)=0,"-",IFERROR(VLOOKUP(C51,FA_2026!$F$10:$AT$65451,14,FALSE),0)) -> - | N51: =IF(IFERROR(VLOOKUP(C51,FA_2026!$F$10:$AT$65451,36,FALSE),0)=0,"-",IFERROR(VLOOKUP(C51,FA_2026!$F$10:$AT$65451,36,FALSE),0)) -> - | O51: =ROUND(IFERROR(+M51-N51,0),0) -> 0 | P51: =IFERROR(VLOOKUP(C51,'List Approval 2026'!$D$7:$M$276,10,FALSE),0) -> 0 | Q51: =(IFERROR(IF(+P51-O51<0,"-",+P51-O51),0)) -> 0 | R51: =(IFERROR(IF(P51-O51>=0,"-",O51-P51),0)) -> - | U51: =IFERROR(VLOOKUP(C51,'List Approval 2026'!$D$7:$P$225,13,FALSE),"-") -> -
A52: =+A51+1 -> 44 | B52: =IF(IFERROR(VLOOKUP(C52,FA_2026!$F$10:$AT$65451,5,FALSE),0)=0,"-",IFERROR(VLOOKUP(C52,FA_2026!$F$10:$AT$65451,5,FALSE),0)) -> - | D52: =IF(IFERROR(VLOOKUP(C52,FA_2026!$F$10:$AT$65451,6,FALSE),0)=0,"-",IFERROR(VLOOKUP(C52,FA_2026!$F$10:$AT$65451,6,FALSE),0)) -> - | E52: =IF(IFERROR(VLOOKUP(C52,FA_2026!$F$10:$AT$65451,7,FALSE),0)=0,"-",IFERROR(VLOOKUP(C52,FA_2026!$F$10:$AT$65451,7,FALSE),0)) -> - | F52: =IF(IFERROR(VLOOKUP(C52,FA_2026!$F$10:$AT$65451,9,FALSE),0)=0,"-",IFERROR(VLOOKUP(C52,FA_2026!$F$10:$AT$65451,9,FALSE),0)) -> - | G52: =IF(IFERROR(VLOOKUP(C52,FA_2026!$F$10:$AT$65451,10,FALSE),0)=0,"-",IFERROR(VLOOKUP(C52,FA_2026!$F$10:$AT$65451,10,FALSE),0)) -> - | H52: =IF(IFERROR(VLOOKUP(C52,FA_2026!$F$10:$AT$65451,11,FALSE),0)=0,"-",IFERROR(VLOOKUP(C52,FA_2026!$F$10:$AT$65451,11,FALSE),0)) -> - | I52: =IFERROR(INDEX(FA_2026!$B$10:$B$1159,MATCH('Disposal 2026'!C52,FA_2026!$F$10:$F$1159,0)),0) -> 0 | J52: =IFERROR(INDEX(FA_2026!$C$10:$C$1159,MATCH('Disposal 2026'!C52,FA_2026!$F$10:$F$1159,0)),0) -> 0 | K52: =IF(IFERROR(VLOOKUP(C52,FA_2026!$F$10:$AT$65451,2,FALSE),0)=0,"-",IFERROR(VLOOKUP(C52,FA_2026!$F$10:$AT$65451,2,FALSE),0)) -> - | L52: =IF(IFERROR(VLOOKUP(C52,'List Approval 2025'!$D$7:$M$65624,5,FALSE),0)=0,"-",IFERROR(VLOOKUP(C52,'List Approval 2025'!$D$7:$M$65624,5,FALSE),0)) -> - | M52: =IF(IFERROR(VLOOKUP(C52,FA_2026!$F$10:$AT$65451,14,FALSE),0)=0,"-",IFERROR(VLOOKUP(C52,FA_2026!$F$10:$AT$65451,14,FALSE),0)) -> - | N52: =IF(IFERROR(VLOOKUP(C52,FA_2026!$F$10:$AT$65451,36,FALSE),0)=0,"-",IFERROR(VLOOKUP(C52,FA_2026!$F$10:$AT$65451,36,FALSE),0)) -> - | O52: =ROUND(IFERROR(+M52-N52,0),0) -> 0 | P52: =IFERROR(VLOOKUP(C52,'List Approval 2026'!$D$7:$M$276,10,FALSE),0) -> 0 | Q52: =(IFERROR(IF(+P52-O52<0,"-",+P52-O52),0)) -> 0 | R52: =(IFERROR(IF(P52-O52>=0,"-",O52-P52),0)) -> - | U52: =IFERROR(VLOOKUP(C52,'List Approval 2026'!$D$7:$P$225,13,FALSE),"-") -> -
A53: =+A52+1 -> 45 | B53: =IF(IFERROR(VLOOKUP(C53,FA_2026!$F$10:$AT$65451,5,FALSE),0)=0,"-",IFERROR(VLOOKUP(C53,FA_2026!$F$10:$AT$65451,5,FALSE),0)) -> - | D53: =IF(IFERROR(VLOOKUP(C53,FA_2026!$F$10:$AT$65451,6,FALSE),0)=0,"-",IFERROR(VLOOKUP(C53,FA_2026!$F$10:$AT$65451,6,FALSE),0)) -> - | E53: =IF(IFERROR(VLOOKUP(C53,FA_2026!$F$10:$AT$65451,7,FALSE),0)=0,"-",IFERROR(VLOOKUP(C53,FA_2026!$F$10:$AT$65451,7,FALSE),0)) -> - | F53: =IF(IFERROR(VLOOKUP(C53,FA_2026!$F$10:$AT$65451,9,FALSE),0)=0,"-",IFERROR(VLOOKUP(C53,FA_2026!$F$10:$AT$65451,9,FALSE),0)) -> - | G53: =IF(IFERROR(VLOOKUP(C53,FA_2026!$F$10:$AT$65451,10,FALSE),0)=0,"-",IFERROR(VLOOKUP(C53,FA_2026!$F$10:$AT$65451,10,FALSE),0)) -> - | H53: =IF(IFERROR(VLOOKUP(C53,FA_2026!$F$10:$AT$65451,11,FALSE),0)=0,"-",IFERROR(VLOOKUP(C53,FA_2026!$F$10:$AT$65451,11,FALSE),0)) -> - | I53: =IFERROR(INDEX(FA_2026!$B$10:$B$1159,MATCH('Disposal 2026'!C53,FA_2026!$F$10:$F$1159,0)),0) -> 0 | J53: =IFERROR(INDEX(FA_2026!$C$10:$C$1159,MATCH('Disposal 2026'!C53,FA_2026!$F$10:$F$1159,0)),0) -> 0 | K53: =IF(IFERROR(VLOOKUP(C53,FA_2026!$F$10:$AT$65451,2,FALSE),0)=0,"-",IFERROR(VLOOKUP(C53,FA_2026!$F$10:$AT$65451,2,FALSE),0)) -> - | L53: =IF(IFERROR(VLOOKUP(C53,'List Approval 2025'!$D$7:$M$65624,5,FALSE),0)=0,"-",IFERROR(VLOOKUP(C53,'List Approval 2025'!$D$7:$M$65624,5,FALSE),0)) -> - | M53: =IF(IFERROR(VLOOKUP(C53,FA_2026!$F$10:$AT$65451,14,FALSE),0)=0,"-",IFERROR(VLOOKUP(C53,FA_2026!$F$10:$AT$65451,14,FALSE),0)) -> - | N53: =IF(IFERROR(VLOOKUP(C53,FA_2026!$F$10:$AT$65451,36,FALSE),0)=0,"-",IFERROR(VLOOKUP(C53,FA_2026!$F$10:$AT$65451,36,FALSE),0)) -> - | O53: =ROUND(IFERROR(+M53-N53,0),0) -> 0 | P53: =IFERROR(VLOOKUP(C53,'List Approval 2026'!$D$7:$M$276,10,FALSE),0) -> 0 | Q53: =(IFERROR(IF(+P53-O53<0,"-",+P53-O53),0)) -> 0 | R53: =(IFERROR(IF(P53-O53>=0,"-",O53-P53),0)) -> - | U53: =IFERROR(VLOOKUP(C53,'List Approval 2026'!$D$7:$P$225,13,FALSE),"-") -> -
A54: =+A53+1 -> 46 | B54: =IF(IFERROR(VLOOKUP(C54,FA_2026!$F$10:$AT$65451,5,FALSE),0)=0,"-",IFERROR(VLOOKUP(C54,FA_2026!$F$10:$AT$65451,5,FALSE),0)) -> - | D54: =IF(IFERROR(VLOOKUP(C54,FA_2026!$F$10:$AT$65451,6,FALSE),0)=0,"-",IFERROR(VLOOKUP(C54,FA_2026!$F$10:$AT$65451,6,FALSE),0)) -> - | E54: =IF(IFERROR(VLOOKUP(C54,FA_2026!$F$10:$AT$65451,7,FALSE),0)=0,"-",IFERROR(VLOOKUP(C54,FA_2026!$F$10:$AT$65451,7,FALSE),0)) -> - | F54: =IF(IFERROR(VLOOKUP(C54,FA_2026!$F$10:$AT$65451,9,FALSE),0)=0,"-",IFERROR(VLOOKUP(C54,FA_2026!$F$10:$AT$65451,9,FALSE),0)) -> - | G54: =IF(IFERROR(VLOOKUP(C54,FA_2026!$F$10:$AT$65451,10,FALSE),0)=0,"-",IFERROR(VLOOKUP(C54,FA_2026!$F$10:$AT$65451,10,FALSE),0)) -> - | H54: =IF(IFERROR(VLOOKUP(C54,FA_2026!$F$10:$AT$65451,11,FALSE),0)=0,"-",IFERROR(VLOOKUP(C54,FA_2026!$F$10:$AT$65451,11,FALSE),0)) -> - | I54: =IFERROR(INDEX(FA_2026!$B$10:$B$1159,MATCH('Disposal 2026'!C54,FA_2026!$F$10:$F$1159,0)),0) -> 0 | J54: =IFERROR(INDEX(FA_2026!$C$10:$C$1159,MATCH('Disposal 2026'!C54,FA_2026!$F$10:$F$1159,0)),0) -> 0 | K54: =IF(IFERROR(VLOOKUP(C54,FA_2026!$F$10:$AT$65451,2,FALSE),0)=0,"-",IFERROR(VLOOKUP(C54,FA_2026!$F$10:$AT$65451,2,FALSE),0)) -> - | L54: =IF(IFERROR(VLOOKUP(C54,'List Approval 2025'!$D$7:$M$65624,5,FALSE),0)=0,"-",IFERROR(VLOOKUP(C54,'List Approval 2025'!$D$7:$M$65624,5,FALSE),0)) -> - | M54: =IF(IFERROR(VLOOKUP(C54,FA_2026!$F$10:$AT$65451,14,FALSE),0)=0,"-",IFERROR(VLOOKUP(C54,FA_2026!$F$10:$AT$65451,14,FALSE),0)) -> - | N54: =IF(IFERROR(VLOOKUP(C54,FA_2026!$F$10:$AT$65451,36,FALSE),0)=0,"-",IFERROR(VLOOKUP(C54,FA_2026!$F$10:$AT$65451,36,FALSE),0)) -> - | O54: =ROUND(IFERROR(+M54-N54,0),0) -> 0 | P54: =IFERROR(VLOOKUP(C54,'List Approval 2026'!$D$7:$M$276,10,FALSE),0) -> 0 | Q54: =(IFERROR(IF(+P54-O54<0,"-",+P54-O54),0)) -> 0 | R54: =(IFERROR(IF(P54-O54>=0,"-",O54-P54),0)) -> - | U54: =IFERROR(VLOOKUP(C54,'List Approval 2026'!$D$7:$P$225,13,FALSE),"-") -> -
A55: =+A54+1 -> 47 | B55: =IF(IFERROR(VLOOKUP(C55,FA_2026!$F$10:$AT$65451,5,FALSE),0)=0,"-",IFERROR(VLOOKUP(C55,FA_2026!$F$10:$AT$65451,5,FALSE),0)) -> - | D55: =IF(IFERROR(VLOOKUP(C55,FA_2026!$F$10:$AT$65451,6,FALSE),0)=0,"-",IFERROR(VLOOKUP(C55,FA_2026!$F$10:$AT$65451,6,FALSE),0)) -> - | E55: =IF(IFERROR(VLOOKUP(C55,FA_2026!$F$10:$AT$65451,7,FALSE),0)=0,"-",IFERROR(VLOOKUP(C55,FA_2026!$F$10:$AT$65451,7,FALSE),0)) -> - | F55: =IF(IFERROR(VLOOKUP(C55,FA_2026!$F$10:$AT$65451,9,FALSE),0)=0,"-",IFERROR(VLOOKUP(C55,FA_2026!$F$10:$AT$65451,9,FALSE),0)) -> - | G55: =IF(IFERROR(VLOOKUP(C55,FA_2026!$F$10:$AT$65451,10,FALSE),0)=0,"-",IFERROR(VLOOKUP(C55,FA_2026!$F$10:$AT$65451,10,FALSE),0)) -> - | H55: =IF(IFERROR(VLOOKUP(C55,FA_2026!$F$10:$AT$65451,11,FALSE),0)=0,"-",IFERROR(VLOOKUP(C55,FA_2026!$F$10:$AT$65451,11,FALSE),0)) -> - | I55: =IFERROR(INDEX(FA_2026!$B$10:$B$1159,MATCH('Disposal 2026'!C55,FA_2026!$F$10:$F$1159,0)),0) -> 0 | J55: =IFERROR(INDEX(FA_2026!$C$10:$C$1159,MATCH('Disposal 2026'!C55,FA_2026!$F$10:$F$1159,0)),0) -> 0 | K55: =IF(IFERROR(VLOOKUP(C55,FA_2026!$F$10:$AT$65451,2,FALSE),0)=0,"-",IFERROR(VLOOKUP(C55,FA_2026!$F$10:$AT$65451,2,FALSE),0)) -> - | L55: =IF(IFERROR(VLOOKUP(C55,'List Approval 2025'!$D$7:$M$65624,5,FALSE),0)=0,"-",IFERROR(VLOOKUP(C55,'List Approval 2025'!$D$7:$M$65624,5,FALSE),0)) -> - | M55: =IF(IFERROR(VLOOKUP(C55,FA_2026!$F$10:$AT$65451,14,FALSE),0)=0,"-",IFERROR(VLOOKUP(C55,FA_2026!$F$10:$AT$65451,14,FALSE),0)) -> - | N55: =IF(IFERROR(VLOOKUP(C55,FA_2026!$F$10:$AT$65451,36,FALSE),0)=0,"-",IFERROR(VLOOKUP(C55,FA_2026!$F$10:$AT$65451,36,FALSE),0)) -> - | O55: =ROUND(IFERROR(+M55-N55,0),0) -> 0 | P55: =IFERROR(VLOOKUP(C55,'List Approval 2026'!$D$7:$M$276,10,FALSE),0) -> 0 | Q55: =(IFERROR(IF(+P55-O55<0,"-",+P55-O55),0)) -> 0 | R55: =(IFERROR(IF(P55-O55>=0,"-",O55-P55),0)) -> - | U55: =IFERROR(VLOOKUP(C55,'List Approval 2026'!$D$7:$P$225,13,FALSE),"-") -> -
A56: =+A55+1 -> 48 | B56: =IF(IFERROR(VLOOKUP(C56,FA_2026!$F$10:$AT$65451,5,FALSE),0)=0,"-",IFERROR(VLOOKUP(C56,FA_2026!$F$10:$AT$65451,5,FALSE),0)) -> - | D56: =IF(IFERROR(VLOOKUP(C56,FA_2026!$F$10:$AT$65451,6,FALSE),0)=0,"-",IFERROR(VLOOKUP(C56,FA_2026!$F$10:$AT$65451,6,FALSE),0)) -> - | E56: =IF(IFERROR(VLOOKUP(C56,FA_2026!$F$10:$AT$65451,7,FALSE),0)=0,"-",IFERROR(VLOOKUP(C56,FA_2026!$F$10:$AT$65451,7,FALSE),0)) -> - | F56: =IF(IFERROR(VLOOKUP(C56,FA_2026!$F$10:$AT$65451,9,FALSE),0)=0,"-",IFERROR(VLOOKUP(C56,FA_2026!$F$10:$AT$65451,9,FALSE),0)) -> - | G56: =IF(IFERROR(VLOOKUP(C56,FA_2026!$F$10:$AT$65451,10,FALSE),0)=0,"-",IFERROR(VLOOKUP(C56,FA_2026!$F$10:$AT$65451,10,FALSE),0)) -> - | H56: =IF(IFERROR(VLOOKUP(C56,FA_2026!$F$10:$AT$65451,11,FALSE),0)=0,"-",IFERROR(VLOOKUP(C56,FA_2026!$F$10:$AT$65451,11,FALSE),0)) -> - | I56: =IFERROR(INDEX(FA_2026!$B$10:$B$1159,MATCH('Disposal 2026'!C56,FA_2026!$F$10:$F$1159,0)),0) -> 0 | J56: =IFERROR(INDEX(FA_2026!$C$10:$C$1159,MATCH('Disposal 2026'!C56,FA_2026!$F$10:$F$1159,0)),0) -> 0 | K56: =IF(IFERROR(VLOOKUP(C56,FA_2026!$F$10:$AT$65451,2,FALSE),0)=0,"-",IFERROR(VLOOKUP(C56,FA_2026!$F$10:$AT$65451,2,FALSE),0)) -> - | L56: =IF(IFERROR(VLOOKUP(C56,'List Approval 2025'!$D$7:$M$65624,5,FALSE),0)=0,"-",IFERROR(VLOOKUP(C56,'List Approval 2025'!$D$7:$M$65624,5,FALSE),0)) -> - | M56: =IF(IFERROR(VLOOKUP(C56,FA_2026!$F$10:$AT$65451,14,FALSE),0)=0,"-",IFERROR(VLOOKUP(C56,FA_2026!$F$10:$AT$65451,14,FALSE),0)) -> - | N56: =IF(IFERROR(VLOOKUP(C56,FA_2026!$F$10:$AT$65451,36,FALSE),0)=0,"-",IFERROR(VLOOKUP(C56,FA_2026!$F$10:$AT$65451,36,FALSE),0)) -> - | O56: =ROUND(IFERROR(+M56-N56,0),0) -> 0 | P56: =IFERROR(VLOOKUP(C56,'List Approval 2026'!$D$7:$M$276,10,FALSE),0) -> 0 | Q56: =(IFERROR(IF(+P56-O56<0,"-",+P56-O56),0)) -> 0 | R56: =(IFERROR(IF(P56-O56>=0,"-",O56-P56),0)) -> - | U56: =IFERROR(VLOOKUP(C56,'List Approval 2026'!$D$7:$P$225,13,FALSE),"-") -> -
... A136: =+A135+1 -> 128 | B136: =IF(IFERROR(VLOOKUP(C136,FA_2026!$F$10:$AT$65451,5,FALSE),0)=0,"-",IFERROR(VLOOKUP(C136,FA_2026!$F$10:$AT$65451,5,FALSE),0)) -> - | D136: =IF(IFERROR(VLOOKUP(C136,FA_2026!$F$10:$AT$65451,6,FALSE),0)=0,"-",IFERROR(VLOOKUP(C136,FA_2026!$F$10:$AT$65451,6,FALSE),0)) -> - | E136: =IF(IFERROR(VLOOKUP(C136,FA_2026!$F$10:$AT$65451,7,FALSE),0)=0,"-",IFERROR(VLOOKUP(C136,FA_2026!$F$10:$AT$65451,7,FALSE),0)) -> - | F136: =IF(IFERROR(VLOOKUP(C136,FA_2026!$F$10:$AT$65451,9,FALSE),0)=0,"-",IFERROR(VLOOKUP(C136,FA_2026!$F$10:$AT$65451,9,FALSE),0)) -> - | G136: =IF(IFERROR(VLOOKUP(C136,FA_2026!$F$10:$AT$65451,10,FALSE),0)=0,"-",IFERROR(VLOOKUP(C136,FA_2026!$F$10:$AT$65451,10,FALSE),0)) -> - | H136: =IF(IFERROR(VLOOKUP(C136,FA_2026!$F$10:$AT$65451,11,FALSE),0)=0,"-",IFERROR(VLOOKUP(C136,FA_2026!$F$10:$AT$65451,11,FALSE),0)) -> - | I136: =IFERROR(INDEX(FA_2026!$B$10:$B$1159,MATCH('Disposal 2026'!C136,FA_2026!$F$10:$F$1159,0)),0) -> 0 | J136: =IFERROR(INDEX(FA_2026!$C$10:$C$1159,MATCH('Disposal 2026'!C136,FA_2026!$F$10:$F$1159,0)),0) -> 0 | K136: =IF(IFERROR(VLOOKUP(C136,FA_2026!$F$10:$AT$65451,2,FALSE),0)=0,"-",IFERROR(VLOOKUP(C136,FA_2026!$F$10:$AT$65451,2,FALSE),0)) -> - | L136: =IF(IFERROR(VLOOKUP(C136,'List Approval 2025'!$D$7:$M$65624,5,FALSE),0)=0,"-",IFERROR(VLOOKUP(C136,'List Approval 2025'!$D$7:$M$65624,5,FALSE),0)) -> - | M136: =IF(IFERROR(VLOOKUP(C136,FA_2026!$F$10:$AT$65451,14,FALSE),0)=0,"-",IFERROR(VLOOKUP(C136,FA_2026!$F$10:$AT$65451,14,FALSE),0)) -> - | N136: =IF(IFERROR(VLOOKUP(C136,FA_2026!$F$10:$AT$65451,36,FALSE),0)=0,"-",IFERROR(VLOOKUP(C136,FA_2026!$F$10:$AT$65451,36,FALSE),0)) -> - | O136: =ROUND(IFERROR(+M136-N136,0),0) -> 0 | P136: =IFERROR(VLOOKUP(C136,'List Approval 2026'!$D$7:$M$276,10,FALSE),0) -> 0 | Q136: =(IFERROR(IF(+P136-O136<0,"-",+P136-O136),0)) -> 0 | R136: =(IFERROR(IF(P136-O136>=0,"-",O136-P136),0)) -> - | U136: =IFERROR(VLOOKUP(C136,'List Approval 2026'!$D$7:$P$225,13,FALSE),"-") -> -
P137: =IFERROR(VLOOKUP(C137,'List Approval 2026'!$D$7:$M$276,10,FALSE),0) -> 0 | Q137: =(IFERROR(IF(+P137-O137<0,"-",+P137-O137),0)) -> 0 | R137: =(IFERROR(IF(P137-O137>=0,"-",O137-P137),0)) -> - | U137: =IFERROR(VLOOKUP(C137,'List Approval 2026'!$D$7:$P$225,13,FALSE),"-") -> -
B138: Grand Total | M138: =SUM(M9:M137) -> 2.3422829e+10 | N138: =SUM(N9:N137) -> 2.3422829e+10 | O138: =SUM(O9:O137) -> 0 | P138: =SUM(P9:P137) -> 3769171174 | Q138: =SUM(Q9:Q137) -> 3769171174 | R138: =SUM(R9:R137) -> 0
Q140: =Q138-R138 -> 3769171174
O142: ="Gain FA as of "&TOTAL!A3&" :" -> Gain FA as of 30 Jun 2026 : | Q142: =-SUM(TB!G22:G25,TB!G28:G29) -> 3769171174
O143: Diff : | Q143: =Q140-Q142 -> 0
P144: ="FA Disposal Amount "&TOTAL!A3&" :" -> FA Disposal Amount 30 Jun 2026 : | Q144: =-SUM(TOTAL!E9:E16) -> 2.3422829e+10
P145: Diff : | Q145: =Q144-M138 -> 0

Sheet List Approval 2026
A1: PT. SANKYU INDONESIA INTERNATIONAL
A2: LIST OF ACQUISITION & DISPOSALS ASSET
A3: JAN - DEC 202
A5: No. | B5: Site | C5: Job | D5: Fixed Asset | F5: Application No | I5: Date | J5: Purchase/ Disposed Date | K5: Bookslip No. | L5: Name of Fixed Asset | M5: Purchase/Disposal Prices | N5: Status | O5: Disposals | P5: Vendor/Customer | Q5: Transaction Status | R5: Date | S5: DP | T5: date | U5: Payment | V5: PIC
D6: AX | E6: No. | N6: Acquisition | R6: of Down Payment | T6: of Repayment
A8: 1 | B8: JKC | C8: D10 | D8: FNF000312 | E8: =INDEX(FA_2026!$E$1:$E$1570,MATCH('List Approval 2026'!D8,FA_2026!$F$1:$F$1570,0)) -> 0 | F8: 001/JKC/FA-Purc/I/2026 | G8: - | H8: 1 | J8: 45688 | K8: 20260226_016-02 | L8: =VLOOKUP(D8,FA_2026!$F$10:$J$1178,5,FALSE) -> Chain Block Cap. 10T | M8: 67860000 | N8: Acquisition | P8: Triputra Bangunjaya Bersama | Y8: OK
B9: JKC | C9: D10 | D9: MNE000340 | E9: =INDEX(FA_2026!$E$1:$E$1570,MATCH('List Approval 2026'!D9,FA_2026!$F$1:$F$1570,0)) -> 0 | F9: 001/JKC/FA-Purc/I/2026 | G9: - | H9: 2 | J9: 45688 | K9: 20260226_016-02 | L9: =VLOOKUP(D9,FA_2026!$F$10:$J$1178,5,FALSE) -> Threading Machine BEAVER 50 ASADA | M9: 25890000 | N9: Acquisition | P9: Triputra Bangunjaya Bersama | Y9: OK
B10: JKC | C10: D10 | D10: MNE000341 | E10: =INDEX(FA_2026!$E$1:$E$1570,MATCH('List Approval 2026'!D10,FA_2026!$F$1:$F$1570,0)) -> 0 | F10: 001/JKC/FA-Purc/I/2026 | G10: - | H10: 3 | J10: 45688 | K10: 20260226_016-02 | L10: =VLOOKUP(D10,FA_2026!$F$10:$J$1178,5,FALSE) -> Threading Machine BEAVER 80 ASADA | M10: 40500000 | N10: Acquisition | P10: Triputra Bangunjaya Bersama | Y10: OK
A11: 2 | B11: CLC | C11: CLCWH | D11: VEH000287 | E11: =INDEX(FA_2026!$E$1:$E$1570,MATCH('List Approval 2026'!D11,FA_2026!$F$1:$F$1570,0)) -> CLC-C-010 | F11: 001/CLC/FA-Disp/III/2026 | G11: - | H11: 1 | J11: 46112 | K11: 20260331_062-03 | L11: =VLOOKUP(D11,FA_2026!$F$10:$J$1178,5,FALSE) -> Forklift Sumitomo | M11: 15765766 | O11: Disposals | P11: Najwa Jaya | Y11: OK
B12: CLC | C12: CLCWH | D12: VEH000290 | E12: =INDEX(FA_2026!$E$1:$E$1570,MATCH('List Approval 2026'!D12,FA_2026!$F$1:$F$1570,0)) -> CLC-C-013 | F12: 001/CLC/FA-Disp/III/2026 | G12: - | H12: 2 | J12: 46112 | K12: 20260331_062-03 | L12: =VLOOKUP(D12,FA_2026!$F$10:$J$1178,5,FALSE) -> Forklift Sumitomo | M12: 15765766 | O12: Disposals | P12: Najwa Jaya | Y12: OK
B13: CLC | C13: CLCWH | D13: VEH000372 | E13: =INDEX(FA_2026!$E$1:$E$1570,MATCH('List Approval 2026'!D13,FA_2026!$F$1:$F$1570,0)) -> CLC-C-33 | F13: 001/CLC/FA-Disp/III/2026 | G13: - | H13: 3 | J13: 46112 | K13: 20260331_062-03 | L13: =VLOOKUP(D13,FA_2026!$F$10:$J$1178,5,FALSE) -> Reach Truck Forklift | M13: 15765766 | O13: Disposals | P13: Najwa Jaya | Y13: OK
B14: CLC | C14: CLCWH | D14: VEH000378 | E14: =INDEX(FA_2026!$E$1:$E$1570,MATCH('List Approval 2026'!D14,FA_2026!$F$1:$F$1570,0)) -> CLC-C-24 | F14: 001/CLC/FA-Disp/III/2026 | G14: - | H14: 4 | J14: 46112 | K14: 20260331_062-03 | L14: =VLOOKUP(D14,FA_2026!$F$10:$J$1178,5,FALSE) -> Counter Balance Forklift | M14: 18018017 | O14: Disposals | P14: Najwa Jaya | Y14: OK
A15: 3 | E15: =INDEX(FA_2026!$E$1:$E$1570,MATCH('List Approval 2026'!D15,FA_2026!$F$1:$F$1570,0)) -> #N/A | F15: 001/CLC/FA-Purc/II/2026
A16: 4 | E16: =INDEX(FA_2026!$E$1:$E$1570,MATCH('List Approval 2026'!D16,FA_2026!$F$1:$F$1570,0)) -> #N/A | F16: 001/CLGA/FA-Purc/I/2026
A17: 5 | B17: D30 | C17: CLGC | D17: STR000057 | E17: =INDEX(FA_2026!$E$1:$E$1570,MATCH('List Approval 2026'!D17,FA_2026!$F$1:$F$1570,0)) -> 7C-A-017 | F17: 001/CLGC/FA-Disp/III/2026 | G17: - | H17: 1 | J17: 46142 | K17: 20260430_063-04 | L17: =VLOOKUP(D17,FA_2026!$F$10:$J$1178,5,FALSE) -> CCTV | M17: 0 | O17: Disposals | P17: SII | Y17: OK
A18: 6 | E18: =INDEX(FA_2026!$E$1:$E$1570,MATCH('List Approval 2026'!D18,FA_2026!$F$1:$F$1570,0)) -> #N/A | F18: 001/CLGC/FA-Purc/III/2026
A19: 7 | B19: D30 | C19: CLGC | D19: VEH000693 | E19: =INDEX(FA_2026!$E$1:$E$1570,MATCH('List Approval 2026'!D19,FA_2026!$F$1:$F$1570,0)) -> M10-C-065 | F19: 001/CLGC/FA-Trf/III/2026 | G19: - | H19: 1 | J19: 46142 | K19: Transfer Asset | L19: =VLOOKUP(D19,FA_2026!$F$10:$J$1178,5,FALSE) -> INNOVA ZENIX G CVT 2.0 | M19: - | N19: Transfer | P19: JKTC | Y19: OK
A20: 8 | B20: AD_HO | C20: AD_HO | D20: FNF000109 | E20: =INDEX(FA_2026!$E$1:$E$1570,MATCH('List Approval 2026'!D20,FA_2026!$F$1:$F$1570,0)) -> PLG-14-001 | F20: 001/HO/FA-Disp/II/2026 | G20: - | H20: 1 | J20: 46142 | K20: 20260430_064-04 | L20: =VLOOKUP(D20,FA_2026!$F$10:$J$1178,5,FALSE) -> Computer | M20: 0 | O20: Disposals | Y20: OK
A21: 9 | E21: =INDEX(FA_2026!$E$1:$E$1570,MATCH('List Approval 2026'!D21,FA_2026!$F$1:$F$1570,0)) -> #N/A | F21: 001/HO/FA-Purc/II/2026
A22: 10 | E22: =INDEX(FA_2026!$E$1:$E$1570,MATCH('List Approval 2026'!D22,FA_2026!$F$1:$F$1570,0)) -> #N/A | F22: 001/MCCI/FA-Purc/IV/2026
A23: 11 | B23: CLC | C23: CLCTRP | D23: VEH000443 | E23: =INDEX(FA_2026!$E$1:$E$1570,MATCH('List Approval 2026'!D23,FA_2026!$F$1:$F$1570,0)) -> CLC-C-45 T | F23: 002/CLC/FA-Disp/III/2026 | G23: - | H23: 1 | J23: 46112 | K23: 20260331_062-03 | L23: =VLOOKUP(D23,FA_2026!$F$10:$J$1178,5,FALSE) -> Head Tractor | M23: 198198198 | O23: Disposals | P23: Citra Seraya Pratama | Y23: OK
B24: CLC | C24: CLCTRP | D24: VEH000395 | E24: =INDEX(FA_2026!$E$1:$E$1570,MATCH('List Approval 2026'!D24,FA_2026!$F$1:$F$1570,0)) -> CLC-C-37T | F24: 002/CLC/FA-Disp/III/2026 | G24: - | H24: 2 | J24: 46112 | K24: 20260331_062-03 | L24: =VLOOKUP(D24,FA_2026!$F$10:$J$1178,5,FALSE) -> Head Truck | M24: 175675676 | O24: Disposals | P24: Citra Seraya Pratama | Y24: OK
B25: CLC | C25: CLCTRP | D25: VEH000211 | E25: =INDEX(FA_2026!$E$1:$E$1570,MATCH('List Approval 2026'!D25,FA_2026!$F$1:$F$1570,0)) -> 7C-C-133 | F25: 002/CLC/FA-Disp/III/2026 | G25: - | H25: 3 | J25: 46112 | K25: 20260331_062-03 | L25: =VLOOKUP(D25,FA_2026!$F$10:$J$1178,5,FALSE) -> Head Tractor | M25: 211711712 | O25: Disposals | P25: Citra Seraya Pratama | Y25: OK
B26: CLC | C26: CLCTRP | D26: VEH000083 | E26: =INDEX(FA_2026!$E$1:$E$1570,MATCH('List Approval 2026'!D26,FA_2026!$F$1:$F$1570,0)) -> TG-C-028 | F26: 002/CLC/FA-Disp/III/2026 | G26: - | H26: 4 | J26: 46112 | K26: 20260331_062-03 | L26: =VLOOKUP(D26,FA_2026!$F$10:$J$1178,5,FALSE) -> Chassis High Bed | M26: 45045045 | O26: Disposals | P26: Citra Seraya Pratama | Y26: OK
B27: CLC | C27: CLCTRP | D27: VEH000393 | E27: =INDEX(FA_2026!$E$1:$E$1570,MATCH('List Approval 2026'!D27,FA_2026!$F$1:$F$1570,0)) -> CLC-C-36T | F27: 002/CLC/FA-Disp/III/2026 | G27: - | H27: 5 | J27: 46112 | K27: 20260331_062-03 | L27: =VLOOKUP(D27,FA_2026!$F$10:$J$1178,5,FALSE) -> Chassis High Bed | M27: 45045045 | O27: Disposals | P27: Citra Seraya Pratama | Y27: OK
B28: CLC | C28: CLCTRP | D28: VEH000392 | E28: =INDEX(FA_2026!$E$1:$E$1570,MATCH('List Approval 2026'!D28,FA_2026!$F$1:$F$1570,0)) -> CLC-C-35T | F28: 002/CLC/FA-Disp/III/2026 | G28: - | H28: 6 | J28: 46112 | K28: 20260331_062-03 | L28: =VLOOKUP(D28,FA_2026!$F$10:$J$1178,5,FALSE) -> Chassis High Bed | M28: 45045045 | O28: Disposals | P28: Citra Seraya Pratama | Y28: OK
A29: 12 | B29: CLC | C29: CLCWH | D29: FNF000315 | E29: =INDEX(FA_2026!$E$1:$E$1570,MATCH('List Approval 2026'!D29,FA_2026!$F$1:$F$1570,0)) -> CLC134-025 | F29: 002/CLC/FA-Purc/II/2026 | G29: - | H29: 1 | J29: 46141 | K29: 20260429_018-04 | L29: =VLOOKUP(D29,FA_2026!$F$10:$J$1178,5,FALSE) -> AC Cassette 2.5pk | M29: 26550000 | N29: Acquisition | P29: SHEO INDO TEKNIK | Y29: OK
A30: 13 | B30: CLGA | C30: AD_CGADM | D30: STR000082 | E30: =INDEX(FA_2026!$E$1:$E$1570,MATCH('List Approval 2026'!D30,FA_2026!$F$1:$F$1570,0)) -> 7-A-053 | F30: 002/CLGA/FA-Purc/I/2026 | G30: - | H30: 1 | J30: 46023
A31: 14 | B31: D30 | C31: CLGC | D31: STR000061 | E31: =INDEX(FA_2026!$E$1:$E$1570,MATCH('List Approval 2026'!D31,FA_2026!$F$1:$F$1570,0)) -> M10-B-127 | F31: 002/CLGC/FA-Disp/III/2026 | G31: - | H31: 1 | J31: 46142 | K31: 20260430_063-04 | L31: =VLOOKUP(D31,FA_2026!$F$10:$J$1178,5,FALSE) -> Bojonegara CCTV Camera System | M31: 0 | O31: Disposals | Y31: oK
A32: 15 | B32: CLC | C32: CLCWH | D32: MNE000202 | E32: =INDEX(FA_2026!$E$1:$E$1570,MATCH('List Approval 2026'!D32,FA_2026!$F$1:$F$1570,0)) -> CLC134-013 | F32: 003/CLC/FA-Disp/III/2026 | J32: 46112 | K32: 20260331_062-03 | L32: =VLOOKUP(D32,FA_2026!$F$10:$J$1178,5,FALSE) -> Lightening Rod | M32: 0 | O32: Disposals | P32: Sankyu CLC | Y32: OK
A33: 16 | B33: CLGA | C33: AD_CGAM | D33: VEH000747 | E33: =INDEX(FA_2026!$E$1:$E$1570,MATCH('List Approval 2026'!D33,FA_2026!$F$1:$F$1570,0)) -> 7-C-009 | F33: 003/CLGA/FA-Purc/I/2026 | G33: - | H33: 1 | J33: 46062 | K33: 20260209_007-02 | L33: =VLOOKUP(D33,FA_2026!$F$10:$J$1178,5,FALSE) -> Suzuki XL-7 ZETA | M33: =222211786+22788214 -> 245000000 | N33: Acquisition | P33: Pusaka Motor | Y33: OK
A34: 17 | B34: KOS | C34: 3KO | D34: VEH000430 | E34: =INDEX(FA_2026!$E$1:$E$1570,MATCH('List Approval 2026'!D34,FA_2026!$F$1:$F$1570,0)) -> 7KO-C-002 | F34: 001/KOS/FA-Disp/IV/2026 | G34: - | H34: 1 | J34: 46171 | K34: 20260529_068-05 | L34: =VLOOKUP(D34,FA_2026!$F$10:$J$1178,5,FALSE) -> Tractor Head | M34: 175675676 | O34: Disposals | P34: Cahaya Said | Y34: OK
B35: KOS | C35: 3KO | D35: VEH000437 | E35: =INDEX(FA_2026!$E$1:$E$1570,MATCH('List Approval 2026'!D35,FA_2026!$F$1:$F$1570,0)) -> 7KO-C-005 | F35: 001/KOS/FA-Disp/IV/2026 | G35: - | H35: 2 | J35: 46171 | K35: 20260529_068-05 | L35: =VLOOKUP(D35,FA_2026!$F$10:$J$1178,5,FALSE) -> Chassis High Bed | M35: 45045045 | O35: Disposals | P35: Cahaya Said | Y35: OK
B36: KOS | C36: 3KO | D36: VEH000476 | E36: =INDEX(FA_2026!$E$1:$E$1570,MATCH('List Approval 2026'!D36,FA_2026!$F$1:$F$1570,0)) -> 7BF-C-004 | F36: 001/KOS/FA-Disp/IV/2026 | G36: - | H36: 3 | J36: 46171 | K36: 20260529_068-05 | L36: =VLOOKUP(D36,FA_2026!$F$10:$J$1178,5,FALSE) -> Dumptruck | M36: 90090090 | O36: Disposals | P36: Cahaya Said | Y36: OK
B37: KOS | C37: 3KO | D37: VEH000432 | E37: =INDEX(FA_2026!$E$1:$E$1570,MATCH('List Approval 2026'!D37,FA_2026!$F$1:$F$1570,0)) -> 7KO-C-004 | F37: 001/KOS/FA-Disp/IV/2026 | G37: - | H37: 4 | J37: 46171 | K37: 20260529_068-05 | L37: =VLOOKUP(D37,FA_2026!$F$10:$J$1178,5,FALSE) -> Dumptruck | M37: 45045045 | O37: Disposals | P37: Cahaya Said | Y37: OK
B38: KOS | C38: 3KO | D38: VEH000503 | E38: =INDEX(FA_2026!$E$1:$E$1570,MATCH('List Approval 2026'!D38,FA_2026!$F$1:$F$1570,0)) -> 7C-C-176 | F38: 001/KOS/FA-Disp/IV/2026 | G38: - | H38: 5 | J38: 46171 | K38: 20260529_068-05 | L38: =VLOOKUP(D38,FA_2026!$F$10:$J$1178,5,FALSE) -> Avanza Toyota 1.3 G M/T | M38: 90090090 | O38: Disposals | P38: Cahaya Said | Y38: OK
A39: 18 | B39: CLC | C39: CLCWH | D39: VEH000756 | E39: =INDEX(FA_2026!$E$1:$E$1570,MATCH('List Approval 2026'!D39,FA_2026!$F$1:$F$1570,0)) -> CLC135-004 | F39: 003/CLC/FA-Purc/IV/2026 | G39: - | H39: 1 | J39: 46164 | K39: 20260522_007-05 | L39: =VLOOKUP(D39,FA_2026!$F$10:$J$1178,5,FALSE) -> New Calya | M39: 170100000 | N39: Acquisition | P39: Astra International | Y39: OK
A40: 19 | B40: CLGA | C40: AD_CGADM | D40: VEH000550 | E40: =INDEX(FA_2026!$E$1:$E$1570,MATCH('List Approval 2026'!D40,FA_2026!$F$1:$F$1570,0)) -> 7-C-008 | F40: 001/CLGA/FA-Disp/IV/2026 | G40: - | H40: 1 | J40: 46142 | K40: 20260430_064-04 | L40: =VLOOKUP(D40,FA_2026!$F$10:$J$1178,5,FALSE) -> Avanza Veloz A/T | M40: 31531532 | O40: Disposals | P40: Fajar Hikmah | Y40: OK
A41: 20 | B41: ASC | C41: 3A1 | D41: VEH000648 | E41: =INDEX(FA_2026!$E$1:$E$1570,MATCH('List Approval 2026'!D41,FA_2026!$F$1:$F$1570,0)) -> 3A-C-282 | F41: 001/ASC/FA-Disp/IV/2026 | G41: - | H41: 1 | J41: 46203 | K41: 20260630_065-06 | L41: =VLOOKUP(D41,FA_2026!$F$10:$J$1178,5,FALSE) -> Bulldozer | M41: 40000000 | O41: Disposals | P41: Biru Revorma Indonesia | Y41: OK
B42: ASC | C42: 3A1 | D42: VEH000649 | E42: =INDEX(FA_2026!$E$1:$E$1570,MATCH('List Approval 2026'!D42,FA_2026!$F$1:$F$1570,0)) -> 3A-C-283 | F42: 001/ASC/FA-Disp/IV/2026 | G42: - | H42: 2 | J42: 46203 | K42: 20260630_065-06 | L42: =VLOOKUP(D42,FA_2026!$F$10:$J$1178,5,FALSE) -> Bulldozer | M42: 20000000 | O42: Disposals | P42: Biru Revorma Indonesia | Y42: OK
A43: 21 | B43: CKR | C43: AD_HO | D43: VEH000460 | E43: =INDEX(FA_2026!$E$1:$E$1570,MATCH('List Approval 2026'!D43,FA_2026!$F$1:$F$1570,0)) -> VEH000460 | F43: 002/HO/FA-Disp/V/2026 | G43: - | H43: 1 | J43: 46171 | K43: 20260529_069-05 | L43: =VLOOKUP(D43,FA_2026!$F$10:$J$1178,5,FALSE) -> Alphard | M43: 216216216 | O43: Disposals | P43: Biru Revorma Indonesia | Y43: OK
A44: 22 | B44: SMI | C44: 3SM | D44: VEH000331 | E44: =INDEX(FA_2026!$E$1:$E$1570,MATCH('List Approval 2026'!D44,FA_2026!$F$1:$F$1570,0)) -> 3A-C-179 | F44: 003/ASC/FA-Disp/V/2026 | G44: - | H44: 1 | J44: 46171 | K44: 20260529_085-05 | L44: =VLOOKUP(D44,FA_2026!$F$10:$J$1178,5,FALSE) -> Forklift Toyota | M44: 31531532 | O44: Disposals | P44: Cahaya Said | Y44: Dokumen sama dengan nomor 23
A45: 23 | B45: ASC | C45: 3A3 | D45: VEH000583 | E45: =INDEX(FA_2026!$E$1:$E$1570,MATCH('List Approval 2026'!D45,FA_2026!$F$1:$F$1570,0)) -> 3A-C-253 | F45: 002/ASC/FA-Disp/V/2026 | G45: - | H45: 1 | J45: 46171 | K45: 20260529_085-05 | L45: =VLOOKUP(D45,FA_2026!$F$10:$J$1178,5,FALSE) -> Forklift (No.23) | M45: 22522523 | O45: Disposals | P45: Cahaya Said | Y45: OK
B46: ASC | C46: 3A3 | D46: VEH000586 | E46: =INDEX(FA_2026!$E$1:$E$1570,MATCH('List Approval 2026'!D46,FA_2026!$F$1:$F$1570,0)) -> 3A-C-254 | F46: 002/ASC/FA-Disp/V/2026 | G46: - | H46: 2 | J46: 46171 | K46: 20260529_085-05 | L46: =VLOOKUP(D46,FA_2026!$F$10:$J$1178,5,FALSE) -> Forklift (No.30) | M46: 22522523 | O46: Disposals | P46: Cahaya Said | Y46: OK
B47: ASC | C47: 3A3 | D47: VEH000585 | E47: =INDEX(FA_2026!$E$1:$E$1570,MATCH('List Approval 2026'!D47,FA_2026!$F$1:$F$1570,0)) -> 3A-C-255 | F47: 002/ASC/FA-Disp/V/2026 | G47: - | H47: 3 | J47: 46171 | K47: 20260529_085-05 | L47: =VLOOKUP(D47,FA_2026!$F$10:$J$1178,5,FALSE) -> Forklift (No.32) | M47: 22522523 | O47: Disposals | P47: Cahaya Said | Y47: OK
B48: ASC | C48: 3A3 | D48: VEH000584 | E48: =INDEX(FA_2026!$E$1:$E$1570,MATCH('List Approval 2026'!D48,FA_2026!$F$1:$F$1570,0)) -> 3A-C-256 | F48: 002/ASC/FA-Disp/V/2026 | G48: - | H48: 4 | J48: 46171 | K48: 20260529_085-05 | L48: =VLOOKUP(D48,FA_2026!$F$10:$J$1178,5,FALSE) -> Forklift (No.31) | M48: 22522523 | O48: Disposals | P48: Cahaya Said | Y48: OK
A49: 24 | B49: CLGC | C49: D30 | D49: VEH000004 | E49: =INDEX(FA_2026!$E$1:$E$1570,MATCH('List Approval 2026'!D49,FA_2026!$F$1:$F$1570,0)) -> 7C-C-017 | F49: 003/CLGC/FA-Disp/V/2026 | G49: - | H49: 1 | J49: 46203 | K49: 20260630_064-06 | L49: =VLOOKUP(D49,FA_2026!$F$10:$J$1178,5,FALSE) -> Dolly | M49: 82234234 | O49: Disposals | P49: MEGA SANKTI HQ | Y49: Ok
B50: CLGC | C50: D30 | D50: VEH000005 | E50: =INDEX(FA_2026!$E$1:$E$1570,MATCH('List Approval 2026'!D50,FA_2026!$F$1:$F$1570,0)) -> 7C-C-018 | F50: 003/CLGC/FA-Disp/V/2026 | G50: - | H50: 2 | J50: 46203 | K50: 20260630_064-06 | L50: =VLOOKUP(D50,FA_2026!$F$10:$J$1178,5,FALSE) -> Dolly | M50: 114918919 | O50: Disposals | P50: MEGA SANKTI HQ | Y50: Ok
B51: CLGC | C51: D30 | D51: VEH000021 | E51: =INDEX(FA_2026!$E$1:$E$1570,MATCH('List Approval 2026'!D51,FA_2026!$F$1:$F$1570,0)) -> 7C-C-019 | F51: 003/CLGC/FA-Disp/V/2026 | G51: - | H51: 3 | J51: 46203 | K51: 20260630_064-06 | L51: =VLOOKUP(D51,FA_2026!$F$10:$J$1178,5,FALSE) -> Dolly (Ex.HKG) | M51: 115603604 | O51: Disposals | P51: MEGA SANKTI HQ | Y51: Ok
B52: CLGC | C52: D30 | D52: VEH000022 | E52: =INDEX(FA_2026!$E$1:$E$1570,MATCH('List Approval 2026'!D52,FA_2026!$F$1:$F$1570,0)) -> 7C-C-020 | F52: 003/CLGC/FA-Disp/V/2026 | G52: - | H52: 4 | J52: 46203 | K52: 20260630_064-06 | L52: =VLOOKUP(D52,FA_2026!$F$10:$J$1178,5,FALSE) -> Dolly (Ex.HKG) | M52: 114630631 | O52: Disposals | P52: MEGA SANKTI HQ | Y52: Ok
B53: CLGC | C53: D30 | D53: VEH000141 | E53: =INDEX(FA_2026!$E$1:$E$1570,MATCH('List Approval 2026'!D53,FA_2026!$F$1:$F$1570,0)) -> 7C-C-093 | F53: 003/CLGC/FA-Disp/V/2026 | G53: - | H53: 5 | J53: 46203 | K53: 20260630_064-06 | L53: =VLOOKUP(D53,FA_2026!$F$10:$J$1178,5,FALSE) -> Dolly Expansion Frame | M53: 82234234 | O53: Disposals | P53: MEGA SANKTI HQ | Y53: Ok

Sheet List Approval 2025
A1: PT. SANKYU INDONESIA INTERNATIONAL
A2: LIST OF ACQUISITION & DISPOSALS ASSET
A3: JAN - DEC 202
A5: No. | B5: Site | C5: Job | D5: Fixed Asset | F5: Application No | I5: Remark | J5: Purchase/ Disposed Date | K5: Bookslip No. | L5: Name of Fixed Asset | M5: Purchase/Disposal Prices | N5: Status | O5: Disposals | P5: Vendor/Customer | Q5: Transaction Status | R5: Date | S5: DP | T5: date | U5: Payment | V5: PIC
D6: AX | E6: No. | N6: Acquisition | R6: of Down Payment | T6: of Repayment
A8: 1 | B8: ASC | C8: D40 | D8: FNF000191 | E8: 3A-A-044 | F8: 001/ASC/FA-Disp/I/2025 | I8: 45716 | J8: 45688 | K8: 20250228_011-02 | L8: Fotocopy Machine Fuji Xerox at ASC | M8: 10000000 | O8: Disposal | P8: Astra Graphia | W8: OK
A9: 2 | B9: ASC | C9: D40 | D9: FNF000305 | E9: 3A-A-082 | F9: 001/ASC/FA-Purc/I/2025 | I9: 45681 | J9: 45716 | K9: 202502_AP_001-01 | L9: SHREDDER Papper | M9: 16590000 | N9: Acquisition | P9: Kokarsi Clg | W9: OK
A10: 3 | B10: ASC | C10: D40 | D10: FNF000306 | E10: 3A-A-083 | F10: 002/ASC/FA-Purc/I/2025 | I10: 45681 | J10: 45716 | K10: 202502_AP_001-01 | L10: Apeos C2060 CPS | M10: 94000000 | N10: Acquisition | P10: Astra Graphia | W10: OK
A11: 4 | B11: CLC | C11: CLCWH | D11: FNF000130 | E11: CLC-A-002 | F11: 001/CLC/FA-Disp/I/2025 | G11: - | H11: 1 | I11: 45663 | J11: 45688 | K11: 20250131_022-01 | L11: Copy Machine | M11: 10000000 | O11: Disposal | P11: Astra Graphia | W11: OK
B12: CLC | C12: CLCWH | D12: FNF000131 | E12: CLC-A-003 | F12: 001/CLC/FA-Disp/I/2025 | G12: - | H12: 2 | I12: 45663 | J12: 45688 | K12: 20250131_022-01 | L12: Copy Machine | M12: 10000000 | O12: Disposal | P12: Astra Graphia | W12: OK
A13: 5 | B13: CLC | C13: CLCWH | D13: FNF000297 | E13: CLC-A-075 | F13: 001/CLC/FA-Purc/I/2025 | G13: - | H13: 1 | I13: 45664 | J13: 45688 | K13: 202501_AP_030-01 | L13: Apeos C3070 CPS | M13: 122000000 | N13: Acquisition | P13: Astra Graphia | W13: OK
A14: 6 | B14: CLGA | E14: #N/A | F14: 001/CLGA/FA-Purc/I/2025 | L14: #N/A | M14: 0 | N14: Acquisition | Q14: Withdrawals | W14: Withdrawals
A15: 7 | B15: CLGA | C15: AD_CGADM | D15: FNF000309 | E15: 7-A-050 | F15: 002/CLGA/FA-Purc/I/2025 | G15: - | H15: 1 | J15: 45777 | K15: 20250829_021-08 | L15: Access Point Meeting Room A | M15: 20255000 | N15: Acquisition | P15: KDDI Indonesia | W15: OK
B16: CLGA | C16: AD_CGADM | D16: FNF000310 | E16: 7-A-051 | F16: 002/CLGA/FA-Purc/I/2025 | G16: - | H16: 2 | J16: 45777 | K16: 20250829_021-08 | L16: Access Point Meeting Room B | M16: 20255000 | N16: Acquisition | P16: KDDI Indonesia | W16: OK
A17: 8 | B17: CLGC | C17: D30 | D17: MNE000069 | E17: M05-B-002-B | F17: 001/CLGC/FA-Disp/II/2025 | G17: - | H17: 1 | I17: 45699 | J17: 45744 | K17: 20250328_059-03 | L17: Miller DC-Rectifier welding machine | M17: 2351351 | O17: Disposal | P17: Kranindo Perjaya | W17: OK
B18: CLGC | C18: D30 | D18: MNE000086 | E18: CM12-B-009 | F18: 001/CLGC/FA-Disp/II/2025 | G18: - | H18: 2 | I18: 45699 | J18: 45744 | K18: 20250328_059-03 | L18: Port portable rotary screw | M18: 2878378 | O18: Disposal | P18: Kranindo Perjaya | W18: OK
B19: CLGC | C19: D30 | D19: MNE000068 | E19: M05-B-001 | F19: 001/CLGC/FA-Disp/II/2025 | G19: - | H19: 3 | I19: 45699 | J19: 45744 | K19: 20250328_059-03 | L19: Plasma cutting | M19: 405406 | O19: Disposal | P19: Kranindo Perjaya | W19: OK
A20: 9 | B20: JKC | C20: D10 | D20: MNE000329 | E20: 0 | F20: 001/JKC/FA-Purc/II/2025 | I20: 45695 | J20: 45716 | K20: 202502_AP_001-01 | L20: Seling Talurit | M20: 51320000 | N20: Acquisition | P20: Triputra Banun Jaya | W20: OK
A21: 10 | B21: KNSS | C21: 3KN | D21: FNF000303 | E21: 3KN-A-003 | F21: 001/KNSS/FA-Purc/II/2025 | I21: 45695 | J21: 45688 | K21: 202501_AP_030-01 | L21: FortiGate 50E | M21: 12880000 | N21: Acquisition | P21: KDDI | W21: OK
A22: 11 | B22: CLC | C22: CLCWH | D22: VEH000273 | E22: CLC-C-01 | F22: 002/CLC/FA-Disp/III/2025 | G22: - | H22: 1 | I22: 45721 | J22: 45744 | K22: 20250328_059-03 | L22: Forklift | M22: 13513514 | O22: Disposal | P22: Anugrah Cahaya Mandiri | W22: OK
B23: CLC | C23: CLCWH | D23: VEH000275 | E23: CLC-C-03 | F23: 002/CLC/FA-Disp/III/2025 | G23: - | H23: 2 | I23: 45721 | J23: 45744 | K23: 20250328_059-03 | L23: Forklift Nichiyu | M23: 22522523 | O23: Disposal | P23: Anugrah Cahaya Mandiri | W23: OK
B24: CLC | C24: CLCWH | D24: VEH000276 | E24: CLC-C-04 | F24: 002/CLC/FA-Disp/III/2025 | G24: - | H24: 3 | I24: 45721 | J24: 45744 | K24: 20250328_059-03 | L24: Forklift Nichiyu | M24: 18018018 | O24: Disposal | P24: Anugrah Cahaya Mandiri | W24: OK
B25: CLC | C25: CLCWH | D25: VEH000279 | E25: CLC-C-07 | F25: 002/CLC/FA-Disp/III/2025 | G25: - | H25: 4 | I25: 45721 | J25: 45744 | K25: 20250328_059-03 | L25: Forklift Nichiyu | M25: 18018018 | O25: Disposal | P25: Anugrah Cahaya Mandiri | W25: OK
B26: CLC | C26: CLCWH | D26: VEH000292 | E26: CLC-C-015 | F26: 002/CLC/FA-Disp/III/2025 | G26: - | H26: 5 | I26: 45721 | J26: 45744 | K26: 20250328_059-03 | L26: Forklift Sumitomo | M26: 10810811 | O26: Disposal | P26: Anugrah Cahaya Mandiri | W26: OK
A27: 12 | B27: ASC | C27: 3A | D27: VEH000485 | E27: 3SM-C-004 | F27: 002/ASC/FA-Disp/III/2025 | G27: - | H27: 1 | I27: 45737 | J27: 45744 | K27: 20250328_059-03 | L27: Wheel Loader | M27: 80000000 | O27: Disposal | P27: Biru Revorma Indonesia | W27: OK
A28: 13 | B28: ASC | C28: 3A | D28: VEH000587 | E28: 3A-C-257 | F28: 003/ASC/FA-Disp/III/2025 | G28: - | H28: 1 | I28: 45779 | J28: 45777 | K28: 20250430_062-04 | L28: Bulldozer (No. 04) | M28: 12500000 | O28: Disposal | P28: Ciptamas Persada | W28: OK
A29: 14 | B29: SMI | C29: 3SM | D29: VEH000720 | E29: 3SM-C-005 | F29: 003/ASC/FA-Purc/II/2025 | G29: - | H29: 1 | J29: 45838 | K29: 202506_AP_039-06 | L29: HITACHI Wheel Loader | M29: 1430000000 | N29: Acquisition | P29: HEXINDO | W29: OK
A30: 15 | B30: ASC | E30: #N/A | F30: 004/ASC/FA-Disp/III/2025 | L30: #N/A | P30: Withdrawals | Q30: Withdrawals | W30: Withdrawals
A31: 16 | B31: ASC | E31: #N/A | F31: 005/ASC/FA-Disp/III/2025 | L31: #N/A | P31: Withdrawals | Q31: Withdrawals | W31: Withdrawals
A32: 17 | B32: ASC | C32: 3A2 | D32: VEH000574 | E32: 3A-C-245 | F32: 006/ASC/FA-Disp/III/2025 | G32: - | H32: 1 | J32: 45869 | K32: 20250731_022-07 | L32: Forklift | M32: 25000000 | O32: Disposal | P32: Multi Akses Kreasitama | W32: OK
B33: ASC | C33: 3A2 | D33: VEH000572 | E33: 3A-C-246 | F33: 006/ASC/FA-Disp/III/2025 | G33: - | H33: 2 | J33: 45869 | K33: 20250731_022-07 | L33: Forklift | M33: 25000000 | O33: Disposal | P33: Multi Akses Kreasitama | W33: OK
B34: ASC | C34: 3A2 | D34: VEH000573 | E34: 3A-C-247 | F34: 006/ASC/FA-Disp/III/2025 | G34: - | H34: 3 | J34: 45869 | K34: 20250731_022-07 | L34: Forklift | M34: 25000000 | O34: Disposal | P34: Multi Akses Kreasitama | W34: OK
B35: ASC | C35: 3A2 | D35: VEH000571 | E35: 3A-C-248 | F35: 006/ASC/FA-Disp/III/2025 | G35: - | H35: 4 | J35: 45869 | K35: 20250731_022-07 | L35: Forklift | M35: 25000000 | O35: Disposal | P35: Multi Akses Kreasitama | W35: OK
A36: 18 | B36: ASC | C36: 3A | D36: VEH000628 | E36: 3A-C-275 | F36: 007/ASC/FA-Disp/III/2025 | G36: - | H36: 1 | I36: 45779 | J36: 45777 | K36: 20250430_062-04 | L36: Bulldozer No. 06 | M36: 17500000 | O36: Disposal | P36: Ciptamas Persada | W36: OK
A37: 19 | B37: ASC | C37: 3LO | D37: VEH000514 | E37: 3L-C-006 | F37: 008/ASC/FA-Disp/III/2025 | G37: - | H37: 1 | I37: 45724 | J37: 45744 | K37: 20250328_059-03 | L37: Forklift Mitsubishi | M37: 22000000 | O37: Disposal | P37: Wijaya Equipment | W37: OK
A38: 20 | E38: #N/A | F38: 001/MCCI/FA-Purc/III/2025 | P38: Withdrawals | Q38: Withdrawals | W38: Withdrawals
A39: 21 | B39: CLGC | C39: D30 | D39: FNF000125 | E39: M10-A-025 | F39: 002/CLGC/FA-Disp/III/2025 | G39: - | H39: 1 | I39: 45733 | J39: 45777 | K39: 2025430_023-04 | L39: Copy Machine | M39: 900901 | O39: Disposal | P39: Kranindo Perjaya | W39: OK
A40: 22 | B40: MCI | C40: D50 | D40: VEH000719 | E40: 3G-C-085 | F40: 002/MCCI/FA-Purc/III/2025 | G40: - | H40: 1 | J40: 45748 | K40: 202504_AP_041-04 | L40: Avanza 1,5 CVT VIN 2025 | M40: 254534286 | N40: Acquisition | P40: Tunas Ridean | W40: OK
A41: 23 | B41: CLC | C41: CLCTRP | D41: VEH000221 | E41: CLC-C-56T | F41: 003/CLC/FA-Disp/III/2025 | G41: - | H41: 1 | J41: 45838 | K41: 20250630_062-06 | L41: Chassis High Bed | M41: 27027027 | O41: Disposal | P41: UNGGUL SUKSES CEMERLANG | W41: OK
B42: CLC | C42: CLCTRP | D42: VEH000077 | E42: CLC-C-21T | F42: 003/CLC/FA-Disp/III/2025 | G42: - | H42: 2 | J42: 45838 | K42: 20250630_062-06 | L42: Chassis High Bed | M42: 27027027 | O42: Disposal | P42: UNGGUL SUKSES CEMERLANG | W42: OK
B43: CLC | C43: CLCTRP | D43: VEH000080 | E43: TG-C-036 | F43: 003/CLC/FA-Disp/III/2025 | G43: - | H43: 3 | J43: 45838 | K43: 20250630_062-06 | L43: Chassis High Bed | M43: 27027027 | O43: Disposal | P43: UNGGUL SUKSES CEMERLANG | W43: OK
B44: CLC | C44: CLCTRP | D44: VEH000084 | E44: TG-C-029 | F44: 003/CLC/FA-Disp/III/2025 | G44: - | H44: 4 | J44: 45838 | K44: 20250630_062-06 | L44: Chassis High Bed | M44: 27027027 | O44: Disposal | P44: UNGGUL SUKSES CEMERLANG | W44: OK
B45: CLC | C45: CLCTRP | D45: VEH000086 | E45: TG-C-031 | F45: 003/CLC/FA-Disp/III/2025 | G45: - | H45: 5 | J45: 45838 | K45: 20250630_062-06 | L45: Chassis High Bed | M45: 27027027 | O45: Disposal | P45: UNGGUL SUKSES CEMERLANG | W45: OK
B46: CLC | C46: CLCTRP | D46: VEH000088 | E46: CLC-C-25T | F46: 003/CLC/FA-Disp/III/2025 | G46: - | H46: 6 | J46: 45838 | K46: 20250630_062-06 | L46: Chassis High Bed | M46: 27027027 | O46: Disposal | P46: UNGGUL SUKSES CEMERLANG | W46: OK
B47: CLC | C47: CLCTRP | D47: VEH000075 | E47: TG-C-021 | F47: 003/CLC/FA-Disp/III/2025 | G47: - | H47: 7 | J47: 45838 | K47: 20250630_062-06 | L47: Head Trucktor | M47: 72072072 | O47: Disposal | P47: UNGGUL SUKSES CEMERLANG | W47: OK
B48: CLC | C48: CLCTRP | D48: VEH000068 | E48: TG-C-014 | F48: 003/CLC/FA-Disp/III/2025 | G48: - | H48: 8 | J48: 45838 | K48: 20250630_062-06 | L48: Head Trucktor | M48: 45045045 | O48: Disposal | P48: UNGGUL SUKSES CEMERLANG | W48: OK
B49: CLC | C49: CLCTRP | D49: VEH000067 | E49: TG-C-015 | F49: 003/CLC/FA-Disp/III/2025 | G49: - | H49: 9 | J49: 45838 | K49: 20250630_062-06 | L49: Head Trucktor | M49: 45045045 | O49: Disposal | P49: UNGGUL SUKSES CEMERLANG | W49: OK
B50: CLC | C50: CLCTRP | D50: VEH000349 | E50: CLC-C-31T | F50: 003/CLC/FA-Disp/III/2025 | G50: - | H50: 10 | J50: 45838 | K50: 20250630_062-06 | L50: Pick Up Box | M50: 27027027 | O50: Disposal | P50: UNGGUL SUKSES CEMERLANG | W50: OK
A51: 24 | B51: MCI | C51: 3MC | D51: VEH000722 | E51: 3G-C-086 | F51: 003/MCCI/FA-Purc/III/2025 | J51: 45870 | K51: 20250821_005-08 | L51: Forklift | M51: 911000000 | N51: Acquisition | P51: GUZZILLA INTEE+RNATIONAL | W51: OK
A52: 25 | B52: ASC | C52: 3A3 | D52: MNE000338 | E52: 3A-B-079 | F52: 004/ASC/FA-Purc/IV/2025 | G52: - | H52: 1 | J52: 45989 | K52: 20251128_066-11 | L52: LOADING BRIDGE NO.2 | M52: 363746857 | N52: Acquisition | P52: JKTC | W52: OK
B53: ASC | C53: 3A3 | D53: MNE000339 | E53: 3A-B-078 | F53: 004/ASC/FA-Purc/IV/2025 | G53: - | H53: 2 | J53: 45989 | K53: 20251128_066-11 | L53: LOADING BRIDGE NO.1 | M53: 363746857 | N53: Acquisition | P53: JKTC | W53: OK
A54: 26 | B54: ASC | C54: 3A3 | D54: VEH000729 | E54: 3A-C-321 | F54: 005/ASC/FA-Purc/V/2025 | G54: - | H54: 1 | J54: 45901 | K54: 202509_AP_014-09 | L54: Forklift (17) | M54: 545000000 | N54: Acquisition | P54: Traktor Nusantara | W54: OK
B55: ASC | C55: 3A3 | D55: VEH000730 | E55: 3A-C-322 | F55: 005/ASC/FA-Purc/V/2025 | G55: - | H55: 2 | J55: 45901 | K55: 202509_AP_014-09 | L55: Forklift (03) | M55: 565000000 | N55: Acquisition | P55: Traktor Nusantara | W55: OK
B56: ASC | C56: 3A3 | D56: VEH000731 | E56: 3A-C-323 | F56: 005/ASC/FA-Purc/V/2025 | G56: - | H56: 3 | J56: 45901 | K56: 202509_AP_014-09 | L56: Forklift (14) | M56: 565000000 | N56: Acquisition | P56: Traktor Nusantara | W56: OK
B57: ASC | C57: 3A3 | D57: VEH000732 | E57: 3A-C-324 | F57: 005/ASC/FA-Purc/V/2025 | G57: - | H57: 4 | J57: 45901 | K57: 202509_AP_014-09 | L57: Forklift (23) | M57: 565000000 | N57: Acquisition | P57: Traktor Nusantara | W57: OK
B58: ASC | C58: 3A3 | D58: VEH000733 | E58: 3A-C-325 | F58: 005/ASC/FA-Purc/V/2025 | G58: - | H58: 5 | J58: 45901 | K58: 202509_AP_014-09 | L58: Forklift (24) | M58: 565000000 | N58: Acquisition | P58: Traktor Nusantara | W58: OK
B59: ASC | C59: 3A3 | D59: VEH000737 | E59: 3A-C-329 | F59: 005/ASC/FA-Purc/V/2025 | G59: - | H59: 6 | J59: 45901 | K59: 202509_AP_014-09 | L59: Forklift (30) | M59: 565000000 | N59: Acquisition | P59: Traktor Nusantara | W59: OK
B60: ASC | C60: 3A3 | D60: VEH000734 | E60: 3A-C-326 | F60: 005/ASC/FA-Purc/V/2025 | G60: - | H60: 7 | J60: 45901 | K60: 202509_AP_014-09 | L60: Forklift (25) | M60: 635000000 | N60: Acquisition | P60: Traktor Nusantara | W60: OK
B61: ASC | C61: 3A3 | D61: VEH000735 | E61: 3A-C-327 | F61: 005/ASC/FA-Purc/V/2025 | G61: - | H61: 8 | J61: 45901 | K61: 202509_AP_014-09 | L61: Forklift (26) | M61: 635000000 | N61: Acquisition | P61: Traktor Nusantara | W61: OK
B62: ASC | C62: 3A3 | D62: VEH000736 | E62: 3A-C-328 | F62: 005/ASC/FA-Purc/V/2025 | G62: - | H62: 9 | J62: 45901 | K62: 202509_AP_014-09 | L62: Forklift (27) | M62: 635000000 | N62: Acquisition | P62: Traktor Nusantara | W62: OK
B63: ASC | C63: 3A3 | D63: VEH000738 | E63: 3A-C-330 | F63: 005/ASC/FA-Purc/V/2025 | G63: - | H63: 10 | J63: 45901 | K63: 202509_AP_014-09 | L63: Forklift (31) | M63: 635000000 | N63: Acquisition | P63: Traktor Nusantara | W63: OK
B64: ASC | C64: 3A3 | D64: VEH000739 | E64: 3A-C-331 | F64: 005/ASC/FA-Purc/V/2025 | G64: - | H64: 11 | J64: 45901 | K64: 202509_AP_014-09 | L64: Forklift (32) | M64: 635000000 | N64: Acquisition | P64: Traktor Nusantara | W64: OK
B65: ASC | C65: 3A1 | D65: VEH000723 | E65: 3A-C-332 | F65: 005/ASC/FA-Purc/V/2025 | G65: - | H65: 12 | J65: 45901 | K65: 202509_AP_014-09 | L65: Forklift (29) | M65: 490000000 | N65: Acquisition | P65: Traktor Nusantara | W65: OK
A66: 27 | B66: ASC | C66: 3A2 | D66: VEH000724 | E66: 3A-C-333 | F66: 006/ASC/FA-Purc/V/2025 | G66: - | H66: 1 | J66: 45901 | K66: 202509_AP_014-09 | L66: Forklift (20) | M66: 635000000 | N66: Acquisition | P66: Traktor Nusantara | W66: OK
B67: ASC | C67: 3A2 | D67: VEH000725 | E67: 3A-C-334 | F67: 006/ASC/FA-Purc/V/2025 | G67: - | H67: 2 | J67: 45901 | K67: 202509_AP_014-09 | L67: Forklift (21) | M67: 635000000 | N67: Acquisition | P67: Traktor Nusantara | W67: OK
B68: ASC | C68: 3A2 | D68: VEH000726 | E68: 3A-C-335 | F68: 006/ASC/FA-Purc/V/2025 | G68: - | H68: 3 | J68: 45901 | K68: 202509_AP_014-09 | L68: Forklift (22) | M68: 635000000 | N68: Acquisition | P68: Traktor Nusantara | W68: OK
B69: ASC | C69: 3A2 | D69: VEH000727 | E69: 3A-C-336 | F69: 006/ASC/FA-Purc/V/2025 | G69: - | H69: 4 | J69: 45901 | K69: 202509_AP_014-09 | L69: Forklift (34) | M69: 635000000 | N69: Acquisition | P69: Traktor Nusantara | W69: OK
